Workbook

Sheet Roadmap (Auto)
A1: Product Roadmap - 2026-2027 | D1: ="Showing "&COUNTIF('Roadmap Calc (Don’t Touch)'!$V$2:$V$151,1)&" of "&COUNTIF('Roadmap Calc (Don’t Touch)'!$V$2:$V$151,">=0")&" rows" -> Showing 25 of 47 rows | AJ1: (All) | AK1: (All) | AL1: (All) | AM1: Theme, then Status
A2: Select Portfolio | B2: Select Theme | C2: Select Status | D2: Sort by
A3: Used | B3: (All) | C3: (All)
AJ4: =IF(COUNTA(Control!A4)=0,"",Control!A4) -> B2B | AK4: =IF(COUNTA(Control!E4)=0,"",Control!E4) -> Improve Discovery | AL4: =IF(COUNTA(Control!B4)=0,"",Control!B4) -> 00. Parking Lot | AM4: Status, then Theme
AJ5: =IF(COUNTA(Control!A5)=0,"",Control!A5) -> Used | AK5: =IF(COUNTA(Control!E5)=0,"",Control!E5) -> Increase Trade In Awareness | AL5: =IF(COUNTA(Control!B5)=0,"",Control!B5) -> 01A. Research - Foundational | AM5: Dev start (earliest)
K6: PD | L6: Prod Disc | N6: UX | O6: UX work | Q6: DEV | R6: Dev sprint | T6: PD+UX | U6: Disc+UX | W6: PD+DEV | X6: Disc+Dev | Z6: UX+DEV | AA6: UX+Dev | AC6: ALL | AD6: All three
A7: Description | B7: =IF(OR($B$3="",$B$3="(All)"),"Hint: Pick a theme in Show theme above to see its description and measures.",IF('Roadmap Calc (Don’t Touch)'!$BA$5="","— no description defined on the Control tab —",'Roadmap Calc (Don’t Touch)'!$BA$5)) -> Hint: Pick a theme in Show theme above to see its description and measures. | AJ7: =IF(COUNTA(Control!A6)=0,"",Control!A6) -> Find | AK7: =IF(COUNTA(Control!E6)=0,"",Control!E6) -> Improve Trade In User Flow | AL7: =IF(COUNTA(Control!B6)=0,"",Control!B6) -> 01. Prod Discovery | AM7: UX start (earliest)
A8: Measure adoption | B8: =IF(OR($B$3="",$B$3="(All)"),"",IF('Roadmap Calc (Don’t Touch)'!$BA$6="","— no adoption measures defined on the Control tab —",'Roadmap Calc (Don’t Touch)'!$BA$6)) | AJ8: =IF(COUNTA(Control!A7)=0,"",Control!A7) | AK8: =IF(COUNTA(Control!E7)=0,"",Control!E7) -> Increase Trade In Reactivation | AL8: =IF(COUNTA(Control!B7)=0,"",Control!B7) -> 02. UX Req | AM8: Deliverable A-Z
A9: Measure impact | B9: =IF(OR($B$3="",$B$3="(All)"),"",IF('Roadmap Calc (Don’t Touch)'!$BA$7="","— no impact measures defined on the Control tab —",'Roadmap Calc (Don’t Touch)'!$BA$7)) | AJ9: =IF(COUNTA(Control!A8)=0,"",Control!A8) | AK9: =IF(COUNTA(Control!E8)=0,"",Control!E8) -> Increase Buy Used Awareness | AL9: =IF(COUNTA(Control!B8)=0,"",Control!B8) -> 03. UX Discovery
AJ11: =IF(COUNTA(Control!A9)=0,"",Control!A9) | AK11: =IF(COUNTA(Control!E9)=0,"",Control!E9) -> Improve Buy Used Customer Experience | AL11: =IF(COUNTA(Control!B9)=0,"",Control!B9) -> 04. UX Design
J12: 46023 | K12: 46054 | L12: 46082 | M12: 46113 | N12: 46143 | O12: 46174 | P12: 46204 | Q12: 46235 | R12: 46266 | S12: 46296 | T12: 46327 | U12: 46357 | V12: 46388 | W12: 46419 | X12: 46447 | Y12: 46478 | Z12: 46508 | AA12: 46539 | AB12: 46569 | AC12: 46600 | AD12: 46631 | AE12: 46661 | AF12: 46692 | AG12: 46722 | AK12: =IF(COUNTA(Control!E10)=0,"",Control!E10) -> Increase Buy Used Reactivation | AL12: =IF(COUNTA(Control!B10)=0,"",Control!B10) -> 04A. Research - Design Validation
A13: Product Goal: Grow B2B Platforms, Used and Trade-In verticals while elevating content quality across the site. | J13: 2026 | V13: 2027 | AK13: =IF(COUNTA(Control!E11)=0,"",Control!E11) -> Increase B2B Acquisition | AL13: =IF(COUNTA(Control!B11)=0,"",Control!B11) -> 05. Business Review
J14: Q1 | M14: Q2 | P14: Q3 | S14: Q4 | V14: Q1 | Y14: Q2 | AB14: Q3 | AE14: Q4 | AK14: =IF(COUNTA(Control!E12)=0,"",Control!E12) -> Increase The Studio B&H Awareness | AL14: =IF(COUNTA(Control!B12)=0,"",Control!B12) -> 06. Architecture
A15: Theme (swim lane) | B15: Deliverable (BHP Link) | C15: Jira | D15: Status | E15: UX From | F15: UX To | G15: UX Wks | H15: Dev From | I15: Dev To | J15: Jan | K15: Feb | L15: Mar | M15: Apr | N15: May | O15: Jun | P15: Jul | Q15: Aug | R15: Sep | S15: Oct | T15: Nov | U15: Dec | V15: Jan | W15: Feb | X15: Mar | Y15: Apr | Z15: May | AA15: Jun | AB15: Jul | AC15: Aug | AD15: Sep | AE15: Oct | AF15: Nov | AG15: Dec | AH15: _theme | AI15: _row | AK15: =IF(COUNTA(Control!E13)=0,"",Control!E13) -> Improve The Studio B&H Customer Experience | AL15: =IF(COUNTA(Control!B13)=0,"",Control!B13) -> 07. Grooming
A16: =IF($AI16="","",IF($AH16=$AH15,"",IF(INDEX('Roadmap Calc (Don’t Touch)'!$U$2:$U$151,$AI16)=0,$AH16,HYPERLINK("#'Control (Don’t Touch)'!E"&INDEX('Roadmap Calc (Don’t Touch)'!$U$2:$U$151,$AI16),$AH16)))) -> Increase Trade In Awareness | B16: =IF($AI16="","",IF(INDEX('Roadmap Calc (Don’t Touch)'!$K$2:$K$151,$AI16)="",INDEX('Roadmap Calc (Don’t Touch)'!$B$2:$B$151,$AI16),HYPERLINK("https://jira.bnh.com/browse/"&INDEX('Roadmap Calc (Don’t Touch)'!$K$2:$K$151,$AI16),INDEX('Roadmap Calc (Don’t Touch)'!$B$2:$B$151,$AI16)))) -> Decouple Sell Used from Used Hub | C16: =IF($AI16="","",IF(INDEX('Roadmap Calc (Don’t Touch)'!$E$2:$E$151,$AI16)="","",HYPERLINK("https://jira.bnh.com/browse/"&INDEX('Roadmap Calc (Don’t Touch)'!$E$2:$E$151,$AI16),INDEX('Roadmap Calc (Don’t Touch)'!$E$2:$E$151,$AI16)))) -> BHP-7431 | D16: =IF($AI16="","",INDEX('Roadmap Calc (Don’t Touch)'!$F$2:$F$151,$AI16)) -> 01. Prod Discovery | E16: =IF($AI16="","",IF(ISNUMBER(INDEX('Roadmap Calc (Don’t Touch)'!$G$2:$G$151,$AI16)),INDEX('Roadmap Calc (Don’t Touch)'!$G$2:$G$151,$AI16),"")) | F16: =IF($AI16="","",IF(ISNUMBER(INDEX('Roadmap Calc (Don’t Touch)'!$H$2:$H$151,$AI16)),INDEX('Roadmap Calc (Don’t Touch)'!$H$2:$H$151,$AI16),"")) | G16: =IF($AI16="","",INDEX('Roadmap Calc (Don’t Touch)'!$T$2:$T$151,$AI16)) -> 0 | H16: =IF($AI16="","",IF(ISNUMBER(INDEX('Roadmap Calc (Don’t Touch)'!$I$2:$I$151,$AI16)),INDEX('Roadmap Calc (Don’t Touch)'!$I$2:$I$151,$AI16),"")) -> 46419 | I16: =IF($AI16="","",IF(ISNUMBER(INDEX('Roadmap Calc (Don’t Touch)'!$J$2:$J$151,$AI16)),INDEX('Roadmap Calc (Don’t Touch)'!$J$2:$J$151,$AI16),"")) -> 46446 | J16: =IF($AI16="","",IF(AND($AN16<>"",$AN16<=EOMONTH(J$12,0),$AO16>=J$12),IF(AND(INDEX('Roadmap Calc (Don’t Touch)'!$AA$2:$AX$151,$AI16,COLUMN()-COLUMN($J$16)+1)>0,OR($D16="03. UX Discovery",$D16="04. UX Design")),IF(AND($H16<>"",$H16<=EOMONTH(J$12,0),$I16>=J$12),"ALL","PD+UX"),IF(AND($H16<>"",$H16<=EOMONTH(J$12,0),$I16>=J$12),"PD+DEV","PD")),IF(AND(INDEX('Roadmap Calc (Don’t Touch)'!$AA$2:$AX$151,$AI16,COLUMN()-COLUMN($J$16)+1)>0,OR($D16="03. UX Discovery",$D16="04. UX Design")),IF(AND($H16<>"",$H16<=EOMONTH(J$12,0),$I16>=J$12),"UX+DEV","UX"),IF(AND($H16<>"",$H16<=EOMONTH(J$12,0),$I16>=J$12),"DEV","")))) | K16: =IF($AI16="","",IF(AND($AN16<>"",$AN16<=EOMONTH(K$12,0),$AO16>=K$12),IF(AND(INDEX('Roadmap Calc (Don’t Touch)'!$AA$2:$AX$151,$AI16,COLUMN()-COLUMN($J$16)+1)>0,OR($D16="03. UX Discovery",$D16="04. UX Design")),IF(AND($H16<>"",$H16<=EOMONTH(K$12,0),$I16>=K$12),"ALL","PD+UX"),IF(AND($H16<>"",$H16<=EOMONTH(K$12,0),$I16>=K$12),"PD+DEV","PD")),IF(AND(INDEX('Roadmap Calc (Don’t Touch)'!$AA$2:$AX$151,$AI16,COLUMN()-COLUMN($J$16)+1)>0,OR($D16="03. UX Discovery",$D16="04. UX Design")),IF(AND($H16<>"",$H16<=EOMONTH(K$12,0),$I16>=K$12),"UX+DEV","UX"),IF(AND($H16<>"",$H16<=EOMONTH(K$12,0),$I16>=K$12),"DEV","")))) | L16: =IF($AI16="","",IF(AND($AN16<>"",$AN16<=EOMONTH(L$12,0),$AO16>=L$12),IF(AND(INDEX('Roadmap Calc (Don’t Touch)'!$AA$2:$AX$151,$AI16,COLUMN()-COLUMN($J$16)+1)>0,OR($D16="03. UX Discovery",$D16="04. UX Design")),IF(AND($H16<>"",$H16<=EOMONTH(L$12,0),$I16>=L$12),"ALL","PD+UX"),IF(AND($H16<>"",$H16<=EOMONTH(L$12,0),$I16>=L$12),"PD+DEV","PD")),IF(AND(INDEX('Roadmap Calc (Don’t Touch)'!$AA$2:$AX$151,$AI16,COLUMN()-COLUMN($J$16)+1)>0,OR($D16="03. UX Discovery",$D16="04. UX Design")),IF(AND($H16<>"",$H16<=EOMONTH(L$12,0),$I16>=L$12),"UX+DEV","UX"),IF(AND($H16<>"",$H16<=EOMONTH(L$12,0),$I16>=L$12),"DEV","")))) | M16: =IF($AI16="","",IF(AND($AN16<>"",$AN16<=EOMONTH(M$12,0),$AO16>=M$12),IF(AND(INDEX('Roadmap Calc (Don’t Touch)'!$AA$2:$AX$151,$AI16,COLUMN()-COLUMN($J$16)+1)>0,OR($D16="03. UX Discovery",$D16="04. UX Design")),IF(AND($H16<>"",$H16<=EOMONTH(M$12,0),$I16>=M$12),"ALL","PD+UX"),IF(AND($H16<>"",$H16<=EOMONTH(M$12,0),$I16>=M$12),"PD+DEV","PD")),IF(AND(INDEX('Roadmap Calc (Don’t Touch)'!$AA$2:$AX$151,$AI16,COLUMN()-COLUMN($J$16)+1)>0,OR($D16="03. UX Discovery",$D16="04. UX Design")),IF(AND($H16<>"",$H16<=EOMONTH(M$12,0),$I16>=M$12),"UX+DEV","UX"),IF(AND($H16<>"",$H16<=EOMONTH(M$12,0),$I16>=M$12),"DEV","")))) | N16: =IF($AI16="","",IF(AND($AN16<>"",$AN16<=EOMONTH(N$12,0),$AO16>=N$12),IF(AND(INDEX('Roadmap Calc (Don’t Touch)'!$AA$2:$AX$151,$AI16,COLUMN()-COLUMN($J$16)+1)>0,OR($D16="03. UX Discovery",$D16="04. UX Design")),IF(AND($H16<>"",$H16<=EOMONTH(N$12,0),$I16>=N$12),"ALL","PD+UX"),IF(AND($H16<>"",$H16<=EOMONTH(N$12,0),$I16>=N$12),"PD+DEV","PD")),IF(AND(INDEX('Roadmap Calc (Don’t Touch)'!$AA$2:$AX$151,$AI16,COLUMN()-COLUMN($J$16)+1)>0,OR($D16="03. UX Discovery",$D16="04. UX Design")),IF(AND($H16<>"",$H16<=EOMONTH(N$12,0),$I16>=N$12),"UX+DEV","UX"),IF(AND($H16<>"",$H16<=EOMONTH(N$12,0),$I16>=N$12),"DEV","")))) | O16: =IF($AI16="","",IF(AND($AN16<>"",$AN16<=EOMONTH(O$12,0),$AO16>=O$12),IF(AND(INDEX('Roadmap Calc (Don’t Touch)'!$AA$2:$AX$151,$AI16,COLUMN()-COLUMN($J$16)+1)>0,OR($D16="03. UX Discovery",$D16="04. UX Design")),IF(AND($H16<>"",$H16<=EOMONTH(O$12,0),$I16>=O$12),"ALL","PD+UX"),IF(AND($H16<>"",$H16<=EOMONTH(O$12,0),$I16>=O$12),"PD+DEV","PD")),IF(AND(INDEX('Roadmap Calc (Don’t Touch)'!$AA$2:$AX$151,$AI16,COLUMN()-COLUMN($J$16)+1)>0,OR($D16="03. UX Discovery",$D16="04. UX Design")),IF(AND($H16<>"",$H16<=EOMONTH(O$12,0),$I16>=O$12),"UX+DEV","UX"),IF(AND($H16<>"",$H16<=EOMONTH(O$12,0),$I16>=O$12),"DEV","")))) | P16: =IF($AI16="","",IF(AND($AN16<>"",$AN16<=EOMONTH(P$12,0),$AO16>=P$12),IF(AND(INDEX('Roadmap Calc (Don’t Touch)'!$AA$2:$AX$151,$AI16,COLUMN()-COLUMN($J$16)+1)>0,OR($D16="03. UX Discovery",$D16="04. UX Design")),IF(AND($H16<>"",$H16<=EOMONTH(P$12,0),$I16>=P$12),"ALL","PD+UX"),IF(AND($H16<>"",$H16<=EOMONTH(P$12,0),$I16>=P$12),"PD+DEV","PD")),IF(AND(INDEX('Roadmap Calc (Don’t Touch)'!$AA$2:$AX$151,$AI16,COLUMN()-COLUMN($J$16)+1)>0,OR($D16="03. UX Discovery",$D16="04. UX Design")),IF(AND($H16<>"",$H16<=EOMONTH(P$12,0),$I16>=P$12),"UX+DEV","UX"),IF(AND($H16<>"",$H16<=EOMONTH(P$12,0),$I16>=P$12),"DEV","")))) | Q16: =IF($AI16="","",IF(AND($AN16<>"",$AN16<=EOMONTH(Q$12,0),$AO16>=Q$12),IF(AND(INDEX('Roadmap Calc (Don’t Touch)'!$AA$2:$AX$151,$AI16,COLUMN()-COLUMN($J$16)+1)>0,OR($D16="03. UX Discovery",$D16="04. UX Design")),IF(AND($H16<>"",$H16<=EOMONTH(Q$12,0),$I16>=Q$12),"ALL","PD+UX"),IF(AND($H16<>"",$H16<=EOMONTH(Q$12,0),$I16>=Q$12),"PD+DEV","PD")),IF(AND(INDEX('Roadmap Calc (Don’t Touch)'!$AA$2:$AX$151,$AI16,COLUMN()-COLUMN($J$16)+1)>0,OR($D16="03. UX Discovery",$D16="04. UX Design")),IF(AND($H16<>"",$H16<=EOMONTH(Q$12,0),$I16>=Q$12),"UX+DEV","UX"),IF(AND($H16<>"",$H16<=EOMONTH(Q$12,0),$I16>=Q$12),"DEV","")))) | ... AG16: =IF($AI16="","",IF(AND($AN16<>"",$AN16<=EOMONTH(AG$12,0),$AO16>=AG$12),IF(AND(INDEX('Roadmap Calc (Don’t Touch)'!$AA$2:$AX$151,$AI16,COLUMN()-COLUMN($J$16)+1)>0,OR($D16="03. UX Discovery",$D16="04. UX Design")),IF(AND($H16<>"",$H16<=EOMONTH(AG$12,0),$I16>=AG$12),"ALL","PD+UX"),IF(AND($H16<>"",$H16<=EOMONTH(AG$12,0),$I16>=AG$12),"PD+DEV","PD")),IF(AND(INDEX('Roadmap Calc (Don’t Touch)'!$AA$2:$AX$151,$AI16,COLUMN()-COLUMN($J$16)+1)>0,OR($D16="03. UX Discovery",$D16="04. UX Design")),IF(AND($H16<>"",$H16<=EOMONTH(AG$12,0),$I16>=AG$12),"UX+DEV","UX"),IF(AND($H16<>"",$H16<=EOMONTH(AG$12,0),$I16>=AG$12),"DEV","")))) | AH16: =IF($AI16="","",INDEX('Roadmap Calc (Don’t Touch)'!$D$2:$D$151,$AI16)) -> Increase Trade In Awareness | AI16: =IFERROR(MATCH(1,'Roadmap Calc (Don’t Touch)'!$O$2:$O$151,0),"") -> 7 | AK16: =IF(COUNTA(Control!E14)=0,"",Control!E14) -> Increase Trust & Condition Transparency | AL16: =IF(COUNTA(Control!B14)=0,"",Control!B14) -> 08. Ready for Dev | AN16: =IF($AI16="","",IF(ISNUMBER(INDEX('Roadmap Calc (Don’t Touch)'!$BB$2:$BB$151,$AI16)),INDEX('Roadmap Calc (Don’t Touch)'!$BB$2:$BB$151,$AI16),"")) | AO16: =IF($AI16="","",IF(ISNUMBER(INDEX('Roadmap Calc (Don’t Touch)'!$BC$2:$BC$151,$AI16)),INDEX('Roadmap Calc (Don’t Touch)'!$BC$2:$BC$151,$AI16),""))
A17: =IF($AI17="","",IF($AH17=$AH16,"",IF(INDEX('Roadmap Calc (Don’t Touch)'!$U$2:$U$151,$AI17)=0,$AH17,HYPERLINK("#'Control (Don’t Touch)'!E"&INDEX('Roadmap Calc (Don’t Touch)'!$U$2:$U$151,$AI17),$AH17)))) | B17: =IF($AI17="","",IF(INDEX('Roadmap Calc (Don’t Touch)'!$K$2:$K$151,$AI17)="",INDEX('Roadmap Calc (Don’t Touch)'!$B$2:$B$151,$AI17),HYPERLINK("https://jira.bnh.com/browse/"&INDEX('Roadmap Calc (Don’t Touch)'!$K$2:$K$151,$AI17),INDEX('Roadmap Calc (Don’t Touch)'!$B$2:$B$151,$AI17)))) -> Sell Used Mega Menu | C17: =IF($AI17="","",IF(INDEX('Roadmap Calc (Don’t Touch)'!$E$2:$E$151,$AI17)="","",HYPERLINK("https://jira.bnh.com/browse/"&INDEX('Roadmap Calc (Don’t Touch)'!$E$2:$E$151,$AI17),INDEX('Roadmap Calc (Don’t Touch)'!$E$2:$E$151,$AI17)))) -> BHP-7430 | D17: =IF($AI17="","",INDEX('Roadmap Calc (Don’t Touch)'!$F$2:$F$151,$AI17)) -> 01. Prod Discovery | E17: =IF($AI17="","",IF(ISNUMBER(INDEX('Roadmap Calc (Don’t Touch)'!$G$2:$G$151,$AI17)),INDEX('Roadmap Calc (Don’t Touch)'!$G$2:$G$151,$AI17),"")) -> 46286 | F17: =IF($AI17="","",IF(ISNUMBER(INDEX('Roadmap Calc (Don’t Touch)'!$H$2:$H$151,$AI17)),INDEX('Roadmap Calc (Don’t Touch)'!$H$2:$H$151,$AI17),"")) -> 46293 | G17: =IF($AI17="","",INDEX('Roadmap Calc (Don’t Touch)'!$T$2:$T$151,$AI17)) -> 2 | H17: =IF($AI17="","",IF(ISNUMBER(INDEX('Roadmap Calc (Don’t Touch)'!$I$2:$I$151,$AI17)),INDEX('Roadmap Calc (Don’t Touch)'!$I$2:$I$151,$AI17),"")) | I17: =IF($AI17="","",IF(ISNUMBER(INDEX('Roadmap Calc (Don’t Touch)'!$J$2:$J$151,$AI17)),INDEX('Roadmap Calc (Don’t Touch)'!$J$2:$J$151,$AI17),"")) | J17: =IF($AI17="","",IF(AND($AN17<>"",$AN17<=EOMONTH(J$12,0),$AO17>=J$12),IF(AND(INDEX('Roadmap Calc (Don’t Touch)'!$AA$2:$AX$151,$AI17,COLUMN()-COLUMN($J$16)+1)>0,OR($D17="03. UX Discovery",$D17="04. UX Design")),IF(AND($H17<>"",$H17<=EOMONTH(J$12,0),$I17>=J$12),"ALL","PD+UX"),IF(AND($H17<>"",$H17<=EOMONTH(J$12,0),$I17>=J$12),"PD+DEV","PD")),IF(AND(INDEX('Roadmap Calc (Don’t Touch)'!$AA$2:$AX$151,$AI17,COLUMN()-COLUMN($J$16)+1)>0,OR($D17="03. UX Discovery",$D17="04. UX Design")),IF(AND($H17<>"",$H17<=EOMONTH(J$12,0),$I17>=J$12),"UX+DEV","UX"),IF(AND($H17<>"",$H17<=EOMONTH(J$12,0),$I17>=J$12),"DEV","")))) | K17: =IF($AI17="","",IF(AND($AN17<>"",$AN17<=EOMONTH(K$12,0),$AO17>=K$12),IF(AND(INDEX('Roadmap Calc (Don’t Touch)'!$AA$2:$AX$151,$AI17,COLUMN()-COLUMN($J$16)+1)>0,OR($D17="03. UX Discovery",$D17="04. UX Design")),IF(AND($H17<>"",$H17<=EOMONTH(K$12,0),$I17>=K$12),"ALL","PD+UX"),IF(AND($H17<>"",$H17<=EOMONTH(K$12,0),$I17>=K$12),"PD+DEV","PD")),IF(AND(INDEX('Roadmap Calc (Don’t Touch)'!$AA$2:$AX$151,$AI17,COLUMN()-COLUMN($J$16)+1)>0,OR($D17="03. UX Discovery",$D17="04. UX Design")),IF(AND($H17<>"",$H17<=EOMONTH(K$12,0),$I17>=K$12),"UX+DEV","UX"),IF(AND($H17<>"",$H17<=EOMONTH(K$12,0),$I17>=K$12),"DEV","")))) | L17: =IF($AI17="","",IF(AND($AN17<>"",$AN17<=EOMONTH(L$12,0),$AO17>=L$12),IF(AND(INDEX('Roadmap Calc (Don’t Touch)'!$AA$2:$AX$151,$AI17,COLUMN()-COLUMN($J$16)+1)>0,OR($D17="03. UX Discovery",$D17="04. UX Design")),IF(AND($H17<>"",$H17<=EOMONTH(L$12,0),$I17>=L$12),"ALL","PD+UX"),IF(AND($H17<>"",$H17<=EOMONTH(L$12,0),$I17>=L$12),"PD+DEV","PD")),IF(AND(INDEX('Roadmap Calc (Don’t Touch)'!$AA$2:$AX$151,$AI17,COLUMN()-COLUMN($J$16)+1)>0,OR($D17="03. UX Discovery",$D17="04. UX Design")),IF(AND($H17<>"",$H17<=EOMONTH(L$12,0),$I17>=L$12),"UX+DEV","UX"),IF(AND($H17<>"",$H17<=EOMONTH(L$12,0),$I17>=L$12),"DEV","")))) | M17: =IF($AI17="","",IF(AND($AN17<>"",$AN17<=EOMONTH(M$12,0),$AO17>=M$12),IF(AND(INDEX('Roadmap Calc (Don’t Touch)'!$AA$2:$AX$151,$AI17,COLUMN()-COLUMN($J$16)+1)>0,OR($D17="03. UX Discovery",$D17="04. UX Design")),IF(AND($H17<>"",$H17<=EOMONTH(M$12,0),$I17>=M$12),"ALL","PD+UX"),IF(AND($H17<>"",$H17<=EOMONTH(M$12,0),$I17>=M$12),"PD+DEV","PD")),IF(AND(INDEX('Roadmap Calc (Don’t Touch)'!$AA$2:$AX$151,$AI17,COLUMN()-COLUMN($J$16)+1)>0,OR($D17="03. UX Discovery",$D17="04. UX Design")),IF(AND($H17<>"",$H17<=EOMONTH(M$12,0),$I17>=M$12),"UX+DEV","UX"),IF(AND($H17<>"",$H17<=EOMONTH(M$12,0),$I17>=M$12),"DEV","")))) | N17: =IF($AI17="","",IF(AND($AN17<>"",$AN17<=EOMONTH(N$12,0),$AO17>=N$12),IF(AND(INDEX('Roadmap Calc (Don’t Touch)'!$AA$2:$AX$151,$AI17,COLUMN()-COLUMN($J$16)+1)>0,OR($D17="03. UX Discovery",$D17="04. UX Design")),IF(AND($H17<>"",$H17<=EOMONTH(N$12,0),$I17>=N$12),"ALL","PD+UX"),IF(AND($H17<>"",$H17<=EOMONTH(N$12,0),$I17>=N$12),"PD+DEV","PD")),IF(AND(INDEX('Roadmap Calc (Don’t Touch)'!$AA$2:$AX$151,$AI17,COLUMN()-COLUMN($J$16)+1)>0,OR($D17="03. UX Discovery",$D17="04. UX Design")),IF(AND($H17<>"",$H17<=EOMONTH(N$12,0),$I17>=N$12),"UX+DEV","UX"),IF(AND($H17<>"",$H17<=EOMONTH(N$12,0),$I17>=N$12),"DEV","")))) | O17: =IF($AI17="","",IF(AND($AN17<>"",$AN17<=EOMONTH(O$12,0),$AO17>=O$12),IF(AND(INDEX('Roadmap Calc (Don’t Touch)'!$AA$2:$AX$151,$AI17,COLUMN()-COLUMN($J$16)+1)>0,OR($D17="03. UX Discovery",$D17="04. UX Design")),IF(AND($H17<>"",$H17<=EOMONTH(O$12,0),$I17>=O$12),"ALL","PD+UX"),IF(AND($H17<>"",$H17<=EOMONTH(O$12,0),$I17>=O$12),"PD+DEV","PD")),IF(AND(INDEX('Roadmap Calc (Don’t Touch)'!$AA$2:$AX$151,$AI17,COLUMN()-COLUMN($J$16)+1)>0,OR($D17="03. UX Discovery",$D17="04. UX Design")),IF(AND($H17<>"",$H17<=EOMONTH(O$12,0),$I17>=O$12),"UX+DEV","UX"),IF(AND($H17<>"",$H17<=EOMONTH(O$12,0),$I17>=O$12),"DEV","")))) | P17: =IF($AI17="","",IF(AND($AN17<>"",$AN17<=EOMONTH(P$12,0),$AO17>=P$12),IF(AND(INDEX('Roadmap Calc (Don’t Touch)'!$AA$2:$AX$151,$AI17,COLUMN()-COLUMN($J$16)+1)>0,OR($D17="03. UX Discovery",$D17="04. UX Design")),IF(AND($H17<>"",$H17<=EOMONTH(P$12,0),$I17>=P$12),"ALL","PD+UX"),IF(AND($H17<>"",$H17<=EOMONTH(P$12,0),$I17>=P$12),"PD+DEV","PD")),IF(AND(INDEX('Roadmap Calc (Don’t Touch)'!$AA$2:$AX$151,$AI17,COLUMN()-COLUMN($J$16)+1)>0,OR($D17="03. UX Discovery",$D17="04. UX Design")),IF(AND($H17<>"",$H17<=EOMONTH(P$12,0),$I17>=P$12),"UX+DEV","UX"),IF(AND($H17<>"",$H17<=EOMONTH(P$12,0),$I17>=P$12),"DEV","")))) | Q17: =IF($AI17="","",IF(AND($AN17<>"",$AN17<=EOMONTH(Q$12,0),$AO17>=Q$12),IF(AND(INDEX('Roadmap Calc (Don’t Touch)'!$AA$2:$AX$151,$AI17,COLUMN()-COLUMN($J$16)+1)>0,OR($D17="03. UX Discovery",$D17="04. UX Design")),IF(AND($H17<>"",$H17<=EOMONTH(Q$12,0),$I17>=Q$12),"ALL","PD+UX"),IF(AND($H17<>"",$H17<=EOMONTH(Q$12,0),$I17>=Q$12),"PD+DEV","PD")),IF(AND(INDEX('Roadmap Calc (Don’t Touch)'!$AA$2:$AX$151,$AI17,COLUMN()-COLUMN($J$16)+1)>0,OR($D17="03. UX Discovery",$D17="04. UX Design")),IF(AND($H17<>"",$H17<=EOMONTH(Q$12,0),$I17>=Q$12),"UX+DEV","UX"),IF(AND($H17<>"",$H17<=EOMONTH(Q$12,0),$I17>=Q$12),"DEV","")))) | ... AG17: =IF($AI17="","",IF(AND($AN17<>"",$AN17<=EOMONTH(AG$12,0),$AO17>=AG$12),IF(AND(INDEX('Roadmap Calc (Don’t Touch)'!$AA$2:$AX$151,$AI17,COLUMN()-COLUMN($J$16)+1)>0,OR($D17="03. UX Discovery",$D17="04. UX Design")),IF(AND($H17<>"",$H17<=EOMONTH(AG$12,0),$I17>=AG$12),"ALL","PD+UX"),IF(AND($H17<>"",$H17<=EOMONTH(AG$12,0),$I17>=AG$12),"PD+DEV","PD")),IF(AND(INDEX('Roadmap Calc (Don’t Touch)'!$AA$2:$AX$151,$AI17,COLUMN()-COLUMN($J$16)+1)>0,OR($D17="03. UX Discovery",$D17="04. UX Design")),IF(AND($H17<>"",$H17<=EOMONTH(AG$12,0),$I17>=AG$12),"UX+DEV","UX"),IF(AND($H17<>"",$H17<=EOMONTH(AG$12,0),$I17>=AG$12),"DEV","")))) | AH17: =IF($AI17="","",INDEX('Roadmap Calc (Don’t Touch)'!$D$2:$D$151,$AI17)) -> Increase Trade In Awareness | AI17: =IFERROR(MATCH(2,'Roadmap Calc (Don’t Touch)'!$O$2:$O$151,0),"") -> 8 | AK17: =IF(COUNTA(Control!E15)=0,"",Control!E15) -> Improve Search & Findability | AL17: =IF(COUNTA(Control!B15)=0,"",Control!B15) -> 09. In Dev | AN17: =IF($AI17="","",IF(ISNUMBER(INDEX('Roadmap Calc (Don’t Touch)'!$BB$2:$BB$151,$AI17)),INDEX('Roadmap Calc (Don’t Touch)'!$BB$2:$BB$151,$AI17),"")) | AO17: =IF($AI17="","",IF(ISNUMBER(INDEX('Roadmap Calc (Don’t Touch)'!$BC$2:$BC$151,$AI17)),INDEX('Roadmap Calc (Don’t Touch)'!$BC$2:$BC$151,$AI17),""))
A18: =IF($AI18="","",IF($AH18=$AH17,"",IF(INDEX('Roadmap Calc (Don’t Touch)'!$U$2:$U$151,$AI18)=0,$AH18,HYPERLINK("#'Control (Don’t Touch)'!E"&INDEX('Roadmap Calc (Don’t Touch)'!$U$2:$U$151,$AI18),$AH18)))) | B18: =IF($AI18="","",IF(INDEX('Roadmap Calc (Don’t Touch)'!$K$2:$K$151,$AI18)="",INDEX('Roadmap Calc (Don’t Touch)'!$B$2:$B$151,$AI18),HYPERLINK("https://jira.bnh.com/browse/"&INDEX('Roadmap Calc (Don’t Touch)'!$K$2:$K$151,$AI18),INDEX('Roadmap Calc (Don’t Touch)'!$B$2:$B$151,$AI18)))) -> Used Activity Notification | C18: =IF($AI18="","",IF(INDEX('Roadmap Calc (Don’t Touch)'!$E$2:$E$151,$AI18)="","",HYPERLINK("https://jira.bnh.com/browse/"&INDEX('Roadmap Calc (Don’t Touch)'!$E$2:$E$151,$AI18),INDEX('Roadmap Calc (Don’t Touch)'!$E$2:$E$151,$AI18)))) -> BHP-7237 | D18: =IF($AI18="","",INDEX('Roadmap Calc (Don’t Touch)'!$F$2:$F$151,$AI18)) -> 02. UX Req | E18: =IF($AI18="","",IF(ISNUMBER(INDEX('Roadmap Calc (Don’t Touch)'!$G$2:$G$151,$AI18)),INDEX('Roadmap Calc (Don’t Touch)'!$G$2:$G$151,$AI18),"")) -> 46279 | F18: =IF($AI18="","",IF(ISNUMBER(INDEX('Roadmap Calc (Don’t Touch)'!$H$2:$H$151,$AI18)),INDEX('Roadmap Calc (Don’t Touch)'!$H$2:$H$151,$AI18),"")) -> 46293 | G18: =IF($AI18="","",INDEX('Roadmap Calc (Don’t Touch)'!$T$2:$T$151,$AI18)) -> 3 | H18: =IF($AI18="","",IF(ISNUMBER(INDEX('Roadmap Calc (Don’t Touch)'!$I$2:$I$151,$AI18)),INDEX('Roadmap Calc (Don’t Touch)'!$I$2:$I$151,$AI18),"")) -> 46357 | I18: =IF($AI18="","",IF(ISNUMBER(INDEX('Roadmap Calc (Don’t Touch)'!$J$2:$J$151,$AI18)),INDEX('Roadmap Calc (Don’t Touch)'!$J$2:$J$151,$AI18),"")) -> 46418 | J18: =IF($AI18="","",IF(AND($AN18<>"",$AN18<=EOMONTH(J$12,0),$AO18>=J$12),IF(AND(INDEX('Roadmap Calc (Don’t Touch)'!$AA$2:$AX$151,$AI18,COLUMN()-COLUMN($J$16)+1)>0,OR($D18="03. UX Discovery",$D18="04. UX Design")),IF(AND($H18<>"",$H18<=EOMONTH(J$12,0),$I18>=J$12),"ALL","PD+UX"),IF(AND($H18<>"",$H18<=EOMONTH(J$12,0),$I18>=J$12),"PD+DEV","PD")),IF(AND(INDEX('Roadmap Calc (Don’t Touch)'!$AA$2:$AX$151,$AI18,COLUMN()-COLUMN($J$16)+1)>0,OR($D18="03. UX Discovery",$D18="04. UX Design")),IF(AND($H18<>"",$H18<=EOMONTH(J$12,0),$I18>=J$12),"UX+DEV","UX"),IF(AND($H18<>"",$H18<=EOMONTH(J$12,0),$I18>=J$12),"DEV","")))) | K18: =IF($AI18="","",IF(AND($AN18<>"",$AN18<=EOMONTH(K$12,0),$AO18>=K$12),IF(AND(INDEX('Roadmap Calc (Don’t Touch)'!$AA$2:$AX$151,$AI18,COLUMN()-COLUMN($J$16)+1)>0,OR($D18="03. UX Discovery",$D18="04. UX Design")),IF(AND($H18<>"",$H18<=EOMONTH(K$12,0),$I18>=K$12),"ALL","PD+UX"),IF(AND($H18<>"",$H18<=EOMONTH(K$12,0),$I18>=K$12),"PD+DEV","PD")),IF(AND(INDEX('Roadmap Calc (Don’t Touch)'!$AA$2:$AX$151,$AI18,COLUMN()-COLUMN($J$16)+1)>0,OR($D18="03. UX Discovery",$D18="04. UX Design")),IF(AND($H18<>"",$H18<=EOMONTH(K$12,0),$I18>=K$12),"UX+DEV","UX"),IF(AND($H18<>"",$H18<=EOMONTH(K$12,0),$I18>=K$12),"DEV","")))) | L18: =IF($AI18="","",IF(AND($AN18<>"",$AN18<=EOMONTH(L$12,0),$AO18>=L$12),IF(AND(INDEX('Roadmap Calc (Don’t Touch)'!$AA$2:$AX$151,$AI18,COLUMN()-COLUMN($J$16)+1)>0,OR($D18="03. UX Discovery",$D18="04. UX Design")),IF(AND($H18<>"",$H18<=EOMONTH(L$12,0),$I18>=L$12),"ALL","PD+UX"),IF(AND($H18<>"",$H18<=EOMONTH(L$12,0),$I18>=L$12),"PD+DEV","PD")),IF(AND(INDEX('Roadmap Calc (Don’t Touch)'!$AA$2:$AX$151,$AI18,COLUMN()-COLUMN($J$16)+1)>0,OR($D18="03. UX Discovery",$D18="04. UX Design")),IF(AND($H18<>"",$H18<=EOMONTH(L$12,0),$I18>=L$12),"UX+DEV","UX"),IF(AND($H18<>"",$H18<=EOMONTH(L$12,0),$I18>=L$12),"DEV","")))) | M18: =IF($AI18="","",IF(AND($AN18<>"",$AN18<=EOMONTH(M$12,0),$AO18>=M$12),IF(AND(INDEX('Roadmap Calc (Don’t Touch)'!$AA$2:$AX$151,$AI18,COLUMN()-COLUMN($J$16)+1)>0,OR($D18="03. UX Discovery",$D18="04. UX Design")),IF(AND($H18<>"",$H18<=EOMONTH(M$12,0),$I18>=M$12),"ALL","PD+UX"),IF(AND($H18<>"",$H18<=EOMONTH(M$12,0),$I18>=M$12),"PD+DEV","PD")),IF(AND(INDEX('Roadmap Calc (Don’t Touch)'!$AA$2:$AX$151,$AI18,COLUMN()-COLUMN($J$16)+1)>0,OR($D18="03. UX Discovery",$D18="04. UX Design")),IF(AND($H18<>"",$H18<=EOMONTH(M$12,0),$I18>=M$12),"UX+DEV","UX"),IF(AND($H18<>"",$H18<=EOMONTH(M$12,0),$I18>=M$12),"DEV","")))) | N18: =IF($AI18="","",IF(AND($AN18<>"",$AN18<=EOMONTH(N$12,0),$AO18>=N$12),IF(AND(INDEX('Roadmap Calc (Don’t Touch)'!$AA$2:$AX$151,$AI18,COLUMN()-COLUMN($J$16)+1)>0,OR($D18="03. UX Discovery",$D18="04. UX Design")),IF(AND($H18<>"",$H18<=EOMONTH(N$12,0),$I18>=N$12),"ALL","PD+UX"),IF(AND($H18<>"",$H18<=EOMONTH(N$12,0),$I18>=N$12),"PD+DEV","PD")),IF(AND(INDEX('Roadmap Calc (Don’t Touch)'!$AA$2:$AX$151,$AI18,COLUMN()-COLUMN($J$16)+1)>0,OR($D18="03. UX Discovery",$D18="04. UX Design")),IF(AND($H18<>"",$H18<=EOMONTH(N$12,0),$I18>=N$12),"UX+DEV","UX"),IF(AND($H18<>"",$H18<=EOMONTH(N$12,0),$I18>=N$12),"DEV","")))) | O18: =IF($AI18="","",IF(AND($AN18<>"",$AN18<=EOMONTH(O$12,0),$AO18>=O$12),IF(AND(INDEX('Roadmap Calc (Don’t Touch)'!$AA$2:$AX$151,$AI18,COLUMN()-COLUMN($J$16)+1)>0,OR($D18="03. UX Discovery",$D18="04. UX Design")),IF(AND($H18<>"",$H18<=EOMONTH(O$12,0),$I18>=O$12),"ALL","PD+UX"),IF(AND($H18<>"",$H18<=EOMONTH(O$12,0),$I18>=O$12),"PD+DEV","PD")),IF(AND(INDEX('Roadmap Calc (Don’t Touch)'!$AA$2:$AX$151,$AI18,COLUMN()-COLUMN($J$16)+1)>0,OR($D18="03. UX Discovery",$D18="04. UX Design")),IF(AND($H18<>"",$H18<=EOMONTH(O$12,0),$I18>=O$12),"UX+DEV","UX"),IF(AND($H18<>"",$H18<=EOMONTH(O$12,0),$I18>=O$12),"DEV","")))) | P18: =IF($AI18="","",IF(AND($AN18<>"",$AN18<=EOMONTH(P$12,0),$AO18>=P$12),IF(AND(INDEX('Roadmap Calc (Don’t Touch)'!$AA$2:$AX$151,$AI18,COLUMN()-COLUMN($J$16)+1)>0,OR($D18="03. UX Discovery",$D18="04. UX Design")),IF(AND($H18<>"",$H18<=EOMONTH(P$12,0),$I18>=P$12),"ALL","PD+UX"),IF(AND($H18<>"",$H18<=EOMONTH(P$12,0),$I18>=P$12),"PD+DEV","PD")),IF(AND(INDEX('Roadmap Calc (Don’t Touch)'!$AA$2:$AX$151,$AI18,COLUMN()-COLUMN($J$16)+1)>0,OR($D18="03. UX Discovery",$D18="04. UX Design")),IF(AND($H18<>"",$H18<=EOMONTH(P$12,0),$I18>=P$12),"UX+DEV","UX"),IF(AND($H18<>"",$H18<=EOMONTH(P$12,0),$I18>=P$12),"DEV","")))) | Q18: =IF($AI18="","",IF(AND($AN18<>"",$AN18<=EOMONTH(Q$12,0),$AO18>=Q$12),IF(AND(INDEX('Roadmap Calc (Don’t Touch)'!$AA$2:$AX$151,$AI18,COLUMN()-COLUMN($J$16)+1)>0,OR($D18="03. UX Discovery",$D18="04. UX Design")),IF(AND($H18<>"",$H18<=EOMONTH(Q$12,0),$I18>=Q$12),"ALL","PD+UX"),IF(AND($H18<>"",$H18<=EOMONTH(Q$12,0),$I18>=Q$12),"PD+DEV","PD")),IF(AND(INDEX('Roadmap Calc (Don’t Touch)'!$AA$2:$AX$151,$AI18,COLUMN()-COLUMN($J$16)+1)>0,OR($D18="03. UX Discovery",$D18="04. UX Design")),IF(AND($H18<>"",$H18<=EOMONTH(Q$12,0),$I18>=Q$12),"UX+DEV","UX"),IF(AND($H18<>"",$H18<=EOMONTH(Q$12,0),$I18>=Q$12),"DEV","")))) | ... AG18: =IF($AI18="","",IF(AND($AN18<>"",$AN18<=EOMONTH(AG$12,0),$AO18>=AG$12),IF(AND(INDEX('Roadmap Calc (Don’t Touch)'!$AA$2:$AX$151,$AI18,COLUMN()-COLUMN($J$16)+1)>0,OR($D18="03. UX Discovery",$D18="04. UX Design")),IF(AND($H18<>"",$H18<=EOMONTH(AG$12,0),$I18>=AG$12),"ALL","PD+UX"),IF(AND($H18<>"",$H18<=EOMONTH(AG$12,0),$I18>=AG$12),"PD+DEV","PD")),IF(AND(INDEX('Roadmap Calc (Don’t Touch)'!$AA$2:$AX$151,$AI18,COLUMN()-COLUMN($J$16)+1)>0,OR($D18="03. UX Discovery",$D18="04. UX Design")),IF(AND($H18<>"",$H18<=EOMONTH(AG$12,0),$I18>=AG$12),"UX+DEV","UX"),IF(AND($H18<>"",$H18<=EOMONTH(AG$12,0),$I18>=AG$12),"DEV","")))) | AH18: =IF($AI18="","",INDEX('Roadmap Calc (Don’t Touch)'!$D$2:$D$151,$AI18)) -> Increase Trade In Awareness | AI18: =IFERROR(MATCH(3,'Roadmap Calc (Don’t Touch)'!$O$2:$O$151,0),"") -> 11 | AK18: =IF(COUNTA(Control!E16)=0,"",Control!E16) | AL18: =IF(COUNTA(Control!B16)=0,"",Control!B16) -> 10. QA | AN18: =IF($AI18="","",IF(ISNUMBER(INDEX('Roadmap Calc (Don’t Touch)'!$BB$2:$BB$151,$AI18)),INDEX('Roadmap Calc (Don’t Touch)'!$BB$2:$BB$151,$AI18),"")) | AO18: =IF($AI18="","",IF(ISNUMBER(INDEX('Roadmap Calc (Don’t Touch)'!$BC$2:$BC$151,$AI18)),INDEX('Roadmap Calc (Don’t Touch)'!$BC$2:$BC$151,$AI18),""))
A19: =IF($AI19="","",IF($AH19=$AH18,"",IF(INDEX('Roadmap Calc (Don’t Touch)'!$U$2:$U$151,$AI19)=0,$AH19,HYPERLINK("#'Control (Don’t Touch)'!E"&INDEX('Roadmap Calc (Don’t Touch)'!$U$2:$U$151,$AI19),$AH19)))) | B19: =IF($AI19="","",IF(INDEX('Roadmap Calc (Don’t Touch)'!$K$2:$K$151,$AI19)="",INDEX('Roadmap Calc (Don’t Touch)'!$B$2:$B$151,$AI19),HYPERLINK("https://jira.bnh.com/browse/"&INDEX('Roadmap Calc (Don’t Touch)'!$K$2:$K$151,$AI19),INDEX('Roadmap Calc (Don’t Touch)'!$B$2:$B$151,$AI19)))) -> Increase Awareness of Trade In Offers - Best Buy Inspiration/Competitive Effort | C19: =IF($AI19="","",IF(INDEX('Roadmap Calc (Don’t Touch)'!$E$2:$E$151,$AI19)="","",HYPERLINK("https://jira.bnh.com/browse/"&INDEX('Roadmap Calc (Don’t Touch)'!$E$2:$E$151,$AI19),INDEX('Roadmap Calc (Don’t Touch)'!$E$2:$E$151,$AI19)))) -> BHP-6827 | D19: =IF($AI19="","",INDEX('Roadmap Calc (Don’t Touch)'!$F$2:$F$151,$AI19)) -> 03. UX Discovery | E19: =IF($AI19="","",IF(ISNUMBER(INDEX('Roadmap Calc (Don’t Touch)'!$G$2:$G$151,$AI19)),INDEX('Roadmap Calc (Don’t Touch)'!$G$2:$G$151,$AI19),"")) | F19: =IF($AI19="","",IF(ISNUMBER(INDEX('Roadmap Calc (Don’t Touch)'!$H$2:$H$151,$AI19)),INDEX('Roadmap Calc (Don’t Touch)'!$H$2:$H$151,$AI19),"")) | G19: =IF($AI19="","",INDEX('Roadmap Calc (Don’t Touch)'!$T$2:$T$151,$AI19)) -> 0 | H19: =IF($AI19="","",IF(ISNUMBER(INDEX('Roadmap Calc (Don’t Touch)'!$I$2:$I$151,$AI19)),INDEX('Roadmap Calc (Don’t Touch)'!$I$2:$I$151,$AI19),"")) -> 46296 | I19: =IF($AI19="","",IF(ISNUMBER(INDEX('Roadmap Calc (Don’t Touch)'!$J$2:$J$151,$AI19)),INDEX('Roadmap Calc (Don’t Touch)'!$J$2:$J$151,$AI19),"")) -> 46326 | J19: =IF($AI19="","",IF(AND($AN19<>"",$AN19<=EOMONTH(J$12,0),$AO19>=J$12),IF(AND(INDEX('Roadmap Calc (Don’t Touch)'!$AA$2:$AX$151,$AI19,COLUMN()-COLUMN($J$16)+1)>0,OR($D19="03. UX Discovery",$D19="04. UX Design")),IF(AND($H19<>"",$H19<=EOMONTH(J$12,0),$I19>=J$12),"ALL","PD+UX"),IF(AND($H19<>"",$H19<=EOMONTH(J$12,0),$I19>=J$12),"PD+DEV","PD")),IF(AND(INDEX('Roadmap Calc (Don’t Touch)'!$AA$2:$AX$151,$AI19,COLUMN()-COLUMN($J$16)+1)>0,OR($D19="03. UX Discovery",$D19="04. UX Design")),IF(AND($H19<>"",$H19<=EOMONTH(J$12,0),$I19>=J$12),"UX+DEV","UX"),IF(AND($H19<>"",$H19<=EOMONTH(J$12,0),$I19>=J$12),"DEV","")))) | K19: =IF($AI19="","",IF(AND($AN19<>"",$AN19<=EOMONTH(K$12,0),$AO19>=K$12),IF(AND(INDEX('Roadmap Calc (Don’t Touch)'!$AA$2:$AX$151,$AI19,COLUMN()-COLUMN($J$16)+1)>0,OR($D19="03. UX Discovery",$D19="04. UX Design")),IF(AND($H19<>"",$H19<=EOMONTH(K$12,0),$I19>=K$12),"ALL","PD+UX"),IF(AND($H19<>"",$H19<=EOMONTH(K$12,0),$I19>=K$12),"PD+DEV","PD")),IF(AND(INDEX('Roadmap Calc (Don’t Touch)'!$AA$2:$AX$151,$AI19,COLUMN()-COLUMN($J$16)+1)>0,OR($D19="03. UX Discovery",$D19="04. UX Design")),IF(AND($H19<>"",$H19<=EOMONTH(K$12,0),$I19>=K$12),"UX+DEV","UX"),IF(AND($H19<>"",$H19<=EOMONTH(K$12,0),$I19>=K$12),"DEV","")))) | L19: =IF($AI19="","",IF(AND($AN19<>"",$AN19<=EOMONTH(L$12,0),$AO19>=L$12),IF(AND(INDEX('Roadmap Calc (Don’t Touch)'!$AA$2:$AX$151,$AI19,COLUMN()-COLUMN($J$16)+1)>0,OR($D19="03. UX Discovery",$D19="04. UX Design")),IF(AND($H19<>"",$H19<=EOMONTH(L$12,0),$I19>=L$12),"ALL","PD+UX"),IF(AND($H19<>"",$H19<=EOMONTH(L$12,0),$I19>=L$12),"PD+DEV","PD")),IF(AND(INDEX('Roadmap Calc (Don’t Touch)'!$AA$2:$AX$151,$AI19,COLUMN()-COLUMN($J$16)+1)>0,OR($D19="03. UX Discovery",$D19="04. UX Design")),IF(AND($H19<>"",$H19<=EOMONTH(L$12,0),$I19>=L$12),"UX+DEV","UX"),IF(AND($H19<>"",$H19<=EOMONTH(L$12,0),$I19>=L$12),"DEV","")))) | M19: =IF($AI19="","",IF(AND($AN19<>"",$AN19<=EOMONTH(M$12,0),$AO19>=M$12),IF(AND(INDEX('Roadmap Calc (Don’t Touch)'!$AA$2:$AX$151,$AI19,COLUMN()-COLUMN($J$16)+1)>0,OR($D19="03. UX Discovery",$D19="04. UX Design")),IF(AND($H19<>"",$H19<=EOMONTH(M$12,0),$I19>=M$12),"ALL","PD+UX"),IF(AND($H19<>"",$H19<=EOMONTH(M$12,0),$I19>=M$12),"PD+DEV","PD")),IF(AND(INDEX('Roadmap Calc (Don’t Touch)'!$AA$2:$AX$151,$AI19,COLUMN()-COLUMN($J$16)+1)>0,OR($D19="03. UX Discovery",$D19="04. UX Design")),IF(AND($H19<>"",$H19<=EOMONTH(M$12,0),$I19>=M$12),"UX+DEV","UX"),IF(AND($H19<>"",$H19<=EOMONTH(M$12,0),$I19>=M$12),"DEV","")))) | N19: =IF($AI19="","",IF(AND($AN19<>"",$AN19<=EOMONTH(N$12,0),$AO19>=N$12),IF(AND(INDEX('Roadmap Calc (Don’t Touch)'!$AA$2:$AX$151,$AI19,COLUMN()-COLUMN($J$16)+1)>0,OR($D19="03. UX Discovery",$D19="04. UX Design")),IF(AND($H19<>"",$H19<=EOMONTH(N$12,0),$I19>=N$12),"ALL","PD+UX"),IF(AND($H19<>"",$H19<=EOMONTH(N$12,0),$I19>=N$12),"PD+DEV","PD")),IF(AND(INDEX('Roadmap Calc (Don’t Touch)'!$AA$2:$AX$151,$AI19,COLUMN()-COLUMN($J$16)+1)>0,OR($D19="03. UX Discovery",$D19="04. UX Design")),IF(AND($H19<>"",$H19<=EOMONTH(N$12,0),$I19>=N$12),"UX+DEV","UX"),IF(AND($H19<>"",$H19<=EOMONTH(N$12,0),$I19>=N$12),"DEV","")))) | O19: =IF($AI19="","",IF(AND($AN19<>"",$AN19<=EOMONTH(O$12,0),$AO19>=O$12),IF(AND(INDEX('Roadmap Calc (Don’t Touch)'!$AA$2:$AX$151,$AI19,COLUMN()-COLUMN($J$16)+1)>0,OR($D19="03. UX Discovery",$D19="04. UX Design")),IF(AND($H19<>"",$H19<=EOMONTH(O$12,0),$I19>=O$12),"ALL","PD+UX"),IF(AND($H19<>"",$H19<=EOMONTH(O$12,0),$I19>=O$12),"PD+DEV","PD")),IF(AND(INDEX('Roadmap Calc (Don’t Touch)'!$AA$2:$AX$151,$AI19,COLUMN()-COLUMN($J$16)+1)>0,OR($D19="03. UX Discovery",$D19="04. UX Design")),IF(AND($H19<>"",$H19<=EOMONTH(O$12,0),$I19>=O$12),"UX+DEV","UX"),IF(AND($H19<>"",$H19<=EOMONTH(O$12,0),$I19>=O$12),"DEV","")))) | P19: =IF($AI19="","",IF(AND($AN19<>"",$AN19<=EOMONTH(P$12,0),$AO19>=P$12),IF(AND(INDEX('Roadmap Calc (Don’t Touch)'!$AA$2:$AX$151,$AI19,COLUMN()-COLUMN($J$16)+1)>0,OR($D19="03. UX Discovery",$D19="04. UX Design")),IF(AND($H19<>"",$H19<=EOMONTH(P$12,0),$I19>=P$12),"ALL","PD+UX"),IF(AND($H19<>"",$H19<=EOMONTH(P$12,0),$I19>=P$12),"PD+DEV","PD")),IF(AND(INDEX('Roadmap Calc (Don’t Touch)'!$AA$2:$AX$151,$AI19,COLUMN()-COLUMN($J$16)+1)>0,OR($D19="03. UX Discovery",$D19="04. UX Design")),IF(AND($H19<>"",$H19<=EOMONTH(P$12,0),$I19>=P$12),"UX+DEV","UX"),IF(AND($H19<>"",$H19<=EOMONTH(P$12,0),$I19>=P$12),"DEV","")))) | Q19: =IF($AI19="","",IF(AND($AN19<>"",$AN19<=EOMONTH(Q$12,0),$AO19>=Q$12),IF(AND(INDEX('Roadmap Calc (Don’t Touch)'!$AA$2:$AX$151,$AI19,COLUMN()-COLUMN($J$16)+1)>0,OR($D19="03. UX Discovery",$D19="04. UX Design")),IF(AND($H19<>"",$H19<=EOMONTH(Q$12,0),$I19>=Q$12),"ALL","PD+UX"),IF(AND($H19<>"",$H19<=EOMONTH(Q$12,0),$I19>=Q$12),"PD+DEV","PD")),IF(AND(INDEX('Roadmap Calc (Don’t Touch)'!$AA$2:$AX$151,$AI19,COLUMN()-COLUMN($J$16)+1)>0,OR($D19="03. UX Discovery",$D19="04. UX Design")),IF(AND($H19<>"",$H19<=EOMONTH(Q$12,0),$I19>=Q$12),"UX+DEV","UX"),IF(AND($H19<>"",$H19<=EOMONTH(Q$12,0),$I19>=Q$12),"DEV","")))) | ... AG19: =IF($AI19="","",IF(AND($AN19<>"",$AN19<=EOMONTH(AG$12,0),$AO19>=AG$12),IF(AND(INDEX('Roadmap Calc (Don’t Touch)'!$AA$2:$AX$151,$AI19,COLUMN()-COLUMN($J$16)+1)>0,OR($D19="03. UX Discovery",$D19="04. UX Design")),IF(AND($H19<>"",$H19<=EOMONTH(AG$12,0),$I19>=AG$12),"ALL","PD+UX"),IF(AND($H19<>"",$H19<=EOMONTH(AG$12,0),$I19>=AG$12),"PD+DEV","PD")),IF(AND(INDEX('Roadmap Calc (Don’t Touch)'!$AA$2:$AX$151,$AI19,COLUMN()-COLUMN($J$16)+1)>0,OR($D19="03. UX Discovery",$D19="04. UX Design")),IF(AND($H19<>"",$H19<=EOMONTH(AG$12,0),$I19>=AG$12),"UX+DEV","UX"),IF(AND($H19<>"",$H19<=EOMONTH(AG$12,0),$I19>=AG$12),"DEV","")))) | AH19: =IF($AI19="","",INDEX('Roadmap Calc (Don’t Touch)'!$D$2:$D$151,$AI19)) -> Increase Trade In Awareness | AI19: =IFERROR(MATCH(4,'Roadmap Calc (Don’t Touch)'!$O$2:$O$151,0),"") -> 15 | AK19: =IF(COUNTA(Control!E17)=0,"",Control!E17) | AL19: =IF(COUNTA(Control!B17)=0,"",Control!B17) -> 11. UAT | AN19: =IF($AI19="","",IF(ISNUMBER(INDEX('Roadmap Calc (Don’t Touch)'!$BB$2:$BB$151,$AI19)),INDEX('Roadmap Calc (Don’t Touch)'!$BB$2:$BB$151,$AI19),"")) | AO19: =IF($AI19="","",IF(ISNUMBER(INDEX('Roadmap Calc (Don’t Touch)'!$BC$2:$BC$151,$AI19)),INDEX('Roadmap Calc (Don’t Touch)'!$BC$2:$BC$151,$AI19),""))
A20: =IF($AI20="","",IF($AH20=$AH19,"",IF(INDEX('Roadmap Calc (Don’t Touch)'!$U$2:$U$151,$AI20)=0,$AH20,HYPERLINK("#'Control (Don’t Touch)'!E"&INDEX('Roadmap Calc (Don’t Touch)'!$U$2:$U$151,$AI20),$AH20)))) | B20: =IF($AI20="","",IF(INDEX('Roadmap Calc (Don’t Touch)'!$K$2:$K$151,$AI20)="",INDEX('Roadmap Calc (Don’t Touch)'!$B$2:$B$151,$AI20),HYPERLINK("https://jira.bnh.com/browse/"&INDEX('Roadmap Calc (Don’t Touch)'!$K$2:$K$151,$AI20),INDEX('Roadmap Calc (Don’t Touch)'!$B$2:$B$151,$AI20)))) -> B2B & Used Visibility in the Nav | C20: =IF($AI20="","",IF(INDEX('Roadmap Calc (Don’t Touch)'!$E$2:$E$151,$AI20)="","",HYPERLINK("https://jira.bnh.com/browse/"&INDEX('Roadmap Calc (Don’t Touch)'!$E$2:$E$151,$AI20),INDEX('Roadmap Calc (Don’t Touch)'!$E$2:$E$151,$AI20)))) -> BHUX-34378 | D20: =IF($AI20="","",INDEX('Roadmap Calc (Don’t Touch)'!$F$2:$F$151,$AI20)) -> 04. UX Design | E20: =IF($AI20="","",IF(ISNUMBER(INDEX('Roadmap Calc (Don’t Touch)'!$G$2:$G$151,$AI20)),INDEX('Roadmap Calc (Don’t Touch)'!$G$2:$G$151,$AI20),"")) -> 46174 | F20: =IF($AI20="","",IF(ISNUMBER(INDEX('Roadmap Calc (Don’t Touch)'!$H$2:$H$151,$AI20)),INDEX('Roadmap Calc (Don’t Touch)'!$H$2:$H$151,$AI20),"")) -> 46293 | G20: =IF($AI20="","",INDEX('Roadmap Calc (Don’t Touch)'!$T$2:$T$151,$AI20)) -> 18 | H20: =IF($AI20="","",IF(ISNUMBER(INDEX('Roadmap Calc (Don’t Touch)'!$I$2:$I$151,$AI20)),INDEX('Roadmap Calc (Don’t Touch)'!$I$2:$I$151,$AI20),"")) -> 46419 | I20: =IF($AI20="","",IF(ISNUMBER(INDEX('Roadmap Calc (Don’t Touch)'!$J$2:$J$151,$AI20)),INDEX('Roadmap Calc (Don’t Touch)'!$J$2:$J$151,$AI20),"")) -> 46446 | J20: =IF($AI20="","",IF(AND($AN20<>"",$AN20<=EOMONTH(J$12,0),$AO20>=J$12),IF(AND(INDEX('Roadmap Calc (Don’t Touch)'!$AA$2:$AX$151,$AI20,COLUMN()-COLUMN($J$16)+1)>0,OR($D20="03. UX Discovery",$D20="04. UX Design")),IF(AND($H20<>"",$H20<=EOMONTH(J$12,0),$I20>=J$12),"ALL","PD+UX"),IF(AND($H20<>"",$H20<=EOMONTH(J$12,0),$I20>=J$12),"PD+DEV","PD")),IF(AND(INDEX('Roadmap Calc (Don’t Touch)'!$AA$2:$AX$151,$AI20,COLUMN()-COLUMN($J$16)+1)>0,OR($D20="03. UX Discovery",$D20="04. UX Design")),IF(AND($H20<>"",$H20<=EOMONTH(J$12,0),$I20>=J$12),"UX+DEV","UX"),IF(AND($H20<>"",$H20<=EOMONTH(J$12,0),$I20>=J$12),"DEV","")))) | K20: =IF($AI20="","",IF(AND($AN20<>"",$AN20<=EOMONTH(K$12,0),$AO20>=K$12),IF(AND(INDEX('Roadmap Calc (Don’t Touch)'!$AA$2:$AX$151,$AI20,COLUMN()-COLUMN($J$16)+1)>0,OR($D20="03. UX Discovery",$D20="04. UX Design")),IF(AND($H20<>"",$H20<=EOMONTH(K$12,0),$I20>=K$12),"ALL","PD+UX"),IF(AND($H20<>"",$H20<=EOMONTH(K$12,0),$I20>=K$12),"PD+DEV","PD")),IF(AND(INDEX('Roadmap Calc (Don’t Touch)'!$AA$2:$AX$151,$AI20,COLUMN()-COLUMN($J$16)+1)>0,OR($D20="03. UX Discovery",$D20="04. UX Design")),IF(AND($H20<>"",$H20<=EOMONTH(K$12,0),$I20>=K$12),"UX+DEV","UX"),IF(AND($H20<>"",$H20<=EOMONTH(K$12,0),$I20>=K$12),"DEV","")))) | L20: =IF($AI20="","",IF(AND($AN20<>"",$AN20<=EOMONTH(L$12,0),$AO20>=L$12),IF(AND(INDEX('Roadmap Calc (Don’t Touch)'!$AA$2:$AX$151,$AI20,COLUMN()-COLUMN($J$16)+1)>0,OR($D20="03. UX Discovery",$D20="04. UX Design")),IF(AND($H20<>"",$H20<=EOMONTH(L$12,0),$I20>=L$12),"ALL","PD+UX"),IF(AND($H20<>"",$H20<=EOMONTH(L$12,0),$I20>=L$12),"PD+DEV","PD")),IF(AND(INDEX('Roadmap Calc (Don’t Touch)'!$AA$2:$AX$151,$AI20,COLUMN()-COLUMN($J$16)+1)>0,OR($D20="03. UX Discovery",$D20="04. UX Design")),IF(AND($H20<>"",$H20<=EOMONTH(L$12,0),$I20>=L$12),"UX+DEV","UX"),IF(AND($H20<>"",$H20<=EOMONTH(L$12,0),$I20>=L$12),"DEV","")))) | M20: =IF($AI20="","",IF(AND($AN20<>"",$AN20<=EOMONTH(M$12,0),$AO20>=M$12),IF(AND(INDEX('Roadmap Calc (Don’t Touch)'!$AA$2:$AX$151,$AI20,COLUMN()-COLUMN($J$16)+1)>0,OR($D20="03. UX Discovery",$D20="04. UX Design")),IF(AND($H20<>"",$H20<=EOMONTH(M$12,0),$I20>=M$12),"ALL","PD+UX"),IF(AND($H20<>"",$H20<=EOMONTH(M$12,0),$I20>=M$12),"PD+DEV","PD")),IF(AND(INDEX('Roadmap Calc (Don’t Touch)'!$AA$2:$AX$151,$AI20,COLUMN()-COLUMN($J$16)+1)>0,OR($D20="03. UX Discovery",$D20="04. UX Design")),IF(AND($H20<>"",$H20<=EOMONTH(M$12,0),$I20>=M$12),"UX+DEV","UX"),IF(AND($H20<>"",$H20<=EOMONTH(M$12,0),$I20>=M$12),"DEV","")))) | N20: =IF($AI20="","",IF(AND($AN20<>"",$AN20<=EOMONTH(N$12,0),$AO20>=N$12),IF(AND(INDEX('Roadmap Calc (Don’t Touch)'!$AA$2:$AX$151,$AI20,COLUMN()-COLUMN($J$16)+1)>0,OR($D20="03. UX Discovery",$D20="04. UX Design")),IF(AND($H20<>"",$H20<=EOMONTH(N$12,0),$I20>=N$12),"ALL","PD+UX"),IF(AND($H20<>"",$H20<=EOMONTH(N$12,0),$I20>=N$12),"PD+DEV","PD")),IF(AND(INDEX('Roadmap Calc (Don’t Touch)'!$AA$2:$AX$151,$AI20,COLUMN()-COLUMN($J$16)+1)>0,OR($D20="03. UX Discovery",$D20="04. UX Design")),IF(AND($H20<>"",$H20<=EOMONTH(N$12,0),$I20>=N$12),"UX+DEV","UX"),IF(AND($H20<>"",$H20<=EOMONTH(N$12,0),$I20>=N$12),"DEV","")))) | O20: =IF($AI20="","",IF(AND($AN20<>"",$AN20<=EOMONTH(O$12,0),$AO20>=O$12),IF(AND(INDEX('Roadmap Calc (Don’t Touch)'!$AA$2:$AX$151,$AI20,COLUMN()-COLUMN($J$16)+1)>0,OR($D20="03. UX Discovery",$D20="04. UX Design")),IF(AND($H20<>"",$H20<=EOMONTH(O$12,0),$I20>=O$12),"ALL","PD+UX"),IF(AND($H20<>"",$H20<=EOMONTH(O$12,0),$I20>=O$12),"PD+DEV","PD")),IF(AND(INDEX('Roadmap Calc (Don’t Touch)'!$AA$2:$AX$151,$AI20,COLUMN()-COLUMN($J$16)+1)>0,OR($D20="03. UX Discovery",$D20="04. UX Design")),IF(AND($H20<>"",$H20<=EOMONTH(O$12,0),$I20>=O$12),"UX+DEV","UX"),IF(AND($H20<>"",$H20<=EOMONTH(O$12,0),$I20>=O$12),"DEV","")))) | P20: =IF($AI20="","",IF(AND($AN20<>"",$AN20<=EOMONTH(P$12,0),$AO20>=P$12),IF(AND(INDEX('Roadmap Calc (Don’t Touch)'!$AA$2:$AX$151,$AI20,COLUMN()-COLUMN($J$16)+1)>0,OR($D20="03. UX Discovery",$D20="04. UX Design")),IF(AND($H20<>"",$H20<=EOMONTH(P$12,0),$I20>=P$12),"ALL","PD+UX"),IF(AND($H20<>"",$H20<=EOMONTH(P$12,0),$I20>=P$12),"PD+DEV","PD")),IF(AND(INDEX('Roadmap Calc (Don’t Touch)'!$AA$2:$AX$151,$AI20,COLUMN()-COLUMN($J$16)+1)>0,OR($D20="03. UX Discovery",$D20="04. UX Design")),IF(AND($H20<>"",$H20<=EOMONTH(P$12,0),$I20>=P$12),"UX+DEV","UX"),IF(AND($H20<>"",$H20<=EOMONTH(P$12,0),$I20>=P$12),"DEV","")))) | Q20: =IF($AI20="","",IF(AND($AN20<>"",$AN20<=EOMONTH(Q$12,0),$AO20>=Q$12),IF(AND(INDEX('Roadmap Calc (Don’t Touch)'!$AA$2:$AX$151,$AI20,COLUMN()-COLUMN($J$16)+1)>0,OR($D20="03. UX Discovery",$D20="04. UX Design")),IF(AND($H20<>"",$H20<=EOMONTH(Q$12,0),$I20>=Q$12),"ALL","PD+UX"),IF(AND($H20<>"",$H20<=EOMONTH(Q$12,0),$I20>=Q$12),"PD+DEV","PD")),IF(AND(INDEX('Roadmap Calc (Don’t Touch)'!$AA$2:$AX$151,$AI20,COLUMN()-COLUMN($J$16)+1)>0,OR($D20="03. UX Discovery",$D20="04. UX Design")),IF(AND($H20<>"",$H20<=EOMONTH(Q$12,0),$I20>=Q$12),"UX+DEV","UX"),IF(AND($H20<>"",$H20<=EOMONTH(Q$12,0),$I20>=Q$12),"DEV","")))) | ... AG20: =IF($AI20="","",IF(AND($AN20<>"",$AN20<=EOMONTH(AG$12,0),$AO20>=AG$12),IF(AND(INDEX('Roadmap Calc (Don’t Touch)'!$AA$2:$AX$151,$AI20,COLUMN()-COLUMN($J$16)+1)>0,OR($D20="03. UX Discovery",$D20="04. UX Design")),IF(AND($H20<>"",$H20<=EOMONTH(AG$12,0),$I20>=AG$12),"ALL","PD+UX"),IF(AND($H20<>"",$H20<=EOMONTH(AG$12,0),$I20>=AG$12),"PD+DEV","PD")),IF(AND(INDEX('Roadmap Calc (Don’t Touch)'!$AA$2:$AX$151,$AI20,COLUMN()-COLUMN($J$16)+1)>0,OR($D20="03. UX Discovery",$D20="04. UX Design")),IF(AND($H20<>"",$H20<=EOMONTH(AG$12,0),$I20>=AG$12),"UX+DEV","UX"),IF(AND($H20<>"",$H20<=EOMONTH(AG$12,0),$I20>=AG$12),"DEV","")))) | AH20: =IF($AI20="","",INDEX('Roadmap Calc (Don’t Touch)'!$D$2:$D$151,$AI20)) -> Increase Trade In Awareness | AI20: =IFERROR(MATCH(5,'Roadmap Calc (Don’t Touch)'!$O$2:$O$151,0),"") -> 26 | AK20: =IF(COUNTA(Control!E18)=0,"",Control!E18) | AL20: =IF(COUNTA(Control!B18)=0,"",Control!B18) -> 12. Release | AN20: =IF($AI20="","",IF(ISNUMBER(INDEX('Roadmap Calc (Don’t Touch)'!$BB$2:$BB$151,$AI20)),INDEX('Roadmap Calc (Don’t Touch)'!$BB$2:$BB$151,$AI20),"")) | AO20: =IF($AI20="","",IF(ISNUMBER(INDEX('Roadmap Calc (Don’t Touch)'!$BC$2:$BC$151,$AI20)),INDEX('Roadmap Calc (Don’t Touch)'!$BC$2:$BC$151,$AI20),""))
A21: =IF($AI21="","",IF($AH21=$AH20,"",IF(INDEX('Roadmap Calc (Don’t Touch)'!$U$2:$U$151,$AI21)=0,$AH21,HYPERLINK("#'Control (Don’t Touch)'!E"&INDEX('Roadmap Calc (Don’t Touch)'!$U$2:$U$151,$AI21),$AH21)))) | B21: =IF($AI21="","",IF(INDEX('Roadmap Calc (Don’t Touch)'!$K$2:$K$151,$AI21)="",INDEX('Roadmap Calc (Don’t Touch)'!$B$2:$B$151,$AI21),HYPERLINK("https://jira.bnh.com/browse/"&INDEX('Roadmap Calc (Don’t Touch)'!$K$2:$K$151,$AI21),INDEX('Roadmap Calc (Don’t Touch)'!$B$2:$B$151,$AI21)))) -> PDP Purchased in 20XX, Trade In Value is $YYY.YY | C21: =IF($AI21="","",IF(INDEX('Roadmap Calc (Don’t Touch)'!$E$2:$E$151,$AI21)="","",HYPERLINK("https://jira.bnh.com/browse/"&INDEX('Roadmap Calc (Don’t Touch)'!$E$2:$E$151,$AI21),INDEX('Roadmap Calc (Don’t Touch)'!$E$2:$E$151,$AI21)))) -> BHUX-35309 | D21: =IF($AI21="","",INDEX('Roadmap Calc (Don’t Touch)'!$F$2:$F$151,$AI21)) -> 06. Architecture | E21: =IF($AI21="","",IF(ISNUMBER(INDEX('Roadmap Calc (Don’t Touch)'!$G$2:$G$151,$AI21)),INDEX('Roadmap Calc (Don’t Touch)'!$G$2:$G$151,$AI21),"")) -> 46251 | F21: =IF($AI21="","",IF(ISNUMBER(INDEX('Roadmap Calc (Don’t Touch)'!$H$2:$H$151,$AI21)),INDEX('Roadmap Calc (Don’t Touch)'!$H$2:$H$151,$AI21),"")) -> 46251 | G21: =IF($AI21="","",INDEX('Roadmap Calc (Don’t Touch)'!$T$2:$T$151,$AI21)) -> 1 | H21: =IF($AI21="","",IF(ISNUMBER(INDEX('Roadmap Calc (Don’t Touch)'!$I$2:$I$151,$AI21)),INDEX('Roadmap Calc (Don’t Touch)'!$I$2:$I$151,$AI21),"")) -> 46296 | I21: =IF($AI21="","",IF(ISNUMBER(INDEX('Roadmap Calc (Don’t Touch)'!$J$2:$J$151,$AI21)),INDEX('Roadmap Calc (Don’t Touch)'!$J$2:$J$151,$AI21),"")) -> 46326 | J21: =IF($AI21="","",IF(AND($AN21<>"",$AN21<=EOMONTH(J$12,0),$AO21>=J$12),IF(AND(INDEX('Roadmap Calc (Don’t Touch)'!$AA$2:$AX$151,$AI21,COLUMN()-COLUMN($J$16)+1)>0,OR($D21="03. UX Discovery",$D21="04. UX Design")),IF(AND($H21<>"",$H21<=EOMONTH(J$12,0),$I21>=J$12),"ALL","PD+UX"),IF(AND($H21<>"",$H21<=EOMONTH(J$12,0),$I21>=J$12),"PD+DEV","PD")),IF(AND(INDEX('Roadmap Calc (Don’t Touch)'!$AA$2:$AX$151,$AI21,COLUMN()-COLUMN($J$16)+1)>0,OR($D21="03. UX Discovery",$D21="04. UX Design")),IF(AND($H21<>"",$H21<=EOMONTH(J$12,0),$I21>=J$12),"UX+DEV","UX"),IF(AND($H21<>"",$H21<=EOMONTH(J$12,0),$I21>=J$12),"DEV","")))) | K21: =IF($AI21="","",IF(AND($AN21<>"",$AN21<=EOMONTH(K$12,0),$AO21>=K$12),IF(AND(INDEX('Roadmap Calc (Don’t Touch)'!$AA$2:$AX$151,$AI21,COLUMN()-COLUMN($J$16)+1)>0,OR($D21="03. UX Discovery",$D21="04. UX Design")),IF(AND($H21<>"",$H21<=EOMONTH(K$12,0),$I21>=K$12),"ALL","PD+UX"),IF(AND($H21<>"",$H21<=EOMONTH(K$12,0),$I21>=K$12),"PD+DEV","PD")),IF(AND(INDEX('Roadmap Calc (Don’t Touch)'!$AA$2:$AX$151,$AI21,COLUMN()-COLUMN($J$16)+1)>0,OR($D21="03. UX Discovery",$D21="04. UX Design")),IF(AND($H21<>"",$H21<=EOMONTH(K$12,0),$I21>=K$12),"UX+DEV","UX"),IF(AND($H21<>"",$H21<=EOMONTH(K$12,0),$I21>=K$12),"DEV","")))) | L21: =IF($AI21="","",IF(AND($AN21<>"",$AN21<=EOMONTH(L$12,0),$AO21>=L$12),IF(AND(INDEX('Roadmap Calc (Don’t Touch)'!$AA$2:$AX$151,$AI21,COLUMN()-COLUMN($J$16)+1)>0,OR($D21="03. UX Discovery",$D21="04. UX Design")),IF(AND($H21<>"",$H21<=EOMONTH(L$12,0),$I21>=L$12),"ALL","PD+UX"),IF(AND($H21<>"",$H21<=EOMONTH(L$12,0),$I21>=L$12),"PD+DEV","PD")),IF(AND(INDEX('Roadmap Calc (Don’t Touch)'!$AA$2:$AX$151,$AI21,COLUMN()-COLUMN($J$16)+1)>0,OR($D21="03. UX Discovery",$D21="04. UX Design")),IF(AND($H21<>"",$H21<=EOMONTH(L$12,0),$I21>=L$12),"UX+DEV","UX"),IF(AND($H21<>"",$H21<=EOMONTH(L$12,0),$I21>=L$12),"DEV","")))) | M21: =IF($AI21="","",IF(AND($AN21<>"",$AN21<=EOMONTH(M$12,0),$AO21>=M$12),IF(AND(INDEX('Roadmap Calc (Don’t Touch)'!$AA$2:$AX$151,$AI21,COLUMN()-COLUMN($J$16)+1)>0,OR($D21="03. UX Discovery",$D21="04. UX Design")),IF(AND($H21<>"",$H21<=EOMONTH(M$12,0),$I21>=M$12),"ALL","PD+UX"),IF(AND($H21<>"",$H21<=EOMONTH(M$12,0),$I21>=M$12),"PD+DEV","PD")),IF(AND(INDEX('Roadmap Calc (Don’t Touch)'!$AA$2:$AX$151,$AI21,COLUMN()-COLUMN($J$16)+1)>0,OR($D21="03. UX Discovery",$D21="04. UX Design")),IF(AND($H21<>"",$H21<=EOMONTH(M$12,0),$I21>=M$12),"UX+DEV","UX"),IF(AND($H21<>"",$H21<=EOMONTH(M$12,0),$I21>=M$12),"DEV","")))) | N21: =IF($AI21="","",IF(AND($AN21<>"",$AN21<=EOMONTH(N$12,0),$AO21>=N$12),IF(AND(INDEX('Roadmap Calc (Don’t Touch)'!$AA$2:$AX$151,$AI21,COLUMN()-COLUMN($J$16)+1)>0,OR($D21="03. UX Discovery",$D21="04. UX Design")),IF(AND($H21<>"",$H21<=EOMONTH(N$12,0),$I21>=N$12),"ALL","PD+UX"),IF(AND($H21<>"",$H21<=EOMONTH(N$12,0),$I21>=N$12),"PD+DEV","PD")),IF(AND(INDEX('Roadmap Calc (Don’t Touch)'!$AA$2:$AX$151,$AI21,COLUMN()-COLUMN($J$16)+1)>0,OR($D21="03. UX Discovery",$D21="04. UX Design")),IF(AND($H21<>"",$H21<=EOMONTH(N$12,0),$I21>=N$12),"UX+DEV","UX"),IF(AND($H21<>"",$H21<=EOMONTH(N$12,0),$I21>=N$12),"DEV","")))) | O21: =IF($AI21="","",IF(AND($AN21<>"",$AN21<=EOMONTH(O$12,0),$AO21>=O$12),IF(AND(INDEX('Roadmap Calc (Don’t Touch)'!$AA$2:$AX$151,$AI21,COLUMN()-COLUMN($J$16)+1)>0,OR($D21="03. UX Discovery",$D21="04. UX Design")),IF(AND($H21<>"",$H21<=EOMONTH(O$12,0),$I21>=O$12),"ALL","PD+UX"),IF(AND($H21<>"",$H21<=EOMONTH(O$12,0),$I21>=O$12),"PD+DEV","PD")),IF(AND(INDEX('Roadmap Calc (Don’t Touch)'!$AA$2:$AX$151,$AI21,COLUMN()-COLUMN($J$16)+1)>0,OR($D21="03. UX Discovery",$D21="04. UX Design")),IF(AND($H21<>"",$H21<=EOMONTH(O$12,0),$I21>=O$12),"UX+DEV","UX"),IF(AND($H21<>"",$H21<=EOMONTH(O$12,0),$I21>=O$12),"DEV","")))) | P21: =IF($AI21="","",IF(AND($AN21<>"",$AN21<=EOMONTH(P$12,0),$AO21>=P$12),IF(AND(INDEX('Roadmap Calc (Don’t Touch)'!$AA$2:$AX$151,$AI21,COLUMN()-COLUMN($J$16)+1)>0,OR($D21="03. UX Discovery",$D21="04. UX Design")),IF(AND($H21<>"",$H21<=EOMONTH(P$12,0),$I21>=P$12),"ALL","PD+UX"),IF(AND($H21<>"",$H21<=EOMONTH(P$12,0),$I21>=P$12),"PD+DEV","PD")),IF(AND(INDEX('Roadmap Calc (Don’t Touch)'!$AA$2:$AX$151,$AI21,COLUMN()-COLUMN($J$16)+1)>0,OR($D21="03. UX Discovery",$D21="04. UX Design")),IF(AND($H21<>"",$H21<=EOMONTH(P$12,0),$I21>=P$12),"UX+DEV","UX"),IF(AND($H21<>"",$H21<=EOMONTH(P$12,0),$I21>=P$12),"DEV","")))) | Q21: =IF($AI21="","",IF(AND($AN21<>"",$AN21<=EOMONTH(Q$12,0),$AO21>=Q$12),IF(AND(INDEX('Roadmap Calc (Don’t Touch)'!$AA$2:$AX$151,$AI21,COLUMN()-COLUMN($J$16)+1)>0,OR($D21="03. UX Discovery",$D21="04. UX Design")),IF(AND($H21<>"",$H21<=EOMONTH(Q$12,0),$I21>=Q$12),"ALL","PD+UX"),IF(AND($H21<>"",$H21<=EOMONTH(Q$12,0),$I21>=Q$12),"PD+DEV","PD")),IF(AND(INDEX('Roadmap Calc (Don’t Touch)'!$AA$2:$AX$151,$AI21,COLUMN()-COLUMN($J$16)+1)>0,OR($D21="03. UX Discovery",$D21="04. UX Design")),IF(AND($H21<>"",$H21<=EOMONTH(Q$12,0),$I21>=Q$12),"UX+DEV","UX"),IF(AND($H21<>"",$H21<=EOMONTH(Q$12,0),$I21>=Q$12),"DEV","")))) | ... AG21: =IF($AI21="","",IF(AND($AN21<>"",$AN21<=EOMONTH(AG$12,0),$AO21>=AG$12),IF(AND(INDEX('Roadmap Calc (Don’t Touch)'!$AA$2:$AX$151,$AI21,COLUMN()-COLUMN($J$16)+1)>0,OR($D21="03. UX Discovery",$D21="04. UX Design")),IF(AND($H21<>"",$H21<=EOMONTH(AG$12,0),$I21>=AG$12),"ALL","PD+UX"),IF(AND($H21<>"",$H21<=EOMONTH(AG$12,0),$I21>=AG$12),"PD+DEV","PD")),IF(AND(INDEX('Roadmap Calc (Don’t Touch)'!$AA$2:$AX$151,$AI21,COLUMN()-COLUMN($J$16)+1)>0,OR($D21="03. UX Discovery",$D21="04. UX Design")),IF(AND($H21<>"",$H21<=EOMONTH(AG$12,0),$I21>=AG$12),"UX+DEV","UX"),IF(AND($H21<>"",$H21<=EOMONTH(AG$12,0),$I21>=AG$12),"DEV","")))) | AH21: =IF($AI21="","",INDEX('Roadmap Calc (Don’t Touch)'!$D$2:$D$151,$AI21)) -> Increase Trade In Awareness | AI21: =IFERROR(MATCH(6,'Roadmap Calc (Don’t Touch)'!$O$2:$O$151,0),"") -> 29 | AL21: =IF(COUNTA(Control!B19)=0,"",Control!B19) -> 13. Live | AN21: =IF($AI21="","",IF(ISNUMBER(INDEX('Roadmap Calc (Don’t Touch)'!$BB$2:$BB$151,$AI21)),INDEX('Roadmap Calc (Don’t Touch)'!$BB$2:$BB$151,$AI21),"")) | AO21: =IF($AI21="","",IF(ISNUMBER(INDEX('Roadmap Calc (Don’t Touch)'!$BC$2:$BC$151,$AI21)),INDEX('Roadmap Calc (Don’t Touch)'!$BC$2:$BC$151,$AI21),""))
A22: =IF($AI22="","",IF($AH22=$AH21,"",IF(INDEX('Roadmap Calc (Don’t Touch)'!$U$2:$U$151,$AI22)=0,$AH22,HYPERLINK("#'Control (Don’t Touch)'!E"&INDEX('Roadmap Calc (Don’t Touch)'!$U$2:$U$151,$AI22),$AH22)))) -> Improve Trade In User Flow | B22: =IF($AI22="","",IF(INDEX('Roadmap Calc (Don’t Touch)'!$K$2:$K$151,$AI22)="",INDEX('Roadmap Calc (Don’t Touch)'!$B$2:$B$151,$AI22),HYPERLINK("https://jira.bnh.com/browse/"&INDEX('Roadmap Calc (Don’t Touch)'!$K$2:$K$151,$AI22),INDEX('Roadmap Calc (Don’t Touch)'!$B$2:$B$151,$AI22)))) -> Sell Used Purchase Look Up | C22: =IF($AI22="","",IF(INDEX('Roadmap Calc (Don’t Touch)'!$E$2:$E$151,$AI22)="","",HYPERLINK("https://jira.bnh.com/browse/"&INDEX('Roadmap Calc (Don’t Touch)'!$E$2:$E$151,$AI22),INDEX('Roadmap Calc (Don’t Touch)'!$E$2:$E$151,$AI22)))) -> BHP-7236 | D22: =IF($AI22="","",INDEX('Roadmap Calc (Don’t Touch)'!$F$2:$F$151,$AI22)) -> 02. UX Req | E22: =IF($AI22="","",IF(ISNUMBER(INDEX('Roadmap Calc (Don’t Touch)'!$G$2:$G$151,$AI22)),INDEX('Roadmap Calc (Don’t Touch)'!$G$2:$G$151,$AI22),"")) -> 46258 | F22: =IF($AI22="","",IF(ISNUMBER(INDEX('Roadmap Calc (Don’t Touch)'!$H$2:$H$151,$AI22)),INDEX('Roadmap Calc (Don’t Touch)'!$H$2:$H$151,$AI22),"")) -> 46272 | G22: =IF($AI22="","",INDEX('Roadmap Calc (Don’t Touch)'!$T$2:$T$151,$AI22)) -> 3 | H22: =IF($AI22="","",IF(ISNUMBER(INDEX('Roadmap Calc (Don’t Touch)'!$I$2:$I$151,$AI22)),INDEX('Roadmap Calc (Don’t Touch)'!$I$2:$I$151,$AI22),"")) -> 46327 | I22: =IF($AI22="","",IF(ISNUMBER(INDEX('Roadmap Calc (Don’t Touch)'!$J$2:$J$151,$AI22)),INDEX('Roadmap Calc (Don’t Touch)'!$J$2:$J$151,$AI22),"")) -> 46418 | J22: =IF($AI22="","",IF(AND($AN22<>"",$AN22<=EOMONTH(J$12,0),$AO22>=J$12),IF(AND(INDEX('Roadmap Calc (Don’t Touch)'!$AA$2:$AX$151,$AI22,COLUMN()-COLUMN($J$16)+1)>0,OR($D22="03. UX Discovery",$D22="04. UX Design")),IF(AND($H22<>"",$H22<=EOMONTH(J$12,0),$I22>=J$12),"ALL","PD+UX"),IF(AND($H22<>"",$H22<=EOMONTH(J$12,0),$I22>=J$12),"PD+DEV","PD")),IF(AND(INDEX('Roadmap Calc (Don’t Touch)'!$AA$2:$AX$151,$AI22,COLUMN()-COLUMN($J$16)+1)>0,OR($D22="03. UX Discovery",$D22="04. UX Design")),IF(AND($H22<>"",$H22<=EOMONTH(J$12,0),$I22>=J$12),"UX+DEV","UX"),IF(AND($H22<>"",$H22<=EOMONTH(J$12,0),$I22>=J$12),"DEV","")))) | K22: =IF($AI22="","",IF(AND($AN22<>"",$AN22<=EOMONTH(K$12,0),$AO22>=K$12),IF(AND(INDEX('Roadmap Calc (Don’t Touch)'!$AA$2:$AX$151,$AI22,COLUMN()-COLUMN($J$16)+1)>0,OR($D22="03. UX Discovery",$D22="04. UX Design")),IF(AND($H22<>"",$H22<=EOMONTH(K$12,0),$I22>=K$12),"ALL","PD+UX"),IF(AND($H22<>"",$H22<=EOMONTH(K$12,0),$I22>=K$12),"PD+DEV","PD")),IF(AND(INDEX('Roadmap Calc (Don’t Touch)'!$AA$2:$AX$151,$AI22,COLUMN()-COLUMN($J$16)+1)>0,OR($D22="03. UX Discovery",$D22="04. UX Design")),IF(AND($H22<>"",$H22<=EOMONTH(K$12,0),$I22>=K$12),"UX+DEV","UX"),IF(AND($H22<>"",$H22<=EOMONTH(K$12,0),$I22>=K$12),"DEV","")))) | L22: =IF($AI22="","",IF(AND($AN22<>"",$AN22<=EOMONTH(L$12,0),$AO22>=L$12),IF(AND(INDEX('Roadmap Calc (Don’t Touch)'!$AA$2:$AX$151,$AI22,COLUMN()-COLUMN($J$16)+1)>0,OR($D22="03. UX Discovery",$D22="04. UX Design")),IF(AND($H22<>"",$H22<=EOMONTH(L$12,0),$I22>=L$12),"ALL","PD+UX"),IF(AND($H22<>"",$H22<=EOMONTH(L$12,0),$I22>=L$12),"PD+DEV","PD")),IF(AND(INDEX('Roadmap Calc (Don’t Touch)'!$AA$2:$AX$151,$AI22,COLUMN()-COLUMN($J$16)+1)>0,OR($D22="03. UX Discovery",$D22="04. UX Design")),IF(AND($H22<>"",$H22<=EOMONTH(L$12,0),$I22>=L$12),"UX+DEV","UX"),IF(AND($H22<>"",$H22<=EOMONTH(L$12,0),$I22>=L$12),"DEV","")))) | M22: =IF($AI22="","",IF(AND($AN22<>"",$AN22<=EOMONTH(M$12,0),$AO22>=M$12),IF(AND(INDEX('Roadmap Calc (Don’t Touch)'!$AA$2:$AX$151,$AI22,COLUMN()-COLUMN($J$16)+1)>0,OR($D22="03. UX Discovery",$D22="04. UX Design")),IF(AND($H22<>"",$H22<=EOMONTH(M$12,0),$I22>=M$12),"ALL","PD+UX"),IF(AND($H22<>"",$H22<=EOMONTH(M$12,0),$I22>=M$12),"PD+DEV","PD")),IF(AND(INDEX('Roadmap Calc (Don’t Touch)'!$AA$2:$AX$151,$AI22,COLUMN()-COLUMN($J$16)+1)>0,OR($D22="03. UX Discovery",$D22="04. UX Design")),IF(AND($H22<>"",$H22<=EOMONTH(M$12,0),$I22>=M$12),"UX+DEV","UX"),IF(AND($H22<>"",$H22<=EOMONTH(M$12,0),$I22>=M$12),"DEV","")))) | N22: =IF($AI22="","",IF(AND($AN22<>"",$AN22<=EOMONTH(N$12,0),$AO22>=N$12),IF(AND(INDEX('Roadmap Calc (Don’t Touch)'!$AA$2:$AX$151,$AI22,COLUMN()-COLUMN($J$16)+1)>0,OR($D22="03. UX Discovery",$D22="04. UX Design")),IF(AND($H22<>"",$H22<=EOMONTH(N$12,0),$I22>=N$12),"ALL","PD+UX"),IF(AND($H22<>"",$H22<=EOMONTH(N$12,0),$I22>=N$12),"PD+DEV","PD")),IF(AND(INDEX('Roadmap Calc (Don’t Touch)'!$AA$2:$AX$151,$AI22,COLUMN()-COLUMN($J$16)+1)>0,OR($D22="03. UX Discovery",$D22="04. UX Design")),IF(AND($H22<>"",$H22<=EOMONTH(N$12,0),$I22>=N$12),"UX+DEV","UX"),IF(AND($H22<>"",$H22<=EOMONTH(N$12,0),$I22>=N$12),"DEV","")))) | O22: =IF($AI22="","",IF(AND($AN22<>"",$AN22<=EOMONTH(O$12,0),$AO22>=O$12),IF(AND(INDEX('Roadmap Calc (Don’t Touch)'!$AA$2:$AX$151,$AI22,COLUMN()-COLUMN($J$16)+1)>0,OR($D22="03. UX Discovery",$D22="04. UX Design")),IF(AND($H22<>"",$H22<=EOMONTH(O$12,0),$I22>=O$12),"ALL","PD+UX"),IF(AND($H22<>"",$H22<=EOMONTH(O$12,0),$I22>=O$12),"PD+DEV","PD")),IF(AND(INDEX('Roadmap Calc (Don’t Touch)'!$AA$2:$AX$151,$AI22,COLUMN()-COLUMN($J$16)+1)>0,OR($D22="03. UX Discovery",$D22="04. UX Design")),IF(AND($H22<>"",$H22<=EOMONTH(O$12,0),$I22>=O$12),"UX+DEV","UX"),IF(AND($H22<>"",$H22<=EOMONTH(O$12,0),$I22>=O$12),"DEV","")))) | P22: =IF($AI22="","",IF(AND($AN22<>"",$AN22<=EOMONTH(P$12,0),$AO22>=P$12),IF(AND(INDEX('Roadmap Calc (Don’t Touch)'!$AA$2:$AX$151,$AI22,COLUMN()-COLUMN($J$16)+1)>0,OR($D22="03. UX Discovery",$D22="04. UX Design")),IF(AND($H22<>"",$H22<=EOMONTH(P$12,0),$I22>=P$12),"ALL","PD+UX"),IF(AND($H22<>"",$H22<=EOMONTH(P$12,0),$I22>=P$12),"PD+DEV","PD")),IF(AND(INDEX('Roadmap Calc (Don’t Touch)'!$AA$2:$AX$151,$AI22,COLUMN()-COLUMN($J$16)+1)>0,OR($D22="03. UX Discovery",$D22="04. UX Design")),IF(AND($H22<>"",$H22<=EOMONTH(P$12,0),$I22>=P$12),"UX+DEV","UX"),IF(AND($H22<>"",$H22<=EOMONTH(P$12,0),$I22>=P$12),"DEV","")))) | Q22: =IF($AI22="","",IF(AND($AN22<>"",$AN22<=EOMONTH(Q$12,0),$AO22>=Q$12),IF(AND(INDEX('Roadmap Calc (Don’t Touch)'!$AA$2:$AX$151,$AI22,COLUMN()-COLUMN($J$16)+1)>0,OR($D22="03. UX Discovery",$D22="04. UX Design")),IF(AND($H22<>"",$H22<=EOMONTH(Q$12,0),$I22>=Q$12),"ALL","PD+UX"),IF(AND($H22<>"",$H22<=EOMONTH(Q$12,0),$I22>=Q$12),"PD+DEV","PD")),IF(AND(INDEX('Roadmap Calc (Don’t Touch)'!$AA$2:$AX$151,$AI22,COLUMN()-COLUMN($J$16)+1)>0,OR($D22="03. UX Discovery",$D22="04. UX Design")),IF(AND($H22<>"",$H22<=EOMONTH(Q$12,0),$I22>=Q$12),"UX+DEV","UX"),IF(AND($H22<>"",$H22<=EOMONTH(Q$12,0),$I22>=Q$12),"DEV","")))) | ... AG22: =IF($AI22="","",IF(AND($AN22<>"",$AN22<=EOMONTH(AG$12,0),$AO22>=AG$12),IF(AND(INDEX('Roadmap Calc (Don’t Touch)'!$AA$2:$AX$151,$AI22,COLUMN()-COLUMN($J$16)+1)>0,OR($D22="03. UX Discovery",$D22="04. UX Design")),IF(AND($H22<>"",$H22<=EOMONTH(AG$12,0),$I22>=AG$12),"ALL","PD+UX"),IF(AND($H22<>"",$H22<=EOMONTH(AG$12,0),$I22>=AG$12),"PD+DEV","PD")),IF(AND(INDEX('Roadmap Calc (Don’t Touch)'!$AA$2:$AX$151,$AI22,COLUMN()-COLUMN($J$16)+1)>0,OR($D22="03. UX Discovery",$D22="04. UX Design")),IF(AND($H22<>"",$H22<=EOMONTH(AG$12,0),$I22>=AG$12),"UX+DEV","UX"),IF(AND($H22<>"",$H22<=EOMONTH(AG$12,0),$I22>=AG$12),"DEV","")))) | AH22: =IF($AI22="","",INDEX('Roadmap Calc (Don’t Touch)'!$D$2:$D$151,$AI22)) -> Improve Trade In User Flow | AI22: =IFERROR(MATCH(7,'Roadmap Calc (Don’t Touch)'!$O$2:$O$151,0),"") -> 10 | AL22: =IF(COUNTA(Control!B20)=0,"",Control!B20) | AN22: =IF($AI22="","",IF(ISNUMBER(INDEX('Roadmap Calc (Don’t Touch)'!$BB$2:$BB$151,$AI22)),INDEX('Roadmap Calc (Don’t Touch)'!$BB$2:$BB$151,$AI22),"")) | AO22: =IF($AI22="","",IF(ISNUMBER(INDEX('Roadmap Calc (Don’t Touch)'!$BC$2:$BC$151,$AI22)),INDEX('Roadmap Calc (Don’t Touch)'!$BC$2:$BC$151,$AI22),""))
A23: =IF($AI23="","",IF($AH23=$AH22,"",IF(INDEX('Roadmap Calc (Don’t Touch)'!$U$2:$U$151,$AI23)=0,$AH23,HYPERLINK("#'Control (Don’t Touch)'!E"&INDEX('Roadmap Calc (Don’t Touch)'!$U$2:$U$151,$AI23),$AH23)))) | B23: =IF($AI23="","",IF(INDEX('Roadmap Calc (Don’t Touch)'!$K$2:$K$151,$AI23)="",INDEX('Roadmap Calc (Don’t Touch)'!$B$2:$B$151,$AI23),HYPERLINK("https://jira.bnh.com/browse/"&INDEX('Roadmap Calc (Don’t Touch)'!$K$2:$K$151,$AI23),INDEX('Roadmap Calc (Don’t Touch)'!$B$2:$B$151,$AI23)))) -> Trade In Email - Comprehensive Refresh Discovery | C23: =IF($AI23="","",IF(INDEX('Roadmap Calc (Don’t Touch)'!$E$2:$E$151,$AI23)="","",HYPERLINK("https://jira.bnh.com/browse/"&INDEX('Roadmap Calc (Don’t Touch)'!$E$2:$E$151,$AI23),INDEX('Roadmap Calc (Don’t Touch)'!$E$2:$E$151,$AI23)))) -> BHUX-34772 | D23: =IF($AI23="","",INDEX('Roadmap Calc (Don’t Touch)'!$F$2:$F$151,$AI23)) -> 04. UX Design | E23: =IF($AI23="","",IF(ISNUMBER(INDEX('Roadmap Calc (Don’t Touch)'!$G$2:$G$151,$AI23)),INDEX('Roadmap Calc (Don’t Touch)'!$G$2:$G$151,$AI23),"")) -> 46216 | F23: =IF($AI23="","",IF(ISNUMBER(INDEX('Roadmap Calc (Don’t Touch)'!$H$2:$H$151,$AI23)),INDEX('Roadmap Calc (Don’t Touch)'!$H$2:$H$151,$AI23),"")) -> 46237 | G23: =IF($AI23="","",INDEX('Roadmap Calc (Don’t Touch)'!$T$2:$T$151,$AI23)) -> 4 | H23: =IF($AI23="","",IF(ISNUMBER(INDEX('Roadmap Calc (Don’t Touch)'!$I$2:$I$151,$AI23)),INDEX('Roadmap Calc (Don’t Touch)'!$I$2:$I$151,$AI23),"")) -> 46296 | I23: =IF($AI23="","",IF(ISNUMBER(INDEX('Roadmap Calc (Don’t Touch)'!$J$2:$J$151,$AI23)),INDEX('Roadmap Calc (Don’t Touch)'!$J$2:$J$151,$AI23),"")) -> 46326 | J23: =IF($AI23="","",IF(AND($AN23<>"",$AN23<=EOMONTH(J$12,0),$AO23>=J$12),IF(AND(INDEX('Roadmap Calc (Don’t Touch)'!$AA$2:$AX$151,$AI23,COLUMN()-COLUMN($J$16)+1)>0,OR($D23="03. UX Discovery",$D23="04. UX Design")),IF(AND($H23<>"",$H23<=EOMONTH(J$12,0),$I23>=J$12),"ALL","PD+UX"),IF(AND($H23<>"",$H23<=EOMONTH(J$12,0),$I23>=J$12),"PD+DEV","PD")),IF(AND(INDEX('Roadmap Calc (Don’t Touch)'!$AA$2:$AX$151,$AI23,COLUMN()-COLUMN($J$16)+1)>0,OR($D23="03. UX Discovery",$D23="04. UX Design")),IF(AND($H23<>"",$H23<=EOMONTH(J$12,0),$I23>=J$12),"UX+DEV","UX"),IF(AND($H23<>"",$H23<=EOMONTH(J$12,0),$I23>=J$12),"DEV","")))) | K23: =IF($AI23="","",IF(AND($AN23<>"",$AN23<=EOMONTH(K$12,0),$AO23>=K$12),IF(AND(INDEX('Roadmap Calc (Don’t Touch)'!$AA$2:$AX$151,$AI23,COLUMN()-COLUMN($J$16)+1)>0,OR($D23="03. UX Discovery",$D23="04. UX Design")),IF(AND($H23<>"",$H23<=EOMONTH(K$12,0),$I23>=K$12),"ALL","PD+UX"),IF(AND($H23<>"",$H23<=EOMONTH(K$12,0),$I23>=K$12),"PD+DEV","PD")),IF(AND(INDEX('Roadmap Calc (Don’t Touch)'!$AA$2:$AX$151,$AI23,COLUMN()-COLUMN($J$16)+1)>0,OR($D23="03. UX Discovery",$D23="04. UX Design")),IF(AND($H23<>"",$H23<=EOMONTH(K$12,0),$I23>=K$12),"UX+DEV","UX"),IF(AND($H23<>"",$H23<=EOMONTH(K$12,0),$I23>=K$12),"DEV","")))) | L23: =IF($AI23="","",IF(AND($AN23<>"",$AN23<=EOMONTH(L$12,0),$AO23>=L$12),IF(AND(INDEX('Roadmap Calc (Don’t Touch)'!$AA$2:$AX$151,$AI23,COLUMN()-COLUMN($J$16)+1)>0,OR($D23="03. UX Discovery",$D23="04. UX Design")),IF(AND($H23<>"",$H23<=EOMONTH(L$12,0),$I23>=L$12),"ALL","PD+UX"),IF(AND($H23<>"",$H23<=EOMONTH(L$12,0),$I23>=L$12),"PD+DEV","PD")),IF(AND(INDEX('Roadmap Calc (Don’t Touch)'!$AA$2:$AX$151,$AI23,COLUMN()-COLUMN($J$16)+1)>0,OR($D23="03. UX Discovery",$D23="04. UX Design")),IF(AND($H23<>"",$H23<=EOMONTH(L$12,0),$I23>=L$12),"UX+DEV","UX"),IF(AND($H23<>"",$H23<=EOMONTH(L$12,0),$I23>=L$12),"DEV","")))) | M23: =IF($AI23="","",IF(AND($AN23<>"",$AN23<=EOMONTH(M$12,0),$AO23>=M$12),IF(AND(INDEX('Roadmap Calc (Don’t Touch)'!$AA$2:$AX$151,$AI23,COLUMN()-COLUMN($J$16)+1)>0,OR($D23="03. UX Discovery",$D23="04. UX Design")),IF(AND($H23<>"",$H23<=EOMONTH(M$12,0),$I23>=M$12),"ALL","PD+UX"),IF(AND($H23<>"",$H23<=EOMONTH(M$12,0),$I23>=M$12),"PD+DEV","PD")),IF(AND(INDEX('Roadmap Calc (Don’t Touch)'!$AA$2:$AX$151,$AI23,COLUMN()-COLUMN($J$16)+1)>0,OR($D23="03. UX Discovery",$D23="04. UX Design")),IF(AND($H23<>"",$H23<=EOMONTH(M$12,0),$I23>=M$12),"UX+DEV","UX"),IF(AND($H23<>"",$H23<=EOMONTH(M$12,0),$I23>=M$12),"DEV","")))) | N23: =IF($AI23="","",IF(AND($AN23<>"",$AN23<=EOMONTH(N$12,0),$AO23>=N$12),IF(AND(INDEX('Roadmap Calc (Don’t Touch)'!$AA$2:$AX$151,$AI23,COLUMN()-COLUMN($J$16)+1)>0,OR($D23="03. UX Discovery",$D23="04. UX Design")),IF(AND($H23<>"",$H23<=EOMONTH(N$12,0),$I23>=N$12),"ALL","PD+UX"),IF(AND($H23<>"",$H23<=EOMONTH(N$12,0),$I23>=N$12),"PD+DEV","PD")),IF(AND(INDEX('Roadmap Calc (Don’t Touch)'!$AA$2:$AX$151,$AI23,COLUMN()-COLUMN($J$16)+1)>0,OR($D23="03. UX Discovery",$D23="04. UX Design")),IF(AND($H23<>"",$H23<=EOMONTH(N$12,0),$I23>=N$12),"UX+DEV","UX"),IF(AND($H23<>"",$H23<=EOMONTH(N$12,0),$I23>=N$12),"DEV","")))) | O23: =IF($AI23="","",IF(AND($AN23<>"",$AN23<=EOMONTH(O$12,0),$AO23>=O$12),IF(AND(INDEX('Roadmap Calc (Don’t Touch)'!$AA$2:$AX$151,$AI23,COLUMN()-COLUMN($J$16)+1)>0,OR($D23="03. UX Discovery",$D23="04. UX Design")),IF(AND($H23<>"",$H23<=EOMONTH(O$12,0),$I23>=O$12),"ALL","PD+UX"),IF(AND($H23<>"",$H23<=EOMONTH(O$12,0),$I23>=O$12),"PD+DEV","PD")),IF(AND(INDEX('Roadmap Calc (Don’t Touch)'!$AA$2:$AX$151,$AI23,COLUMN()-COLUMN($J$16)+1)>0,OR($D23="03. UX Discovery",$D23="04. UX Design")),IF(AND($H23<>"",$H23<=EOMONTH(O$12,0),$I23>=O$12),"UX+DEV","UX"),IF(AND($H23<>"",$H23<=EOMONTH(O$12,0),$I23>=O$12),"DEV","")))) | P23: =IF($AI23="","",IF(AND($AN23<>"",$AN23<=EOMONTH(P$12,0),$AO23>=P$12),IF(AND(INDEX('Roadmap Calc (Don’t Touch)'!$AA$2:$AX$151,$AI23,COLUMN()-COLUMN($J$16)+1)>0,OR($D23="03. UX Discovery",$D23="04. UX Design")),IF(AND($H23<>"",$H23<=EOMONTH(P$12,0),$I23>=P$12),"ALL","PD+UX"),IF(AND($H23<>"",$H23<=EOMONTH(P$12,0),$I23>=P$12),"PD+DEV","PD")),IF(AND(INDEX('Roadmap Calc (Don’t Touch)'!$AA$2:$AX$151,$AI23,COLUMN()-COLUMN($J$16)+1)>0,OR($D23="03. UX Discovery",$D23="04. UX Design")),IF(AND($H23<>"",$H23<=EOMONTH(P$12,0),$I23>=P$12),"UX+DEV","UX"),IF(AND($H23<>"",$H23<=EOMONTH(P$12,0),$I23>=P$12),"DEV","")))) | Q23: =IF($AI23="","",IF(AND($AN23<>"",$AN23<=EOMONTH(Q$12,0),$AO23>=Q$12),IF(AND(INDEX('Roadmap Calc (Don’t Touch)'!$AA$2:$AX$151,$AI23,COLUMN()-COLUMN($J$16)+1)>0,OR($D23="03. UX Discovery",$D23="04. UX Design")),IF(AND($H23<>"",$H23<=EOMONTH(Q$12,0),$I23>=Q$12),"ALL","PD+UX"),IF(AND($H23<>"",$H23<=EOMONTH(Q$12,0),$I23>=Q$12),"PD+DEV","PD")),IF(AND(INDEX('Roadmap Calc (Don’t Touch)'!$AA$2:$AX$151,$AI23,COLUMN()-COLUMN($J$16)+1)>0,OR($D23="03. UX Discovery",$D23="04. UX Design")),IF(AND($H23<>"",$H23<=EOMONTH(Q$12,0),$I23>=Q$12),"UX+DEV","UX"),IF(AND($H23<>"",$H23<=EOMONTH(Q$12,0),$I23>=Q$12),"DEV","")))) | ... AG23: =IF($AI23="","",IF(AND($AN23<>"",$AN23<=EOMONTH(AG$12,0),$AO23>=AG$12),IF(AND(INDEX('Roadmap Calc (Don’t Touch)'!$AA$2:$AX$151,$AI23,COLUMN()-COLUMN($J$16)+1)>0,OR($D23="03. UX Discovery",$D23="04. UX Design")),IF(AND($H23<>"",$H23<=EOMONTH(AG$12,0),$I23>=AG$12),"ALL","PD+UX"),IF(AND($H23<>"",$H23<=EOMONTH(AG$12,0),$I23>=AG$12),"PD+DEV","PD")),IF(AND(INDEX('Roadmap Calc (Don’t Touch)'!$AA$2:$AX$151,$AI23,COLUMN()-COLUMN($J$16)+1)>0,OR($D23="03. UX Discovery",$D23="04. UX Design")),IF(AND($H23<>"",$H23<=EOMONTH(AG$12,0),$I23>=AG$12),"UX+DEV","UX"),IF(AND($H23<>"",$H23<=EOMONTH(AG$12,0),$I23>=AG$12),"DEV","")))) | AH23: =IF($AI23="","",INDEX('Roadmap Calc (Don’t Touch)'!$D$2:$D$151,$AI23)) -> Improve Trade In User Flow | AI23: =IFERROR(MATCH(8,'Roadmap Calc (Don’t Touch)'!$O$2:$O$151,0),"") -> 21 | AL23: =IF(COUNTA(Control!B21)=0,"",Control!B21) | AN23: =IF($AI23="","",IF(ISNUMBER(INDEX('Roadmap Calc (Don’t Touch)'!$BB$2:$BB$151,$AI23)),INDEX('Roadmap Calc (Don’t Touch)'!$BB$2:$BB$151,$AI23),"")) | AO23: =IF($AI23="","",IF(ISNUMBER(INDEX('Roadmap Calc (Don’t Touch)'!$BC$2:$BC$151,$AI23)),INDEX('Roadmap Calc (Don’t Touch)'!$BC$2:$BC$151,$AI23),""))
A24: =IF($AI24="","",IF($AH24=$AH23,"",IF(INDEX('Roadmap Calc (Don’t Touch)'!$U$2:$U$151,$AI24)=0,$AH24,HYPERLINK("#'Control (Don’t Touch)'!E"&INDEX('Roadmap Calc (Don’t Touch)'!$U$2:$U$151,$AI24),$AH24)))) | B24: =IF($AI24="","",IF(INDEX('Roadmap Calc (Don’t Touch)'!$K$2:$K$151,$AI24)="",INDEX('Roadmap Calc (Don’t Touch)'!$B$2:$B$151,$AI24),HYPERLINK("https://jira.bnh.com/browse/"&INDEX('Roadmap Calc (Don’t Touch)'!$K$2:$K$151,$AI24),INDEX('Roadmap Calc (Don’t Touch)'!$B$2:$B$151,$AI24)))) -> Used - Sell Used Experience | C24: =IF($AI24="","",IF(INDEX('Roadmap Calc (Don’t Touch)'!$E$2:$E$151,$AI24)="","",HYPERLINK("https://jira.bnh.com/browse/"&INDEX('Roadmap Calc (Don’t Touch)'!$E$2:$E$151,$AI24),INDEX('Roadmap Calc (Don’t Touch)'!$E$2:$E$151,$AI24)))) -> BHUX-33009 | D24: =IF($AI24="","",INDEX('Roadmap Calc (Don’t Touch)'!$F$2:$F$151,$AI24)) -> 04. UX Design | E24: =IF($AI24="","",IF(ISNUMBER(INDEX('Roadmap Calc (Don’t Touch)'!$G$2:$G$151,$AI24)),INDEX('Roadmap Calc (Don’t Touch)'!$G$2:$G$151,$AI24),"")) -> 46132 | F24: =IF($AI24="","",IF(ISNUMBER(INDEX('Roadmap Calc (Don’t Touch)'!$H$2:$H$151,$AI24)),INDEX('Roadmap Calc (Don’t Touch)'!$H$2:$H$151,$AI24),"")) -> 46293 | G24: =IF($AI24="","",INDEX('Roadmap Calc (Don’t Touch)'!$T$2:$T$151,$AI24)) -> 24 | H24: =IF($AI24="","",IF(ISNUMBER(INDEX('Roadmap Calc (Don’t Touch)'!$I$2:$I$151,$AI24)),INDEX('Roadmap Calc (Don’t Touch)'!$I$2:$I$151,$AI24),"")) -> 46388 | I24: =IF($AI24="","",IF(ISNUMBER(INDEX('Roadmap Calc (Don’t Touch)'!$J$2:$J$151,$AI24)),INDEX('Roadmap Calc (Don’t Touch)'!$J$2:$J$151,$AI24),"")) -> 46477 | J24: =IF($AI24="","",IF(AND($AN24<>"",$AN24<=EOMONTH(J$12,0),$AO24>=J$12),IF(AND(INDEX('Roadmap Calc (Don’t Touch)'!$AA$2:$AX$151,$AI24,COLUMN()-COLUMN($J$16)+1)>0,OR($D24="03. UX Discovery",$D24="04. UX Design")),IF(AND($H24<>"",$H24<=EOMONTH(J$12,0),$I24>=J$12),"ALL","PD+UX"),IF(AND($H24<>"",$H24<=EOMONTH(J$12,0),$I24>=J$12),"PD+DEV","PD")),IF(AND(INDEX('Roadmap Calc (Don’t Touch)'!$AA$2:$AX$151,$AI24,COLUMN()-COLUMN($J$16)+1)>0,OR($D24="03. UX Discovery",$D24="04. UX Design")),IF(AND($H24<>"",$H24<=EOMONTH(J$12,0),$I24>=J$12),"UX+DEV","UX"),IF(AND($H24<>"",$H24<=EOMONTH(J$12,0),$I24>=J$12),"DEV","")))) | K24: =IF($AI24="","",IF(AND($AN24<>"",$AN24<=EOMONTH(K$12,0),$AO24>=K$12),IF(AND(INDEX('Roadmap Calc (Don’t Touch)'!$AA$2:$AX$151,$AI24,COLUMN()-COLUMN($J$16)+1)>0,OR($D24="03. UX Discovery",$D24="04. UX Design")),IF(AND($H24<>"",$H24<=EOMONTH(K$12,0),$I24>=K$12),"ALL","PD+UX"),IF(AND($H24<>"",$H24<=EOMONTH(K$12,0),$I24>=K$12),"PD+DEV","PD")),IF(AND(INDEX('Roadmap Calc (Don’t Touch)'!$AA$2:$AX$151,$AI24,COLUMN()-COLUMN($J$16)+1)>0,OR($D24="03. UX Discovery",$D24="04. UX Design")),IF(AND($H24<>"",$H24<=EOMONTH(K$12,0),$I24>=K$12),"UX+DEV","UX"),IF(AND($H24<>"",$H24<=EOMONTH(K$12,0),$I24>=K$12),"DEV","")))) | L24: =IF($AI24="","",IF(AND($AN24<>"",$AN24<=EOMONTH(L$12,0),$AO24>=L$12),IF(AND(INDEX('Roadmap Calc (Don’t Touch)'!$AA$2:$AX$151,$AI24,COLUMN()-COLUMN($J$16)+1)>0,OR($D24="03. UX Discovery",$D24="04. UX Design")),IF(AND($H24<>"",$H24<=EOMONTH(L$12,0),$I24>=L$12),"ALL","PD+UX"),IF(AND($H24<>"",$H24<=EOMONTH(L$12,0),$I24>=L$12),"PD+DEV","PD")),IF(AND(INDEX('Roadmap Calc (Don’t Touch)'!$AA$2:$AX$151,$AI24,COLUMN()-COLUMN($J$16)+1)>0,OR($D24="03. UX Discovery",$D24="04. UX Design")),IF(AND($H24<>"",$H24<=EOMONTH(L$12,0),$I24>=L$12),"UX+DEV","UX"),IF(AND($H24<>"",$H24<=EOMONTH(L$12,0),$I24>=L$12),"DEV","")))) | M24: =IF($AI24="","",IF(AND($AN24<>"",$AN24<=EOMONTH(M$12,0),$AO24>=M$12),IF(AND(INDEX('Roadmap Calc (Don’t Touch)'!$AA$2:$AX$151,$AI24,COLUMN()-COLUMN($J$16)+1)>0,OR($D24="03. UX Discovery",$D24="04. UX Design")),IF(AND($H24<>"",$H24<=EOMONTH(M$12,0),$I24>=M$12),"ALL","PD+UX"),IF(AND($H24<>"",$H24<=EOMONTH(M$12,0),$I24>=M$12),"PD+DEV","PD")),IF(AND(INDEX('Roadmap Calc (Don’t Touch)'!$AA$2:$AX$151,$AI24,COLUMN()-COLUMN($J$16)+1)>0,OR($D24="03. UX Discovery",$D24="04. UX Design")),IF(AND($H24<>"",$H24<=EOMONTH(M$12,0),$I24>=M$12),"UX+DEV","UX"),IF(AND($H24<>"",$H24<=EOMONTH(M$12,0),$I24>=M$12),"DEV","")))) | N24: =IF($AI24="","",IF(AND($AN24<>"",$AN24<=EOMONTH(N$12,0),$AO24>=N$12),IF(AND(INDEX('Roadmap Calc (Don’t Touch)'!$AA$2:$AX$151,$AI24,COLUMN()-COLUMN($J$16)+1)>0,OR($D24="03. UX Discovery",$D24="04. UX Design")),IF(AND($H24<>"",$H24<=EOMONTH(N$12,0),$I24>=N$12),"ALL","PD+UX"),IF(AND($H24<>"",$H24<=EOMONTH(N$12,0),$I24>=N$12),"PD+DEV","PD")),IF(AND(INDEX('Roadmap Calc (Don’t Touch)'!$AA$2:$AX$151,$AI24,COLUMN()-COLUMN($J$16)+1)>0,OR($D24="03. UX Discovery",$D24="04. UX Design")),IF(AND($H24<>"",$H24<=EOMONTH(N$12,0),$I24>=N$12),"UX+DEV","UX"),IF(AND($H24<>"",$H24<=EOMONTH(N$12,0),$I24>=N$12),"DEV","")))) | O24: =IF($AI24="","",IF(AND($AN24<>"",$AN24<=EOMONTH(O$12,0),$AO24>=O$12),IF(AND(INDEX('Roadmap Calc (Don’t Touch)'!$AA$2:$AX$151,$AI24,COLUMN()-COLUMN($J$16)+1)>0,OR($D24="03. UX Discovery",$D24="04. UX Design")),IF(AND($H24<>"",$H24<=EOMONTH(O$12,0),$I24>=O$12),"ALL","PD+UX"),IF(AND($H24<>"",$H24<=EOMONTH(O$12,0),$I24>=O$12),"PD+DEV","PD")),IF(AND(INDEX('Roadmap Calc (Don’t Touch)'!$AA$2:$AX$151,$AI24,COLUMN()-COLUMN($J$16)+1)>0,OR($D24="03. UX Discovery",$D24="04. UX Design")),IF(AND($H24<>"",$H24<=EOMONTH(O$12,0),$I24>=O$12),"UX+DEV","UX"),IF(AND($H24<>"",$H24<=EOMONTH(O$12,0),$I24>=O$12),"DEV","")))) | P24: =IF($AI24="","",IF(AND($AN24<>"",$AN24<=EOMONTH(P$12,0),$AO24>=P$12),IF(AND(INDEX('Roadmap Calc (Don’t Touch)'!$AA$2:$AX$151,$AI24,COLUMN()-COLUMN($J$16)+1)>0,OR($D24="03. UX Discovery",$D24="04. UX Design")),IF(AND($H24<>"",$H24<=EOMONTH(P$12,0),$I24>=P$12),"ALL","PD+UX"),IF(AND($H24<>"",$H24<=EOMONTH(P$12,0),$I24>=P$12),"PD+DEV","PD")),IF(AND(INDEX('Roadmap Calc (Don’t Touch)'!$AA$2:$AX$151,$AI24,COLUMN()-COLUMN($J$16)+1)>0,OR($D24="03. UX Discovery",$D24="04. UX Design")),IF(AND($H24<>"",$H24<=EOMONTH(P$12,0),$I24>=P$12),"UX+DEV","UX"),IF(AND($H24<>"",$H24<=EOMONTH(P$12,0),$I24>=P$12),"DEV","")))) | Q24: =IF($AI24="","",IF(AND($AN24<>"",$AN24<=EOMONTH(Q$12,0),$AO24>=Q$12),IF(AND(INDEX('Roadmap Calc (Don’t Touch)'!$AA$2:$AX$151,$AI24,COLUMN()-COLUMN($J$16)+1)>0,OR($D24="03. UX Discovery",$D24="04. UX Design")),IF(AND($H24<>"",$H24<=EOMONTH(Q$12,0),$I24>=Q$12),"ALL","PD+UX"),IF(AND($H24<>"",$H24<=EOMONTH(Q$12,0),$I24>=Q$12),"PD+DEV","PD")),IF(AND(INDEX('Roadmap Calc (Don’t Touch)'!$AA$2:$AX$151,$AI24,COLUMN()-COLUMN($J$16)+1)>0,OR($D24="03. UX Discovery",$D24="04. UX Design")),IF(AND($H24<>"",$H24<=EOMONTH(Q$12,0),$I24>=Q$12),"UX+DEV","UX"),IF(AND($H24<>"",$H24<=EOMONTH(Q$12,0),$I24>=Q$12),"DEV","")))) | ... AG24: =IF($AI24="","",IF(AND($AN24<>"",$AN24<=EOMONTH(AG$12,0),$AO24>=AG$12),IF(AND(INDEX('Roadmap Calc (Don’t Touch)'!$AA$2:$AX$151,$AI24,COLUMN()-COLUMN($J$16)+1)>0,OR($D24="03. UX Discovery",$D24="04. UX Design")),IF(AND($H24<>"",$H24<=EOMONTH(AG$12,0),$I24>=AG$12),"ALL","PD+UX"),IF(AND($H24<>"",$H24<=EOMONTH(AG$12,0),$I24>=AG$12),"PD+DEV","PD")),IF(AND(INDEX('Roadmap Calc (Don’t Touch)'!$AA$2:$AX$151,$AI24,COLUMN()-COLUMN($J$16)+1)>0,OR($D24="03. UX Discovery",$D24="04. UX Design")),IF(AND($H24<>"",$H24<=EOMONTH(AG$12,0),$I24>=AG$12),"UX+DEV","UX"),IF(AND($H24<>"",$H24<=EOMONTH(AG$12,0),$I24>=AG$12),"DEV","")))) | AH24: =IF($AI24="","",INDEX('Roadmap Calc (Don’t Touch)'!$D$2:$D$151,$AI24)) -> Improve Trade In User Flow | AI24: =IFERROR(MATCH(9,'Roadmap Calc (Don’t Touch)'!$O$2:$O$151,0),"") -> 22 | AL24: =IF(COUNTA(Control!B22)=0,"",Control!B22) | AN24: =IF($AI24="","",IF(ISNUMBER(INDEX('Roadmap Calc (Don’t Touch)'!$BB$2:$BB$151,$AI24)),INDEX('Roadmap Calc (Don’t Touch)'!$BB$2:$BB$151,$AI24),"")) | AO24: =IF($AI24="","",IF(ISNUMBER(INDEX('Roadmap Calc (Don’t Touch)'!$BC$2:$BC$151,$AI24)),INDEX('Roadmap Calc (Don’t Touch)'!$BC$2:$BC$151,$AI24),""))
A25: =IF($AI25="","",IF($AH25=$AH24,"",IF(INDEX('Roadmap Calc (Don’t Touch)'!$U$2:$U$151,$AI25)=0,$AH25,HYPERLINK("#'Control (Don’t Touch)'!E"&INDEX('Roadmap Calc (Don’t Touch)'!$U$2:$U$151,$AI25),$AH25)))) | B25: =IF($AI25="","",IF(INDEX('Roadmap Calc (Don’t Touch)'!$K$2:$K$151,$AI25)="",INDEX('Roadmap Calc (Don’t Touch)'!$B$2:$B$151,$AI25),HYPERLINK("https://jira.bnh.com/browse/"&INDEX('Roadmap Calc (Don’t Touch)'!$K$2:$K$151,$AI25),INDEX('Roadmap Calc (Don’t Touch)'!$B$2:$B$151,$AI25)))) -> Sell Used User Flow Design Validation | C25: =IF($AI25="","",IF(INDEX('Roadmap Calc (Don’t Touch)'!$E$2:$E$151,$AI25)="","",HYPERLINK("https://jira.bnh.com/browse/"&INDEX('Roadmap Calc (Don’t Touch)'!$E$2:$E$151,$AI25),INDEX('Roadmap Calc (Don’t Touch)'!$E$2:$E$151,$AI25)))) -> BHUR-133 | D25: =IF($AI25="","",INDEX('Roadmap Calc (Don’t Touch)'!$F$2:$F$151,$AI25)) -> 04A. Research - Design Validation | E25: =IF($AI25="","",IF(ISNUMBER(INDEX('Roadmap Calc (Don’t Touch)'!$G$2:$G$151,$AI25)),INDEX('Roadmap Calc (Don’t Touch)'!$G$2:$G$151,$AI25),"")) -> 46209 | F25: =IF($AI25="","",IF(ISNUMBER(INDEX('Roadmap Calc (Don’t Touch)'!$H$2:$H$151,$AI25)),INDEX('Roadmap Calc (Don’t Touch)'!$H$2:$H$151,$AI25),"")) -> 46272 | G25: =IF($AI25="","",INDEX('Roadmap Calc (Don’t Touch)'!$T$2:$T$151,$AI25)) -> 10 | H25: =IF($AI25="","",IF(ISNUMBER(INDEX('Roadmap Calc (Don’t Touch)'!$I$2:$I$151,$AI25)),INDEX('Roadmap Calc (Don’t Touch)'!$I$2:$I$151,$AI25),"")) | I25: =IF($AI25="","",IF(ISNUMBER(INDEX('Roadmap Calc (Don’t Touch)'!$J$2:$J$151,$AI25)),INDEX('Roadmap Calc (Don’t Touch)'!$J$2:$J$151,$AI25),"")) | J25: =IF($AI25="","",IF(AND($AN25<>"",$AN25<=EOMONTH(J$12,0),$AO25>=J$12),IF(AND(INDEX('Roadmap Calc (Don’t Touch)'!$AA$2:$AX$151,$AI25,COLUMN()-COLUMN($J$16)+1)>0,OR($D25="03. UX Discovery",$D25="04. UX Design")),IF(AND($H25<>"",$H25<=EOMONTH(J$12,0),$I25>=J$12),"ALL","PD+UX"),IF(AND($H25<>"",$H25<=EOMONTH(J$12,0),$I25>=J$12),"PD+DEV","PD")),IF(AND(INDEX('Roadmap Calc (Don’t Touch)'!$AA$2:$AX$151,$AI25,COLUMN()-COLUMN($J$16)+1)>0,OR($D25="03. UX Discovery",$D25="04. UX Design")),IF(AND($H25<>"",$H25<=EOMONTH(J$12,0),$I25>=J$12),"UX+DEV","UX"),IF(AND($H25<>"",$H25<=EOMONTH(J$12,0),$I25>=J$12),"DEV","")))) | K25: =IF($AI25="","",IF(AND($AN25<>"",$AN25<=EOMONTH(K$12,0),$AO25>=K$12),IF(AND(INDEX('Roadmap Calc (Don’t Touch)'!$AA$2:$AX$151,$AI25,COLUMN()-COLUMN($J$16)+1)>0,OR($D25="03. UX Discovery",$D25="04. UX Design")),IF(AND($H25<>"",$H25<=EOMONTH(K$12,0),$I25>=K$12),"ALL","PD+UX"),IF(AND($H25<>"",$H25<=EOMONTH(K$12,0),$I25>=K$12),"PD+DEV","PD")),IF(AND(INDEX('Roadmap Calc (Don’t Touch)'!$AA$2:$AX$151,$AI25,COLUMN()-COLUMN($J$16)+1)>0,OR($D25="03. UX Discovery",$D25="04. UX Design")),IF(AND($H25<>"",$H25<=EOMONTH(K$12,0),$I25>=K$12),"UX+DEV","UX"),IF(AND($H25<>"",$H25<=EOMONTH(K$12,0),$I25>=K$12),"DEV","")))) | L25: =IF($AI25="","",IF(AND($AN25<>"",$AN25<=EOMONTH(L$12,0),$AO25>=L$12),IF(AND(INDEX('Roadmap Calc (Don’t Touch)'!$AA$2:$AX$151,$AI25,COLUMN()-COLUMN($J$16)+1)>0,OR($D25="03. UX Discovery",$D25="04. UX Design")),IF(AND($H25<>"",$H25<=EOMONTH(L$12,0),$I25>=L$12),"ALL","PD+UX"),IF(AND($H25<>"",$H25<=EOMONTH(L$12,0),$I25>=L$12),"PD+DEV","PD")),IF(AND(INDEX('Roadmap Calc (Don’t Touch)'!$AA$2:$AX$151,$AI25,COLUMN()-COLUMN($J$16)+1)>0,OR($D25="03. UX Discovery",$D25="04. UX Design")),IF(AND($H25<>"",$H25<=EOMONTH(L$12,0),$I25>=L$12),"UX+DEV","UX"),IF(AND($H25<>"",$H25<=EOMONTH(L$12,0),$I25>=L$12),"DEV","")))) | M25: =IF($AI25="","",IF(AND($AN25<>"",$AN25<=EOMONTH(M$12,0),$AO25>=M$12),IF(AND(INDEX('Roadmap Calc (Don’t Touch)'!$AA$2:$AX$151,$AI25,COLUMN()-COLUMN($J$16)+1)>0,OR($D25="03. UX Discovery",$D25="04. UX Design")),IF(AND($H25<>"",$H25<=EOMONTH(M$12,0),$I25>=M$12),"ALL","PD+UX"),IF(AND($H25<>"",$H25<=EOMONTH(M$12,0),$I25>=M$12),"PD+DEV","PD")),IF(AND(INDEX('Roadmap Calc (Don’t Touch)'!$AA$2:$AX$151,$AI25,COLUMN()-COLUMN($J$16)+1)>0,OR($D25="03. UX Discovery",$D25="04. UX Design")),IF(AND($H25<>"",$H25<=EOMONTH(M$12,0),$I25>=M$12),"UX+DEV","UX"),IF(AND($H25<>"",$H25<=EOMONTH(M$12,0),$I25>=M$12),"DEV","")))) | N25: =IF($AI25="","",IF(AND($AN25<>"",$AN25<=EOMONTH(N$12,0),$AO25>=N$12),IF(AND(INDEX('Roadmap Calc (Don’t Touch)'!$AA$2:$AX$151,$AI25,COLUMN()-COLUMN($J$16)+1)>0,OR($D25="03. UX Discovery",$D25="04. UX Design")),IF(AND($H25<>"",$H25<=EOMONTH(N$12,0),$I25>=N$12),"ALL","PD+UX"),IF(AND($H25<>"",$H25<=EOMONTH(N$12,0),$I25>=N$12),"PD+DEV","PD")),IF(AND(INDEX('Roadmap Calc (Don’t Touch)'!$AA$2:$AX$151,$AI25,COLUMN()-COLUMN($J$16)+1)>0,OR($D25="03. UX Discovery",$D25="04. UX Design")),IF(AND($H25<>"",$H25<=EOMONTH(N$12,0),$I25>=N$12),"UX+DEV","UX"),IF(AND($H25<>"",$H25<=EOMONTH(N$12,0),$I25>=N$12),"DEV","")))) | O25: =IF($AI25="","",IF(AND($AN25<>"",$AN25<=EOMONTH(O$12,0),$AO25>=O$12),IF(AND(INDEX('Roadmap Calc (Don’t Touch)'!$AA$2:$AX$151,$AI25,COLUMN()-COLUMN($J$16)+1)>0,OR($D25="03. UX Discovery",$D25="04. UX Design")),IF(AND($H25<>"",$H25<=EOMONTH(O$12,0),$I25>=O$12),"ALL","PD+UX"),IF(AND($H25<>"",$H25<=EOMONTH(O$12,0),$I25>=O$12),"PD+DEV","PD")),IF(AND(INDEX('Roadmap Calc (Don’t Touch)'!$AA$2:$AX$151,$AI25,COLUMN()-COLUMN($J$16)+1)>0,OR($D25="03. UX Discovery",$D25="04. UX Design")),IF(AND($H25<>"",$H25<=EOMONTH(O$12,0),$I25>=O$12),"UX+DEV","UX"),IF(AND($H25<>"",$H25<=EOMONTH(O$12,0),$I25>=O$12),"DEV","")))) | P25: =IF($AI25="","",IF(AND($AN25<>"",$AN25<=EOMONTH(P$12,0),$AO25>=P$12),IF(AND(INDEX('Roadmap Calc (Don’t Touch)'!$AA$2:$AX$151,$AI25,COLUMN()-COLUMN($J$16)+1)>0,OR($D25="03. UX Discovery",$D25="04. UX Design")),IF(AND($H25<>"",$H25<=EOMONTH(P$12,0),$I25>=P$12),"ALL","PD+UX"),IF(AND($H25<>"",$H25<=EOMONTH(P$12,0),$I25>=P$12),"PD+DEV","PD")),IF(AND(INDEX('Roadmap Calc (Don’t Touch)'!$AA$2:$AX$151,$AI25,COLUMN()-COLUMN($J$16)+1)>0,OR($D25="03. UX Discovery",$D25="04. UX Design")),IF(AND($H25<>"",$H25<=EOMONTH(P$12,0),$I25>=P$12),"UX+DEV","UX"),IF(AND($H25<>"",$H25<=EOMONTH(P$12,0),$I25>=P$12),"DEV","")))) | Q25: =IF($AI25="","",IF(AND($AN25<>"",$AN25<=EOMONTH(Q$12,0),$AO25>=Q$12),IF(AND(INDEX('Roadmap Calc (Don’t Touch)'!$AA$2:$AX$151,$AI25,COLUMN()-COLUMN($J$16)+1)>0,OR($D25="03. UX Discovery",$D25="04. UX Design")),IF(AND($H25<>"",$H25<=EOMONTH(Q$12,0),$I25>=Q$12),"ALL","PD+UX"),IF(AND($H25<>"",$H25<=EOMONTH(Q$12,0),$I25>=Q$12),"PD+DEV","PD")),IF(AND(INDEX('Roadmap Calc (Don’t Touch)'!$AA$2:$AX$151,$AI25,COLUMN()-COLUMN($J$16)+1)>0,OR($D25="03. UX Discovery",$D25="04. UX Design")),IF(AND($H25<>"",$H25<=EOMONTH(Q$12,0),$I25>=Q$12),"UX+DEV","UX"),IF(AND($H25<>"",$H25<=EOMONTH(Q$12,0),$I25>=Q$12),"DEV","")))) | ... AG25: =IF($AI25="","",IF(AND($AN25<>"",$AN25<=EOMONTH(AG$12,0),$AO25>=AG$12),IF(AND(INDEX('Roadmap Calc (Don’t Touch)'!$AA$2:$AX$151,$AI25,COLUMN()-COLUMN($J$16)+1)>0,OR($D25="03. UX Discovery",$D25="04. UX Design")),IF(AND($H25<>"",$H25<=EOMONTH(AG$12,0),$I25>=AG$12),"ALL","PD+UX"),IF(AND($H25<>"",$H25<=EOMONTH(AG$12,0),$I25>=AG$12),"PD+DEV","PD")),IF(AND(INDEX('Roadmap Calc (Don’t Touch)'!$AA$2:$AX$151,$AI25,COLUMN()-COLUMN($J$16)+1)>0,OR($D25="03. UX Discovery",$D25="04. UX Design")),IF(AND($H25<>"",$H25<=EOMONTH(AG$12,0),$I25>=AG$12),"UX+DEV","UX"),IF(AND($H25<>"",$H25<=EOMONTH(AG$12,0),$I25>=AG$12),"DEV","")))) | AH25: =IF($AI25="","",INDEX('Roadmap Calc (Don’t Touch)'!$D$2:$D$151,$AI25)) -> Improve Trade In User Flow | AI25: =IFERROR(MATCH(10,'Roadmap Calc (Don’t Touch)'!$O$2:$O$151,0),"") -> 27 | AN25: =IF($AI25="","",IF(ISNUMBER(INDEX('Roadmap Calc (Don’t Touch)'!$BB$2:$BB$151,$AI25)),INDEX('Roadmap Calc (Don’t Touch)'!$BB$2:$BB$151,$AI25),"")) | AO25: =IF($AI25="","",IF(ISNUMBER(INDEX('Roadmap Calc (Don’t Touch)'!$BC$2:$BC$151,$AI25)),INDEX('Roadmap Calc (Don’t Touch)'!$BC$2:$BC$151,$AI25),""))
A26: =IF($AI26="","",IF($AH26=$AH25,"",IF(INDEX('Roadmap Calc (Don’t Touch)'!$U$2:$U$151,$AI26)=0,$AH26,HYPERLINK("#'Control (Don’t Touch)'!E"&INDEX('Roadmap Calc (Don’t Touch)'!$U$2:$U$151,$AI26),$AH26)))) | B26: =IF($AI26="","",IF(INDEX('Roadmap Calc (Don’t Touch)'!$K$2:$K$151,$AI26)="",INDEX('Roadmap Calc (Don’t Touch)'!$B$2:$B$151,$AI26),HYPERLINK("https://jira.bnh.com/browse/"&INDEX('Roadmap Calc (Don’t Touch)'!$K$2:$K$151,$AI26),INDEX('Roadmap Calc (Don’t Touch)'!$B$2:$B$151,$AI26)))) -> Used Status Email Update | C26: =IF($AI26="","",IF(INDEX('Roadmap Calc (Don’t Touch)'!$E$2:$E$151,$AI26)="","",HYPERLINK("https://jira.bnh.com/browse/"&INDEX('Roadmap Calc (Don’t Touch)'!$E$2:$E$151,$AI26),INDEX('Roadmap Calc (Don’t Touch)'!$E$2:$E$151,$AI26)))) -> BHUX-34723 | D26: =IF($AI26="","",INDEX('Roadmap Calc (Don’t Touch)'!$F$2:$F$151,$AI26)) -> 06. Architecture | E26: =IF($AI26="","",IF(ISNUMBER(INDEX('Roadmap Calc (Don’t Touch)'!$G$2:$G$151,$AI26)),INDEX('Roadmap Calc (Don’t Touch)'!$G$2:$G$151,$AI26),"")) -> 46216 | F26: =IF($AI26="","",IF(ISNUMBER(INDEX('Roadmap Calc (Don’t Touch)'!$H$2:$H$151,$AI26)),INDEX('Roadmap Calc (Don’t Touch)'!$H$2:$H$151,$AI26),"")) -> 46216 | G26: =IF($AI26="","",INDEX('Roadmap Calc (Don’t Touch)'!$T$2:$T$151,$AI26)) -> 1 | H26: =IF($AI26="","",IF(ISNUMBER(INDEX('Roadmap Calc (Don’t Touch)'!$I$2:$I$151,$AI26)),INDEX('Roadmap Calc (Don’t Touch)'!$I$2:$I$151,$AI26),"")) -> 46296 | I26: =IF($AI26="","",IF(ISNUMBER(INDEX('Roadmap Calc (Don’t Touch)'!$J$2:$J$151,$AI26)),INDEX('Roadmap Calc (Don’t Touch)'!$J$2:$J$151,$AI26),"")) -> 46326 | J26: =IF($AI26="","",IF(AND($AN26<>"",$AN26<=EOMONTH(J$12,0),$AO26>=J$12),IF(AND(INDEX('Roadmap Calc (Don’t Touch)'!$AA$2:$AX$151,$AI26,COLUMN()-COLUMN($J$16)+1)>0,OR($D26="03. UX Discovery",$D26="04. UX Design")),IF(AND($H26<>"",$H26<=EOMONTH(J$12,0),$I26>=J$12),"ALL","PD+UX"),IF(AND($H26<>"",$H26<=EOMONTH(J$12,0),$I26>=J$12),"PD+DEV","PD")),IF(AND(INDEX('Roadmap Calc (Don’t Touch)'!$AA$2:$AX$151,$AI26,COLUMN()-COLUMN($J$16)+1)>0,OR($D26="03. UX Discovery",$D26="04. UX Design")),IF(AND($H26<>"",$H26<=EOMONTH(J$12,0),$I26>=J$12),"UX+DEV","UX"),IF(AND($H26<>"",$H26<=EOMONTH(J$12,0),$I26>=J$12),"DEV","")))) | K26: =IF($AI26="","",IF(AND($AN26<>"",$AN26<=EOMONTH(K$12,0),$AO26>=K$12),IF(AND(INDEX('Roadmap Calc (Don’t Touch)'!$AA$2:$AX$151,$AI26,COLUMN()-COLUMN($J$16)+1)>0,OR($D26="03. UX Discovery",$D26="04. UX Design")),IF(AND($H26<>"",$H26<=EOMONTH(K$12,0),$I26>=K$12),"ALL","PD+UX"),IF(AND($H26<>"",$H26<=EOMONTH(K$12,0),$I26>=K$12),"PD+DEV","PD")),IF(AND(INDEX('Roadmap Calc (Don’t Touch)'!$AA$2:$AX$151,$AI26,COLUMN()-COLUMN($J$16)+1)>0,OR($D26="03. UX Discovery",$D26="04. UX Design")),IF(AND($H26<>"",$H26<=EOMONTH(K$12,0),$I26>=K$12),"UX+DEV","UX"),IF(AND($H26<>"",$H26<=EOMONTH(K$12,0),$I26>=K$12),"DEV","")))) | L26: =IF($AI26="","",IF(AND($AN26<>"",$AN26<=EOMONTH(L$12,0),$AO26>=L$12),IF(AND(INDEX('Roadmap Calc (Don’t Touch)'!$AA$2:$AX$151,$AI26,COLUMN()-COLUMN($J$16)+1)>0,OR($D26="03. UX Discovery",$D26="04. UX Design")),IF(AND($H26<>"",$H26<=EOMONTH(L$12,0),$I26>=L$12),"ALL","PD+UX"),IF(AND($H26<>"",$H26<=EOMONTH(L$12,0),$I26>=L$12),"PD+DEV","PD")),IF(AND(INDEX('Roadmap Calc (Don’t Touch)'!$AA$2:$AX$151,$AI26,COLUMN()-COLUMN($J$16)+1)>0,OR($D26="03. UX Discovery",$D26="04. UX Design")),IF(AND($H26<>"",$H26<=EOMONTH(L$12,0),$I26>=L$12),"UX+DEV","UX"),IF(AND($H26<>"",$H26<=EOMONTH(L$12,0),$I26>=L$12),"DEV","")))) | M26: =IF($AI26="","",IF(AND($AN26<>"",$AN26<=EOMONTH(M$12,0),$AO26>=M$12),IF(AND(INDEX('Roadmap Calc (Don’t Touch)'!$AA$2:$AX$151,$AI26,COLUMN()-COLUMN($J$16)+1)>0,OR($D26="03. UX Discovery",$D26="04. UX Design")),IF(AND($H26<>"",$H26<=EOMONTH(M$12,0),$I26>=M$12),"ALL","PD+UX"),IF(AND($H26<>"",$H26<=EOMONTH(M$12,0),$I26>=M$12),"PD+DEV","PD")),IF(AND(INDEX('Roadmap Calc (Don’t Touch)'!$AA$2:$AX$151,$AI26,COLUMN()-COLUMN($J$16)+1)>0,OR($D26="03. UX Discovery",$D26="04. UX Design")),IF(AND($H26<>"",$H26<=EOMONTH(M$12,0),$I26>=M$12),"UX+DEV","UX"),IF(AND($H26<>"",$H26<=EOMONTH(M$12,0),$I26>=M$12),"DEV","")))) | N26: =IF($AI26="","",IF(AND($AN26<>"",$AN26<=EOMONTH(N$12,0),$AO26>=N$12),IF(AND(INDEX('Roadmap Calc (Don’t Touch)'!$AA$2:$AX$151,$AI26,COLUMN()-COLUMN($J$16)+1)>0,OR($D26="03. UX Discovery",$D26="04. UX Design")),IF(AND($H26<>"",$H26<=EOMONTH(N$12,0),$I26>=N$12),"ALL","PD+UX"),IF(AND($H26<>"",$H26<=EOMONTH(N$12,0),$I26>=N$12),"PD+DEV","PD")),IF(AND(INDEX('Roadmap Calc (Don’t Touch)'!$AA$2:$AX$151,$AI26,COLUMN()-COLUMN($J$16)+1)>0,OR($D26="03. UX Discovery",$D26="04. UX Design")),IF(AND($H26<>"",$H26<=EOMONTH(N$12,0),$I26>=N$12),"UX+DEV","UX"),IF(AND($H26<>"",$H26<=EOMONTH(N$12,0),$I26>=N$12),"DEV","")))) | O26: =IF($AI26="","",IF(AND($AN26<>"",$AN26<=EOMONTH(O$12,0),$AO26>=O$12),IF(AND(INDEX('Roadmap Calc (Don’t Touch)'!$AA$2:$AX$151,$AI26,COLUMN()-COLUMN($J$16)+1)>0,OR($D26="03. UX Discovery",$D26="04. UX Design")),IF(AND($H26<>"",$H26<=EOMONTH(O$12,0),$I26>=O$12),"ALL","PD+UX"),IF(AND($H26<>"",$H26<=EOMONTH(O$12,0),$I26>=O$12),"PD+DEV","PD")),IF(AND(INDEX('Roadmap Calc (Don’t Touch)'!$AA$2:$AX$151,$AI26,COLUMN()-COLUMN($J$16)+1)>0,OR($D26="03. UX Discovery",$D26="04. UX Design")),IF(AND($H26<>"",$H26<=EOMONTH(O$12,0),$I26>=O$12),"UX+DEV","UX"),IF(AND($H26<>"",$H26<=EOMONTH(O$12,0),$I26>=O$12),"DEV","")))) | P26: =IF($AI26="","",IF(AND($AN26<>"",$AN26<=EOMONTH(P$12,0),$AO26>=P$12),IF(AND(INDEX('Roadmap Calc (Don’t Touch)'!$AA$2:$AX$151,$AI26,COLUMN()-COLUMN($J$16)+1)>0,OR($D26="03. UX Discovery",$D26="04. UX Design")),IF(AND($H26<>"",$H26<=EOMONTH(P$12,0),$I26>=P$12),"ALL","PD+UX"),IF(AND($H26<>"",$H26<=EOMONTH(P$12,0),$I26>=P$12),"PD+DEV","PD")),IF(AND(INDEX('Roadmap Calc (Don’t Touch)'!$AA$2:$AX$151,$AI26,COLUMN()-COLUMN($J$16)+1)>0,OR($D26="03. UX Discovery",$D26="04. UX Design")),IF(AND($H26<>"",$H26<=EOMONTH(P$12,0),$I26>=P$12),"UX+DEV","UX"),IF(AND($H26<>"",$H26<=EOMONTH(P$12,0),$I26>=P$12),"DEV","")))) | Q26: =IF($AI26="","",IF(AND($AN26<>"",$AN26<=EOMONTH(Q$12,0),$AO26>=Q$12),IF(AND(INDEX('Roadmap Calc (Don’t Touch)'!$AA$2:$AX$151,$AI26,COLUMN()-COLUMN($J$16)+1)>0,OR($D26="03. UX Discovery",$D26="04. UX Design")),IF(AND($H26<>"",$H26<=EOMONTH(Q$12,0),$I26>=Q$12),"ALL","PD+UX"),IF(AND($H26<>"",$H26<=EOMONTH(Q$12,0),$I26>=Q$12),"PD+DEV","PD")),IF(AND(INDEX('Roadmap Calc (Don’t Touch)'!$AA$2:$AX$151,$AI26,COLUMN()-COLUMN($J$16)+1)>0,OR($D26="03. UX Discovery",$D26="04. UX Design")),IF(AND($H26<>"",$H26<=EOMONTH(Q$12,0),$I26>=Q$12),"UX+DEV","UX"),IF(AND($H26<>"",$H26<=EOMONTH(Q$12,0),$I26>=Q$12),"DEV","")))) | ... AG26: =IF($AI26="","",IF(AND($AN26<>"",$AN26<=EOMONTH(AG$12,0),$AO26>=AG$12),IF(AND(INDEX('Roadmap Calc (Don’t Touch)'!$AA$2:$AX$151,$AI26,COLUMN()-COLUMN($J$16)+1)>0,OR($D26="03. UX Discovery",$D26="04. UX Design")),IF(AND($H26<>"",$H26<=EOMONTH(AG$12,0),$I26>=AG$12),"ALL","PD+UX"),IF(AND($H26<>"",$H26<=EOMONTH(AG$12,0),$I26>=AG$12),"PD+DEV","PD")),IF(AND(INDEX('Roadmap Calc (Don’t Touch)'!$AA$2:$AX$151,$AI26,COLUMN()-COLUMN($J$16)+1)>0,OR($D26="03. UX Discovery",$D26="04. UX Design")),IF(AND($H26<>"",$H26<=EOMONTH(AG$12,0),$I26>=AG$12),"UX+DEV","UX"),IF(AND($H26<>"",$H26<=EOMONTH(AG$12,0),$I26>=AG$12),"DEV","")))) | AH26: =IF($AI26="","",INDEX('Roadmap Calc (Don’t Touch)'!$D$2:$D$151,$AI26)) -> Improve Trade In User Flow | AI26: =IFERROR(MATCH(11,'Roadmap Calc (Don’t Touch)'!$O$2:$O$151,0),"") -> 28 | AN26: =IF($AI26="","",IF(ISNUMBER(INDEX('Roadmap Calc (Don’t Touch)'!$BB$2:$BB$151,$AI26)),INDEX('Roadmap Calc (Don’t Touch)'!$BB$2:$BB$151,$AI26),"")) | AO26: =IF($AI26="","",IF(ISNUMBER(INDEX('Roadmap Calc (Don’t Touch)'!$BC$2:$BC$151,$AI26)),INDEX('Roadmap Calc (Don’t Touch)'!$BC$2:$BC$151,$AI26),""))
A27: =IF($AI27="","",IF($AH27=$AH26,"",IF(INDEX('Roadmap Calc (Don’t Touch)'!$U$2:$U$151,$AI27)=0,$AH27,HYPERLINK("#'Control (Don’t Touch)'!E"&INDEX('Roadmap Calc (Don’t Touch)'!$U$2:$U$151,$AI27),$AH27)))) | B27: =IF($AI27="","",IF(INDEX('Roadmap Calc (Don’t Touch)'!$K$2:$K$151,$AI27)="",INDEX('Roadmap Calc (Don’t Touch)'!$B$2:$B$151,$AI27),HYPERLINK("https://jira.bnh.com/browse/"&INDEX('Roadmap Calc (Don’t Touch)'!$K$2:$K$151,$AI27),INDEX('Roadmap Calc (Don’t Touch)'!$B$2:$B$151,$AI27)))) -> Trade In Discrepancy Email Refresh (Copy Only) | C27: =IF($AI27="","",IF(INDEX('Roadmap Calc (Don’t Touch)'!$E$2:$E$151,$AI27)="","",HYPERLINK("https://jira.bnh.com/browse/"&INDEX('Roadmap Calc (Don’t Touch)'!$E$2:$E$151,$AI27),INDEX('Roadmap Calc (Don’t Touch)'!$E$2:$E$151,$AI27)))) | D27: =IF($AI27="","",INDEX('Roadmap Calc (Don’t Touch)'!$F$2:$F$151,$AI27)) -> 09. In Dev | E27: =IF($AI27="","",IF(ISNUMBER(INDEX('Roadmap Calc (Don’t Touch)'!$G$2:$G$151,$AI27)),INDEX('Roadmap Calc (Don’t Touch)'!$G$2:$G$151,$AI27),"")) -> 46216 | F27: =IF($AI27="","",IF(ISNUMBER(INDEX('Roadmap Calc (Don’t Touch)'!$H$2:$H$151,$AI27)),INDEX('Roadmap Calc (Don’t Touch)'!$H$2:$H$151,$AI27),"")) -> 46223 | G27: =IF($AI27="","",INDEX('Roadmap Calc (Don’t Touch)'!$T$2:$T$151,$AI27)) -> 2 | H27: =IF($AI27="","",IF(ISNUMBER(INDEX('Roadmap Calc (Don’t Touch)'!$I$2:$I$151,$AI27)),INDEX('Roadmap Calc (Don’t Touch)'!$I$2:$I$151,$AI27),"")) -> 46266 | I27: =IF($AI27="","",IF(ISNUMBER(INDEX('Roadmap Calc (Don’t Touch)'!$J$2:$J$151,$AI27)),INDEX('Roadmap Calc (Don’t Touch)'!$J$2:$J$151,$AI27),"")) -> 46295 | J27: =IF($AI27="","",IF(AND($AN27<>"",$AN27<=EOMONTH(J$12,0),$AO27>=J$12),IF(AND(INDEX('Roadmap Calc (Don’t Touch)'!$AA$2:$AX$151,$AI27,COLUMN()-COLUMN($J$16)+1)>0,OR($D27="03. UX Discovery",$D27="04. UX Design")),IF(AND($H27<>"",$H27<=EOMONTH(J$12,0),$I27>=J$12),"ALL","PD+UX"),IF(AND($H27<>"",$H27<=EOMONTH(J$12,0),$I27>=J$12),"PD+DEV","PD")),IF(AND(INDEX('Roadmap Calc (Don’t Touch)'!$AA$2:$AX$151,$AI27,COLUMN()-COLUMN($J$16)+1)>0,OR($D27="03. UX Discovery",$D27="04. UX Design")),IF(AND($H27<>"",$H27<=EOMONTH(J$12,0),$I27>=J$12),"UX+DEV","UX"),IF(AND($H27<>"",$H27<=EOMONTH(J$12,0),$I27>=J$12),"DEV","")))) | K27: =IF($AI27="","",IF(AND($AN27<>"",$AN27<=EOMONTH(K$12,0),$AO27>=K$12),IF(AND(INDEX('Roadmap Calc (Don’t Touch)'!$AA$2:$AX$151,$AI27,COLUMN()-COLUMN($J$16)+1)>0,OR($D27="03. UX Discovery",$D27="04. UX Design")),IF(AND($H27<>"",$H27<=EOMONTH(K$12,0),$I27>=K$12),"ALL","PD+UX"),IF(AND($H27<>"",$H27<=EOMONTH(K$12,0),$I27>=K$12),"PD+DEV","PD")),IF(AND(INDEX('Roadmap Calc (Don’t Touch)'!$AA$2:$AX$151,$AI27,COLUMN()-COLUMN($J$16)+1)>0,OR($D27="03. UX Discovery",$D27="04. UX Design")),IF(AND($H27<>"",$H27<=EOMONTH(K$12,0),$I27>=K$12),"UX+DEV","UX"),IF(AND($H27<>"",$H27<=EOMONTH(K$12,0),$I27>=K$12),"DEV","")))) | L27: =IF($AI27="","",IF(AND($AN27<>"",$AN27<=EOMONTH(L$12,0),$AO27>=L$12),IF(AND(INDEX('Roadmap Calc (Don’t Touch)'!$AA$2:$AX$151,$AI27,COLUMN()-COLUMN($J$16)+1)>0,OR($D27="03. UX Discovery",$D27="04. UX Design")),IF(AND($H27<>"",$H27<=EOMONTH(L$12,0),$I27>=L$12),"ALL","PD+UX"),IF(AND($H27<>"",$H27<=EOMONTH(L$12,0),$I27>=L$12),"PD+DEV","PD")),IF(AND(INDEX('Roadmap Calc (Don’t Touch)'!$AA$2:$AX$151,$AI27,COLUMN()-COLUMN($J$16)+1)>0,OR($D27="03. UX Discovery",$D27="04. UX Design")),IF(AND($H27<>"",$H27<=EOMONTH(L$12,0),$I27>=L$12),"UX+DEV","UX"),IF(AND($H27<>"",$H27<=EOMONTH(L$12,0),$I27>=L$12),"DEV","")))) | M27: =IF($AI27="","",IF(AND($AN27<>"",$AN27<=EOMONTH(M$12,0),$AO27>=M$12),IF(AND(INDEX('Roadmap Calc (Don’t Touch)'!$AA$2:$AX$151,$AI27,COLUMN()-COLUMN($J$16)+1)>0,OR($D27="03. UX Discovery",$D27="04. UX Design")),IF(AND($H27<>"",$H27<=EOMONTH(M$12,0),$I27>=M$12),"ALL","PD+UX"),IF(AND($H27<>"",$H27<=EOMONTH(M$12,0),$I27>=M$12),"PD+DEV","PD")),IF(AND(INDEX('Roadmap Calc (Don’t Touch)'!$AA$2:$AX$151,$AI27,COLUMN()-COLUMN($J$16)+1)>0,OR($D27="03. UX Discovery",$D27="04. UX Design")),IF(AND($H27<>"",$H27<=EOMONTH(M$12,0),$I27>=M$12),"UX+DEV","UX"),IF(AND($H27<>"",$H27<=EOMONTH(M$12,0),$I27>=M$12),"DEV","")))) | N27: =IF($AI27="","",IF(AND($AN27<>"",$AN27<=EOMONTH(N$12,0),$AO27>=N$12),IF(AND(INDEX('Roadmap Calc (Don’t Touch)'!$AA$2:$AX$151,$AI27,COLUMN()-COLUMN($J$16)+1)>0,OR($D27="03. UX Discovery",$D27="04. UX Design")),IF(AND($H27<>"",$H27<=EOMONTH(N$12,0),$I27>=N$12),"ALL","PD+UX"),IF(AND($H27<>"",$H27<=EOMONTH(N$12,0),$I27>=N$12),"PD+DEV","PD")),IF(AND(INDEX('Roadmap Calc (Don’t Touch)'!$AA$2:$AX$151,$AI27,COLUMN()-COLUMN($J$16)+1)>0,OR($D27="03. UX Discovery",$D27="04. UX Design")),IF(AND($H27<>"",$H27<=EOMONTH(N$12,0),$I27>=N$12),"UX+DEV","UX"),IF(AND($H27<>"",$H27<=EOMONTH(N$12,0),$I27>=N$12),"DEV","")))) | O27: =IF($AI27="","",IF(AND($AN27<>"",$AN27<=EOMONTH(O$12,0),$AO27>=O$12),IF(AND(INDEX('Roadmap Calc (Don’t Touch)'!$AA$2:$AX$151,$AI27,COLUMN()-COLUMN($J$16)+1)>0,OR($D27="03. UX Discovery",$D27="04. UX Design")),IF(AND($H27<>"",$H27<=EOMONTH(O$12,0),$I27>=O$12),"ALL","PD+UX"),IF(AND($H27<>"",$H27<=EOMONTH(O$12,0),$I27>=O$12),"PD+DEV","PD")),IF(AND(INDEX('Roadmap Calc (Don’t Touch)'!$AA$2:$AX$151,$AI27,COLUMN()-COLUMN($J$16)+1)>0,OR($D27="03. UX Discovery",$D27="04. UX Design")),IF(AND($H27<>"",$H27<=EOMONTH(O$12,0),$I27>=O$12),"UX+DEV","UX"),IF(AND($H27<>"",$H27<=EOMONTH(O$12,0),$I27>=O$12),"DEV","")))) | P27: =IF($AI27="","",IF(AND($AN27<>"",$AN27<=EOMONTH(P$12,0),$AO27>=P$12),IF(AND(INDEX('Roadmap Calc (Don’t Touch)'!$AA$2:$AX$151,$AI27,COLUMN()-COLUMN($J$16)+1)>0,OR($D27="03. UX Discovery",$D27="04. UX Design")),IF(AND($H27<>"",$H27<=EOMONTH(P$12,0),$I27>=P$12),"ALL","PD+UX"),IF(AND($H27<>"",$H27<=EOMONTH(P$12,0),$I27>=P$12),"PD+DEV","PD")),IF(AND(INDEX('Roadmap Calc (Don’t Touch)'!$AA$2:$AX$151,$AI27,COLUMN()-COLUMN($J$16)+1)>0,OR($D27="03. UX Discovery",$D27="04. UX Design")),IF(AND($H27<>"",$H27<=EOMONTH(P$12,0),$I27>=P$12),"UX+DEV","UX"),IF(AND($H27<>"",$H27<=EOMONTH(P$12,0),$I27>=P$12),"DEV","")))) | Q27: =IF($AI27="","",IF(AND($AN27<>"",$AN27<=EOMONTH(Q$12,0),$AO27>=Q$12),IF(AND(INDEX('Roadmap Calc (Don’t Touch)'!$AA$2:$AX$151,$AI27,COLUMN()-COLUMN($J$16)+1)>0,OR($D27="03. UX Discovery",$D27="04. UX Design")),IF(AND($H27<>"",$H27<=EOMONTH(Q$12,0),$I27>=Q$12),"ALL","PD+UX"),IF(AND($H27<>"",$H27<=EOMONTH(Q$12,0),$I27>=Q$12),"PD+DEV","PD")),IF(AND(INDEX('Roadmap Calc (Don’t Touch)'!$AA$2:$AX$151,$AI27,COLUMN()-COLUMN($J$16)+1)>0,OR($D27="03. UX Discovery",$D27="04. UX Design")),IF(AND($H27<>"",$H27<=EOMONTH(Q$12,0),$I27>=Q$12),"UX+DEV","UX"),IF(AND($H27<>"",$H27<=EOMONTH(Q$12,0),$I27>=Q$12),"DEV","")))) | ... AG27: =IF($AI27="","",IF(AND($AN27<>"",$AN27<=EOMONTH(AG$12,0),$AO27>=AG$12),IF(AND(INDEX('Roadmap Calc (Don’t Touch)'!$AA$2:$AX$151,$AI27,COLUMN()-COLUMN($J$16)+1)>0,OR($D27="03. UX Discovery",$D27="04. UX Design")),IF(AND($H27<>"",$H27<=EOMONTH(AG$12,0),$I27>=AG$12),"ALL","PD+UX"),IF(AND($H27<>"",$H27<=EOMONTH(AG$12,0),$I27>=AG$12),"PD+DEV","PD")),IF(AND(INDEX('Roadmap Calc (Don’t Touch)'!$AA$2:$AX$151,$AI27,COLUMN()-COLUMN($J$16)+1)>0,OR($D27="03. UX Discovery",$D27="04. UX Design")),IF(AND($H27<>"",$H27<=EOMONTH(AG$12,0),$I27>=AG$12),"UX+DEV","UX"),IF(AND($H27<>"",$H27<=EOMONTH(AG$12,0),$I27>=AG$12),"DEV","")))) | AH27: =IF($AI27="","",INDEX('Roadmap Calc (Don’t Touch)'!$D$2:$D$151,$AI27)) -> Improve Trade In User Flow | AI27: =IFERROR(MATCH(12,'Roadmap Calc (Don’t Touch)'!$O$2:$O$151,0),"") -> 37 | AN27: =IF($AI27="","",IF(ISNUMBER(INDEX('Roadmap Calc (Don’t Touch)'!$BB$2:$BB$151,$AI27)),INDEX('Roadmap Calc (Don’t Touch)'!$BB$2:$BB$151,$AI27),"")) | AO27: =IF($AI27="","",IF(ISNUMBER(INDEX('Roadmap Calc (Don’t Touch)'!$BC$2:$BC$151,$AI27)),INDEX('Roadmap Calc (Don’t Touch)'!$BC$2:$BC$151,$AI27),""))
A28: =IF($AI28="","",IF($AH28=$AH27,"",IF(INDEX('Roadmap Calc (Don’t Touch)'!$U$2:$U$151,$AI28)=0,$AH28,HYPERLINK("#'Control (Don’t Touch)'!E"&INDEX('Roadmap Calc (Don’t Touch)'!$U$2:$U$151,$AI28),$AH28)))) -> Increase Buy Used Awareness | B28: =IF($AI28="","",IF(INDEX('Roadmap Calc (Don’t Touch)'!$K$2:$K$151,$AI28)="",INDEX('Roadmap Calc (Don’t Touch)'!$B$2:$B$151,$AI28),HYPERLINK("https://jira.bnh.com/browse/"&INDEX('Roadmap Calc (Don’t Touch)'!$K$2:$K$151,$AI28),INDEX('Roadmap Calc (Don’t Touch)'!$B$2:$B$151,$AI28)))) -> Used Hub - Just Added Component | C28: =IF($AI28="","",IF(INDEX('Roadmap Calc (Don’t Touch)'!$E$2:$E$151,$AI28)="","",HYPERLINK("https://jira.bnh.com/browse/"&INDEX('Roadmap Calc (Don’t Touch)'!$E$2:$E$151,$AI28),INDEX('Roadmap Calc (Don’t Touch)'!$E$2:$E$151,$AI28)))) -> BHP-7229 | D28: =IF($AI28="","",INDEX('Roadmap Calc (Don’t Touch)'!$F$2:$F$151,$AI28)) -> 02. UX Req | E28: =IF($AI28="","",IF(ISNUMBER(INDEX('Roadmap Calc (Don’t Touch)'!$G$2:$G$151,$AI28)),INDEX('Roadmap Calc (Don’t Touch)'!$G$2:$G$151,$AI28),"")) -> 46244 | F28: =IF($AI28="","",IF(ISNUMBER(INDEX('Roadmap Calc (Don’t Touch)'!$H$2:$H$151,$AI28)),INDEX('Roadmap Calc (Don’t Touch)'!$H$2:$H$151,$AI28),"")) -> 46279 | G28: =IF($AI28="","",INDEX('Roadmap Calc (Don’t Touch)'!$T$2:$T$151,$AI28)) -> 3 | H28: =IF($AI28="","",IF(ISNUMBER(INDEX('Roadmap Calc (Don’t Touch)'!$I$2:$I$151,$AI28)),INDEX('Roadmap Calc (Don’t Touch)'!$I$2:$I$151,$AI28),"")) -> 46419 | I28: =IF($AI28="","",IF(ISNUMBER(INDEX('Roadmap Calc (Don’t Touch)'!$J$2:$J$151,$AI28)),INDEX('Roadmap Calc (Don’t Touch)'!$J$2:$J$151,$AI28),"")) -> 46446 | J28: =IF($AI28="","",IF(AND($AN28<>"",$AN28<=EOMONTH(J$12,0),$AO28>=J$12),IF(AND(INDEX('Roadmap Calc (Don’t Touch)'!$AA$2:$AX$151,$AI28,COLUMN()-COLUMN($J$16)+1)>0,OR($D28="03. UX Discovery",$D28="04. UX Design")),IF(AND($H28<>"",$H28<=EOMONTH(J$12,0),$I28>=J$12),"ALL","PD+UX"),IF(AND($H28<>"",$H28<=EOMONTH(J$12,0),$I28>=J$12),"PD+DEV","PD")),IF(AND(INDEX('Roadmap Calc (Don’t Touch)'!$AA$2:$AX$151,$AI28,COLUMN()-COLUMN($J$16)+1)>0,OR($D28="03. UX Discovery",$D28="04. UX Design")),IF(AND($H28<>"",$H28<=EOMONTH(J$12,0),$I28>=J$12),"UX+DEV","UX"),IF(AND($H28<>"",$H28<=EOMONTH(J$12,0),$I28>=J$12),"DEV","")))) | K28: =IF($AI28="","",IF(AND($AN28<>"",$AN28<=EOMONTH(K$12,0),$AO28>=K$12),IF(AND(INDEX('Roadmap Calc (Don’t Touch)'!$AA$2:$AX$151,$AI28,COLUMN()-COLUMN($J$16)+1)>0,OR($D28="03. UX Discovery",$D28="04. UX Design")),IF(AND($H28<>"",$H28<=EOMONTH(K$12,0),$I28>=K$12),"ALL","PD+UX"),IF(AND($H28<>"",$H28<=EOMONTH(K$12,0),$I28>=K$12),"PD+DEV","PD")),IF(AND(INDEX('Roadmap Calc (Don’t Touch)'!$AA$2:$AX$151,$AI28,COLUMN()-COLUMN($J$16)+1)>0,OR($D28="03. UX Discovery",$D28="04. UX Design")),IF(AND($H28<>"",$H28<=EOMONTH(K$12,0),$I28>=K$12),"UX+DEV","UX"),IF(AND($H28<>"",$H28<=EOMONTH(K$12,0),$I28>=K$12),"DEV","")))) | L28: =IF($AI28="","",IF(AND($AN28<>"",$AN28<=EOMONTH(L$12,0),$AO28>=L$12),IF(AND(INDEX('Roadmap Calc (Don’t Touch)'!$AA$2:$AX$151,$AI28,COLUMN()-COLUMN($J$16)+1)>0,OR($D28="03. UX Discovery",$D28="04. UX Design")),IF(AND($H28<>"",$H28<=EOMONTH(L$12,0),$I28>=L$12),"ALL","PD+UX"),IF(AND($H28<>"",$H28<=EOMONTH(L$12,0),$I28>=L$12),"PD+DEV","PD")),IF(AND(INDEX('Roadmap Calc (Don’t Touch)'!$AA$2:$AX$151,$AI28,COLUMN()-COLUMN($J$16)+1)>0,OR($D28="03. UX Discovery",$D28="04. UX Design")),IF(AND($H28<>"",$H28<=EOMONTH(L$12,0),$I28>=L$12),"UX+DEV","UX"),IF(AND($H28<>"",$H28<=EOMONTH(L$12,0),$I28>=L$12),"DEV","")))) | M28: =IF($AI28="","",IF(AND($AN28<>"",$AN28<=EOMONTH(M$12,0),$AO28>=M$12),IF(AND(INDEX('Roadmap Calc (Don’t Touch)'!$AA$2:$AX$151,$AI28,COLUMN()-COLUMN($J$16)+1)>0,OR($D28="03. UX Discovery",$D28="04. UX Design")),IF(AND($H28<>"",$H28<=EOMONTH(M$12,0),$I28>=M$12),"ALL","PD+UX"),IF(AND($H28<>"",$H28<=EOMONTH(M$12,0),$I28>=M$12),"PD+DEV","PD")),IF(AND(INDEX('Roadmap Calc (Don’t Touch)'!$AA$2:$AX$151,$AI28,COLUMN()-COLUMN($J$16)+1)>0,OR($D28="03. UX Discovery",$D28="04. UX Design")),IF(AND($H28<>"",$H28<=EOMONTH(M$12,0),$I28>=M$12),"UX+DEV","UX"),IF(AND($H28<>"",$H28<=EOMONTH(M$12,0),$I28>=M$12),"DEV","")))) | N28: =IF($AI28="","",IF(AND($AN28<>"",$AN28<=EOMONTH(N$12,0),$AO28>=N$12),IF(AND(INDEX('Roadmap Calc (Don’t Touch)'!$AA$2:$AX$151,$AI28,COLUMN()-COLUMN($J$16)+1)>0,OR($D28="03. UX Discovery",$D28="04. UX Design")),IF(AND($H28<>"",$H28<=EOMONTH(N$12,0),$I28>=N$12),"ALL","PD+UX"),IF(AND($H28<>"",$H28<=EOMONTH(N$12,0),$I28>=N$12),"PD+DEV","PD")),IF(AND(INDEX('Roadmap Calc (Don’t Touch)'!$AA$2:$AX$151,$AI28,COLUMN()-COLUMN($J$16)+1)>0,OR($D28="03. UX Discovery",$D28="04. UX Design")),IF(AND($H28<>"",$H28<=EOMONTH(N$12,0),$I28>=N$12),"UX+DEV","UX"),IF(AND($H28<>"",$H28<=EOMONTH(N$12,0),$I28>=N$12),"DEV","")))) | O28: =IF($AI28="","",IF(AND($AN28<>"",$AN28<=EOMONTH(O$12,0),$AO28>=O$12),IF(AND(INDEX('Roadmap Calc (Don’t Touch)'!$AA$2:$AX$151,$AI28,COLUMN()-COLUMN($J$16)+1)>0,OR($D28="03. UX Discovery",$D28="04. UX Design")),IF(AND($H28<>"",$H28<=EOMONTH(O$12,0),$I28>=O$12),"ALL","PD+UX"),IF(AND($H28<>"",$H28<=EOMONTH(O$12,0),$I28>=O$12),"PD+DEV","PD")),IF(AND(INDEX('Roadmap Calc (Don’t Touch)'!$AA$2:$AX$151,$AI28,COLUMN()-COLUMN($J$16)+1)>0,OR($D28="03. UX Discovery",$D28="04. UX Design")),IF(AND($H28<>"",$H28<=EOMONTH(O$12,0),$I28>=O$12),"UX+DEV","UX"),IF(AND($H28<>"",$H28<=EOMONTH(O$12,0),$I28>=O$12),"DEV","")))) | P28: =IF($AI28="","",IF(AND($AN28<>"",$AN28<=EOMONTH(P$12,0),$AO28>=P$12),IF(AND(INDEX('Roadmap Calc (Don’t Touch)'!$AA$2:$AX$151,$AI28,COLUMN()-COLUMN($J$16)+1)>0,OR($D28="03. UX Discovery",$D28="04. UX Design")),IF(AND($H28<>"",$H28<=EOMONTH(P$12,0),$I28>=P$12),"ALL","PD+UX"),IF(AND($H28<>"",$H28<=EOMONTH(P$12,0),$I28>=P$12),"PD+DEV","PD")),IF(AND(INDEX('Roadmap Calc (Don’t Touch)'!$AA$2:$AX$151,$AI28,COLUMN()-COLUMN($J$16)+1)>0,OR($D28="03. UX Discovery",$D28="04. UX Design")),IF(AND($H28<>"",$H28<=EOMONTH(P$12,0),$I28>=P$12),"UX+DEV","UX"),IF(AND($H28<>"",$H28<=EOMONTH(P$12,0),$I28>=P$12),"DEV","")))) | Q28: =IF($AI28="","",IF(AND($AN28<>"",$AN28<=EOMONTH(Q$12,0),$AO28>=Q$12),IF(AND(INDEX('Roadmap Calc (Don’t Touch)'!$AA$2:$AX$151,$AI28,COLUMN()-COLUMN($J$16)+1)>0,OR($D28="03. UX Discovery",$D28="04. UX Design")),IF(AND($H28<>"",$H28<=EOMONTH(Q$12,0),$I28>=Q$12),"ALL","PD+UX"),IF(AND($H28<>"",$H28<=EOMONTH(Q$12,0),$I28>=Q$12),"PD+DEV","PD")),IF(AND(INDEX('Roadmap Calc (Don’t Touch)'!$AA$2:$AX$151,$AI28,COLUMN()-COLUMN($J$16)+1)>0,OR($D28="03. UX Discovery",$D28="04. UX Design")),IF(AND($H28<>"",$H28<=EOMONTH(Q$12,0),$I28>=Q$12),"UX+DEV","UX"),IF(AND($H28<>"",$H28<=EOMONTH(Q$12,0),$I28>=Q$12),"DEV","")))) | ... AG28: =IF($AI28="","",IF(AND($AN28<>"",$AN28<=EOMONTH(AG$12,0),$AO28>=AG$12),IF(AND(INDEX('Roadmap Calc (Don’t Touch)'!$AA$2:$AX$151,$AI28,COLUMN()-COLUMN($J$16)+1)>0,OR($D28="03. UX Discovery",$D28="04. UX Design")),IF(AND($H28<>"",$H28<=EOMONTH(AG$12,0),$I28>=AG$12),"ALL","PD+UX"),IF(AND($H28<>"",$H28<=EOMONTH(AG$12,0),$I28>=AG$12),"PD+DEV","PD")),IF(AND(INDEX('Roadmap Calc (Don’t Touch)'!$AA$2:$AX$151,$AI28,COLUMN()-COLUMN($J$16)+1)>0,OR($D28="03. UX Discovery",$D28="04. UX Design")),IF(AND($H28<>"",$H28<=EOMONTH(AG$12,0),$I28>=AG$12),"UX+DEV","UX"),IF(AND($H28<>"",$H28<=EOMONTH(AG$12,0),$I28>=AG$12),"DEV","")))) | AH28: =IF($AI28="","",INDEX('Roadmap Calc (Don’t Touch)'!$D$2:$D$151,$AI28)) -> Increase Buy Used Awareness | AI28: =IFERROR(MATCH(13,'Roadmap Calc (Don’t Touch)'!$O$2:$O$151,0),"") -> 13 | AN28: =IF($AI28="","",IF(ISNUMBER(INDEX('Roadmap Calc (Don’t Touch)'!$BB$2:$BB$151,$AI28)),INDEX('Roadmap Calc (Don’t Touch)'!$BB$2:$BB$151,$AI28),"")) | AO28: =IF($AI28="","",IF(ISNUMBER(INDEX('Roadmap Calc (Don’t Touch)'!$BC$2:$BC$151,$AI28)),INDEX('Roadmap Calc (Don’t Touch)'!$BC$2:$BC$151,$AI28),""))
A29: =IF($AI29="","",IF($AH29=$AH28,"",IF(INDEX('Roadmap Calc (Don’t Touch)'!$U$2:$U$151,$AI29)=0,$AH29,HYPERLINK("#'Control (Don’t Touch)'!E"&INDEX('Roadmap Calc (Don’t Touch)'!$U$2:$U$151,$AI29),$AH29)))) | B29: =IF($AI29="","",IF(INDEX('Roadmap Calc (Don’t Touch)'!$K$2:$K$151,$AI29)="",INDEX('Roadmap Calc (Don’t Touch)'!$B$2:$B$151,$AI29),HYPERLINK("https://jira.bnh.com/browse/"&INDEX('Roadmap Calc (Don’t Touch)'!$K$2:$K$151,$AI29),INDEX('Roadmap Calc (Don’t Touch)'!$B$2:$B$151,$AI29)))) -> Used Just Added Page | C29: =IF($AI29="","",IF(INDEX('Roadmap Calc (Don’t Touch)'!$E$2:$E$151,$AI29)="","",HYPERLINK("https://jira.bnh.com/browse/"&INDEX('Roadmap Calc (Don’t Touch)'!$E$2:$E$151,$AI29),INDEX('Roadmap Calc (Don’t Touch)'!$E$2:$E$151,$AI29)))) -> BHP-7230 | D29: =IF($AI29="","",INDEX('Roadmap Calc (Don’t Touch)'!$F$2:$F$151,$AI29)) -> 02. UX Req | E29: =IF($AI29="","",IF(ISNUMBER(INDEX('Roadmap Calc (Don’t Touch)'!$G$2:$G$151,$AI29)),INDEX('Roadmap Calc (Don’t Touch)'!$G$2:$G$151,$AI29),"")) -> 46160 | F29: =IF($AI29="","",IF(ISNUMBER(INDEX('Roadmap Calc (Don’t Touch)'!$H$2:$H$151,$AI29)),INDEX('Roadmap Calc (Don’t Touch)'!$H$2:$H$151,$AI29),"")) -> 46307 | G29: =IF($AI29="","",INDEX('Roadmap Calc (Don’t Touch)'!$T$2:$T$151,$AI29)) -> 4 | H29: =IF($AI29="","",IF(ISNUMBER(INDEX('Roadmap Calc (Don’t Touch)'!$I$2:$I$151,$AI29)),INDEX('Roadmap Calc (Don’t Touch)'!$I$2:$I$151,$AI29),"")) -> 46419 | I29: =IF($AI29="","",IF(ISNUMBER(INDEX('Roadmap Calc (Don’t Touch)'!$J$2:$J$151,$AI29)),INDEX('Roadmap Calc (Don’t Touch)'!$J$2:$J$151,$AI29),"")) -> 46446 | J29: =IF($AI29="","",IF(AND($AN29<>"",$AN29<=EOMONTH(J$12,0),$AO29>=J$12),IF(AND(INDEX('Roadmap Calc (Don’t Touch)'!$AA$2:$AX$151,$AI29,COLUMN()-COLUMN($J$16)+1)>0,OR($D29="03. UX Discovery",$D29="04. UX Design")),IF(AND($H29<>"",$H29<=EOMONTH(J$12,0),$I29>=J$12),"ALL","PD+UX"),IF(AND($H29<>"",$H29<=EOMONTH(J$12,0),$I29>=J$12),"PD+DEV","PD")),IF(AND(INDEX('Roadmap Calc (Don’t Touch)'!$AA$2:$AX$151,$AI29,COLUMN()-COLUMN($J$16)+1)>0,OR($D29="03. UX Discovery",$D29="04. UX Design")),IF(AND($H29<>"",$H29<=EOMONTH(J$12,0),$I29>=J$12),"UX+DEV","UX"),IF(AND($H29<>"",$H29<=EOMONTH(J$12,0),$I29>=J$12),"DEV","")))) | K29: =IF($AI29="","",IF(AND($AN29<>"",$AN29<=EOMONTH(K$12,0),$AO29>=K$12),IF(AND(INDEX('Roadmap Calc (Don’t Touch)'!$AA$2:$AX$151,$AI29,COLUMN()-COLUMN($J$16)+1)>0,OR($D29="03. UX Discovery",$D29="04. UX Design")),IF(AND($H29<>"",$H29<=EOMONTH(K$12,0),$I29>=K$12),"ALL","PD+UX"),IF(AND($H29<>"",$H29<=EOMONTH(K$12,0),$I29>=K$12),"PD+DEV","PD")),IF(AND(INDEX('Roadmap Calc (Don’t Touch)'!$AA$2:$AX$151,$AI29,COLUMN()-COLUMN($J$16)+1)>0,OR($D29="03. UX Discovery",$D29="04. UX Design")),IF(AND($H29<>"",$H29<=EOMONTH(K$12,0),$I29>=K$12),"UX+DEV","UX"),IF(AND($H29<>"",$H29<=EOMONTH(K$12,0),$I29>=K$12),"DEV","")))) | L29: =IF($AI29="","",IF(AND($AN29<>"",$AN29<=EOMONTH(L$12,0),$AO29>=L$12),IF(AND(INDEX('Roadmap Calc (Don’t Touch)'!$AA$2:$AX$151,$AI29,COLUMN()-COLUMN($J$16)+1)>0,OR($D29="03. UX Discovery",$D29="04. UX Design")),IF(AND($H29<>"",$H29<=EOMONTH(L$12,0),$I29>=L$12),"ALL","PD+UX"),IF(AND($H29<>"",$H29<=EOMONTH(L$12,0),$I29>=L$12),"PD+DEV","PD")),IF(AND(INDEX('Roadmap Calc (Don’t Touch)'!$AA$2:$AX$151,$AI29,COLUMN()-COLUMN($J$16)+1)>0,OR($D29="03. UX Discovery",$D29="04. UX Design")),IF(AND($H29<>"",$H29<=EOMONTH(L$12,0),$I29>=L$12),"UX+DEV","UX"),IF(AND($H29<>"",$H29<=EOMONTH(L$12,0),$I29>=L$12),"DEV","")))) | M29: =IF($AI29="","",IF(AND($AN29<>"",$AN29<=EOMONTH(M$12,0),$AO29>=M$12),IF(AND(INDEX('Roadmap Calc (Don’t Touch)'!$AA$2:$AX$151,$AI29,COLUMN()-COLUMN($J$16)+1)>0,OR($D29="03. UX Discovery",$D29="04. UX Design")),IF(AND($H29<>"",$H29<=EOMONTH(M$12,0),$I29>=M$12),"ALL","PD+UX"),IF(AND($H29<>"",$H29<=EOMONTH(M$12,0),$I29>=M$12),"PD+DEV","PD")),IF(AND(INDEX('Roadmap Calc (Don’t Touch)'!$AA$2:$AX$151,$AI29,COLUMN()-COLUMN($J$16)+1)>0,OR($D29="03. UX Discovery",$D29="04. UX Design")),IF(AND($H29<>"",$H29<=EOMONTH(M$12,0),$I29>=M$12),"UX+DEV","UX"),IF(AND($H29<>"",$H29<=EOMONTH(M$12,0),$I29>=M$12),"DEV","")))) | N29: =IF($AI29="","",IF(AND($AN29<>"",$AN29<=EOMONTH(N$12,0),$AO29>=N$12),IF(AND(INDEX('Roadmap Calc (Don’t Touch)'!$AA$2:$AX$151,$AI29,COLUMN()-COLUMN($J$16)+1)>0,OR($D29="03. UX Discovery",$D29="04. UX Design")),IF(AND($H29<>"",$H29<=EOMONTH(N$12,0),$I29>=N$12),"ALL","PD+UX"),IF(AND($H29<>"",$H29<=EOMONTH(N$12,0),$I29>=N$12),"PD+DEV","PD")),IF(AND(INDEX('Roadmap Calc (Don’t Touch)'!$AA$2:$AX$151,$AI29,COLUMN()-COLUMN($J$16)+1)>0,OR($D29="03. UX Discovery",$D29="04. UX Design")),IF(AND($H29<>"",$H29<=EOMONTH(N$12,0),$I29>=N$12),"UX+DEV","UX"),IF(AND($H29<>"",$H29<=EOMONTH(N$12,0),$I29>=N$12),"DEV","")))) | O29: =IF($AI29="","",IF(AND($AN29<>"",$AN29<=EOMONTH(O$12,0),$AO29>=O$12),IF(AND(INDEX('Roadmap Calc (Don’t Touch)'!$AA$2:$AX$151,$AI29,COLUMN()-COLUMN($J$16)+1)>0,OR($D29="03. UX Discovery",$D29="04. UX Design")),IF(AND($H29<>"",$H29<=EOMONTH(O$12,0),$I29>=O$12),"ALL","PD+UX"),IF(AND($H29<>"",$H29<=EOMONTH(O$12,0),$I29>=O$12),"PD+DEV","PD")),IF(AND(INDEX('Roadmap Calc (Don’t Touch)'!$AA$2:$AX$151,$AI29,COLUMN()-COLUMN($J$16)+1)>0,OR($D29="03. UX Discovery",$D29="04. UX Design")),IF(AND($H29<>"",$H29<=EOMONTH(O$12,0),$I29>=O$12),"UX+DEV","UX"),IF(AND($H29<>"",$H29<=EOMONTH(O$12,0),$I29>=O$12),"DEV","")))) | P29: =IF($AI29="","",IF(AND($AN29<>"",$AN29<=EOMONTH(P$12,0),$AO29>=P$12),IF(AND(INDEX('Roadmap Calc (Don’t Touch)'!$AA$2:$AX$151,$AI29,COLUMN()-COLUMN($J$16)+1)>0,OR($D29="03. UX Discovery",$D29="04. UX Design")),IF(AND($H29<>"",$H29<=EOMONTH(P$12,0),$I29>=P$12),"ALL","PD+UX"),IF(AND($H29<>"",$H29<=EOMONTH(P$12,0),$I29>=P$12),"PD+DEV","PD")),IF(AND(INDEX('Roadmap Calc (Don’t Touch)'!$AA$2:$AX$151,$AI29,COLUMN()-COLUMN($J$16)+1)>0,OR($D29="03. UX Discovery",$D29="04. UX Design")),IF(AND($H29<>"",$H29<=EOMONTH(P$12,0),$I29>=P$12),"UX+DEV","UX"),IF(AND($H29<>"",$H29<=EOMONTH(P$12,0),$I29>=P$12),"DEV","")))) | Q29: =IF($AI29="","",IF(AND($AN29<>"",$AN29<=EOMONTH(Q$12,0),$AO29>=Q$12),IF(AND(INDEX('Roadmap Calc (Don’t Touch)'!$AA$2:$AX$151,$AI29,COLUMN()-COLUMN($J$16)+1)>0,OR($D29="03. UX Discovery",$D29="04. UX Design")),IF(AND($H29<>"",$H29<=EOMONTH(Q$12,0),$I29>=Q$12),"ALL","PD+UX"),IF(AND($H29<>"",$H29<=EOMONTH(Q$12,0),$I29>=Q$12),"PD+DEV","PD")),IF(AND(INDEX('Roadmap Calc (Don’t Touch)'!$AA$2:$AX$151,$AI29,COLUMN()-COLUMN($J$16)+1)>0,OR($D29="03. UX Discovery",$D29="04. UX Design")),IF(AND($H29<>"",$H29<=EOMONTH(Q$12,0),$I29>=Q$12),"UX+DEV","UX"),IF(AND($H29<>"",$H29<=EOMONTH(Q$12,0),$I29>=Q$12),"DEV","")))) | ... AG29: =IF($AI29="","",IF(AND($AN29<>"",$AN29<=EOMONTH(AG$12,0),$AO29>=AG$12),IF(AND(INDEX('Roadmap Calc (Don’t Touch)'!$AA$2:$AX$151,$AI29,COLUMN()-COLUMN($J$16)+1)>0,OR($D29="03. UX Discovery",$D29="04. UX Design")),IF(AND($H29<>"",$H29<=EOMONTH(AG$12,0),$I29>=AG$12),"ALL","PD+UX"),IF(AND($H29<>"",$H29<=EOMONTH(AG$12,0),$I29>=AG$12),"PD+DEV","PD")),IF(AND(INDEX('Roadmap Calc (Don’t Touch)'!$AA$2:$AX$151,$AI29,COLUMN()-COLUMN($J$16)+1)>0,OR($D29="03. UX Discovery",$D29="04. UX Design")),IF(AND($H29<>"",$H29<=EOMONTH(AG$12,0),$I29>=AG$12),"UX+DEV","UX"),IF(AND($H29<>"",$H29<=EOMONTH(AG$12,0),$I29>=AG$12),"DEV","")))) | AH29: =IF($AI29="","",INDEX('Roadmap Calc (Don’t Touch)'!$D$2:$D$151,$AI29)) -> Increase Buy Used Awareness | AI29: =IFERROR(MATCH(14,'Roadmap Calc (Don’t Touch)'!$O$2:$O$151,0),"") -> 14 | AN29: =IF($AI29="","",IF(ISNUMBER(INDEX('Roadmap Calc (Don’t Touch)'!$BB$2:$BB$151,$AI29)),INDEX('Roadmap Calc (Don’t Touch)'!$BB$2:$BB$151,$AI29),"")) | AO29: =IF($AI29="","",IF(ISNUMBER(INDEX('Roadmap Calc (Don’t Touch)'!$BC$2:$BC$151,$AI29)),INDEX('Roadmap Calc (Don’t Touch)'!$BC$2:$BC$151,$AI29),""))
A30: =IF($AI30="","",IF($AH30=$AH29,"",IF(INDEX('Roadmap Calc (Don’t Touch)'!$U$2:$U$151,$AI30)=0,$AH30,HYPERLINK("#'Control (Don’t Touch)'!E"&INDEX('Roadmap Calc (Don’t Touch)'!$U$2:$U$151,$AI30),$AH30)))) | B30: =IF($AI30="","",IF(INDEX('Roadmap Calc (Don’t Touch)'!$K$2:$K$151,$AI30)="",INDEX('Roadmap Calc (Don’t Touch)'!$B$2:$B$151,$AI30),HYPERLINK("https://jira.bnh.com/browse/"&INDEX('Roadmap Calc (Don’t Touch)'!$K$2:$K$151,$AI30),INDEX('Roadmap Calc (Don’t Touch)'!$B$2:$B$151,$AI30)))) -> Out of stock Alerts for used products | C30: =IF($AI30="","",IF(INDEX('Roadmap Calc (Don’t Touch)'!$E$2:$E$151,$AI30)="","",HYPERLINK("https://jira.bnh.com/browse/"&INDEX('Roadmap Calc (Don’t Touch)'!$E$2:$E$151,$AI30),INDEX('Roadmap Calc (Don’t Touch)'!$E$2:$E$151,$AI30)))) -> BHUX-35020 | D30: =IF($AI30="","",INDEX('Roadmap Calc (Don’t Touch)'!$F$2:$F$151,$AI30)) -> 03. UX Discovery | E30: =IF($AI30="","",IF(ISNUMBER(INDEX('Roadmap Calc (Don’t Touch)'!$G$2:$G$151,$AI30)),INDEX('Roadmap Calc (Don’t Touch)'!$G$2:$G$151,$AI30),"")) -> 46237 | F30: =IF($AI30="","",IF(ISNUMBER(INDEX('Roadmap Calc (Don’t Touch)'!$H$2:$H$151,$AI30)),INDEX('Roadmap Calc (Don’t Touch)'!$H$2:$H$151,$AI30),"")) -> 46258 | G30: =IF($AI30="","",INDEX('Roadmap Calc (Don’t Touch)'!$T$2:$T$151,$AI30)) -> 4 | H30: =IF($AI30="","",IF(ISNUMBER(INDEX('Roadmap Calc (Don’t Touch)'!$I$2:$I$151,$AI30)),INDEX('Roadmap Calc (Don’t Touch)'!$I$2:$I$151,$AI30),"")) -> 46296 | I30: =IF($AI30="","",IF(ISNUMBER(INDEX('Roadmap Calc (Don’t Touch)'!$J$2:$J$151,$AI30)),INDEX('Roadmap Calc (Don’t Touch)'!$J$2:$J$151,$AI30),"")) -> 46326 | J30: =IF($AI30="","",IF(AND($AN30<>"",$AN30<=EOMONTH(J$12,0),$AO30>=J$12),IF(AND(INDEX('Roadmap Calc (Don’t Touch)'!$AA$2:$AX$151,$AI30,COLUMN()-COLUMN($J$16)+1)>0,OR($D30="03. UX Discovery",$D30="04. UX Design")),IF(AND($H30<>"",$H30<=EOMONTH(J$12,0),$I30>=J$12),"ALL","PD+UX"),IF(AND($H30<>"",$H30<=EOMONTH(J$12,0),$I30>=J$12),"PD+DEV","PD")),IF(AND(INDEX('Roadmap Calc (Don’t Touch)'!$AA$2:$AX$151,$AI30,COLUMN()-COLUMN($J$16)+1)>0,OR($D30="03. UX Discovery",$D30="04. UX Design")),IF(AND($H30<>"",$H30<=EOMONTH(J$12,0),$I30>=J$12),"UX+DEV","UX"),IF(AND($H30<>"",$H30<=EOMONTH(J$12,0),$I30>=J$12),"DEV","")))) | K30: =IF($AI30="","",IF(AND($AN30<>"",$AN30<=EOMONTH(K$12,0),$AO30>=K$12),IF(AND(INDEX('Roadmap Calc (Don’t Touch)'!$AA$2:$AX$151,$AI30,COLUMN()-COLUMN($J$16)+1)>0,OR($D30="03. UX Discovery",$D30="04. UX Design")),IF(AND($H30<>"",$H30<=EOMONTH(K$12,0),$I30>=K$12),"ALL","PD+UX"),IF(AND($H30<>"",$H30<=EOMONTH(K$12,0),$I30>=K$12),"PD+DEV","PD")),IF(AND(INDEX('Roadmap Calc (Don’t Touch)'!$AA$2:$AX$151,$AI30,COLUMN()-COLUMN($J$16)+1)>0,OR($D30="03. UX Discovery",$D30="04. UX Design")),IF(AND($H30<>"",$H30<=EOMONTH(K$12,0),$I30>=K$12),"UX+DEV","UX"),IF(AND($H30<>"",$H30<=EOMONTH(K$12,0),$I30>=K$12),"DEV","")))) | L30: =IF($AI30="","",IF(AND($AN30<>"",$AN30<=EOMONTH(L$12,0),$AO30>=L$12),IF(AND(INDEX('Roadmap Calc (Don’t Touch)'!$AA$2:$AX$151,$AI30,COLUMN()-COLUMN($J$16)+1)>0,OR($D30="03. UX Discovery",$D30="04. UX Design")),IF(AND($H30<>"",$H30<=EOMONTH(L$12,0),$I30>=L$12),"ALL","PD+UX"),IF(AND($H30<>"",$H30<=EOMONTH(L$12,0),$I30>=L$12),"PD+DEV","PD")),IF(AND(INDEX('Roadmap Calc (Don’t Touch)'!$AA$2:$AX$151,$AI30,COLUMN()-COLUMN($J$16)+1)>0,OR($D30="03. UX Discovery",$D30="04. UX Design")),IF(AND($H30<>"",$H30<=EOMONTH(L$12,0),$I30>=L$12),"UX+DEV","UX"),IF(AND($H30<>"",$H30<=EOMONTH(L$12,0),$I30>=L$12),"DEV","")))) | M30: =IF($AI30="","",IF(AND($AN30<>"",$AN30<=EOMONTH(M$12,0),$AO30>=M$12),IF(AND(INDEX('Roadmap Calc (Don’t Touch)'!$AA$2:$AX$151,$AI30,COLUMN()-COLUMN($J$16)+1)>0,OR($D30="03. UX Discovery",$D30="04. UX Design")),IF(AND($H30<>"",$H30<=EOMONTH(M$12,0),$I30>=M$12),"ALL","PD+UX"),IF(AND($H30<>"",$H30<=EOMONTH(M$12,0),$I30>=M$12),"PD+DEV","PD")),IF(AND(INDEX('Roadmap Calc (Don’t Touch)'!$AA$2:$AX$151,$AI30,COLUMN()-COLUMN($J$16)+1)>0,OR($D30="03. UX Discovery",$D30="04. UX Design")),IF(AND($H30<>"",$H30<=EOMONTH(M$12,0),$I30>=M$12),"UX+DEV","UX"),IF(AND($H30<>"",$H30<=EOMONTH(M$12,0),$I30>=M$12),"DEV","")))) | N30: =IF($AI30="","",IF(AND($AN30<>"",$AN30<=EOMONTH(N$12,0),$AO30>=N$12),IF(AND(INDEX('Roadmap Calc (Don’t Touch)'!$AA$2:$AX$151,$AI30,COLUMN()-COLUMN($J$16)+1)>0,OR($D30="03. UX Discovery",$D30="04. UX Design")),IF(AND($H30<>"",$H30<=EOMONTH(N$12,0),$I30>=N$12),"ALL","PD+UX"),IF(AND($H30<>"",$H30<=EOMONTH(N$12,0),$I30>=N$12),"PD+DEV","PD")),IF(AND(INDEX('Roadmap Calc (Don’t Touch)'!$AA$2:$AX$151,$AI30,COLUMN()-COLUMN($J$16)+1)>0,OR($D30="03. UX Discovery",$D30="04. UX Design")),IF(AND($H30<>"",$H30<=EOMONTH(N$12,0),$I30>=N$12),"UX+DEV","UX"),IF(AND($H30<>"",$H30<=EOMONTH(N$12,0),$I30>=N$12),"DEV","")))) | O30: =IF($AI30="","",IF(AND($AN30<>"",$AN30<=EOMONTH(O$12,0),$AO30>=O$12),IF(AND(INDEX('Roadmap Calc (Don’t Touch)'!$AA$2:$AX$151,$AI30,COLUMN()-COLUMN($J$16)+1)>0,OR($D30="03. UX Discovery",$D30="04. UX Design")),IF(AND($H30<>"",$H30<=EOMONTH(O$12,0),$I30>=O$12),"ALL","PD+UX"),IF(AND($H30<>"",$H30<=EOMONTH(O$12,0),$I30>=O$12),"PD+DEV","PD")),IF(AND(INDEX('Roadmap Calc (Don’t Touch)'!$AA$2:$AX$151,$AI30,COLUMN()-COLUMN($J$16)+1)>0,OR($D30="03. UX Discovery",$D30="04. UX Design")),IF(AND($H30<>"",$H30<=EOMONTH(O$12,0),$I30>=O$12),"UX+DEV","UX"),IF(AND($H30<>"",$H30<=EOMONTH(O$12,0),$I30>=O$12),"DEV","")))) | P30: =IF($AI30="","",IF(AND($AN30<>"",$AN30<=EOMONTH(P$12,0),$AO30>=P$12),IF(AND(INDEX('Roadmap Calc (Don’t Touch)'!$AA$2:$AX$151,$AI30,COLUMN()-COLUMN($J$16)+1)>0,OR($D30="03. UX Discovery",$D30="04. UX Design")),IF(AND($H30<>"",$H30<=EOMONTH(P$12,0),$I30>=P$12),"ALL","PD+UX"),IF(AND($H30<>"",$H30<=EOMONTH(P$12,0),$I30>=P$12),"PD+DEV","PD")),IF(AND(INDEX('Roadmap Calc (Don’t Touch)'!$AA$2:$AX$151,$AI30,COLUMN()-COLUMN($J$16)+1)>0,OR($D30="03. UX Discovery",$D30="04. UX Design")),IF(AND($H30<>"",$H30<=EOMONTH(P$12,0),$I30>=P$12),"UX+DEV","UX"),IF(AND($H30<>"",$H30<=EOMONTH(P$12,0),$I30>=P$12),"DEV","")))) | Q30: =IF($AI30="","",IF(AND($AN30<>"",$AN30<=EOMONTH(Q$12,0),$AO30>=Q$12),IF(AND(INDEX('Roadmap Calc (Don’t Touch)'!$AA$2:$AX$151,$AI30,COLUMN()-COLUMN($J$16)+1)>0,OR($D30="03. UX Discovery",$D30="04. UX Design")),IF(AND($H30<>"",$H30<=EOMONTH(Q$12,0),$I30>=Q$12),"ALL","PD+UX"),IF(AND($H30<>"",$H30<=EOMONTH(Q$12,0),$I30>=Q$12),"PD+DEV","PD")),IF(AND(INDEX('Roadmap Calc (Don’t Touch)'!$AA$2:$AX$151,$AI30,COLUMN()-COLUMN($J$16)+1)>0,OR($D30="03. UX Discovery",$D30="04. UX Design")),IF(AND($H30<>"",$H30<=EOMONTH(Q$12,0),$I30>=Q$12),"UX+DEV","UX"),IF(AND($H30<>"",$H30<=EOMONTH(Q$12,0),$I30>=Q$12),"DEV","")))) | ... AG30: =IF($AI30="","",IF(AND($AN30<>"",$AN30<=EOMONTH(AG$12,0),$AO30>=AG$12),IF(AND(INDEX('Roadmap Calc (Don’t Touch)'!$AA$2:$AX$151,$AI30,COLUMN()-COLUMN($J$16)+1)>0,OR($D30="03. UX Discovery",$D30="04. UX Design")),IF(AND($H30<>"",$H30<=EOMONTH(AG$12,0),$I30>=AG$12),"ALL","PD+UX"),IF(AND($H30<>"",$H30<=EOMONTH(AG$12,0),$I30>=AG$12),"PD+DEV","PD")),IF(AND(INDEX('Roadmap Calc (Don’t Touch)'!$AA$2:$AX$151,$AI30,COLUMN()-COLUMN($J$16)+1)>0,OR($D30="03. UX Discovery",$D30="04. UX Design")),IF(AND($H30<>"",$H30<=EOMONTH(AG$12,0),$I30>=AG$12),"UX+DEV","UX"),IF(AND($H30<>"",$H30<=EOMONTH(AG$12,0),$I30>=AG$12),"DEV","")))) | AH30: =IF($AI30="","",INDEX('Roadmap Calc (Don’t Touch)'!$D$2:$D$151,$AI30)) -> Increase Buy Used Awareness | AI30: =IFERROR(MATCH(15,'Roadmap Calc (Don’t Touch)'!$O$2:$O$151,0),"") -> 16 | AN30: =IF($AI30="","",IF(ISNUMBER(INDEX('Roadmap Calc (Don’t Touch)'!$BB$2:$BB$151,$AI30)),INDEX('Roadmap Calc (Don’t Touch)'!$BB$2:$BB$151,$AI30),"")) | AO30: =IF($AI30="","",IF(ISNUMBER(INDEX('Roadmap Calc (Don’t Touch)'!$BC$2:$BC$151,$AI30)),INDEX('Roadmap Calc (Don’t Touch)'!$BC$2:$BC$151,$AI30),""))
A31: =IF($AI31="","",IF($AH31=$AH30,"",IF(INDEX('Roadmap Calc (Don’t Touch)'!$U$2:$U$151,$AI31)=0,$AH31,HYPERLINK("#'Control (Don’t Touch)'!E"&INDEX('Roadmap Calc (Don’t Touch)'!$U$2:$U$151,$AI31),$AH31)))) | B31: =IF($AI31="","",IF(INDEX('Roadmap Calc (Don’t Touch)'!$K$2:$K$151,$AI31)="",INDEX('Roadmap Calc (Don’t Touch)'!$B$2:$B$151,$AI31),HYPERLINK("https://jira.bnh.com/browse/"&INDEX('Roadmap Calc (Don’t Touch)'!$K$2:$K$151,$AI31),INDEX('Roadmap Calc (Don’t Touch)'!$B$2:$B$151,$AI31)))) -> Add New | Used tab to all listing pages and search results pages | C31: =IF($AI31="","",IF(INDEX('Roadmap Calc (Don’t Touch)'!$E$2:$E$151,$AI31)="","",HYPERLINK("https://jira.bnh.com/browse/"&INDEX('Roadmap Calc (Don’t Touch)'!$E$2:$E$151,$AI31),INDEX('Roadmap Calc (Don’t Touch)'!$E$2:$E$151,$AI31)))) -> BHUX-35303 | D31: =IF($AI31="","",INDEX('Roadmap Calc (Don’t Touch)'!$F$2:$F$151,$AI31)) -> 03. UX Discovery | E31: =IF($AI31="","",IF(ISNUMBER(INDEX('Roadmap Calc (Don’t Touch)'!$G$2:$G$151,$AI31)),INDEX('Roadmap Calc (Don’t Touch)'!$G$2:$G$151,$AI31),"")) -> 46258 | F31: =IF($AI31="","",IF(ISNUMBER(INDEX('Roadmap Calc (Don’t Touch)'!$H$2:$H$151,$AI31)),INDEX('Roadmap Calc (Don’t Touch)'!$H$2:$H$151,$AI31),"")) -> 46279 | G31: =IF($AI31="","",INDEX('Roadmap Calc (Don’t Touch)'!$T$2:$T$151,$AI31)) -> 4 | H31: =IF($AI31="","",IF(ISNUMBER(INDEX('Roadmap Calc (Don’t Touch)'!$I$2:$I$151,$AI31)),INDEX('Roadmap Calc (Don’t Touch)'!$I$2:$I$151,$AI31),"")) -> 46327 | I31: =IF($AI31="","",IF(ISNUMBER(INDEX('Roadmap Calc (Don’t Touch)'!$J$2:$J$151,$AI31)),INDEX('Roadmap Calc (Don’t Touch)'!$J$2:$J$151,$AI31),"")) -> 46356 | J31: =IF($AI31="","",IF(AND($AN31<>"",$AN31<=EOMONTH(J$12,0),$AO31>=J$12),IF(AND(INDEX('Roadmap Calc (Don’t Touch)'!$AA$2:$AX$151,$AI31,COLUMN()-COLUMN($J$16)+1)>0,OR($D31="03. UX Discovery",$D31="04. UX Design")),IF(AND($H31<>"",$H31<=EOMONTH(J$12,0),$I31>=J$12),"ALL","PD+UX"),IF(AND($H31<>"",$H31<=EOMONTH(J$12,0),$I31>=J$12),"PD+DEV","PD")),IF(AND(INDEX('Roadmap Calc (Don’t Touch)'!$AA$2:$AX$151,$AI31,COLUMN()-COLUMN($J$16)+1)>0,OR($D31="03. UX Discovery",$D31="04. UX Design")),IF(AND($H31<>"",$H31<=EOMONTH(J$12,0),$I31>=J$12),"UX+DEV","UX"),IF(AND($H31<>"",$H31<=EOMONTH(J$12,0),$I31>=J$12),"DEV","")))) | K31: =IF($AI31="","",IF(AND($AN31<>"",$AN31<=EOMONTH(K$12,0),$AO31>=K$12),IF(AND(INDEX('Roadmap Calc (Don’t Touch)'!$AA$2:$AX$151,$AI31,COLUMN()-COLUMN($J$16)+1)>0,OR($D31="03. UX Discovery",$D31="04. UX Design")),IF(AND($H31<>"",$H31<=EOMONTH(K$12,0),$I31>=K$12),"ALL","PD+UX"),IF(AND($H31<>"",$H31<=EOMONTH(K$12,0),$I31>=K$12),"PD+DEV","PD")),IF(AND(INDEX('Roadmap Calc (Don’t Touch)'!$AA$2:$AX$151,$AI31,COLUMN()-COLUMN($J$16)+1)>0,OR($D31="03. UX Discovery",$D31="04. UX Design")),IF(AND($H31<>"",$H31<=EOMONTH(K$12,0),$I31>=K$12),"UX+DEV","UX"),IF(AND($H31<>"",$H31<=EOMONTH(K$12,0),$I31>=K$12),"DEV","")))) | L31: =IF($AI31="","",IF(AND($AN31<>"",$AN31<=EOMONTH(L$12,0),$AO31>=L$12),IF(AND(INDEX('Roadmap Calc (Don’t Touch)'!$AA$2:$AX$151,$AI31,COLUMN()-COLUMN($J$16)+1)>0,OR($D31="03. UX Discovery",$D31="04. UX Design")),IF(AND($H31<>"",$H31<=EOMONTH(L$12,0),$I31>=L$12),"ALL","PD+UX"),IF(AND($H31<>"",$H31<=EOMONTH(L$12,0),$I31>=L$12),"PD+DEV","PD")),IF(AND(INDEX('Roadmap Calc (Don’t Touch)'!$AA$2:$AX$151,$AI31,COLUMN()-COLUMN($J$16)+1)>0,OR($D31="03. UX Discovery",$D31="04. UX Design")),IF(AND($H31<>"",$H31<=EOMONTH(L$12,0),$I31>=L$12),"UX+DEV","UX"),IF(AND($H31<>"",$H31<=EOMONTH(L$12,0),$I31>=L$12),"DEV","")))) | M31: =IF($AI31="","",IF(AND($AN31<>"",$AN31<=EOMONTH(M$12,0),$AO31>=M$12),IF(AND(INDEX('Roadmap Calc (Don’t Touch)'!$AA$2:$AX$151,$AI31,COLUMN()-COLUMN($J$16)+1)>0,OR($D31="03. UX Discovery",$D31="04. UX Design")),IF(AND($H31<>"",$H31<=EOMONTH(M$12,0),$I31>=M$12),"ALL","PD+UX"),IF(AND($H31<>"",$H31<=EOMONTH(M$12,0),$I31>=M$12),"PD+DEV","PD")),IF(AND(INDEX('Roadmap Calc (Don’t Touch)'!$AA$2:$AX$151,$AI31,COLUMN()-COLUMN($J$16)+1)>0,OR($D31="03. UX Discovery",$D31="04. UX Design")),IF(AND($H31<>"",$H31<=EOMONTH(M$12,0),$I31>=M$12),"UX+DEV","UX"),IF(AND($H31<>"",$H31<=EOMONTH(M$12,0),$I31>=M$12),"DEV","")))) | N31: =IF($AI31="","",IF(AND($AN31<>"",$AN31<=EOMONTH(N$12,0),$AO31>=N$12),IF(AND(INDEX('Roadmap Calc (Don’t Touch)'!$AA$2:$AX$151,$AI31,COLUMN()-COLUMN($J$16)+1)>0,OR($D31="03. UX Discovery",$D31="04. UX Design")),IF(AND($H31<>"",$H31<=EOMONTH(N$12,0),$I31>=N$12),"ALL","PD+UX"),IF(AND($H31<>"",$H31<=EOMONTH(N$12,0),$I31>=N$12),"PD+DEV","PD")),IF(AND(INDEX('Roadmap Calc (Don’t Touch)'!$AA$2:$AX$151,$AI31,COLUMN()-COLUMN($J$16)+1)>0,OR($D31="03. UX Discovery",$D31="04. UX Design")),IF(AND($H31<>"",$H31<=EOMONTH(N$12,0),$I31>=N$12),"UX+DEV","UX"),IF(AND($H31<>"",$H31<=EOMONTH(N$12,0),$I31>=N$12),"DEV","")))) | O31: =IF($AI31="","",IF(AND($AN31<>"",$AN31<=EOMONTH(O$12,0),$AO31>=O$12),IF(AND(INDEX('Roadmap Calc (Don’t Touch)'!$AA$2:$AX$151,$AI31,COLUMN()-COLUMN($J$16)+1)>0,OR($D31="03. UX Discovery",$D31="04. UX Design")),IF(AND($H31<>"",$H31<=EOMONTH(O$12,0),$I31>=O$12),"ALL","PD+UX"),IF(AND($H31<>"",$H31<=EOMONTH(O$12,0),$I31>=O$12),"PD+DEV","PD")),IF(AND(INDEX('Roadmap Calc (Don’t Touch)'!$AA$2:$AX$151,$AI31,COLUMN()-COLUMN($J$16)+1)>0,OR($D31="03. UX Discovery",$D31="04. UX Design")),IF(AND($H31<>"",$H31<=EOMONTH(O$12,0),$I31>=O$12),"UX+DEV","UX"),IF(AND($H31<>"",$H31<=EOMONTH(O$12,0),$I31>=O$12),"DEV","")))) | P31: =IF($AI31="","",IF(AND($AN31<>"",$AN31<=EOMONTH(P$12,0),$AO31>=P$12),IF(AND(INDEX('Roadmap Calc (Don’t Touch)'!$AA$2:$AX$151,$AI31,COLUMN()-COLUMN($J$16)+1)>0,OR($D31="03. UX Discovery",$D31="04. UX Design")),IF(AND($H31<>"",$H31<=EOMONTH(P$12,0),$I31>=P$12),"ALL","PD+UX"),IF(AND($H31<>"",$H31<=EOMONTH(P$12,0),$I31>=P$12),"PD+DEV","PD")),IF(AND(INDEX('Roadmap Calc (Don’t Touch)'!$AA$2:$AX$151,$AI31,COLUMN()-COLUMN($J$16)+1)>0,OR($D31="03. UX Discovery",$D31="04. UX Design")),IF(AND($H31<>"",$H31<=EOMONTH(P$12,0),$I31>=P$12),"UX+DEV","UX"),IF(AND($H31<>"",$H31<=EOMONTH(P$12,0),$I31>=P$12),"DEV","")))) | Q31: =IF($AI31="","",IF(AND($AN31<>"",$AN31<=EOMONTH(Q$12,0),$AO31>=Q$12),IF(AND(INDEX('Roadmap Calc (Don’t Touch)'!$AA$2:$AX$151,$AI31,COLUMN()-COLUMN($J$16)+1)>0,OR($D31="03. UX Discovery",$D31="04. UX Design")),IF(AND($H31<>"",$H31<=EOMONTH(Q$12,0),$I31>=Q$12),"ALL","PD+UX"),IF(AND($H31<>"",$H31<=EOMONTH(Q$12,0),$I31>=Q$12),"PD+DEV","PD")),IF(AND(INDEX('Roadmap Calc (Don’t Touch)'!$AA$2:$AX$151,$AI31,COLUMN()-COLUMN($J$16)+1)>0,OR($D31="03. UX Discovery",$D31="04. UX Design")),IF(AND($H31<>"",$H31<=EOMONTH(Q$12,0),$I31>=Q$12),"UX+DEV","UX"),IF(AND($H31<>"",$H31<=EOMONTH(Q$12,0),$I31>=Q$12),"DEV","")))) | ... AG31: =IF($AI31="","",IF(AND($AN31<>"",$AN31<=EOMONTH(AG$12,0),$AO31>=AG$12),IF(AND(INDEX('Roadmap Calc (Don’t Touch)'!$AA$2:$AX$151,$AI31,COLUMN()-COLUMN($J$16)+1)>0,OR($D31="03. UX Discovery",$D31="04. UX Design")),IF(AND($H31<>"",$H31<=EOMONTH(AG$12,0),$I31>=AG$12),"ALL","PD+UX"),IF(AND($H31<>"",$H31<=EOMONTH(AG$12,0),$I31>=AG$12),"PD+DEV","PD")),IF(AND(INDEX('Roadmap Calc (Don’t Touch)'!$AA$2:$AX$151,$AI31,COLUMN()-COLUMN($J$16)+1)>0,OR($D31="03. UX Discovery",$D31="04. UX Design")),IF(AND($H31<>"",$H31<=EOMONTH(AG$12,0),$I31>=AG$12),"UX+DEV","UX"),IF(AND($H31<>"",$H31<=EOMONTH(AG$12,0),$I31>=AG$12),"DEV","")))) | AH31: =IF($AI31="","",INDEX('Roadmap Calc (Don’t Touch)'!$D$2:$D$151,$AI31)) -> Increase Buy Used Awareness | AI31: =IFERROR(MATCH(16,'Roadmap Calc (Don’t Touch)'!$O$2:$O$151,0),"") -> 18 | AN31: =IF($AI31="","",IF(ISNUMBER(INDEX('Roadmap Calc (Don’t Touch)'!$BB$2:$BB$151,$AI31)),INDEX('Roadmap Calc (Don’t Touch)'!$BB$2:$BB$151,$AI31),"")) | AO31: =IF($AI31="","",IF(ISNUMBER(INDEX('Roadmap Calc (Don’t Touch)'!$BC$2:$BC$151,$AI31)),INDEX('Roadmap Calc (Don’t Touch)'!$BC$2:$BC$151,$AI31),""))
A32: =IF($AI32="","",IF($AH32=$AH31,"",IF(INDEX('Roadmap Calc (Don’t Touch)'!$U$2:$U$151,$AI32)=0,$AH32,HYPERLINK("#'Control (Don’t Touch)'!E"&INDEX('Roadmap Calc (Don’t Touch)'!$U$2:$U$151,$AI32),$AH32)))) | B32: =IF($AI32="","",IF(INDEX('Roadmap Calc (Don’t Touch)'!$K$2:$K$151,$AI32)="",INDEX('Roadmap Calc (Don’t Touch)'!$B$2:$B$151,$AI32),HYPERLINK("https://jira.bnh.com/browse/"&INDEX('Roadmap Calc (Don’t Touch)'!$K$2:$K$151,$AI32),INDEX('Roadmap Calc (Don’t Touch)'!$B$2:$B$151,$AI32)))) -> Add 'shop by popular brands' section to Used Homepage | C32: =IF($AI32="","",IF(INDEX('Roadmap Calc (Don’t Touch)'!$E$2:$E$151,$AI32)="","",HYPERLINK("https://jira.bnh.com/browse/"&INDEX('Roadmap Calc (Don’t Touch)'!$E$2:$E$151,$AI32),INDEX('Roadmap Calc (Don’t Touch)'!$E$2:$E$151,$AI32)))) -> BHUX-34844 | D32: =IF($AI32="","",INDEX('Roadmap Calc (Don’t Touch)'!$F$2:$F$151,$AI32)) -> 04. UX Design | E32: =IF($AI32="","",IF(ISNUMBER(INDEX('Roadmap Calc (Don’t Touch)'!$G$2:$G$151,$AI32)),INDEX('Roadmap Calc (Don’t Touch)'!$G$2:$G$151,$AI32),"")) -> 46223 | F32: =IF($AI32="","",IF(ISNUMBER(INDEX('Roadmap Calc (Don’t Touch)'!$H$2:$H$151,$AI32)),INDEX('Roadmap Calc (Don’t Touch)'!$H$2:$H$151,$AI32),"")) -> 46272 | G32: =IF($AI32="","",INDEX('Roadmap Calc (Don’t Touch)'!$T$2:$T$151,$AI32)) -> 8 | H32: =IF($AI32="","",IF(ISNUMBER(INDEX('Roadmap Calc (Don’t Touch)'!$I$2:$I$151,$AI32)),INDEX('Roadmap Calc (Don’t Touch)'!$I$2:$I$151,$AI32),"")) -> 46327 | I32: =IF($AI32="","",IF(ISNUMBER(INDEX('Roadmap Calc (Don’t Touch)'!$J$2:$J$151,$AI32)),INDEX('Roadmap Calc (Don’t Touch)'!$J$2:$J$151,$AI32),"")) -> 46418 | J32: =IF($AI32="","",IF(AND($AN32<>"",$AN32<=EOMONTH(J$12,0),$AO32>=J$12),IF(AND(INDEX('Roadmap Calc (Don’t Touch)'!$AA$2:$AX$151,$AI32,COLUMN()-COLUMN($J$16)+1)>0,OR($D32="03. UX Discovery",$D32="04. UX Design")),IF(AND($H32<>"",$H32<=EOMONTH(J$12,0),$I32>=J$12),"ALL","PD+UX"),IF(AND($H32<>"",$H32<=EOMONTH(J$12,0),$I32>=J$12),"PD+DEV","PD")),IF(AND(INDEX('Roadmap Calc (Don’t Touch)'!$AA$2:$AX$151,$AI32,COLUMN()-COLUMN($J$16)+1)>0,OR($D32="03. UX Discovery",$D32="04. UX Design")),IF(AND($H32<>"",$H32<=EOMONTH(J$12,0),$I32>=J$12),"UX+DEV","UX"),IF(AND($H32<>"",$H32<=EOMONTH(J$12,0),$I32>=J$12),"DEV","")))) | K32: =IF($AI32="","",IF(AND($AN32<>"",$AN32<=EOMONTH(K$12,0),$AO32>=K$12),IF(AND(INDEX('Roadmap Calc (Don’t Touch)'!$AA$2:$AX$151,$AI32,COLUMN()-COLUMN($J$16)+1)>0,OR($D32="03. UX Discovery",$D32="04. UX Design")),IF(AND($H32<>"",$H32<=EOMONTH(K$12,0),$I32>=K$12),"ALL","PD+UX"),IF(AND($H32<>"",$H32<=EOMONTH(K$12,0),$I32>=K$12),"PD+DEV","PD")),IF(AND(INDEX('Roadmap Calc (Don’t Touch)'!$AA$2:$AX$151,$AI32,COLUMN()-COLUMN($J$16)+1)>0,OR($D32="03. UX Discovery",$D32="04. UX Design")),IF(AND($H32<>"",$H32<=EOMONTH(K$12,0),$I32>=K$12),"UX+DEV","UX"),IF(AND($H32<>"",$H32<=EOMONTH(K$12,0),$I32>=K$12),"DEV","")))) | L32: =IF($AI32="","",IF(AND($AN32<>"",$AN32<=EOMONTH(L$12,0),$AO32>=L$12),IF(AND(INDEX('Roadmap Calc (Don’t Touch)'!$AA$2:$AX$151,$AI32,COLUMN()-COLUMN($J$16)+1)>0,OR($D32="03. UX Discovery",$D32="04. UX Design")),IF(AND($H32<>"",$H32<=EOMONTH(L$12,0),$I32>=L$12),"ALL","PD+UX"),IF(AND($H32<>"",$H32<=EOMONTH(L$12,0),$I32>=L$12),"PD+DEV","PD")),IF(AND(INDEX('Roadmap Calc (Don’t Touch)'!$AA$2:$AX$151,$AI32,COLUMN()-COLUMN($J$16)+1)>0,OR($D32="03. UX Discovery",$D32="04. UX Design")),IF(AND($H32<>"",$H32<=EOMONTH(L$12,0),$I32>=L$12),"UX+DEV","UX"),IF(AND($H32<>"",$H32<=EOMONTH(L$12,0),$I32>=L$12),"DEV","")))) | M32: =IF($AI32="","",IF(AND($AN32<>"",$AN32<=EOMONTH(M$12,0),$AO32>=M$12),IF(AND(INDEX('Roadmap Calc (Don’t Touch)'!$AA$2:$AX$151,$AI32,COLUMN()-COLUMN($J$16)+1)>0,OR($D32="03. UX Discovery",$D32="04. UX Design")),IF(AND($H32<>"",$H32<=EOMONTH(M$12,0),$I32>=M$12),"ALL","PD+UX"),IF(AND($H32<>"",$H32<=EOMONTH(M$12,0),$I32>=M$12),"PD+DEV","PD")),IF(AND(INDEX('Roadmap Calc (Don’t Touch)'!$AA$2:$AX$151,$AI32,COLUMN()-COLUMN($J$16)+1)>0,OR($D32="03. UX Discovery",$D32="04. UX Design")),IF(AND($H32<>"",$H32<=EOMONTH(M$12,0),$I32>=M$12),"UX+DEV","UX"),IF(AND($H32<>"",$H32<=EOMONTH(M$12,0),$I32>=M$12),"DEV","")))) | N32: =IF($AI32="","",IF(AND($AN32<>"",$AN32<=EOMONTH(N$12,0),$AO32>=N$12),IF(AND(INDEX('Roadmap Calc (Don’t Touch)'!$AA$2:$AX$151,$AI32,COLUMN()-COLUMN($J$16)+1)>0,OR($D32="03. UX Discovery",$D32="04. UX Design")),IF(AND($H32<>"",$H32<=EOMONTH(N$12,0),$I32>=N$12),"ALL","PD+UX"),IF(AND($H32<>"",$H32<=EOMONTH(N$12,0),$I32>=N$12),"PD+DEV","PD")),IF(AND(INDEX('Roadmap Calc (Don’t Touch)'!$AA$2:$AX$151,$AI32,COLUMN()-COLUMN($J$16)+1)>0,OR($D32="03. UX Discovery",$D32="04. UX Design")),IF(AND($H32<>"",$H32<=EOMONTH(N$12,0),$I32>=N$12),"UX+DEV","UX"),IF(AND($H32<>"",$H32<=EOMONTH(N$12,0),$I32>=N$12),"DEV","")))) | O32: =IF($AI32="","",IF(AND($AN32<>"",$AN32<=EOMONTH(O$12,0),$AO32>=O$12),IF(AND(INDEX('Roadmap Calc (Don’t Touch)'!$AA$2:$AX$151,$AI32,COLUMN()-COLUMN($J$16)+1)>0,OR($D32="03. UX Discovery",$D32="04. UX Design")),IF(AND($H32<>"",$H32<=EOMONTH(O$12,0),$I32>=O$12),"ALL","PD+UX"),IF(AND($H32<>"",$H32<=EOMONTH(O$12,0),$I32>=O$12),"PD+DEV","PD")),IF(AND(INDEX('Roadmap Calc (Don’t Touch)'!$AA$2:$AX$151,$AI32,COLUMN()-COLUMN($J$16)+1)>0,OR($D32="03. UX Discovery",$D32="04. UX Design")),IF(AND($H32<>"",$H32<=EOMONTH(O$12,0),$I32>=O$12),"UX+DEV","UX"),IF(AND($H32<>"",$H32<=EOMONTH(O$12,0),$I32>=O$12),"DEV","")))) | P32: =IF($AI32="","",IF(AND($AN32<>"",$AN32<=EOMONTH(P$12,0),$AO32>=P$12),IF(AND(INDEX('Roadmap Calc (Don’t Touch)'!$AA$2:$AX$151,$AI32,COLUMN()-COLUMN($J$16)+1)>0,OR($D32="03. UX Discovery",$D32="04. UX Design")),IF(AND($H32<>"",$H32<=EOMONTH(P$12,0),$I32>=P$12),"ALL","PD+UX"),IF(AND($H32<>"",$H32<=EOMONTH(P$12,0),$I32>=P$12),"PD+DEV","PD")),IF(AND(INDEX('Roadmap Calc (Don’t Touch)'!$AA$2:$AX$151,$AI32,COLUMN()-COLUMN($J$16)+1)>0,OR($D32="03. UX Discovery",$D32="04. UX Design")),IF(AND($H32<>"",$H32<=EOMONTH(P$12,0),$I32>=P$12),"UX+DEV","UX"),IF(AND($H32<>"",$H32<=EOMONTH(P$12,0),$I32>=P$12),"DEV","")))) | Q32: =IF($AI32="","",IF(AND($AN32<>"",$AN32<=EOMONTH(Q$12,0),$AO32>=Q$12),IF(AND(INDEX('Roadmap Calc (Don’t Touch)'!$AA$2:$AX$151,$AI32,COLUMN()-COLUMN($J$16)+1)>0,OR($D32="03. UX Discovery",$D32="04. UX Design")),IF(AND($H32<>"",$H32<=EOMONTH(Q$12,0),$I32>=Q$12),"ALL","PD+UX"),IF(AND($H32<>"",$H32<=EOMONTH(Q$12,0),$I32>=Q$12),"PD+DEV","PD")),IF(AND(INDEX('Roadmap Calc (Don’t Touch)'!$AA$2:$AX$151,$AI32,COLUMN()-COLUMN($J$16)+1)>0,OR($D32="03. UX Discovery",$D32="04. UX Design")),IF(AND($H32<>"",$H32<=EOMONTH(Q$12,0),$I32>=Q$12),"UX+DEV","UX"),IF(AND($H32<>"",$H32<=EOMONTH(Q$12,0),$I32>=Q$12),"DEV","")))) | ... AG32: =IF($AI32="","",IF(AND($AN32<>"",$AN32<=EOMONTH(AG$12,0),$AO32>=AG$12),IF(AND(INDEX('Roadmap Calc (Don’t Touch)'!$AA$2:$AX$151,$AI32,COLUMN()-COLUMN($J$16)+1)>0,OR($D32="03. UX Discovery",$D32="04. UX Design")),IF(AND($H32<>"",$H32<=EOMONTH(AG$12,0),$I32>=AG$12),"ALL","PD+UX"),IF(AND($H32<>"",$H32<=EOMONTH(AG$12,0),$I32>=AG$12),"PD+DEV","PD")),IF(AND(INDEX('Roadmap Calc (Don’t Touch)'!$AA$2:$AX$151,$AI32,COLUMN()-COLUMN($J$16)+1)>0,OR($D32="03. UX Discovery",$D32="04. UX Design")),IF(AND($H32<>"",$H32<=EOMONTH(AG$12,0),$I32>=AG$12),"UX+DEV","UX"),IF(AND($H32<>"",$H32<=EOMONTH(AG$12,0),$I32>=AG$12),"DEV","")))) | AH32: =IF($AI32="","",INDEX('Roadmap Calc (Don’t Touch)'!$D$2:$D$151,$AI32)) -> Increase Buy Used Awareness | AI32: =IFERROR(MATCH(17,'Roadmap Calc (Don’t Touch)'!$O$2:$O$151,0),"") -> 23 | AN32: =IF($AI32="","",IF(ISNUMBER(INDEX('Roadmap Calc (Don’t Touch)'!$BB$2:$BB$151,$AI32)),INDEX('Roadmap Calc (Don’t Touch)'!$BB$2:$BB$151,$AI32),"")) | AO32: =IF($AI32="","",IF(ISNUMBER(INDEX('Roadmap Calc (Don’t Touch)'!$BC$2:$BC$151,$AI32)),INDEX('Roadmap Calc (Don’t Touch)'!$BC$2:$BC$151,$AI32),""))
A33: =IF($AI33="","",IF($AH33=$AH32,"",IF(INDEX('Roadmap Calc (Don’t Touch)'!$U$2:$U$151,$AI33)=0,$AH33,HYPERLINK("#'Control (Don’t Touch)'!E"&INDEX('Roadmap Calc (Don’t Touch)'!$U$2:$U$151,$AI33),$AH33)))) | B33: =IF($AI33="","",IF(INDEX('Roadmap Calc (Don’t Touch)'!$K$2:$K$151,$AI33)="",INDEX('Roadmap Calc (Don’t Touch)'!$B$2:$B$151,$AI33),HYPERLINK("https://jira.bnh.com/browse/"&INDEX('Roadmap Calc (Don’t Touch)'!$K$2:$K$151,$AI33),INDEX('Roadmap Calc (Don’t Touch)'!$B$2:$B$151,$AI33)))) -> Shop By Popular Brand' Listing Pages Discovery | C33: =IF($AI33="","",IF(INDEX('Roadmap Calc (Don’t Touch)'!$E$2:$E$151,$AI33)="","",HYPERLINK("https://jira.bnh.com/browse/"&INDEX('Roadmap Calc (Don’t Touch)'!$E$2:$E$151,$AI33),INDEX('Roadmap Calc (Don’t Touch)'!$E$2:$E$151,$AI33)))) -> BHUX-34845 | D33: =IF($AI33="","",INDEX('Roadmap Calc (Don’t Touch)'!$F$2:$F$151,$AI33)) -> 04. UX Design | E33: =IF($AI33="","",IF(ISNUMBER(INDEX('Roadmap Calc (Don’t Touch)'!$G$2:$G$151,$AI33)),INDEX('Roadmap Calc (Don’t Touch)'!$G$2:$G$151,$AI33),"")) -> 46230 | F33: =IF($AI33="","",IF(ISNUMBER(INDEX('Roadmap Calc (Don’t Touch)'!$H$2:$H$151,$AI33)),INDEX('Roadmap Calc (Don’t Touch)'!$H$2:$H$151,$AI33),"")) -> 46272 | G33: =IF($AI33="","",INDEX('Roadmap Calc (Don’t Touch)'!$T$2:$T$151,$AI33)) -> 7 | H33: =IF($AI33="","",IF(ISNUMBER(INDEX('Roadmap Calc (Don’t Touch)'!$I$2:$I$151,$AI33)),INDEX('Roadmap Calc (Don’t Touch)'!$I$2:$I$151,$AI33),"")) -> 46327 | I33: =IF($AI33="","",IF(ISNUMBER(INDEX('Roadmap Calc (Don’t Touch)'!$J$2:$J$151,$AI33)),INDEX('Roadmap Calc (Don’t Touch)'!$J$2:$J$151,$AI33),"")) -> 46418 | J33: =IF($AI33="","",IF(AND($AN33<>"",$AN33<=EOMONTH(J$12,0),$AO33>=J$12),IF(AND(INDEX('Roadmap Calc (Don’t Touch)'!$AA$2:$AX$151,$AI33,COLUMN()-COLUMN($J$16)+1)>0,OR($D33="03. UX Discovery",$D33="04. UX Design")),IF(AND($H33<>"",$H33<=EOMONTH(J$12,0),$I33>=J$12),"ALL","PD+UX"),IF(AND($H33<>"",$H33<=EOMONTH(J$12,0),$I33>=J$12),"PD+DEV","PD")),IF(AND(INDEX('Roadmap Calc (Don’t Touch)'!$AA$2:$AX$151,$AI33,COLUMN()-COLUMN($J$16)+1)>0,OR($D33="03. UX Discovery",$D33="04. UX Design")),IF(AND($H33<>"",$H33<=EOMONTH(J$12,0),$I33>=J$12),"UX+DEV","UX"),IF(AND($H33<>"",$H33<=EOMONTH(J$12,0),$I33>=J$12),"DEV","")))) | K33: =IF($AI33="","",IF(AND($AN33<>"",$AN33<=EOMONTH(K$12,0),$AO33>=K$12),IF(AND(INDEX('Roadmap Calc (Don’t Touch)'!$AA$2:$AX$151,$AI33,COLUMN()-COLUMN($J$16)+1)>0,OR($D33="03. UX Discovery",$D33="04. UX Design")),IF(AND($H33<>"",$H33<=EOMONTH(K$12,0),$I33>=K$12),"ALL","PD+UX"),IF(AND($H33<>"",$H33<=EOMONTH(K$12,0),$I33>=K$12),"PD+DEV","PD")),IF(AND(INDEX('Roadmap Calc (Don’t Touch)'!$AA$2:$AX$151,$AI33,COLUMN()-COLUMN($J$16)+1)>0,OR($D33="03. UX Discovery",$D33="04. UX Design")),IF(AND($H33<>"",$H33<=EOMONTH(K$12,0),$I33>=K$12),"UX+DEV","UX"),IF(AND($H33<>"",$H33<=EOMONTH(K$12,0),$I33>=K$12),"DEV","")))) | L33: =IF($AI33="","",IF(AND($AN33<>"",$AN33<=EOMONTH(L$12,0),$AO33>=L$12),IF(AND(INDEX('Roadmap Calc (Don’t Touch)'!$AA$2:$AX$151,$AI33,COLUMN()-COLUMN($J$16)+1)>0,OR($D33="03. UX Discovery",$D33="04. UX Design")),IF(AND($H33<>"",$H33<=EOMONTH(L$12,0),$I33>=L$12),"ALL","PD+UX"),IF(AND($H33<>"",$H33<=EOMONTH(L$12,0),$I33>=L$12),"PD+DEV","PD")),IF(AND(INDEX('Roadmap Calc (Don’t Touch)'!$AA$2:$AX$151,$AI33,COLUMN()-COLUMN($J$16)+1)>0,OR($D33="03. UX Discovery",$D33="04. UX Design")),IF(AND($H33<>"",$H33<=EOMONTH(L$12,0),$I33>=L$12),"UX+DEV","UX"),IF(AND($H33<>"",$H33<=EOMONTH(L$12,0),$I33>=L$12),"DEV","")))) | M33: =IF($AI33="","",IF(AND($AN33<>"",$AN33<=EOMONTH(M$12,0),$AO33>=M$12),IF(AND(INDEX('Roadmap Calc (Don’t Touch)'!$AA$2:$AX$151,$AI33,COLUMN()-COLUMN($J$16)+1)>0,OR($D33="03. UX Discovery",$D33="04. UX Design")),IF(AND($H33<>"",$H33<=EOMONTH(M$12,0),$I33>=M$12),"ALL","PD+UX"),IF(AND($H33<>"",$H33<=EOMONTH(M$12,0),$I33>=M$12),"PD+DEV","PD")),IF(AND(INDEX('Roadmap Calc (Don’t Touch)'!$AA$2:$AX$151,$AI33,COLUMN()-COLUMN($J$16)+1)>0,OR($D33="03. UX Discovery",$D33="04. UX Design")),IF(AND($H33<>"",$H33<=EOMONTH(M$12,0),$I33>=M$12),"UX+DEV","UX"),IF(AND($H33<>"",$H33<=EOMONTH(M$12,0),$I33>=M$12),"DEV","")))) | N33: =IF($AI33="","",IF(AND($AN33<>"",$AN33<=EOMONTH(N$12,0),$AO33>=N$12),IF(AND(INDEX('Roadmap Calc (Don’t Touch)'!$AA$2:$AX$151,$AI33,COLUMN()-COLUMN($J$16)+1)>0,OR($D33="03. UX Discovery",$D33="04. UX Design")),IF(AND($H33<>"",$H33<=EOMONTH(N$12,0),$I33>=N$12),"ALL","PD+UX"),IF(AND($H33<>"",$H33<=EOMONTH(N$12,0),$I33>=N$12),"PD+DEV","PD")),IF(AND(INDEX('Roadmap Calc (Don’t Touch)'!$AA$2:$AX$151,$AI33,COLUMN()-COLUMN($J$16)+1)>0,OR($D33="03. UX Discovery",$D33="04. UX Design")),IF(AND($H33<>"",$H33<=EOMONTH(N$12,0),$I33>=N$12),"UX+DEV","UX"),IF(AND($H33<>"",$H33<=EOMONTH(N$12,0),$I33>=N$12),"DEV","")))) | O33: =IF($AI33="","",IF(AND($AN33<>"",$AN33<=EOMONTH(O$12,0),$AO33>=O$12),IF(AND(INDEX('Roadmap Calc (Don’t Touch)'!$AA$2:$AX$151,$AI33,COLUMN()-COLUMN($J$16)+1)>0,OR($D33="03. UX Discovery",$D33="04. UX Design")),IF(AND($H33<>"",$H33<=EOMONTH(O$12,0),$I33>=O$12),"ALL","PD+UX"),IF(AND($H33<>"",$H33<=EOMONTH(O$12,0),$I33>=O$12),"PD+DEV","PD")),IF(AND(INDEX('Roadmap Calc (Don’t Touch)'!$AA$2:$AX$151,$AI33,COLUMN()-COLUMN($J$16)+1)>0,OR($D33="03. UX Discovery",$D33="04. UX Design")),IF(AND($H33<>"",$H33<=EOMONTH(O$12,0),$I33>=O$12),"UX+DEV","UX"),IF(AND($H33<>"",$H33<=EOMONTH(O$12,0),$I33>=O$12),"DEV","")))) | P33: =IF($AI33="","",IF(AND($AN33<>"",$AN33<=EOMONTH(P$12,0),$AO33>=P$12),IF(AND(INDEX('Roadmap Calc (Don’t Touch)'!$AA$2:$AX$151,$AI33,COLUMN()-COLUMN($J$16)+1)>0,OR($D33="03. UX Discovery",$D33="04. UX Design")),IF(AND($H33<>"",$H33<=EOMONTH(P$12,0),$I33>=P$12),"ALL","PD+UX"),IF(AND($H33<>"",$H33<=EOMONTH(P$12,0),$I33>=P$12),"PD+DEV","PD")),IF(AND(INDEX('Roadmap Calc (Don’t Touch)'!$AA$2:$AX$151,$AI33,COLUMN()-COLUMN($J$16)+1)>0,OR($D33="03. UX Discovery",$D33="04. UX Design")),IF(AND($H33<>"",$H33<=EOMONTH(P$12,0),$I33>=P$12),"UX+DEV","UX"),IF(AND($H33<>"",$H33<=EOMONTH(P$12,0),$I33>=P$12),"DEV","")))) | Q33: =IF($AI33="","",IF(AND($AN33<>"",$AN33<=EOMONTH(Q$12,0),$AO33>=Q$12),IF(AND(INDEX('Roadmap Calc (Don’t Touch)'!$AA$2:$AX$151,$AI33,COLUMN()-COLUMN($J$16)+1)>0,OR($D33="03. UX Discovery",$D33="04. UX Design")),IF(AND($H33<>"",$H33<=EOMONTH(Q$12,0),$I33>=Q$12),"ALL","PD+UX"),IF(AND($H33<>"",$H33<=EOMONTH(Q$12,0),$I33>=Q$12),"PD+DEV","PD")),IF(AND(INDEX('Roadmap Calc (Don’t Touch)'!$AA$2:$AX$151,$AI33,COLUMN()-COLUMN($J$16)+1)>0,OR($D33="03. UX Discovery",$D33="04. UX Design")),IF(AND($H33<>"",$H33<=EOMONTH(Q$12,0),$I33>=Q$12),"UX+DEV","UX"),IF(AND($H33<>"",$H33<=EOMONTH(Q$12,0),$I33>=Q$12),"DEV","")))) | ... AG33: =IF($AI33="","",IF(AND($AN33<>"",$AN33<=EOMONTH(AG$12,0),$AO33>=AG$12),IF(AND(INDEX('Roadmap Calc (Don’t Touch)'!$AA$2:$AX$151,$AI33,COLUMN()-COLUMN($J$16)+1)>0,OR($D33="03. UX Discovery",$D33="04. UX Design")),IF(AND($H33<>"",$H33<=EOMONTH(AG$12,0),$I33>=AG$12),"ALL","PD+UX"),IF(AND($H33<>"",$H33<=EOMONTH(AG$12,0),$I33>=AG$12),"PD+DEV","PD")),IF(AND(INDEX('Roadmap Calc (Don’t Touch)'!$AA$2:$AX$151,$AI33,COLUMN()-COLUMN($J$16)+1)>0,OR($D33="03. UX Discovery",$D33="04. UX Design")),IF(AND($H33<>"",$H33<=EOMONTH(AG$12,0),$I33>=AG$12),"UX+DEV","UX"),IF(AND($H33<>"",$H33<=EOMONTH(AG$12,0),$I33>=AG$12),"DEV","")))) | AH33: =IF($AI33="","",INDEX('Roadmap Calc (Don’t Touch)'!$D$2:$D$151,$AI33)) -> Increase Buy Used Awareness | AI33: =IFERROR(MATCH(18,'Roadmap Calc (Don’t Touch)'!$O$2:$O$151,0),"") -> 24 | AN33: =IF($AI33="","",IF(ISNUMBER(INDEX('Roadmap Calc (Don’t Touch)'!$BB$2:$BB$151,$AI33)),INDEX('Roadmap Calc (Don’t Touch)'!$BB$2:$BB$151,$AI33),"")) | AO33: =IF($AI33="","",IF(ISNUMBER(INDEX('Roadmap Calc (Don’t Touch)'!$BC$2:$BC$151,$AI33)),INDEX('Roadmap Calc (Don’t Touch)'!$BC$2:$BC$151,$AI33),""))
A34: =IF($AI34="","",IF($AH34=$AH33,"",IF(INDEX('Roadmap Calc (Don’t Touch)'!$U$2:$U$151,$AI34)=0,$AH34,HYPERLINK("#'Control (Don’t Touch)'!E"&INDEX('Roadmap Calc (Don’t Touch)'!$U$2:$U$151,$AI34),$AH34)))) | B34: =IF($AI34="","",IF(INDEX('Roadmap Calc (Don’t Touch)'!$K$2:$K$151,$AI34)="",INDEX('Roadmap Calc (Don’t Touch)'!$B$2:$B$151,$AI34),HYPERLINK("https://jira.bnh.com/browse/"&INDEX('Roadmap Calc (Don’t Touch)'!$K$2:$K$151,$AI34),INDEX('Roadmap Calc (Don’t Touch)'!$B$2:$B$151,$AI34)))) -> My Account > Trade In Awareness | C34: =IF($AI34="","",IF(INDEX('Roadmap Calc (Don’t Touch)'!$E$2:$E$151,$AI34)="","",HYPERLINK("https://jira.bnh.com/browse/"&INDEX('Roadmap Calc (Don’t Touch)'!$E$2:$E$151,$AI34),INDEX('Roadmap Calc (Don’t Touch)'!$E$2:$E$151,$AI34)))) -> BHUX-35010 | D34: =IF($AI34="","",INDEX('Roadmap Calc (Don’t Touch)'!$F$2:$F$151,$AI34)) -> 04. UX Design | E34: =IF($AI34="","",IF(ISNUMBER(INDEX('Roadmap Calc (Don’t Touch)'!$G$2:$G$151,$AI34)),INDEX('Roadmap Calc (Don’t Touch)'!$G$2:$G$151,$AI34),"")) -> 46244 | F34: =IF($AI34="","",IF(ISNUMBER(INDEX('Roadmap Calc (Don’t Touch)'!$H$2:$H$151,$AI34)),INDEX('Roadmap Calc (Don’t Touch)'!$H$2:$H$151,$AI34),"")) -> 46258 | G34: =IF($AI34="","",INDEX('Roadmap Calc (Don’t Touch)'!$T$2:$T$151,$AI34)) -> 3 | H34: =IF($AI34="","",IF(ISNUMBER(INDEX('Roadmap Calc (Don’t Touch)'!$I$2:$I$151,$AI34)),INDEX('Roadmap Calc (Don’t Touch)'!$I$2:$I$151,$AI34),"")) -> 46357 | I34: =IF($AI34="","",IF(ISNUMBER(INDEX('Roadmap Calc (Don’t Touch)'!$J$2:$J$151,$AI34)),INDEX('Roadmap Calc (Don’t Touch)'!$J$2:$J$151,$AI34),"")) -> 46387 | J34: =IF($AI34="","",IF(AND($AN34<>"",$AN34<=EOMONTH(J$12,0),$AO34>=J$12),IF(AND(INDEX('Roadmap Calc (Don’t Touch)'!$AA$2:$AX$151,$AI34,COLUMN()-COLUMN($J$16)+1)>0,OR($D34="03. UX Discovery",$D34="04. UX Design")),IF(AND($H34<>"",$H34<=EOMONTH(J$12,0),$I34>=J$12),"ALL","PD+UX"),IF(AND($H34<>"",$H34<=EOMONTH(J$12,0),$I34>=J$12),"PD+DEV","PD")),IF(AND(INDEX('Roadmap Calc (Don’t Touch)'!$AA$2:$AX$151,$AI34,COLUMN()-COLUMN($J$16)+1)>0,OR($D34="03. UX Discovery",$D34="04. UX Design")),IF(AND($H34<>"",$H34<=EOMONTH(J$12,0),$I34>=J$12),"UX+DEV","UX"),IF(AND($H34<>"",$H34<=EOMONTH(J$12,0),$I34>=J$12),"DEV","")))) | K34: =IF($AI34="","",IF(AND($AN34<>"",$AN34<=EOMONTH(K$12,0),$AO34>=K$12),IF(AND(INDEX('Roadmap Calc (Don’t Touch)'!$AA$2:$AX$151,$AI34,COLUMN()-COLUMN($J$16)+1)>0,OR($D34="03. UX Discovery",$D34="04. UX Design")),IF(AND($H34<>"",$H34<=EOMONTH(K$12,0),$I34>=K$12),"ALL","PD+UX"),IF(AND($H34<>"",$H34<=EOMONTH(K$12,0),$I34>=K$12),"PD+DEV","PD")),IF(AND(INDEX('Roadmap Calc (Don’t Touch)'!$AA$2:$AX$151,$AI34,COLUMN()-COLUMN($J$16)+1)>0,OR($D34="03. UX Discovery",$D34="04. UX Design")),IF(AND($H34<>"",$H34<=EOMONTH(K$12,0),$I34>=K$12),"UX+DEV","UX"),IF(AND($H34<>"",$H34<=EOMONTH(K$12,0),$I34>=K$12),"DEV","")))) | L34: =IF($AI34="","",IF(AND($AN34<>"",$AN34<=EOMONTH(L$12,0),$AO34>=L$12),IF(AND(INDEX('Roadmap Calc (Don’t Touch)'!$AA$2:$AX$151,$AI34,COLUMN()-COLUMN($J$16)+1)>0,OR($D34="03. UX Discovery",$D34="04. UX Design")),IF(AND($H34<>"",$H34<=EOMONTH(L$12,0),$I34>=L$12),"ALL","PD+UX"),IF(AND($H34<>"",$H34<=EOMONTH(L$12,0),$I34>=L$12),"PD+DEV","PD")),IF(AND(INDEX('Roadmap Calc (Don’t Touch)'!$AA$2:$AX$151,$AI34,COLUMN()-COLUMN($J$16)+1)>0,OR($D34="03. UX Discovery",$D34="04. UX Design")),IF(AND($H34<>"",$H34<=EOMONTH(L$12,0),$I34>=L$12),"UX+DEV","UX"),IF(AND($H34<>"",$H34<=EOMONTH(L$12,0),$I34>=L$12),"DEV","")))) | M34: =IF($AI34="","",IF(AND($AN34<>"",$AN34<=EOMONTH(M$12,0),$AO34>=M$12),IF(AND(INDEX('Roadmap Calc (Don’t Touch)'!$AA$2:$AX$151,$AI34,COLUMN()-COLUMN($J$16)+1)>0,OR($D34="03. UX Discovery",$D34="04. UX Design")),IF(AND($H34<>"",$H34<=EOMONTH(M$12,0),$I34>=M$12),"ALL","PD+UX"),IF(AND($H34<>"",$H34<=EOMONTH(M$12,0),$I34>=M$12),"PD+DEV","PD")),IF(AND(INDEX('Roadmap Calc (Don’t Touch)'!$AA$2:$AX$151,$AI34,COLUMN()-COLUMN($J$16)+1)>0,OR($D34="03. UX Discovery",$D34="04. UX Design")),IF(AND($H34<>"",$H34<=EOMONTH(M$12,0),$I34>=M$12),"UX+DEV","UX"),IF(AND($H34<>"",$H34<=EOMONTH(M$12,0),$I34>=M$12),"DEV","")))) | N34: =IF($AI34="","",IF(AND($AN34<>"",$AN34<=EOMONTH(N$12,0),$AO34>=N$12),IF(AND(INDEX('Roadmap Calc (Don’t Touch)'!$AA$2:$AX$151,$AI34,COLUMN()-COLUMN($J$16)+1)>0,OR($D34="03. UX Discovery",$D34="04. UX Design")),IF(AND($H34<>"",$H34<=EOMONTH(N$12,0),$I34>=N$12),"ALL","PD+UX"),IF(AND($H34<>"",$H34<=EOMONTH(N$12,0),$I34>=N$12),"PD+DEV","PD")),IF(AND(INDEX('Roadmap Calc (Don’t Touch)'!$AA$2:$AX$151,$AI34,COLUMN()-COLUMN($J$16)+1)>0,OR($D34="03. UX Discovery",$D34="04. UX Design")),IF(AND($H34<>"",$H34<=EOMONTH(N$12,0),$I34>=N$12),"UX+DEV","UX"),IF(AND($H34<>"",$H34<=EOMONTH(N$12,0),$I34>=N$12),"DEV","")))) | O34: =IF($AI34="","",IF(AND($AN34<>"",$AN34<=EOMONTH(O$12,0),$AO34>=O$12),IF(AND(INDEX('Roadmap Calc (Don’t Touch)'!$AA$2:$AX$151,$AI34,COLUMN()-COLUMN($J$16)+1)>0,OR($D34="03. UX Discovery",$D34="04. UX Design")),IF(AND($H34<>"",$H34<=EOMONTH(O$12,0),$I34>=O$12),"ALL","PD+UX"),IF(AND($H34<>"",$H34<=EOMONTH(O$12,0),$I34>=O$12),"PD+DEV","PD")),IF(AND(INDEX('Roadmap Calc (Don’t Touch)'!$AA$2:$AX$151,$AI34,COLUMN()-COLUMN($J$16)+1)>0,OR($D34="03. UX Discovery",$D34="04. UX Design")),IF(AND($H34<>"",$H34<=EOMONTH(O$12,0),$I34>=O$12),"UX+DEV","UX"),IF(AND($H34<>"",$H34<=EOMONTH(O$12,0),$I34>=O$12),"DEV","")))) | P34: =IF($AI34="","",IF(AND($AN34<>"",$AN34<=EOMONTH(P$12,0),$AO34>=P$12),IF(AND(INDEX('Roadmap Calc (Don’t Touch)'!$AA$2:$AX$151,$AI34,COLUMN()-COLUMN($J$16)+1)>0,OR($D34="03. UX Discovery",$D34="04. UX Design")),IF(AND($H34<>"",$H34<=EOMONTH(P$12,0),$I34>=P$12),"ALL","PD+UX"),IF(AND($H34<>"",$H34<=EOMONTH(P$12,0),$I34>=P$12),"PD+DEV","PD")),IF(AND(INDEX('Roadmap Calc (Don’t Touch)'!$AA$2:$AX$151,$AI34,COLUMN()-COLUMN($J$16)+1)>0,OR($D34="03. UX Discovery",$D34="04. UX Design")),IF(AND($H34<>"",$H34<=EOMONTH(P$12,0),$I34>=P$12),"UX+DEV","UX"),IF(AND($H34<>"",$H34<=EOMONTH(P$12,0),$I34>=P$12),"DEV","")))) | Q34: =IF($AI34="","",IF(AND($AN34<>"",$AN34<=EOMONTH(Q$12,0),$AO34>=Q$12),IF(AND(INDEX('Roadmap Calc (Don’t Touch)'!$AA$2:$AX$151,$AI34,COLUMN()-COLUMN($J$16)+1)>0,OR($D34="03. UX Discovery",$D34="04. UX Design")),IF(AND($H34<>"",$H34<=EOMONTH(Q$12,0),$I34>=Q$12),"ALL","PD+UX"),IF(AND($H34<>"",$H34<=EOMONTH(Q$12,0),$I34>=Q$12),"PD+DEV","PD")),IF(AND(INDEX('Roadmap Calc (Don’t Touch)'!$AA$2:$AX$151,$AI34,COLUMN()-COLUMN($J$16)+1)>0,OR($D34="03. UX Discovery",$D34="04. UX Design")),IF(AND($H34<>"",$H34<=EOMONTH(Q$12,0),$I34>=Q$12),"UX+DEV","UX"),IF(AND($H34<>"",$H34<=EOMONTH(Q$12,0),$I34>=Q$12),"DEV","")))) | ... AG34: =IF($AI34="","",IF(AND($AN34<>"",$AN34<=EOMONTH(AG$12,0),$AO34>=AG$12),IF(AND(INDEX('Roadmap Calc (Don’t Touch)'!$AA$2:$AX$151,$AI34,COLUMN()-COLUMN($J$16)+1)>0,OR($D34="03. UX Discovery",$D34="04. UX Design")),IF(AND($H34<>"",$H34<=EOMONTH(AG$12,0),$I34>=AG$12),"ALL","PD+UX"),IF(AND($H34<>"",$H34<=EOMONTH(AG$12,0),$I34>=AG$12),"PD+DEV","PD")),IF(AND(INDEX('Roadmap Calc (Don’t Touch)'!$AA$2:$AX$151,$AI34,COLUMN()-COLUMN($J$16)+1)>0,OR($D34="03. UX Discovery",$D34="04. UX Design")),IF(AND($H34<>"",$H34<=EOMONTH(AG$12,0),$I34>=AG$12),"UX+DEV","UX"),IF(AND($H34<>"",$H34<=EOMONTH(AG$12,0),$I34>=AG$12),"DEV","")))) | AH34: =IF($AI34="","",INDEX('Roadmap Calc (Don’t Touch)'!$D$2:$D$151,$AI34)) -> Increase Buy Used Awareness | AI34: =IFERROR(MATCH(19,'Roadmap Calc (Don’t Touch)'!$O$2:$O$151,0),"") -> 25 | AN34: =IF($AI34="","",IF(ISNUMBER(INDEX('Roadmap Calc (Don’t Touch)'!$BB$2:$BB$151,$AI34)),INDEX('Roadmap Calc (Don’t Touch)'!$BB$2:$BB$151,$AI34),"")) | AO34: =IF($AI34="","",IF(ISNUMBER(INDEX('Roadmap Calc (Don’t Touch)'!$BC$2:$BC$151,$AI34)),INDEX('Roadmap Calc (Don’t Touch)'!$BC$2:$BC$151,$AI34),""))
A35: =IF($AI35="","",IF($AH35=$AH34,"",IF(INDEX('Roadmap Calc (Don’t Touch)'!$U$2:$U$151,$AI35)=0,$AH35,HYPERLINK("#'Control (Don’t Touch)'!E"&INDEX('Roadmap Calc (Don’t Touch)'!$U$2:$U$151,$AI35),$AH35)))) | B35: =IF($AI35="","",IF(INDEX('Roadmap Calc (Don’t Touch)'!$K$2:$K$151,$AI35)="",INDEX('Roadmap Calc (Don’t Touch)'!$B$2:$B$151,$AI35),HYPERLINK("https://jira.bnh.com/browse/"&INDEX('Roadmap Calc (Don’t Touch)'!$K$2:$K$151,$AI35),INDEX('Roadmap Calc (Don’t Touch)'!$B$2:$B$151,$AI35)))) -> Condition Grouping | C35: =IF($AI35="","",IF(INDEX('Roadmap Calc (Don’t Touch)'!$E$2:$E$151,$AI35)="","",HYPERLINK("https://jira.bnh.com/browse/"&INDEX('Roadmap Calc (Don’t Touch)'!$E$2:$E$151,$AI35),INDEX('Roadmap Calc (Don’t Touch)'!$E$2:$E$151,$AI35)))) -> BHUX-33519 | D35: =IF($AI35="","",INDEX('Roadmap Calc (Don’t Touch)'!$F$2:$F$151,$AI35)) -> 13. Live | E35: =IF($AI35="","",IF(ISNUMBER(INDEX('Roadmap Calc (Don’t Touch)'!$G$2:$G$151,$AI35)),INDEX('Roadmap Calc (Don’t Touch)'!$G$2:$G$151,$AI35),"")) -> 46139 | F35: =IF($AI35="","",IF(ISNUMBER(INDEX('Roadmap Calc (Don’t Touch)'!$H$2:$H$151,$AI35)),INDEX('Roadmap Calc (Don’t Touch)'!$H$2:$H$151,$AI35),"")) -> 46146 | G35: =IF($AI35="","",INDEX('Roadmap Calc (Don’t Touch)'!$T$2:$T$151,$AI35)) -> 2 | H35: =IF($AI35="","",IF(ISNUMBER(INDEX('Roadmap Calc (Don’t Touch)'!$I$2:$I$151,$AI35)),INDEX('Roadmap Calc (Don’t Touch)'!$I$2:$I$151,$AI35),"")) -> 46235 | I35: =IF($AI35="","",IF(ISNUMBER(INDEX('Roadmap Calc (Don’t Touch)'!$J$2:$J$151,$AI35)),INDEX('Roadmap Calc (Don’t Touch)'!$J$2:$J$151,$AI35),"")) -> 46265 | J35: =IF($AI35="","",IF(AND($AN35<>"",$AN35<=EOMONTH(J$12,0),$AO35>=J$12),IF(AND(INDEX('Roadmap Calc (Don’t Touch)'!$AA$2:$AX$151,$AI35,COLUMN()-COLUMN($J$16)+1)>0,OR($D35="03. UX Discovery",$D35="04. UX Design")),IF(AND($H35<>"",$H35<=EOMONTH(J$12,0),$I35>=J$12),"ALL","PD+UX"),IF(AND($H35<>"",$H35<=EOMONTH(J$12,0),$I35>=J$12),"PD+DEV","PD")),IF(AND(INDEX('Roadmap Calc (Don’t Touch)'!$AA$2:$AX$151,$AI35,COLUMN()-COLUMN($J$16)+1)>0,OR($D35="03. UX Discovery",$D35="04. UX Design")),IF(AND($H35<>"",$H35<=EOMONTH(J$12,0),$I35>=J$12),"UX+DEV","UX"),IF(AND($H35<>"",$H35<=EOMONTH(J$12,0),$I35>=J$12),"DEV","")))) | K35: =IF($AI35="","",IF(AND($AN35<>"",$AN35<=EOMONTH(K$12,0),$AO35>=K$12),IF(AND(INDEX('Roadmap Calc (Don’t Touch)'!$AA$2:$AX$151,$AI35,COLUMN()-COLUMN($J$16)+1)>0,OR($D35="03. UX Discovery",$D35="04. UX Design")),IF(AND($H35<>"",$H35<=EOMONTH(K$12,0),$I35>=K$12),"ALL","PD+UX"),IF(AND($H35<>"",$H35<=EOMONTH(K$12,0),$I35>=K$12),"PD+DEV","PD")),IF(AND(INDEX('Roadmap Calc (Don’t Touch)'!$AA$2:$AX$151,$AI35,COLUMN()-COLUMN($J$16)+1)>0,OR($D35="03. UX Discovery",$D35="04. UX Design")),IF(AND($H35<>"",$H35<=EOMONTH(K$12,0),$I35>=K$12),"UX+DEV","UX"),IF(AND($H35<>"",$H35<=EOMONTH(K$12,0),$I35>=K$12),"DEV","")))) | L35: =IF($AI35="","",IF(AND($AN35<>"",$AN35<=EOMONTH(L$12,0),$AO35>=L$12),IF(AND(INDEX('Roadmap Calc (Don’t Touch)'!$AA$2:$AX$151,$AI35,COLUMN()-COLUMN($J$16)+1)>0,OR($D35="03. UX Discovery",$D35="04. UX Design")),IF(AND($H35<>"",$H35<=EOMONTH(L$12,0),$I35>=L$12),"ALL","PD+UX"),IF(AND($H35<>"",$H35<=EOMONTH(L$12,0),$I35>=L$12),"PD+DEV","PD")),IF(AND(INDEX('Roadmap Calc (Don’t Touch)'!$AA$2:$AX$151,$AI35,COLUMN()-COLUMN($J$16)+1)>0,OR($D35="03. UX Discovery",$D35="04. UX Design")),IF(AND($H35<>"",$H35<=EOMONTH(L$12,0),$I35>=L$12),"UX+DEV","UX"),IF(AND($H35<>"",$H35<=EOMONTH(L$12,0),$I35>=L$12),"DEV","")))) | M35: =IF($AI35="","",IF(AND($AN35<>"",$AN35<=EOMONTH(M$12,0),$AO35>=M$12),IF(AND(INDEX('Roadmap Calc (Don’t Touch)'!$AA$2:$AX$151,$AI35,COLUMN()-COLUMN($J$16)+1)>0,OR($D35="03. UX Discovery",$D35="04. UX Design")),IF(AND($H35<>"",$H35<=EOMONTH(M$12,0),$I35>=M$12),"ALL","PD+UX"),IF(AND($H35<>"",$H35<=EOMONTH(M$12,0),$I35>=M$12),"PD+DEV","PD")),IF(AND(INDEX('Roadmap Calc (Don’t Touch)'!$AA$2:$AX$151,$AI35,COLUMN()-COLUMN($J$16)+1)>0,OR($D35="03. UX Discovery",$D35="04. UX Design")),IF(AND($H35<>"",$H35<=EOMONTH(M$12,0),$I35>=M$12),"UX+DEV","UX"),IF(AND($H35<>"",$H35<=EOMONTH(M$12,0),$I35>=M$12),"DEV","")))) | N35: =IF($AI35="","",IF(AND($AN35<>"",$AN35<=EOMONTH(N$12,0),$AO35>=N$12),IF(AND(INDEX('Roadmap Calc (Don’t Touch)'!$AA$2:$AX$151,$AI35,COLUMN()-COLUMN($J$16)+1)>0,OR($D35="03. UX Discovery",$D35="04. UX Design")),IF(AND($H35<>"",$H35<=EOMONTH(N$12,0),$I35>=N$12),"ALL","PD+UX"),IF(AND($H35<>"",$H35<=EOMONTH(N$12,0),$I35>=N$12),"PD+DEV","PD")),IF(AND(INDEX('Roadmap Calc (Don’t Touch)'!$AA$2:$AX$151,$AI35,COLUMN()-COLUMN($J$16)+1)>0,OR($D35="03. UX Discovery",$D35="04. UX Design")),IF(AND($H35<>"",$H35<=EOMONTH(N$12,0),$I35>=N$12),"UX+DEV","UX"),IF(AND($H35<>"",$H35<=EOMONTH(N$12,0),$I35>=N$12),"DEV","")))) | O35: =IF($AI35="","",IF(AND($AN35<>"",$AN35<=EOMONTH(O$12,0),$AO35>=O$12),IF(AND(INDEX('Roadmap Calc (Don’t Touch)'!$AA$2:$AX$151,$AI35,COLUMN()-COLUMN($J$16)+1)>0,OR($D35="03. UX Discovery",$D35="04. UX Design")),IF(AND($H35<>"",$H35<=EOMONTH(O$12,0),$I35>=O$12),"ALL","PD+UX"),IF(AND($H35<>"",$H35<=EOMONTH(O$12,0),$I35>=O$12),"PD+DEV","PD")),IF(AND(INDEX('Roadmap Calc (Don’t Touch)'!$AA$2:$AX$151,$AI35,COLUMN()-COLUMN($J$16)+1)>0,OR($D35="03. UX Discovery",$D35="04. UX Design")),IF(AND($H35<>"",$H35<=EOMONTH(O$12,0),$I35>=O$12),"UX+DEV","UX"),IF(AND($H35<>"",$H35<=EOMONTH(O$12,0),$I35>=O$12),"DEV","")))) | P35: =IF($AI35="","",IF(AND($AN35<>"",$AN35<=EOMONTH(P$12,0),$AO35>=P$12),IF(AND(INDEX('Roadmap Calc (Don’t Touch)'!$AA$2:$AX$151,$AI35,COLUMN()-COLUMN($J$16)+1)>0,OR($D35="03. UX Discovery",$D35="04. UX Design")),IF(AND($H35<>"",$H35<=EOMONTH(P$12,0),$I35>=P$12),"ALL","PD+UX"),IF(AND($H35<>"",$H35<=EOMONTH(P$12,0),$I35>=P$12),"PD+DEV","PD")),IF(AND(INDEX('Roadmap Calc (Don’t Touch)'!$AA$2:$AX$151,$AI35,COLUMN()-COLUMN($J$16)+1)>0,OR($D35="03. UX Discovery",$D35="04. UX Design")),IF(AND($H35<>"",$H35<=EOMONTH(P$12,0),$I35>=P$12),"UX+DEV","UX"),IF(AND($H35<>"",$H35<=EOMONTH(P$12,0),$I35>=P$12),"DEV","")))) | Q35: =IF($AI35="","",IF(AND($AN35<>"",$AN35<=EOMONTH(Q$12,0),$AO35>=Q$12),IF(AND(INDEX('Roadmap Calc (Don’t Touch)'!$AA$2:$AX$151,$AI35,COLUMN()-COLUMN($J$16)+1)>0,OR($D35="03. UX Discovery",$D35="04. UX Design")),IF(AND($H35<>"",$H35<=EOMONTH(Q$12,0),$I35>=Q$12),"ALL","PD+UX"),IF(AND($H35<>"",$H35<=EOMONTH(Q$12,0),$I35>=Q$12),"PD+DEV","PD")),IF(AND(INDEX('Roadmap Calc (Don’t Touch)'!$AA$2:$AX$151,$AI35,COLUMN()-COLUMN($J$16)+1)>0,OR($D35="03. UX Discovery",$D35="04. UX Design")),IF(AND($H35<>"",$H35<=EOMONTH(Q$12,0),$I35>=Q$12),"UX+DEV","UX"),IF(AND($H35<>"",$H35<=EOMONTH(Q$12,0),$I35>=Q$12),"DEV","")))) | ... AG35: =IF($AI35="","",IF(AND($AN35<>"",$AN35<=EOMONTH(AG$12,0),$AO35>=AG$12),IF(AND(INDEX('Roadmap Calc (Don’t Touch)'!$AA$2:$AX$151,$AI35,COLUMN()-COLUMN($J$16)+1)>0,OR($D35="03. UX Discovery",$D35="04. UX Design")),IF(AND($H35<>"",$H35<=EOMONTH(AG$12,0),$I35>=AG$12),"ALL","PD+UX"),IF(AND($H35<>"",$H35<=EOMONTH(AG$12,0),$I35>=AG$12),"PD+DEV","PD")),IF(AND(INDEX('Roadmap Calc (Don’t Touch)'!$AA$2:$AX$151,$AI35,COLUMN()-COLUMN($J$16)+1)>0,OR($D35="03. UX Discovery",$D35="04. UX Design")),IF(AND($H35<>"",$H35<=EOMONTH(AG$12,0),$I35>=AG$12),"UX+DEV","UX"),IF(AND($H35<>"",$H35<=EOMONTH(AG$12,0),$I35>=AG$12),"DEV","")))) | AH35: =IF($AI35="","",INDEX('Roadmap Calc (Don’t Touch)'!$D$2:$D$151,$AI35)) -> Increase Buy Used Awareness | AI35: =IFERROR(MATCH(20,'Roadmap Calc (Don’t Touch)'!$O$2:$O$151,0),"") -> 38 | AN35: =IF($AI35="","",IF(ISNUMBER(INDEX('Roadmap Calc (Don’t Touch)'!$BB$2:$BB$151,$AI35)),INDEX('Roadmap Calc (Don’t Touch)'!$BB$2:$BB$151,$AI35),"")) | AO35: =IF($AI35="","",IF(ISNUMBER(INDEX('Roadmap Calc (Don’t Touch)'!$BC$2:$BC$151,$AI35)),INDEX('Roadmap Calc (Don’t Touch)'!$BC$2:$BC$151,$AI35),""))
A36: =IF($AI36="","",IF($AH36=$AH35,"",IF(INDEX('Roadmap Calc (Don’t Touch)'!$U$2:$U$151,$AI36)=0,$AH36,HYPERLINK("#'Control (Don’t Touch)'!E"&INDEX('Roadmap Calc (Don’t Touch)'!$U$2:$U$151,$AI36),$AH36)))) | B36: =IF($AI36="","",IF(INDEX('Roadmap Calc (Don’t Touch)'!$K$2:$K$151,$AI36)="",INDEX('Roadmap Calc (Don’t Touch)'!$B$2:$B$151,$AI36),HYPERLINK("https://jira.bnh.com/browse/"&INDEX('Roadmap Calc (Don’t Touch)'!$K$2:$K$151,$AI36),INDEX('Roadmap Calc (Don’t Touch)'!$B$2:$B$151,$AI36)))) -> Used Hub Enhancements | C36: =IF($AI36="","",IF(INDEX('Roadmap Calc (Don’t Touch)'!$E$2:$E$151,$AI36)="","",HYPERLINK("https://jira.bnh.com/browse/"&INDEX('Roadmap Calc (Don’t Touch)'!$E$2:$E$151,$AI36),INDEX('Roadmap Calc (Don’t Touch)'!$E$2:$E$151,$AI36)))) -> BHUX-31354 | D36: =IF($AI36="","",INDEX('Roadmap Calc (Don’t Touch)'!$F$2:$F$151,$AI36)) -> 13. Live | E36: =IF($AI36="","",IF(ISNUMBER(INDEX('Roadmap Calc (Don’t Touch)'!$G$2:$G$151,$AI36)),INDEX('Roadmap Calc (Don’t Touch)'!$G$2:$G$151,$AI36),"")) | F36: =IF($AI36="","",IF(ISNUMBER(INDEX('Roadmap Calc (Don’t Touch)'!$H$2:$H$151,$AI36)),INDEX('Roadmap Calc (Don’t Touch)'!$H$2:$H$151,$AI36),"")) | G36: =IF($AI36="","",INDEX('Roadmap Calc (Don’t Touch)'!$T$2:$T$151,$AI36)) -> 0 | H36: =IF($AI36="","",IF(ISNUMBER(INDEX('Roadmap Calc (Don’t Touch)'!$I$2:$I$151,$AI36)),INDEX('Roadmap Calc (Don’t Touch)'!$I$2:$I$151,$AI36),"")) | I36: =IF($AI36="","",IF(ISNUMBER(INDEX('Roadmap Calc (Don’t Touch)'!$J$2:$J$151,$AI36)),INDEX('Roadmap Calc (Don’t Touch)'!$J$2:$J$151,$AI36),"")) | J36: =IF($AI36="","",IF(AND($AN36<>"",$AN36<=EOMONTH(J$12,0),$AO36>=J$12),IF(AND(INDEX('Roadmap Calc (Don’t Touch)'!$AA$2:$AX$151,$AI36,COLUMN()-COLUMN($J$16)+1)>0,OR($D36="03. UX Discovery",$D36="04. UX Design")),IF(AND($H36<>"",$H36<=EOMONTH(J$12,0),$I36>=J$12),"ALL","PD+UX"),IF(AND($H36<>"",$H36<=EOMONTH(J$12,0),$I36>=J$12),"PD+DEV","PD")),IF(AND(INDEX('Roadmap Calc (Don’t Touch)'!$AA$2:$AX$151,$AI36,COLUMN()-COLUMN($J$16)+1)>0,OR($D36="03. UX Discovery",$D36="04. UX Design")),IF(AND($H36<>"",$H36<=EOMONTH(J$12,0),$I36>=J$12),"UX+DEV","UX"),IF(AND($H36<>"",$H36<=EOMONTH(J$12,0),$I36>=J$12),"DEV","")))) | K36: =IF($AI36="","",IF(AND($AN36<>"",$AN36<=EOMONTH(K$12,0),$AO36>=K$12),IF(AND(INDEX('Roadmap Calc (Don’t Touch)'!$AA$2:$AX$151,$AI36,COLUMN()-COLUMN($J$16)+1)>0,OR($D36="03. UX Discovery",$D36="04. UX Design")),IF(AND($H36<>"",$H36<=EOMONTH(K$12,0),$I36>=K$12),"ALL","PD+UX"),IF(AND($H36<>"",$H36<=EOMONTH(K$12,0),$I36>=K$12),"PD+DEV","PD")),IF(AND(INDEX('Roadmap Calc (Don’t Touch)'!$AA$2:$AX$151,$AI36,COLUMN()-COLUMN($J$16)+1)>0,OR($D36="03. UX Discovery",$D36="04. UX Design")),IF(AND($H36<>"",$H36<=EOMONTH(K$12,0),$I36>=K$12),"UX+DEV","UX"),IF(AND($H36<>"",$H36<=EOMONTH(K$12,0),$I36>=K$12),"DEV","")))) | L36: =IF($AI36="","",IF(AND($AN36<>"",$AN36<=EOMONTH(L$12,0),$AO36>=L$12),IF(AND(INDEX('Roadmap Calc (Don’t Touch)'!$AA$2:$AX$151,$AI36,COLUMN()-COLUMN($J$16)+1)>0,OR($D36="03. UX Discovery",$D36="04. UX Design")),IF(AND($H36<>"",$H36<=EOMONTH(L$12,0),$I36>=L$12),"ALL","PD+UX"),IF(AND($H36<>"",$H36<=EOMONTH(L$12,0),$I36>=L$12),"PD+DEV","PD")),IF(AND(INDEX('Roadmap Calc (Don’t Touch)'!$AA$2:$AX$151,$AI36,COLUMN()-COLUMN($J$16)+1)>0,OR($D36="03. UX Discovery",$D36="04. UX Design")),IF(AND($H36<>"",$H36<=EOMONTH(L$12,0),$I36>=L$12),"UX+DEV","UX"),IF(AND($H36<>"",$H36<=EOMONTH(L$12,0),$I36>=L$12),"DEV","")))) | M36: =IF($AI36="","",IF(AND($AN36<>"",$AN36<=EOMONTH(M$12,0),$AO36>=M$12),IF(AND(INDEX('Roadmap Calc (Don’t Touch)'!$AA$2:$AX$151,$AI36,COLUMN()-COLUMN($J$16)+1)>0,OR($D36="03. UX Discovery",$D36="04. UX Design")),IF(AND($H36<>"",$H36<=EOMONTH(M$12,0),$I36>=M$12),"ALL","PD+UX"),IF(AND($H36<>"",$H36<=EOMONTH(M$12,0),$I36>=M$12),"PD+DEV","PD")),IF(AND(INDEX('Roadmap Calc (Don’t Touch)'!$AA$2:$AX$151,$AI36,COLUMN()-COLUMN($J$16)+1)>0,OR($D36="03. UX Discovery",$D36="04. UX Design")),IF(AND($H36<>"",$H36<=EOMONTH(M$12,0),$I36>=M$12),"UX+DEV","UX"),IF(AND($H36<>"",$H36<=EOMONTH(M$12,0),$I36>=M$12),"DEV","")))) | N36: =IF($AI36="","",IF(AND($AN36<>"",$AN36<=EOMONTH(N$12,0),$AO36>=N$12),IF(AND(INDEX('Roadmap Calc (Don’t Touch)'!$AA$2:$AX$151,$AI36,COLUMN()-COLUMN($J$16)+1)>0,OR($D36="03. UX Discovery",$D36="04. UX Design")),IF(AND($H36<>"",$H36<=EOMONTH(N$12,0),$I36>=N$12),"ALL","PD+UX"),IF(AND($H36<>"",$H36<=EOMONTH(N$12,0),$I36>=N$12),"PD+DEV","PD")),IF(AND(INDEX('Roadmap Calc (Don’t Touch)'!$AA$2:$AX$151,$AI36,COLUMN()-COLUMN($J$16)+1)>0,OR($D36="03. UX Discovery",$D36="04. UX Design")),IF(AND($H36<>"",$H36<=EOMONTH(N$12,0),$I36>=N$12),"UX+DEV","UX"),IF(AND($H36<>"",$H36<=EOMONTH(N$12,0),$I36>=N$12),"DEV","")))) | O36: =IF($AI36="","",IF(AND($AN36<>"",$AN36<=EOMONTH(O$12,0),$AO36>=O$12),IF(AND(INDEX('Roadmap Calc (Don’t Touch)'!$AA$2:$AX$151,$AI36,COLUMN()-COLUMN($J$16)+1)>0,OR($D36="03. UX Discovery",$D36="04. UX Design")),IF(AND($H36<>"",$H36<=EOMONTH(O$12,0),$I36>=O$12),"ALL","PD+UX"),IF(AND($H36<>"",$H36<=EOMONTH(O$12,0),$I36>=O$12),"PD+DEV","PD")),IF(AND(INDEX('Roadmap Calc (Don’t Touch)'!$AA$2:$AX$151,$AI36,COLUMN()-COLUMN($J$16)+1)>0,OR($D36="03. UX Discovery",$D36="04. UX Design")),IF(AND($H36<>"",$H36<=EOMONTH(O$12,0),$I36>=O$12),"UX+DEV","UX"),IF(AND($H36<>"",$H36<=EOMONTH(O$12,0),$I36>=O$12),"DEV","")))) | P36: =IF($AI36="","",IF(AND($AN36<>"",$AN36<=EOMONTH(P$12,0),$AO36>=P$12),IF(AND(INDEX('Roadmap Calc (Don’t Touch)'!$AA$2:$AX$151,$AI36,COLUMN()-COLUMN($J$16)+1)>0,OR($D36="03. UX Discovery",$D36="04. UX Design")),IF(AND($H36<>"",$H36<=EOMONTH(P$12,0),$I36>=P$12),"ALL","PD+UX"),IF(AND($H36<>"",$H36<=EOMONTH(P$12,0),$I36>=P$12),"PD+DEV","PD")),IF(AND(INDEX('Roadmap Calc (Don’t Touch)'!$AA$2:$AX$151,$AI36,COLUMN()-COLUMN($J$16)+1)>0,OR($D36="03. UX Discovery",$D36="04. UX Design")),IF(AND($H36<>"",$H36<=EOMONTH(P$12,0),$I36>=P$12),"UX+DEV","UX"),IF(AND($H36<>"",$H36<=EOMONTH(P$12,0),$I36>=P$12),"DEV","")))) | Q36: =IF($AI36="","",IF(AND($AN36<>"",$AN36<=EOMONTH(Q$12,0),$AO36>=Q$12),IF(AND(INDEX('Roadmap Calc (Don’t Touch)'!$AA$2:$AX$151,$AI36,COLUMN()-COLUMN($J$16)+1)>0,OR($D36="03. UX Discovery",$D36="04. UX Design")),IF(AND($H36<>"",$H36<=EOMONTH(Q$12,0),$I36>=Q$12),"ALL","PD+UX"),IF(AND($H36<>"",$H36<=EOMONTH(Q$12,0),$I36>=Q$12),"PD+DEV","PD")),IF(AND(INDEX('Roadmap Calc (Don’t Touch)'!$AA$2:$AX$151,$AI36,COLUMN()-COLUMN($J$16)+1)>0,OR($D36="03. UX Discovery",$D36="04. UX Design")),IF(AND($H36<>"",$H36<=EOMONTH(Q$12,0),$I36>=Q$12),"UX+DEV","UX"),IF(AND($H36<>"",$H36<=EOMONTH(Q$12,0),$I36>=Q$12),"DEV","")))) | ... AG36: =IF($AI36="","",IF(AND($AN36<>"",$AN36<=EOMONTH(AG$12,0),$AO36>=AG$12),IF(AND(INDEX('Roadmap Calc (Don’t Touch)'!$AA$2:$AX$151,$AI36,COLUMN()-COLUMN($J$16)+1)>0,OR($D36="03. UX Discovery",$D36="04. UX Design")),IF(AND($H36<>"",$H36<=EOMONTH(AG$12,0),$I36>=AG$12),"ALL","PD+UX"),IF(AND($H36<>"",$H36<=EOMONTH(AG$12,0),$I36>=AG$12),"PD+DEV","PD")),IF(AND(INDEX('Roadmap Calc (Don’t Touch)'!$AA$2:$AX$151,$AI36,COLUMN()-COLUMN($J$16)+1)>0,OR($D36="03. UX Discovery",$D36="04. UX Design")),IF(AND($H36<>"",$H36<=EOMONTH(AG$12,0),$I36>=AG$12),"UX+DEV","UX"),IF(AND($H36<>"",$H36<=EOMONTH(AG$12,0),$I36>=AG$12),"DEV","")))) | AH36: =IF($AI36="","",INDEX('Roadmap Calc (Don’t Touch)'!$D$2:$D$151,$AI36)) -> Increase Buy Used Awareness | AI36: =IFERROR(MATCH(21,'Roadmap Calc (Don’t Touch)'!$O$2:$O$151,0),"") -> 47 | AN36: =IF($AI36="","",IF(ISNUMBER(INDEX('Roadmap Calc (Don’t Touch)'!$BB$2:$BB$151,$AI36)),INDEX('Roadmap Calc (Don’t Touch)'!$BB$2:$BB$151,$AI36),"")) | AO36: =IF($AI36="","",IF(ISNUMBER(INDEX('Roadmap Calc (Don’t Touch)'!$BC$2:$BC$151,$AI36)),INDEX('Roadmap Calc (Don’t Touch)'!$BC$2:$BC$151,$AI36),""))
A37: =IF($AI37="","",IF($AH37=$AH36,"",IF(INDEX('Roadmap Calc (Don’t Touch)'!$U$2:$U$151,$AI37)=0,$AH37,HYPERLINK("#'Control (Don’t Touch)'!E"&INDEX('Roadmap Calc (Don’t Touch)'!$U$2:$U$151,$AI37),$AH37)))) -> Improve Buy Used Customer Experience | B37: =IF($AI37="","",IF(INDEX('Roadmap Calc (Don’t Touch)'!$K$2:$K$151,$AI37)="",INDEX('Roadmap Calc (Don’t Touch)'!$B$2:$B$151,$AI37),HYPERLINK("https://jira.bnh.com/browse/"&INDEX('Roadmap Calc (Don’t Touch)'!$K$2:$K$151,$AI37),INDEX('Roadmap Calc (Don’t Touch)'!$B$2:$B$151,$AI37)))) -> New Condition Rating Scale | C37: =IF($AI37="","",IF(INDEX('Roadmap Calc (Don’t Touch)'!$E$2:$E$151,$AI37)="","",HYPERLINK("https://jira.bnh.com/browse/"&INDEX('Roadmap Calc (Don’t Touch)'!$E$2:$E$151,$AI37),INDEX('Roadmap Calc (Don’t Touch)'!$E$2:$E$151,$AI37)))) -> BHUX-33510 | D37: =IF($AI37="","",INDEX('Roadmap Calc (Don’t Touch)'!$F$2:$F$151,$AI37)) -> 00. Parking Lot | E37: =IF($AI37="","",IF(ISNUMBER(INDEX('Roadmap Calc (Don’t Touch)'!$G$2:$G$151,$AI37)),INDEX('Roadmap Calc (Don’t Touch)'!$G$2:$G$151,$AI37),"")) -> 46174 | F37: =IF($AI37="","",IF(ISNUMBER(INDEX('Roadmap Calc (Don’t Touch)'!$H$2:$H$151,$AI37)),INDEX('Roadmap Calc (Don’t Touch)'!$H$2:$H$151,$AI37),"")) -> 46188 | G37: =IF($AI37="","",INDEX('Roadmap Calc (Don’t Touch)'!$T$2:$T$151,$AI37)) -> 3 | H37: =IF($AI37="","",IF(ISNUMBER(INDEX('Roadmap Calc (Don’t Touch)'!$I$2:$I$151,$AI37)),INDEX('Roadmap Calc (Don’t Touch)'!$I$2:$I$151,$AI37),"")) -> 46388 | I37: =IF($AI37="","",IF(ISNUMBER(INDEX('Roadmap Calc (Don’t Touch)'!$J$2:$J$151,$AI37)),INDEX('Roadmap Calc (Don’t Touch)'!$J$2:$J$151,$AI37),"")) -> 46418 | J37: =IF($AI37="","",IF(AND($AN37<>"",$AN37<=EOMONTH(J$12,0),$AO37>=J$12),IF(AND(INDEX('Roadmap Calc (Don’t Touch)'!$AA$2:$AX$151,$AI37,COLUMN()-COLUMN($J$16)+1)>0,OR($D37="03. UX Discovery",$D37="04. UX Design")),IF(AND($H37<>"",$H37<=EOMONTH(J$12,0),$I37>=J$12),"ALL","PD+UX"),IF(AND($H37<>"",$H37<=EOMONTH(J$12,0),$I37>=J$12),"PD+DEV","PD")),IF(AND(INDEX('Roadmap Calc (Don’t Touch)'!$AA$2:$AX$151,$AI37,COLUMN()-COLUMN($J$16)+1)>0,OR($D37="03. UX Discovery",$D37="04. UX Design")),IF(AND($H37<>"",$H37<=EOMONTH(J$12,0),$I37>=J$12),"UX+DEV","UX"),IF(AND($H37<>"",$H37<=EOMONTH(J$12,0),$I37>=J$12),"DEV","")))) | K37: =IF($AI37="","",IF(AND($AN37<>"",$AN37<=EOMONTH(K$12,0),$AO37>=K$12),IF(AND(INDEX('Roadmap Calc (Don’t Touch)'!$AA$2:$AX$151,$AI37,COLUMN()-COLUMN($J$16)+1)>0,OR($D37="03. UX Discovery",$D37="04. UX Design")),IF(AND($H37<>"",$H37<=EOMONTH(K$12,0),$I37>=K$12),"ALL","PD+UX"),IF(AND($H37<>"",$H37<=EOMONTH(K$12,0),$I37>=K$12),"PD+DEV","PD")),IF(AND(INDEX('Roadmap Calc (Don’t Touch)'!$AA$2:$AX$151,$AI37,COLUMN()-COLUMN($J$16)+1)>0,OR($D37="03. UX Discovery",$D37="04. UX Design")),IF(AND($H37<>"",$H37<=EOMONTH(K$12,0),$I37>=K$12),"UX+DEV","UX"),IF(AND($H37<>"",$H37<=EOMONTH(K$12,0),$I37>=K$12),"DEV","")))) | L37: =IF($AI37="","",IF(AND($AN37<>"",$AN37<=EOMONTH(L$12,0),$AO37>=L$12),IF(AND(INDEX('Roadmap Calc (Don’t Touch)'!$AA$2:$AX$151,$AI37,COLUMN()-COLUMN($J$16)+1)>0,OR($D37="03. UX Discovery",$D37="04. UX Design")),IF(AND($H37<>"",$H37<=EOMONTH(L$12,0),$I37>=L$12),"ALL","PD+UX"),IF(AND($H37<>"",$H37<=EOMONTH(L$12,0),$I37>=L$12),"PD+DEV","PD")),IF(AND(INDEX('Roadmap Calc (Don’t Touch)'!$AA$2:$AX$151,$AI37,COLUMN()-COLUMN($J$16)+1)>0,OR($D37="03. UX Discovery",$D37="04. UX Design")),IF(AND($H37<>"",$H37<=EOMONTH(L$12,0),$I37>=L$12),"UX+DEV","UX"),IF(AND($H37<>"",$H37<=EOMONTH(L$12,0),$I37>=L$12),"DEV","")))) | M37: =IF($AI37="","",IF(AND($AN37<>"",$AN37<=EOMONTH(M$12,0),$AO37>=M$12),IF(AND(INDEX('Roadmap Calc (Don’t Touch)'!$AA$2:$AX$151,$AI37,COLUMN()-COLUMN($J$16)+1)>0,OR($D37="03. UX Discovery",$D37="04. UX Design")),IF(AND($H37<>"",$H37<=EOMONTH(M$12,0),$I37>=M$12),"ALL","PD+UX"),IF(AND($H37<>"",$H37<=EOMONTH(M$12,0),$I37>=M$12),"PD+DEV","PD")),IF(AND(INDEX('Roadmap Calc (Don’t Touch)'!$AA$2:$AX$151,$AI37,COLUMN()-COLUMN($J$16)+1)>0,OR($D37="03. UX Discovery",$D37="04. UX Design")),IF(AND($H37<>"",$H37<=EOMONTH(M$12,0),$I37>=M$12),"UX+DEV","UX"),IF(AND($H37<>"",$H37<=EOMONTH(M$12,0),$I37>=M$12),"DEV","")))) | N37: =IF($AI37="","",IF(AND($AN37<>"",$AN37<=EOMONTH(N$12,0),$AO37>=N$12),IF(AND(INDEX('Roadmap Calc (Don’t Touch)'!$AA$2:$AX$151,$AI37,COLUMN()-COLUMN($J$16)+1)>0,OR($D37="03. UX Discovery",$D37="04. UX Design")),IF(AND($H37<>"",$H37<=EOMONTH(N$12,0),$I37>=N$12),"ALL","PD+UX"),IF(AND($H37<>"",$H37<=EOMONTH(N$12,0),$I37>=N$12),"PD+DEV","PD")),IF(AND(INDEX('Roadmap Calc (Don’t Touch)'!$AA$2:$AX$151,$AI37,COLUMN()-COLUMN($J$16)+1)>0,OR($D37="03. UX Discovery",$D37="04. UX Design")),IF(AND($H37<>"",$H37<=EOMONTH(N$12,0),$I37>=N$12),"UX+DEV","UX"),IF(AND($H37<>"",$H37<=EOMONTH(N$12,0),$I37>=N$12),"DEV","")))) | O37: =IF($AI37="","",IF(AND($AN37<>"",$AN37<=EOMONTH(O$12,0),$AO37>=O$12),IF(AND(INDEX('Roadmap Calc (Don’t Touch)'!$AA$2:$AX$151,$AI37,COLUMN()-COLUMN($J$16)+1)>0,OR($D37="03. UX Discovery",$D37="04. UX Design")),IF(AND($H37<>"",$H37<=EOMONTH(O$12,0),$I37>=O$12),"ALL","PD+UX"),IF(AND($H37<>"",$H37<=EOMONTH(O$12,0),$I37>=O$12),"PD+DEV","PD")),IF(AND(INDEX('Roadmap Calc (Don’t Touch)'!$AA$2:$AX$151,$AI37,COLUMN()-COLUMN($J$16)+1)>0,OR($D37="03. UX Discovery",$D37="04. UX Design")),IF(AND($H37<>"",$H37<=EOMONTH(O$12,0),$I37>=O$12),"UX+DEV","UX"),IF(AND($H37<>"",$H37<=EOMONTH(O$12,0),$I37>=O$12),"DEV","")))) | P37: =IF($AI37="","",IF(AND($AN37<>"",$AN37<=EOMONTH(P$12,0),$AO37>=P$12),IF(AND(INDEX('Roadmap Calc (Don’t Touch)'!$AA$2:$AX$151,$AI37,COLUMN()-COLUMN($J$16)+1)>0,OR($D37="03. UX Discovery",$D37="04. UX Design")),IF(AND($H37<>"",$H37<=EOMONTH(P$12,0),$I37>=P$12),"ALL","PD+UX"),IF(AND($H37<>"",$H37<=EOMONTH(P$12,0),$I37>=P$12),"PD+DEV","PD")),IF(AND(INDEX('Roadmap Calc (Don’t Touch)'!$AA$2:$AX$151,$AI37,COLUMN()-COLUMN($J$16)+1)>0,OR($D37="03. UX Discovery",$D37="04. UX Design")),IF(AND($H37<>"",$H37<=EOMONTH(P$12,0),$I37>=P$12),"UX+DEV","UX"),IF(AND($H37<>"",$H37<=EOMONTH(P$12,0),$I37>=P$12),"DEV","")))) | Q37: =IF($AI37="","",IF(AND($AN37<>"",$AN37<=EOMONTH(Q$12,0),$AO37>=Q$12),IF(AND(INDEX('Roadmap Calc (Don’t Touch)'!$AA$2:$AX$151,$AI37,COLUMN()-COLUMN($J$16)+1)>0,OR($D37="03. UX Discovery",$D37="04. UX Design")),IF(AND($H37<>"",$H37<=EOMONTH(Q$12,0),$I37>=Q$12),"ALL","PD+UX"),IF(AND($H37<>"",$H37<=EOMONTH(Q$12,0),$I37>=Q$12),"PD+DEV","PD")),IF(AND(INDEX('Roadmap Calc (Don’t Touch)'!$AA$2:$AX$151,$AI37,COLUMN()-COLUMN($J$16)+1)>0,OR($D37="03. UX Discovery",$D37="04. UX Design")),IF(AND($H37<>"",$H37<=EOMONTH(Q$12,0),$I37>=Q$12),"UX+DEV","UX"),IF(AND($H37<>"",$H37<=EOMONTH(Q$12,0),$I37>=Q$12),"DEV","")))) | ... AG37: =IF($AI37="","",IF(AND($AN37<>"",$AN37<=EOMONTH(AG$12,0),$AO37>=AG$12),IF(AND(INDEX('Roadmap Calc (Don’t Touch)'!$AA$2:$AX$151,$AI37,COLUMN()-COLUMN($J$16)+1)>0,OR($D37="03. UX Discovery",$D37="04. UX Design")),IF(AND($H37<>"",$H37<=EOMONTH(AG$12,0),$I37>=AG$12),"ALL","PD+UX"),IF(AND($H37<>"",$H37<=EOMONTH(AG$12,0),$I37>=AG$12),"PD+DEV","PD")),IF(AND(INDEX('Roadmap Calc (Don’t Touch)'!$AA$2:$AX$151,$AI37,COLUMN()-COLUMN($J$16)+1)>0,OR($D37="03. UX Discovery",$D37="04. UX Design")),IF(AND($H37<>"",$H37<=EOMONTH(AG$12,0),$I37>=AG$12),"UX+DEV","UX"),IF(AND($H37<>"",$H37<=EOMONTH(AG$12,0),$I37>=AG$12),"DEV","")))) | AH37: =IF($AI37="","",INDEX('Roadmap Calc (Don’t Touch)'!$D$2:$D$151,$AI37)) -> Improve Buy Used Customer Experience | AI37: =IFERROR(MATCH(22,'Roadmap Calc (Don’t Touch)'!$O$2:$O$151,0),"") -> 1 | AN37: =IF($AI37="","",IF(ISNUMBER(INDEX('Roadmap Calc (Don’t Touch)'!$BB$2:$BB$151,$AI37)),INDEX('Roadmap Calc (Don’t Touch)'!$BB$2:$BB$151,$AI37),"")) | AO37: =IF($AI37="","",IF(ISNUMBER(INDEX('Roadmap Calc (Don’t Touch)'!$BC$2:$BC$151,$AI37)),INDEX('Roadmap Calc (Don’t Touch)'!$BC$2:$BC$151,$AI37),""))
A38: =IF($AI38="","",IF($AH38=$AH37,"",IF(INDEX('Roadmap Calc (Don’t Touch)'!$U$2:$U$151,$AI38)=0,$AH38,HYPERLINK("#'Control (Don’t Touch)'!E"&INDEX('Roadmap Calc (Don’t Touch)'!$U$2:$U$151,$AI38),$AH38)))) | B38: =IF($AI38="","",IF(INDEX('Roadmap Calc (Don’t Touch)'!$K$2:$K$151,$AI38)="",INDEX('Roadmap Calc (Don’t Touch)'!$B$2:$B$151,$AI38),HYPERLINK("https://jira.bnh.com/browse/"&INDEX('Roadmap Calc (Don’t Touch)'!$K$2:$K$151,$AI38),INDEX('Roadmap Calc (Don’t Touch)'!$B$2:$B$151,$AI38)))) -> New Condition Rating Scale (Intermediate Step) | C38: =IF($AI38="","",IF(INDEX('Roadmap Calc (Don’t Touch)'!$E$2:$E$151,$AI38)="","",HYPERLINK("https://jira.bnh.com/browse/"&INDEX('Roadmap Calc (Don’t Touch)'!$E$2:$E$151,$AI38),INDEX('Roadmap Calc (Don’t Touch)'!$E$2:$E$151,$AI38)))) -> BHJ-121278 | D38: =IF($AI38="","",INDEX('Roadmap Calc (Don’t Touch)'!$F$2:$F$151,$AI38)) -> 00. Parking Lot | E38: =IF($AI38="","",IF(ISNUMBER(INDEX('Roadmap Calc (Don’t Touch)'!$G$2:$G$151,$AI38)),INDEX('Roadmap Calc (Don’t Touch)'!$G$2:$G$151,$AI38),"")) | F38: =IF($AI38="","",IF(ISNUMBER(INDEX('Roadmap Calc (Don’t Touch)'!$H$2:$H$151,$AI38)),INDEX('Roadmap Calc (Don’t Touch)'!$H$2:$H$151,$AI38),"")) | G38: =IF($AI38="","",INDEX('Roadmap Calc (Don’t Touch)'!$T$2:$T$151,$AI38)) -> 0 | H38: =IF($AI38="","",IF(ISNUMBER(INDEX('Roadmap Calc (Don’t Touch)'!$I$2:$I$151,$AI38)),INDEX('Roadmap Calc (Don’t Touch)'!$I$2:$I$151,$AI38),"")) -> 46296 | I38: =IF($AI38="","",IF(ISNUMBER(INDEX('Roadmap Calc (Don’t Touch)'!$J$2:$J$151,$AI38)),INDEX('Roadmap Calc (Don’t Touch)'!$J$2:$J$151,$AI38),"")) -> 46326 | J38: =IF($AI38="","",IF(AND($AN38<>"",$AN38<=EOMONTH(J$12,0),$AO38>=J$12),IF(AND(INDEX('Roadmap Calc (Don’t Touch)'!$AA$2:$AX$151,$AI38,COLUMN()-COLUMN($J$16)+1)>0,OR($D38="03. UX Discovery",$D38="04. UX Design")),IF(AND($H38<>"",$H38<=EOMONTH(J$12,0),$I38>=J$12),"ALL","PD+UX"),IF(AND($H38<>"",$H38<=EOMONTH(J$12,0),$I38>=J$12),"PD+DEV","PD")),IF(AND(INDEX('Roadmap Calc (Don’t Touch)'!$AA$2:$AX$151,$AI38,COLUMN()-COLUMN($J$16)+1)>0,OR($D38="03. UX Discovery",$D38="04. UX Design")),IF(AND($H38<>"",$H38<=EOMONTH(J$12,0),$I38>=J$12),"UX+DEV","UX"),IF(AND($H38<>"",$H38<=EOMONTH(J$12,0),$I38>=J$12),"DEV","")))) | K38: =IF($AI38="","",IF(AND($AN38<>"",$AN38<=EOMONTH(K$12,0),$AO38>=K$12),IF(AND(INDEX('Roadmap Calc (Don’t Touch)'!$AA$2:$AX$151,$AI38,COLUMN()-COLUMN($J$16)+1)>0,OR($D38="03. UX Discovery",$D38="04. UX Design")),IF(AND($H38<>"",$H38<=EOMONTH(K$12,0),$I38>=K$12),"ALL","PD+UX"),IF(AND($H38<>"",$H38<=EOMONTH(K$12,0),$I38>=K$12),"PD+DEV","PD")),IF(AND(INDEX('Roadmap Calc (Don’t Touch)'!$AA$2:$AX$151,$AI38,COLUMN()-COLUMN($J$16)+1)>0,OR($D38="03. UX Discovery",$D38="04. UX Design")),IF(AND($H38<>"",$H38<=EOMONTH(K$12,0),$I38>=K$12),"UX+DEV","UX"),IF(AND($H38<>"",$H38<=EOMONTH(K$12,0),$I38>=K$12),"DEV","")))) | L38: =IF($AI38="","",IF(AND($AN38<>"",$AN38<=EOMONTH(L$12,0),$AO38>=L$12),IF(AND(INDEX('Roadmap Calc (Don’t Touch)'!$AA$2:$AX$151,$AI38,COLUMN()-COLUMN($J$16)+1)>0,OR($D38="03. UX Discovery",$D38="04. UX Design")),IF(AND($H38<>"",$H38<=EOMONTH(L$12,0),$I38>=L$12),"ALL","PD+UX"),IF(AND($H38<>"",$H38<=EOMONTH(L$12,0),$I38>=L$12),"PD+DEV","PD")),IF(AND(INDEX('Roadmap Calc (Don’t Touch)'!$AA$2:$AX$151,$AI38,COLUMN()-COLUMN($J$16)+1)>0,OR($D38="03. UX Discovery",$D38="04. UX Design")),IF(AND($H38<>"",$H38<=EOMONTH(L$12,0),$I38>=L$12),"UX+DEV","UX"),IF(AND($H38<>"",$H38<=EOMONTH(L$12,0),$I38>=L$12),"DEV","")))) | M38: =IF($AI38="","",IF(AND($AN38<>"",$AN38<=EOMONTH(M$12,0),$AO38>=M$12),IF(AND(INDEX('Roadmap Calc (Don’t Touch)'!$AA$2:$AX$151,$AI38,COLUMN()-COLUMN($J$16)+1)>0,OR($D38="03. UX Discovery",$D38="04. UX Design")),IF(AND($H38<>"",$H38<=EOMONTH(M$12,0),$I38>=M$12),"ALL","PD+UX"),IF(AND($H38<>"",$H38<=EOMONTH(M$12,0),$I38>=M$12),"PD+DEV","PD")),IF(AND(INDEX('Roadmap Calc (Don’t Touch)'!$AA$2:$AX$151,$AI38,COLUMN()-COLUMN($J$16)+1)>0,OR($D38="03. UX Discovery",$D38="04. UX Design")),IF(AND($H38<>"",$H38<=EOMONTH(M$12,0),$I38>=M$12),"UX+DEV","UX"),IF(AND($H38<>"",$H38<=EOMONTH(M$12,0),$I38>=M$12),"DEV","")))) | N38: =IF($AI38="","",IF(AND($AN38<>"",$AN38<=EOMONTH(N$12,0),$AO38>=N$12),IF(AND(INDEX('Roadmap Calc (Don’t Touch)'!$AA$2:$AX$151,$AI38,COLUMN()-COLUMN($J$16)+1)>0,OR($D38="03. UX Discovery",$D38="04. UX Design")),IF(AND($H38<>"",$H38<=EOMONTH(N$12,0),$I38>=N$12),"ALL","PD+UX"),IF(AND($H38<>"",$H38<=EOMONTH(N$12,0),$I38>=N$12),"PD+DEV","PD")),IF(AND(INDEX('Roadmap Calc (Don’t Touch)'!$AA$2:$AX$151,$AI38,COLUMN()-COLUMN($J$16)+1)>0,OR($D38="03. UX Discovery",$D38="04. UX Design")),IF(AND($H38<>"",$H38<=EOMONTH(N$12,0),$I38>=N$12),"UX+DEV","UX"),IF(AND($H38<>"",$H38<=EOMONTH(N$12,0),$I38>=N$12),"DEV","")))) | O38: =IF($AI38="","",IF(AND($AN38<>"",$AN38<=EOMONTH(O$12,0),$AO38>=O$12),IF(AND(INDEX('Roadmap Calc (Don’t Touch)'!$AA$2:$AX$151,$AI38,COLUMN()-COLUMN($J$16)+1)>0,OR($D38="03. UX Discovery",$D38="04. UX Design")),IF(AND($H38<>"",$H38<=EOMONTH(O$12,0),$I38>=O$12),"ALL","PD+UX"),IF(AND($H38<>"",$H38<=EOMONTH(O$12,0),$I38>=O$12),"PD+DEV","PD")),IF(AND(INDEX('Roadmap Calc (Don’t Touch)'!$AA$2:$AX$151,$AI38,COLUMN()-COLUMN($J$16)+1)>0,OR($D38="03. UX Discovery",$D38="04. UX Design")),IF(AND($H38<>"",$H38<=EOMONTH(O$12,0),$I38>=O$12),"UX+DEV","UX"),IF(AND($H38<>"",$H38<=EOMONTH(O$12,0),$I38>=O$12),"DEV","")))) | P38: =IF($AI38="","",IF(AND($AN38<>"",$AN38<=EOMONTH(P$12,0),$AO38>=P$12),IF(AND(INDEX('Roadmap Calc (Don’t Touch)'!$AA$2:$AX$151,$AI38,COLUMN()-COLUMN($J$16)+1)>0,OR($D38="03. UX Discovery",$D38="04. UX Design")),IF(AND($H38<>"",$H38<=EOMONTH(P$12,0),$I38>=P$12),"ALL","PD+UX"),IF(AND($H38<>"",$H38<=EOMONTH(P$12,0),$I38>=P$12),"PD+DEV","PD")),IF(AND(INDEX('Roadmap Calc (Don’t Touch)'!$AA$2:$AX$151,$AI38,COLUMN()-COLUMN($J$16)+1)>0,OR($D38="03. UX Discovery",$D38="04. UX Design")),IF(AND($H38<>"",$H38<=EOMONTH(P$12,0),$I38>=P$12),"UX+DEV","UX"),IF(AND($H38<>"",$H38<=EOMONTH(P$12,0),$I38>=P$12),"DEV","")))) | Q38: =IF($AI38="","",IF(AND($AN38<>"",$AN38<=EOMONTH(Q$12,0),$AO38>=Q$12),IF(AND(INDEX('Roadmap Calc (Don’t Touch)'!$AA$2:$AX$151,$AI38,COLUMN()-COLUMN($J$16)+1)>0,OR($D38="03. UX Discovery",$D38="04. UX Design")),IF(AND($H38<>"",$H38<=EOMONTH(Q$12,0),$I38>=Q$12),"ALL","PD+UX"),IF(AND($H38<>"",$H38<=EOMONTH(Q$12,0),$I38>=Q$12),"PD+DEV","PD")),IF(AND(INDEX('Roadmap Calc (Don’t Touch)'!$AA$2:$AX$151,$AI38,COLUMN()-COLUMN($J$16)+1)>0,OR($D38="03. UX Discovery",$D38="04. UX Design")),IF(AND($H38<>"",$H38<=EOMONTH(Q$12,0),$I38>=Q$12),"UX+DEV","UX"),IF(AND($H38<>"",$H38<=EOMONTH(Q$12,0),$I38>=Q$12),"DEV","")))) | ... AG38: =IF($AI38="","",IF(AND($AN38<>"",$AN38<=EOMONTH(AG$12,0),$AO38>=AG$12),IF(AND(INDEX('Roadmap Calc (Don’t Touch)'!$AA$2:$AX$151,$AI38,COLUMN()-COLUMN($J$16)+1)>0,OR($D38="03. UX Discovery",$D38="04. UX Design")),IF(AND($H38<>"",$H38<=EOMONTH(AG$12,0),$I38>=AG$12),"ALL","PD+UX"),IF(AND($H38<>"",$H38<=EOMONTH(AG$12,0),$I38>=AG$12),"PD+DEV","PD")),IF(AND(INDEX('Roadmap Calc (Don’t Touch)'!$AA$2:$AX$151,$AI38,COLUMN()-COLUMN($J$16)+1)>0,OR($D38="03. UX Discovery",$D38="04. UX Design")),IF(AND($H38<>"",$H38<=EOMONTH(AG$12,0),$I38>=AG$12),"UX+DEV","UX"),IF(AND($H38<>"",$H38<=EOMONTH(AG$12,0),$I38>=AG$12),"DEV","")))) | AH38: =IF($AI38="","",INDEX('Roadmap Calc (Don’t Touch)'!$D$2:$D$151,$AI38)) -> Improve Buy Used Customer Experience | AI38: =IFERROR(MATCH(23,'Roadmap Calc (Don’t Touch)'!$O$2:$O$151,0),"") -> 3 | AN38: =IF($AI38="","",IF(ISNUMBER(INDEX('Roadmap Calc (Don’t Touch)'!$BB$2:$BB$151,$AI38)),INDEX('Roadmap Calc (Don’t Touch)'!$BB$2:$BB$151,$AI38),"")) | AO38: =IF($AI38="","",IF(ISNUMBER(INDEX('Roadmap Calc (Don’t Touch)'!$BC$2:$BC$151,$AI38)),INDEX('Roadmap Calc (Don’t Touch)'!$BC$2:$BC$151,$AI38),""))
A39: =IF($AI39="","",IF($AH39=$AH38,"",IF(INDEX('Roadmap Calc (Don’t Touch)'!$U$2:$U$151,$AI39)=0,$AH39,HYPERLINK("#'Control (Don’t Touch)'!E"&INDEX('Roadmap Calc (Don’t Touch)'!$U$2:$U$151,$AI39),$AH39)))) | B39: =IF($AI39="","",IF(INDEX('Roadmap Calc (Don’t Touch)'!$K$2:$K$151,$AI39)="",INDEX('Roadmap Calc (Don’t Touch)'!$B$2:$B$151,$AI39),HYPERLINK("https://jira.bnh.com/browse/"&INDEX('Roadmap Calc (Don’t Touch)'!$K$2:$K$151,$AI39),INDEX('Roadmap Calc (Don’t Touch)'!$B$2:$B$151,$AI39)))) -> Used Roll Up SKUs | C39: =IF($AI39="","",IF(INDEX('Roadmap Calc (Don’t Touch)'!$E$2:$E$151,$AI39)="","",HYPERLINK("https://jira.bnh.com/browse/"&INDEX('Roadmap Calc (Don’t Touch)'!$E$2:$E$151,$AI39),INDEX('Roadmap Calc (Don’t Touch)'!$E$2:$E$151,$AI39)))) -> BHP-6479 | D39: =IF($AI39="","",INDEX('Roadmap Calc (Don’t Touch)'!$F$2:$F$151,$AI39)) -> 01. Prod Discovery | E39: =IF($AI39="","",IF(ISNUMBER(INDEX('Roadmap Calc (Don’t Touch)'!$G$2:$G$151,$AI39)),INDEX('Roadmap Calc (Don’t Touch)'!$G$2:$G$151,$AI39),"")) | F39: =IF($AI39="","",IF(ISNUMBER(INDEX('Roadmap Calc (Don’t Touch)'!$H$2:$H$151,$AI39)),INDEX('Roadmap Calc (Don’t Touch)'!$H$2:$H$151,$AI39),"")) | G39: =IF($AI39="","",INDEX('Roadmap Calc (Don’t Touch)'!$T$2:$T$151,$AI39)) -> 0 | H39: =IF($AI39="","",IF(ISNUMBER(INDEX('Roadmap Calc (Don’t Touch)'!$I$2:$I$151,$AI39)),INDEX('Roadmap Calc (Don’t Touch)'!$I$2:$I$151,$AI39),"")) -> 46357 | I39: =IF($AI39="","",IF(ISNUMBER(INDEX('Roadmap Calc (Don’t Touch)'!$J$2:$J$151,$AI39)),INDEX('Roadmap Calc (Don’t Touch)'!$J$2:$J$151,$AI39),"")) -> 46446 | J39: =IF($AI39="","",IF(AND($AN39<>"",$AN39<=EOMONTH(J$12,0),$AO39>=J$12),IF(AND(INDEX('Roadmap Calc (Don’t Touch)'!$AA$2:$AX$151,$AI39,COLUMN()-COLUMN($J$16)+1)>0,OR($D39="03. UX Discovery",$D39="04. UX Design")),IF(AND($H39<>"",$H39<=EOMONTH(J$12,0),$I39>=J$12),"ALL","PD+UX"),IF(AND($H39<>"",$H39<=EOMONTH(J$12,0),$I39>=J$12),"PD+DEV","PD")),IF(AND(INDEX('Roadmap Calc (Don’t Touch)'!$AA$2:$AX$151,$AI39,COLUMN()-COLUMN($J$16)+1)>0,OR($D39="03. UX Discovery",$D39="04. UX Design")),IF(AND($H39<>"",$H39<=EOMONTH(J$12,0),$I39>=J$12),"UX+DEV","UX"),IF(AND($H39<>"",$H39<=EOMONTH(J$12,0),$I39>=J$12),"DEV","")))) | K39: =IF($AI39="","",IF(AND($AN39<>"",$AN39<=EOMONTH(K$12,0),$AO39>=K$12),IF(AND(INDEX('Roadmap Calc (Don’t Touch)'!$AA$2:$AX$151,$AI39,COLUMN()-COLUMN($J$16)+1)>0,OR($D39="03. UX Discovery",$D39="04. UX Design")),IF(AND($H39<>"",$H39<=EOMONTH(K$12,0),$I39>=K$12),"ALL","PD+UX"),IF(AND($H39<>"",$H39<=EOMONTH(K$12,0),$I39>=K$12),"PD+DEV","PD")),IF(AND(INDEX('Roadmap Calc (Don’t Touch)'!$AA$2:$AX$151,$AI39,COLUMN()-COLUMN($J$16)+1)>0,OR($D39="03. UX Discovery",$D39="04. UX Design")),IF(AND($H39<>"",$H39<=EOMONTH(K$12,0),$I39>=K$12),"UX+DEV","UX"),IF(AND($H39<>"",$H39<=EOMONTH(K$12,0),$I39>=K$12),"DEV","")))) | L39: =IF($AI39="","",IF(AND($AN39<>"",$AN39<=EOMONTH(L$12,0),$AO39>=L$12),IF(AND(INDEX('Roadmap Calc (Don’t Touch)'!$AA$2:$AX$151,$AI39,COLUMN()-COLUMN($J$16)+1)>0,OR($D39="03. UX Discovery",$D39="04. UX Design")),IF(AND($H39<>"",$H39<=EOMONTH(L$12,0),$I39>=L$12),"ALL","PD+UX"),IF(AND($H39<>"",$H39<=EOMONTH(L$12,0),$I39>=L$12),"PD+DEV","PD")),IF(AND(INDEX('Roadmap Calc (Don’t Touch)'!$AA$2:$AX$151,$AI39,COLUMN()-COLUMN($J$16)+1)>0,OR($D39="03. UX Discovery",$D39="04. UX Design")),IF(AND($H39<>"",$H39<=EOMONTH(L$12,0),$I39>=L$12),"UX+DEV","UX"),IF(AND($H39<>"",$H39<=EOMONTH(L$12,0),$I39>=L$12),"DEV","")))) | M39: =IF($AI39="","",IF(AND($AN39<>"",$AN39<=EOMONTH(M$12,0),$AO39>=M$12),IF(AND(INDEX('Roadmap Calc (Don’t Touch)'!$AA$2:$AX$151,$AI39,COLUMN()-COLUMN($J$16)+1)>0,OR($D39="03. UX Discovery",$D39="04. UX Design")),IF(AND($H39<>"",$H39<=EOMONTH(M$12,0),$I39>=M$12),"ALL","PD+UX"),IF(AND($H39<>"",$H39<=EOMONTH(M$12,0),$I39>=M$12),"PD+DEV","PD")),IF(AND(INDEX('Roadmap Calc (Don’t Touch)'!$AA$2:$AX$151,$AI39,COLUMN()-COLUMN($J$16)+1)>0,OR($D39="03. UX Discovery",$D39="04. UX Design")),IF(AND($H39<>"",$H39<=EOMONTH(M$12,0),$I39>=M$12),"UX+DEV","UX"),IF(AND($H39<>"",$H39<=EOMONTH(M$12,0),$I39>=M$12),"DEV","")))) | N39: =IF($AI39="","",IF(AND($AN39<>"",$AN39<=EOMONTH(N$12,0),$AO39>=N$12),IF(AND(INDEX('Roadmap Calc (Don’t Touch)'!$AA$2:$AX$151,$AI39,COLUMN()-COLUMN($J$16)+1)>0,OR($D39="03. UX Discovery",$D39="04. UX Design")),IF(AND($H39<>"",$H39<=EOMONTH(N$12,0),$I39>=N$12),"ALL","PD+UX"),IF(AND($H39<>"",$H39<=EOMONTH(N$12,0),$I39>=N$12),"PD+DEV","PD")),IF(AND(INDEX('Roadmap Calc (Don’t Touch)'!$AA$2:$AX$151,$AI39,COLUMN()-COLUMN($J$16)+1)>0,OR($D39="03. UX Discovery",$D39="04. UX Design")),IF(AND($H39<>"",$H39<=EOMONTH(N$12,0),$I39>=N$12),"UX+DEV","UX"),IF(AND($H39<>"",$H39<=EOMONTH(N$12,0),$I39>=N$12),"DEV","")))) | O39: =IF($AI39="","",IF(AND($AN39<>"",$AN39<=EOMONTH(O$12,0),$AO39>=O$12),IF(AND(INDEX('Roadmap Calc (Don’t Touch)'!$AA$2:$AX$151,$AI39,COLUMN()-COLUMN($J$16)+1)>0,OR($D39="03. UX Discovery",$D39="04. UX Design")),IF(AND($H39<>"",$H39<=EOMONTH(O$12,0),$I39>=O$12),"ALL","PD+UX"),IF(AND($H39<>"",$H39<=EOMONTH(O$12,0),$I39>=O$12),"PD+DEV","PD")),IF(AND(INDEX('Roadmap Calc (Don’t Touch)'!$AA$2:$AX$151,$AI39,COLUMN()-COLUMN($J$16)+1)>0,OR($D39="03. UX Discovery",$D39="04. UX Design")),IF(AND($H39<>"",$H39<=EOMONTH(O$12,0),$I39>=O$12),"UX+DEV","UX"),IF(AND($H39<>"",$H39<=EOMONTH(O$12,0),$I39>=O$12),"DEV","")))) | P39: =IF($AI39="","",IF(AND($AN39<>"",$AN39<=EOMONTH(P$12,0),$AO39>=P$12),IF(AND(INDEX('Roadmap Calc (Don’t Touch)'!$AA$2:$AX$151,$AI39,COLUMN()-COLUMN($J$16)+1)>0,OR($D39="03. UX Discovery",$D39="04. UX Design")),IF(AND($H39<>"",$H39<=EOMONTH(P$12,0),$I39>=P$12),"ALL","PD+UX"),IF(AND($H39<>"",$H39<=EOMONTH(P$12,0),$I39>=P$12),"PD+DEV","PD")),IF(AND(INDEX('Roadmap Calc (Don’t Touch)'!$AA$2:$AX$151,$AI39,COLUMN()-COLUMN($J$16)+1)>0,OR($D39="03. UX Discovery",$D39="04. UX Design")),IF(AND($H39<>"",$H39<=EOMONTH(P$12,0),$I39>=P$12),"UX+DEV","UX"),IF(AND($H39<>"",$H39<=EOMONTH(P$12,0),$I39>=P$12),"DEV","")))) | Q39: =IF($AI39="","",IF(AND($AN39<>"",$AN39<=EOMONTH(Q$12,0),$AO39>=Q$12),IF(AND(INDEX('Roadmap Calc (Don’t Touch)'!$AA$2:$AX$151,$AI39,COLUMN()-COLUMN($J$16)+1)>0,OR($D39="03. UX Discovery",$D39="04. UX Design")),IF(AND($H39<>"",$H39<=EOMONTH(Q$12,0),$I39>=Q$12),"ALL","PD+UX"),IF(AND($H39<>"",$H39<=EOMONTH(Q$12,0),$I39>=Q$12),"PD+DEV","PD")),IF(AND(INDEX('Roadmap Calc (Don’t Touch)'!$AA$2:$AX$151,$AI39,COLUMN()-COLUMN($J$16)+1)>0,OR($D39="03. UX Discovery",$D39="04. UX Design")),IF(AND($H39<>"",$H39<=EOMONTH(Q$12,0),$I39>=Q$12),"UX+DEV","UX"),IF(AND($H39<>"",$H39<=EOMONTH(Q$12,0),$I39>=Q$12),"DEV","")))) | ... AG39: =IF($AI39="","",IF(AND($AN39<>"",$AN39<=EOMONTH(AG$12,0),$AO39>=AG$12),IF(AND(INDEX('Roadmap Calc (Don’t Touch)'!$AA$2:$AX$151,$AI39,COLUMN()-COLUMN($J$16)+1)>0,OR($D39="03. UX Discovery",$D39="04. UX Design")),IF(AND($H39<>"",$H39<=EOMONTH(AG$12,0),$I39>=AG$12),"ALL","PD+UX"),IF(AND($H39<>"",$H39<=EOMONTH(AG$12,0),$I39>=AG$12),"PD+DEV","PD")),IF(AND(INDEX('Roadmap Calc (Don’t Touch)'!$AA$2:$AX$151,$AI39,COLUMN()-COLUMN($J$16)+1)>0,OR($D39="03. UX Discovery",$D39="04. UX Design")),IF(AND($H39<>"",$H39<=EOMONTH(AG$12,0),$I39>=AG$12),"UX+DEV","UX"),IF(AND($H39<>"",$H39<=EOMONTH(AG$12,0),$I39>=AG$12),"DEV","")))) | AH39: =IF($AI39="","",INDEX('Roadmap Calc (Don’t Touch)'!$D$2:$D$151,$AI39)) -> Improve Buy Used Customer Experience | AI39: =IFERROR(MATCH(24,'Roadmap Calc (Don’t Touch)'!$O$2:$O$151,0),"") -> 9 | AN39: =IF($AI39="","",IF(ISNUMBER(INDEX('Roadmap Calc (Don’t Touch)'!$BB$2:$BB$151,$AI39)),INDEX('Roadmap Calc (Don’t Touch)'!$BB$2:$BB$151,$AI39),"")) | AO39: =IF($AI39="","",IF(ISNUMBER(INDEX('Roadmap Calc (Don’t Touch)'!$BC$2:$BC$151,$AI39)),INDEX('Roadmap Calc (Don’t Touch)'!$BC$2:$BC$151,$AI39),""))
A40: =IF($AI40="","",IF($AH40=$AH39,"",IF(INDEX('Roadmap Calc (Don’t Touch)'!$U$2:$U$151,$AI40)=0,$AH40,HYPERLINK("#'Control (Don’t Touch)'!E"&INDEX('Roadmap Calc (Don’t Touch)'!$U$2:$U$151,$AI40),$AH40)))) | B40: =IF($AI40="","",IF(INDEX('Roadmap Calc (Don’t Touch)'!$K$2:$K$151,$AI40)="",INDEX('Roadmap Calc (Don’t Touch)'!$B$2:$B$151,$AI40),HYPERLINK("https://jira.bnh.com/browse/"&INDEX('Roadmap Calc (Don’t Touch)'!$K$2:$K$151,$AI40),INDEX('Roadmap Calc (Don’t Touch)'!$B$2:$B$151,$AI40)))) -> Actual Used Images | C40: =IF($AI40="","",IF(INDEX('Roadmap Calc (Don’t Touch)'!$E$2:$E$151,$AI40)="","",HYPERLINK("https://jira.bnh.com/browse/"&INDEX('Roadmap Calc (Don’t Touch)'!$E$2:$E$151,$AI40),INDEX('Roadmap Calc (Don’t Touch)'!$E$2:$E$151,$AI40)))) -> BHP-4563 | D40: =IF($AI40="","",INDEX('Roadmap Calc (Don’t Touch)'!$F$2:$F$151,$AI40)) -> 13. Live | E40: =IF($AI40="","",IF(ISNUMBER(INDEX('Roadmap Calc (Don’t Touch)'!$G$2:$G$151,$AI40)),INDEX('Roadmap Calc (Don’t Touch)'!$G$2:$G$151,$AI40),"")) | F40: =IF($AI40="","",IF(ISNUMBER(INDEX('Roadmap Calc (Don’t Touch)'!$H$2:$H$151,$AI40)),INDEX('Roadmap Calc (Don’t Touch)'!$H$2:$H$151,$AI40),"")) | G40: =IF($AI40="","",INDEX('Roadmap Calc (Don’t Touch)'!$T$2:$T$151,$AI40)) -> 0 | H40: =IF($AI40="","",IF(ISNUMBER(INDEX('Roadmap Calc (Don’t Touch)'!$I$2:$I$151,$AI40)),INDEX('Roadmap Calc (Don’t Touch)'!$I$2:$I$151,$AI40),"")) | I40: =IF($AI40="","",IF(ISNUMBER(INDEX('Roadmap Calc (Don’t Touch)'!$J$2:$J$151,$AI40)),INDEX('Roadmap Calc (Don’t Touch)'!$J$2:$J$151,$AI40),"")) | J40: =IF($AI40="","",IF(AND($AN40<>"",$AN40<=EOMONTH(J$12,0),$AO40>=J$12),IF(AND(INDEX('Roadmap Calc (Don’t Touch)'!$AA$2:$AX$151,$AI40,COLUMN()-COLUMN($J$16)+1)>0,OR($D40="03. UX Discovery",$D40="04. UX Design")),IF(AND($H40<>"",$H40<=EOMONTH(J$12,0),$I40>=J$12),"ALL","PD+UX"),IF(AND($H40<>"",$H40<=EOMONTH(J$12,0),$I40>=J$12),"PD+DEV","PD")),IF(AND(INDEX('Roadmap Calc (Don’t Touch)'!$AA$2:$AX$151,$AI40,COLUMN()-COLUMN($J$16)+1)>0,OR($D40="03. UX Discovery",$D40="04. UX Design")),IF(AND($H40<>"",$H40<=EOMONTH(J$12,0),$I40>=J$12),"UX+DEV","UX"),IF(AND($H40<>"",$H40<=EOMONTH(J$12,0),$I40>=J$12),"DEV","")))) | K40: =IF($AI40="","",IF(AND($AN40<>"",$AN40<=EOMONTH(K$12,0),$AO40>=K$12),IF(AND(INDEX('Roadmap Calc (Don’t Touch)'!$AA$2:$AX$151,$AI40,COLUMN()-COLUMN($J$16)+1)>0,OR($D40="03. UX Discovery",$D40="04. UX Design")),IF(AND($H40<>"",$H40<=EOMONTH(K$12,0),$I40>=K$12),"ALL","PD+UX"),IF(AND($H40<>"",$H40<=EOMONTH(K$12,0),$I40>=K$12),"PD+DEV","PD")),IF(AND(INDEX('Roadmap Calc (Don’t Touch)'!$AA$2:$AX$151,$AI40,COLUMN()-COLUMN($J$16)+1)>0,OR($D40="03. UX Discovery",$D40="04. UX Design")),IF(AND($H40<>"",$H40<=EOMONTH(K$12,0),$I40>=K$12),"UX+DEV","UX"),IF(AND($H40<>"",$H40<=EOMONTH(K$12,0),$I40>=K$12),"DEV","")))) | L40: =IF($AI40="","",IF(AND($AN40<>"",$AN40<=EOMONTH(L$12,0),$AO40>=L$12),IF(AND(INDEX('Roadmap Calc (Don’t Touch)'!$AA$2:$AX$151,$AI40,COLUMN()-COLUMN($J$16)+1)>0,OR($D40="03. UX Discovery",$D40="04. UX Design")),IF(AND($H40<>"",$H40<=EOMONTH(L$12,0),$I40>=L$12),"ALL","PD+UX"),IF(AND($H40<>"",$H40<=EOMONTH(L$12,0),$I40>=L$12),"PD+DEV","PD")),IF(AND(INDEX('Roadmap Calc (Don’t Touch)'!$AA$2:$AX$151,$AI40,COLUMN()-COLUMN($J$16)+1)>0,OR($D40="03. UX Discovery",$D40="04. UX Design")),IF(AND($H40<>"",$H40<=EOMONTH(L$12,0),$I40>=L$12),"UX+DEV","UX"),IF(AND($H40<>"",$H40<=EOMONTH(L$12,0),$I40>=L$12),"DEV","")))) | M40: =IF($AI40="","",IF(AND($AN40<>"",$AN40<=EOMONTH(M$12,0),$AO40>=M$12),IF(AND(INDEX('Roadmap Calc (Don’t Touch)'!$AA$2:$AX$151,$AI40,COLUMN()-COLUMN($J$16)+1)>0,OR($D40="03. UX Discovery",$D40="04. UX Design")),IF(AND($H40<>"",$H40<=EOMONTH(M$12,0),$I40>=M$12),"ALL","PD+UX"),IF(AND($H40<>"",$H40<=EOMONTH(M$12,0),$I40>=M$12),"PD+DEV","PD")),IF(AND(INDEX('Roadmap Calc (Don’t Touch)'!$AA$2:$AX$151,$AI40,COLUMN()-COLUMN($J$16)+1)>0,OR($D40="03. UX Discovery",$D40="04. UX Design")),IF(AND($H40<>"",$H40<=EOMONTH(M$12,0),$I40>=M$12),"UX+DEV","UX"),IF(AND($H40<>"",$H40<=EOMONTH(M$12,0),$I40>=M$12),"DEV","")))) | N40: =IF($AI40="","",IF(AND($AN40<>"",$AN40<=EOMONTH(N$12,0),$AO40>=N$12),IF(AND(INDEX('Roadmap Calc (Don’t Touch)'!$AA$2:$AX$151,$AI40,COLUMN()-COLUMN($J$16)+1)>0,OR($D40="03. UX Discovery",$D40="04. UX Design")),IF(AND($H40<>"",$H40<=EOMONTH(N$12,0),$I40>=N$12),"ALL","PD+UX"),IF(AND($H40<>"",$H40<=EOMONTH(N$12,0),$I40>=N$12),"PD+DEV","PD")),IF(AND(INDEX('Roadmap Calc (Don’t Touch)'!$AA$2:$AX$151,$AI40,COLUMN()-COLUMN($J$16)+1)>0,OR($D40="03. UX Discovery",$D40="04. UX Design")),IF(AND($H40<>"",$H40<=EOMONTH(N$12,0),$I40>=N$12),"UX+DEV","UX"),IF(AND($H40<>"",$H40<=EOMONTH(N$12,0),$I40>=N$12),"DEV","")))) | O40: =IF($AI40="","",IF(AND($AN40<>"",$AN40<=EOMONTH(O$12,0),$AO40>=O$12),IF(AND(INDEX('Roadmap Calc (Don’t Touch)'!$AA$2:$AX$151,$AI40,COLUMN()-COLUMN($J$16)+1)>0,OR($D40="03. UX Discovery",$D40="04. UX Design")),IF(AND($H40<>"",$H40<=EOMONTH(O$12,0),$I40>=O$12),"ALL","PD+UX"),IF(AND($H40<>"",$H40<=EOMONTH(O$12,0),$I40>=O$12),"PD+DEV","PD")),IF(AND(INDEX('Roadmap Calc (Don’t Touch)'!$AA$2:$AX$151,$AI40,COLUMN()-COLUMN($J$16)+1)>0,OR($D40="03. UX Discovery",$D40="04. UX Design")),IF(AND($H40<>"",$H40<=EOMONTH(O$12,0),$I40>=O$12),"UX+DEV","UX"),IF(AND($H40<>"",$H40<=EOMONTH(O$12,0),$I40>=O$12),"DEV","")))) | P40: =IF($AI40="","",IF(AND($AN40<>"",$AN40<=EOMONTH(P$12,0),$AO40>=P$12),IF(AND(INDEX('Roadmap Calc (Don’t Touch)'!$AA$2:$AX$151,$AI40,COLUMN()-COLUMN($J$16)+1)>0,OR($D40="03. UX Discovery",$D40="04. UX Design")),IF(AND($H40<>"",$H40<=EOMONTH(P$12,0),$I40>=P$12),"ALL","PD+UX"),IF(AND($H40<>"",$H40<=EOMONTH(P$12,0),$I40>=P$12),"PD+DEV","PD")),IF(AND(INDEX('Roadmap Calc (Don’t Touch)'!$AA$2:$AX$151,$AI40,COLUMN()-COLUMN($J$16)+1)>0,OR($D40="03. UX Discovery",$D40="04. UX Design")),IF(AND($H40<>"",$H40<=EOMONTH(P$12,0),$I40>=P$12),"UX+DEV","UX"),IF(AND($H40<>"",$H40<=EOMONTH(P$12,0),$I40>=P$12),"DEV","")))) | Q40: =IF($AI40="","",IF(AND($AN40<>"",$AN40<=EOMONTH(Q$12,0),$AO40>=Q$12),IF(AND(INDEX('Roadmap Calc (Don’t Touch)'!$AA$2:$AX$151,$AI40,COLUMN()-COLUMN($J$16)+1)>0,OR($D40="03. UX Discovery",$D40="04. UX Design")),IF(AND($H40<>"",$H40<=EOMONTH(Q$12,0),$I40>=Q$12),"ALL","PD+UX"),IF(AND($H40<>"",$H40<=EOMONTH(Q$12,0),$I40>=Q$12),"PD+DEV","PD")),IF(AND(INDEX('Roadmap Calc (Don’t Touch)'!$AA$2:$AX$151,$AI40,COLUMN()-COLUMN($J$16)+1)>0,OR($D40="03. UX Discovery",$D40="04. UX Design")),IF(AND($H40<>"",$H40<=EOMONTH(Q$12,0),$I40>=Q$12),"UX+DEV","UX"),IF(AND($H40<>"",$H40<=EOMONTH(Q$12,0),$I40>=Q$12),"DEV","")))) | ... AG40: =IF($AI40="","",IF(AND($AN40<>"",$AN40<=EOMONTH(AG$12,0),$AO40>=AG$12),IF(AND(INDEX('Roadmap Calc (Don’t Touch)'!$AA$2:$AX$151,$AI40,COLUMN()-COLUMN($J$16)+1)>0,OR($D40="03. UX Discovery",$D40="04. UX Design")),IF(AND($H40<>"",$H40<=EOMONTH(AG$12,0),$I40>=AG$12),"ALL","PD+UX"),IF(AND($H40<>"",$H40<=EOMONTH(AG$12,0),$I40>=AG$12),"PD+DEV","PD")),IF(AND(INDEX('Roadmap Calc (Don’t Touch)'!$AA$2:$AX$151,$AI40,COLUMN()-COLUMN($J$16)+1)>0,OR($D40="03. UX Discovery",$D40="04. UX Design")),IF(AND($H40<>"",$H40<=EOMONTH(AG$12,0),$I40>=AG$12),"UX+DEV","UX"),IF(AND($H40<>"",$H40<=EOMONTH(AG$12,0),$I40>=AG$12),"DEV","")))) | AH40: =IF($AI40="","",INDEX('Roadmap Calc (Don’t Touch)'!$D$2:$D$151,$AI40)) -> Improve Buy Used Customer Experience | AI40: =IFERROR(MATCH(25,'Roadmap Calc (Don’t Touch)'!$O$2:$O$151,0),"") -> 46 | AN40: =IF($AI40="","",IF(ISNUMBER(INDEX('Roadmap Calc (Don’t Touch)'!$BB$2:$BB$151,$AI40)),INDEX('Roadmap Calc (Don’t Touch)'!$BB$2:$BB$151,$AI40),"")) | AO40: =IF($AI40="","",IF(ISNUMBER(INDEX('Roadmap Calc (Don’t Touch)'!$BC$2:$BC$151,$AI40)),INDEX('Roadmap Calc (Don’t Touch)'!$BC$2:$BC$151,$AI40),""))
