Workbook

Sheet Quaterly
A1: 2026 Roadmap - Jerel Smith
B2: Q1 2026 | C2: Q2 2026 | D2: Q3 2026 | E2: Q4 2026 | F2: Q1 2027 | G2: Q2 2027 | H2: Q3 2027 | I2: Q4 2027 | J2: Q1 2028 | K2: Q2 2028 | L2: Q3 2028 | M2: Q4 2028
A3: 1. B2B | E3: Freeze
A4: PMO-5000
A5: >CMS Lite | B5: Discovery | C5: Design + Dev | D5: Dev + Live
A6: >Sign Up | B6: Discovery | C6: Design + Dev | D6: Dev + Live
A7: >Internal Pages | B7: Discovery + Research | C7: Design + Dev | D7: Dev + Live
A8: B2B Hub Health Dashboard | D8: All
A9: The Studio
A10: Categories | B10: Discovery + Research | C10: Stakeholder Input | D10: Dev + Live
A11: >Landing Page | B11: Discovery + Research | C11: Design + Dev | D11: Dev + Live
A12: >Multi-Page | B12: Discovery + Research
A13: 2. Used
A14: Sell Used/Trade In
A15: >Sell Used Experience | B15: Discovery + Research | C15: Design + Dev | D15: Live
A16: >Trade In Experience | B16: Discovery + Research | C16: Design + Dev | D16: Live
A17: Trade In Emails | B17: Discovery | D17: …Live
A18: Used Hub Health Dashboard | C18: Discovery + Research | D18: …Live
A19: Condition Rating Scale
A20: >New Condition Rating Scale | B20: Discovery | C20: Design | D20: Dev + Live
A21: PDP - Group By Condition | B21: Discovery | C21: Design | D21: Dev + Live
A22: PLP - Roll Up By Condition
A23: Actual Used Images (Tim) | B23: Dev | C23: Operationalize | D23: Live
A24: 3. Legacy Find (Submitting to Dev - Not Owning Afterwards)
A25: Mega Menu | B25: Discovery + Research | C25: Design + Dev | D25: Live
A26: Roll Up SKUs | B26: Design + Grooming
A27: Nested Refinements | B27: Discovery + Design | C27: Design | D27: Dev + Live

Sheet Monthly
A2: Journey/Initiative | B2: Q1 | E2: Q2 | H2: Q3 | K2: Q4 | N2: Q1 | Q2: Q2 | T2: Q3 | W2: Q4
A3: Enterprise Platforms & Used | B3: January | C3: February | D3: March | E3: April | F3: May | G3: June | H3: July | I3: August | J3: September | K3: October | L3: November | M3: December | N3: January | O3: February | P3: March | Q3: April | R3: May | S3: June | T3: July | U3: August | V3: September | W3: October | X3: November | Y3: December
A4: 1. B2B | L4: Freeze
A5: PMO-5000
A6: >Weblogic-> Apeture/JSON Led | D6: Discovery + Research | E6: Design | G6: Dev | I6: Live
A7: >Sign Up | D7: Discovery + Research
A8: >Internal Pages | D8: Discovery + Research
A9: B2B Hub Health Dashboard | E9: Discovery | F9: Research | G9: Dev | H9: Live
A10: The Studio
A11: Categories | D11: Discovery + Research | E11: Design | F11: Dev
A12: >Landing Page | D12: Discovery | E12: Research | F12: Design | G12: Dev
A13: >Multi-Page | G13: Design | H13: Dev | I13: Dev | J13: Live
A14: EDU | B14: Design | F14: Dev | G14: Live
A15: 2. Used
A16: Sell Used/Trade In
A17: >Sell Used Experience | D17: Discovery + Research | E17: Design | F17: Design | G17: Dev | H17: Dev | I17: Live
A18: >Trade In Experience | D18: Discovery + Research | F18: Design | G18: Dev | H18: …Live
A19: Trade In Emails | D19: Discovery | E19: Design | F19: Dev | G19: Live
A20: Used Hub Health Dashboard | F20: Discovery + Research | G20: Dev | H20: Live
A21: Condition Rating Scale
A22: >New Condition Rating Scale | B22: Discovery | C22: Research | D22: Socialize | E22: Socialize | F22: Dev | G22: Live
A23: PDP - Group By Condition | E23: Design | F23: …Live
A24: PLP - Roll Up By Condition | H24: Discovery | I24: Research | J24: Live
A25: Actual Used Images (Tim) | E25: Design | F25: Dev | G25: Operationalize | H25: Operationalize | I25: Live
A26: 3. Legacy Find (Submitting to Dev - Not Owning Afterwards)
A27: Mega Menu | B27: Discovery | C27: Research | D27: Design | F27: …Live
A28: Nested Refinements | B28: Discovery | C28: Research | D28: Design | F28: Dev | G28: Live

Sheet Weekly
A1: Product | B1: Portfolio | C1: Theme #1 | D1: Theme #2 | E1: Title | F1: Jira | G1: Status | H1: 46125 | I1: 46132 | J1: 46139 | K1: 46146 | L1: 46153 | M1: 46160 | N1: 46167 | O1: 46174 | P1: 46181 | Q1: 46188 | R1: 46195 | S1: 46202 | T1: 46209 | U1: 46216 | V1: 46223 | W1: 46230 | X1: 46237 | Y1: 46244 | Z1: 46251 | AA1: 46258 | AB1: 46265 | AC1: 46272 | AD1: 46279 | AE1: 46286 | AF1: 46293 | AG1: 46300 | AH1: 46307 | AI1: 46314 | AJ1: 46321 | AK1: 46328 | AL1: 46335 | AM1: 46342 | AN1: 46349 | AO1: 46356 | AP1: 46363 | AQ1: 46370 | AR1: 46377 | AS1: 46384 | AT1: 46391 | AU1: 46398 | AV1: 46405 | AW1: 46412 | AX1: 46419 | AY1: 46426 | AZ1: 46433 | BA1: 46440 | BB1: 46447 | BC1: 46454 | BD1: 46461 | BE1: 46468 | BF1: 46475 | BG1: 46482 | BH1: 46489 | BI1: 46496 | BJ1: 46503 | BK1: 46510 | BL1: 46517 | BM1: 46524 | BN1: 46531 | BO1: 46538 | BP1: 46545 | BQ1: 46552 | BR1: 46559 | BS1: 46566 | BT1: 46573 | BU1: 46580 | BV1: 46587 | BW1: 46594 | BX1: 46601 | BY1: 46608 | BZ1: 46615 | CA1: 46622 | CB1: 46629 | CC1: 46636 | CD1: 46643 | CE1: 46650 | CF1: 46657 | CG1: 46664 | CH1: 46671 | CI1: 46678 | CJ1: 46685 | CK1: 46692 | CL1: 46699 | CM1: 46706 | CN1: 46713 | CO1: 46720 | CP1: 46727 | CQ1: 46734 | CR1: 46741 | CS1: 46748 | CT1: 46755
A2: Jerel Smith | B2: Used | C2: Improve Buy Used Customer Experience | D2: Improve Trade In User Flow | E2: New Condition Rating Scale | F2: BHUX-33510 | G2: 00. Parking Lot | O2: Leo | P2: Leo | Q2: Leo
A3: Jerel Smith | B3: B2B | C3: Increase B2B Acquisition | E3: B2B Hub - Logged In B2B Experience | F3: BHP-6901 | G3: 00. Parking Lot | P3: Jaye | AG3: Jaye | AH3: Jaye | AI3: Jaye | AJ3: Jaye
A4: Jerel Smith | B4: B2B | C4: Improve The Studio B&H Customer Experience | E4: B2B - The Studio Categories | F4: BHUX-33434 | G4: 01. Prod Discovery | I4: Hilli | K4: Hilli | P4: Hilli | AB4: Hilli | AC4: Hilli | AD4: Hilli
A5: Jerel Smith | B5: B2B | C5: Increase The Studio B&H Awareness | E5: The Studio - Stand Alone Website | G5: 01. Prod Discovery | AC5: Sumit | AD5: Sumit | AE5: Sumit
A6: Jerel Smith | B6: B2B | E6: Homepage Header: B2B | F6: BHP-7274 | G6: 01. Prod Discovery
B7: Used | C7: Increase Trade In Awareness | E7: Decouple Sell Used from Used Hub | F7: BHP-7431 | G7: 01. Prod Discovery
A8: Jerel Smith | B8: Used | C8: Improve Trade In User Flow | E8: Sell Used Purchase Look Up | F8: BHP-7236 | G8: 02. UX Req | AA8: John | AB8: John | AC8: John
A9: Jerel Smith | B9: Used | C9: Increase Trade In Awareness | E9: Used Activity Notification | F9: BHP-7237 | G9: 02. UX Req | AD9: John | AE9: John | AF9: John
A10: Jerel Smith | B10: B2B | C10: Improve The Studio B&H Customer Experience | E10: The Studio - Enhanced Landing Page | F10: BHP-6444 | G10: 02. UX Req | AC10: Sumit | AD10: Sumit | AE10: Sumit
B11: B2B | C11: Increase B2B Acquisition | E11: FDOT Hero Image | F11: BHP-7394 | G11: 02. UX Req | AA11: Nachman
A12: Jerel Smith | B12: Used | C12: Increase Buy Used Awareness | E12: Used Hub - Just Added Component | F12: BHP-7229 | G12: 02. UX Req | Y12: John | AC12: John | AD12: John
A13: Jerel Smith | B13: B2B | C13: Increase The Studio B&H Awareness | E13: The Studio - Category Hybrid Page | F13: BHP-7301 | G13: 02. UX Req | Y13: Sumit | AA13: Sumit | AB13: Sumit
A14: Jerel Smith | B14: Used | C14: Increase Buy Used Awareness | E14: Used Just Added Page | F14: BHP-7230 | G14: 02. UX Req | M14: Nachman | N14: Nachman | AG14: Nachman | AH14: Nachman
A15: Jerel Smith | B15: Used | C15: Increase Trade In Awareness | E15: Increase Awareness of Trade In Offers - Best Buy Inspiration/Competitive Effort | F15: BHP-6827 | G15: 02. UX Req
A16: Jerel Smith | B16: Used | C16: Increase Buy Used Awareness | E16: Out of stock Alerts for used products | F16: BHUX-35020 | G16: 03. UX Discovery | X16: Leo | Y16: Leo | Z16: Leo | AA16: Leo
A17: Jerel Smith | B17: B2B | C17: Increase The Studio B&H Awareness | E17: The Studio - B&H Awareness on High Ticket Items | F17: BHUX-35304 | G17: 03. UX Discovery | Z17: Leo | AA17: Leo | AB17: Leo | AC17: Leo
A18: Jerel Smith | B18: Used | C18: Increase Buy Used Awareness | D18: Improve Discovery | E18: Add New | Used tab to all listing pages and search results pages | F18: BHUX-35303 | G18: 03. UX Discovery | AA18: Sumit | AB18: Sumit | AC18: Sumit | AD18: Sumit
A19: Jerel Smith | B19: Find | C19: Improve Discovery | E19: Highlighted Refinements Enhancement | F19: BHUX-35302 | G19: 04. UX Design | AA19: Sumit | AB19: Sumit | AC19: Sumit | AD19: Sumit
A20: Jerel Smith | B20: Used | C20: Improve Trade In User Flow | E20: Trade In Email - Comprehensive Refresh Discovery | F20: BHUX-34772 | G20: 04. UX Design | U20: John | V20: John | W20: John | X20: John
A21: Jerel Smith | B21: Used | C21: Improve Trade In User Flow | E21: Used - Sell Used Experience | F21: BHUX-33009 | G21: 04. UX Design | I21: John | J21: John | K21: John | L21: John | M21: John | N21: John | O21: John | P21: John | Q21: John | R21: John | S21: John | T21: John | U21: John | V21: John | W21: John | X21: John | Y21: John | Z21: John | AA21: John | AB21: John | AC21: John | AD21: John | AE21: John | AF21: John
A22: Jerel Smith | B22: Used | C22: Increase Buy Used Awareness | E22: Add 'shop by popular brands' section to Used Homepage | F22: BHUX-34844 | G22: 04. UX Design | V22: John | W22: John | X22: John | Y22: John | Z22: John | AA22: John
A23: Jerel Smith | B23: Used | C23: Increase Buy Used Awareness | E23: Shop By Popular Brand' Listing Pages Discovery | F23: BHUX-34845 | G23: 04. UX Design | W23: Sumit | X23: Sumit | Y23: Sumit | Z23: Sumit | AA23: Sumit
A24: Jerel Smith | B24: Used | C24: Increase Buy Used Awareness | E24: My Account > Trade In Awareness | F24: BHUX-35010 | G24: 04. UX Design | Y24: Mehek | Z24: Mehek | AA24: Mehek
A25: Jerel Smith | B25: B2B/Used | C25: Increase Trade In Awareness | D25: Increase B2B Acquisition | E25: B2B & Used Visibility in the Nav | F25: BHUX-34378 | G25: 04. UX Design | O25: Sumit | P25: Sumit | Q25: Sumit | R25: Sumit | S25: Sumit | T25: Sumit | U25: Sumit | V25: Sumit | W25: Sumit | X25: Sumit | Y25: Sumit | Z25: Sumit | AA25: Sumit | AB25: Sumit | AC25: Sumit | AD25: Sumit | AE25: Sumit | AF25: Sumit
A26: Jerel Smith | B26: Used | C26: Improve Trade In User Flow | E26: Sell Used User Flow Design Validation | F26: BHUR-133 | G26: 04A. Research - Design Validation | T26: Hanna | U26: Hanna | V26: Hanna | W26: Hanna | X26: Hanna | Y26: Hanna | Z26: Hanna | AA26: Hanna
A27: Jerel Smith | B27: Used | C27: Improve Trade In User Flow | E27: Used Status Email Update | F27: BHUX-34723 | G27: 06. Architecture | U27: John
A28: Jerel Smith | B28: Used | C28: Increase Trade In Awareness | E28: PDP Purchased in 20XX, Trade In Value is $YYY.YY | F28: BHUX-35309 | G28: 06. Architecture | Z28: Alice
A29: Jerel Smith | B29: Find | C29: Improve Discovery | E29: Mega Menu | F29: BHUX-29580 | G29: 07. Grooming | J29: Laura | K29: Laura | O29: Sumit
A30: Jerel Smith | B30: B2B | C30: Increase B2B Acquisition | E30: School Safety Landing Page | F30: BHUX-34377 | G30: 07. Grooming | Q30: Hilli | R30: Hilli | S30: Hilli | T30: Hilli | U30: Hilli | V30: Hilli | W30: Hilli | X30: Hilli | Y30: Hilli
A31: Jerel Smith | B31: B2B | C31: Increase B2B Acquisition | E31: B2B Hub Landing Page - redesign | F31: BHUX-26541 | G31: 07. Grooming | H31: Jaye | I31: Jaye | J31: Jaye | K31: Jaye | L31: Jaye
A32: Jerel Smith | B32: B2B | C32: Increase B2B Acquisition | E32: B2B Hub - Revisit Signup Flow | F32: BHUX-31874 | G32: 07. Grooming | H32: Jaye | I32: Jaye | J32: Jaye | K32: Jaye | L32: Jaye | M32: Jaye | N32: Jaye
A33: Jerel Smith | B33: B2B | C33: Increase B2B Acquisition | E33: B2B Hub Redesign - Internal Pages | F33: BHUX-32257 | G33: 07. Grooming | I33: Jaye | J33: Jaye | K33: Jaye | L33: Jaye
A34: Jerel Smith | B34: Used | C34: Improve Buy Used Customer Experience | D34: Improve Trade In User Flow | E34: New Condition Rating Scale (Intermediate Step) | F34: BHJ-121278 | G34: 07. Grooming
A35: Jerel Smith | B35: Find | C35: Improve Discovery | E35: Nested Refinements | F35: BHUX-32621 | G35: 08. Ready for Dev
A36: Jerel Smith | B36: Find | C36: Improve Discovery | E36: Sunset Modals for Drawers | F36: BHUX-32543 | G36: 09. In Dev
A37: Jerel Smith | B37: Used | C37: Improve Trade In User Flow | E37: Trade In Discrepancy Email Refresh (Copy Only) | G37: 09. In Dev | U37: John | V37: John
A38: Jerel Smith | B38: Used | C38: Increase Buy Used Awareness | E38: Condition Grouping | F38: BHUX-33519 | G38: 10. QA | J38: Leo | K38: Leo
B39: Find | C39: Improve Discovery | E39: Sliders | F39: BHUX-17615 | G39: 13. Live
B40: Find | C40: Improve Discovery | E40: Refinement - Select All/Deselect All | F40: BHUX-23755 | G40: 13. Live
B41: Find | C41: Improve Discovery | E41: My Gear 2 - Tray | F41: BHUX-28124 | G41: 13. Live
B42: Find | C42: Improve Discovery | E42: H2 on listing pages | F42: BHUX-31245 | G42: 13. Live
B43: Find | C43: Improve Discovery | E43: Sunset Dealzone | F43: BHUX-32071 | G43: 13. Live
B44: Find | C44: Improve Discovery | E44: Highlighted Refinements | F44: BHUX-29921 | G44: 13. Live
A45: Jerel Smith | B45: B2B | C45: Increase B2B Acquisition | E45: EDU Homepage | F45: BHUX-25601 | G45: 13. Live | K45: Hilli | Q45: Hilli
B46: Used | C46: Improve Buy Used Customer Experience | E46: Actual Used Images | F46: BHP-4563 | G46: 13. Live
B47: Used | C47: Increase Buy Used Awareness | E47: Used Hub Enhancements | F47: BHUX-31354 | G47: 13. Live

Sheet Model (Don't Touch)
B3: Reduce impediments and increase transparency/trust across internal teams by answering the following questions:
B4: Who wants this?
B5: Why are we doing this?
B6: What's the bigger picture?
B7: How do we know if it worked?
B8: Where will the customer encounter this experience?
B37: Portfolios | C37: Who are the primary stakeholders?
B38: Theme | C38: What are the ongoing high level efforts that create a positive impact on customer experience and revenue?
B39: Roadmap | C39: What is the sequence of deliverables and why?
B40: Metrics | C40: Through which lens do we judge performance/success?
B41: Components | C41: What elements are involved in this theme/request?
B42: GA4 | C42: Is the Component tagged? If so, is it tagged in a meaningful way?

Sheet Initiative Tracker
A4: Title | B4: Ticket | C4: Status | D4: Portfolio | E4: Component | F4: Tech | G4: Start Sprint | H4: End Sprint | I4: Notes
A5: Post Hub | B5: BHP-6901 | C5: 99. Parking Lot | D5: B2B | E5: B2B Hub | F5: BHJ | G5: Oct 2026 | H5: Jan 2027 | I5: Deprioritized by Ariel until visibility in the Nav is addressed
A6: School Safety Landing Page | B6: BHP-5830 | C6: 2. Design | D6: B2B | E6: B2B Hub Plus | F6: BHJ | G6: Sep 2026 | H6: Sep 2026 | I6: https://www.bhphotovideo.com/c/browse/school-safety/ci/64314 has been created to point the categories on the landing page towards
A7: EDU Homepage | B7: BHP-3583 | C7: 4. Dev | D7: B2B | E7: EDU | F7: BHJ | G7: Aug 2026 | H7: Aug 2026
A8: B2B Hub | B8: PMO-5000 | C8: 7. Live | D8: B2B | E8: B2B Hub | F8: BHJ
A9: B2B The Studio Categories | B9: BHP-6446 | C9: 99. Parking Lot | D9: B2B | E9: B2B Hub | F9: BHJ | I9: Impeded by stakehodler availability
A10: Mega Menu | B10: BHP-6955 | C10: 3. Architecture | D10: Merchandising | E10: Navigation | F10: BHJ, BHIA, BIDW | G10: Aug 2026 | H10: Oct 2026 | I10: Four technical ideation meetings booked, two complete, Progress being made with tech reqs
A11: Highlighted Refinements | C11: 7. Live | D11: Merchandising | E11: PLP/Search | F11: BHJ, Search, BHIA | G11: May | H11: Jul 2026 | I11: Operationalizing with Shalom Oster & Daniel Ballas, should be live late June, currently in Pull Request
A12: Sell Used | B12: BHP-6434 | C12: 2B. Research | D12: Used Operations | E12: Sell Used | F12: UNIX, BHJ, SEARCH | G12: Sep 2026 | H12: Jan 2027 | I12: Research transitioned from Birdie to Hanna, pausing for ramp up
A13: New Condition Rating Scale | B13: BHP-4771 | C13: 99. Parking Lot | D13: Used Operations | E13: PLP/PDP | F13: UNIX, BHJ | G13: Aug 2026 | H13: Aug 2026 | I13: Due to trepidation by the stakeholder, let's freeze this initiative and pivot to a slow release: remove +9, Demo and add short and long term descriptions via DBA requests (no BHJ)
A14: Group by Conditon | B14: BHP-4518 | C14: 4. Dev | D14: Used Operations | E14: PLP/PDP | F14: BHJ | G14: Aug 2026 | H14: Aug 2026 | I14: Met with architecture, requirements confirmed, moving forward with dev
A15: Actual Used Images | C15: 5. Implementation | D15: Used Operations | E15: PDP/ Images | F15: BHJ, BHIA | G15: Mar 2026 | H15: Jun 2026 | I15: Reached out to Isaac to make the Ortery Purchase
A16: Trade In Emails - Comprehensive Revamp | B16: BHP-6391 | C16: 1. UX Discovery | D16: Used Operations | E16: Trade In Email | F16: UNIX | G16: Aug 2026 | H16: Aug 2026
A17: Used Search Terms | B17: BIDW-98341 | C17: 4. Dev | D17: Used Operations | E17: Sell Used | F17: BIDW | G17: Aug 2026 | H17: Aug 2026 | I17: Research the search terms used over the last 6 months https://jira.bnh.com/browse/BIDW-98341
A18: Nested Refinements | B18: BHP-2802 | C18: 4. Dev | D18: Web Experience | E18: PLP/Search | F18: BHJ, BHIA, SEARCH | G18: Sep 2026 | H18: Nov | I18: Multiple Prerequisites and dependencies: BHIA, BHJs
A19: My Gear Release 2 | B19: BHP-3683 | C19: 4. Dev | D19: Web Experience | E19: My Gear | F19: BHJ, BHIA, SEARCH
A20: Sunset Deal Zone | C20: 7. Live | D20: Web Experience | E20: Navigation | F20: BHJ | G20: Jun 2026 | H20: Aug 2026 | I20: Almost complete, need Permalink and nav jiras live
A21: View All Category Landing Page | C21: 7. Live | D21: Web Experience | E21: Category Landing Page | F21: BHJ, BHIA | H21: Jul 2026 | I21: Approved UAT; operationalizing with nav arcs
A22: Roll Up SKUs | B22: BHP-11 | C22: 99. Parking Lot | D22: Web Experience | E22: PLP/Search | F22: BHJ, BHIA, SEARCH
A23: The Studio - Stand Alone Website | D23: The Studio - B2B | E23: The Studio | F23: BHJ | G23: Sep 2026 | H23: Mar 2027
A24: The Studio - Enhanced Landing Page | B24: BHP-6444 | C24: 0. Discovery | D24: The Studio - B2B | E24: B2B Hub | F24: BHJ | G24: Oct 2026 | H24: Jan 2027
A25: The Studio - Category Hybrid Page | B25: BHP-7301 | C25: 1. UX Discovery | D25: The Studio - B2B | E25: PLP/Search | F25: BHJ | G25: Aug 2026 | H25: Oct 2026
A26: The Studio - B&H Awareness on High Ticket Items | B26: BHP-7239 | C26: 2. Design | D26: The Studio - B2B | E26: PDP | F26: BHJ
A27: Sell Used Purchase Look Up | B27: BHP-7236 | C27: 1. UX Discovery | D27: Used Operations | E27: Sell Used | F27: BHJ, UNIX
A28: PDP Purchased in 20XX, Trade In Value is $YYY.YY | B28: BHP-7228 | D28: Used Operations | E28: PDP | F28: BHJ, BHIA
A29: Used Just Added Page | B29: BHP-7230 | D29: Used Operations | F29: BHJ
A30: Used Activity Notification | B30: BHP-7237 | C30: 0. Discovery | D30: Used Operations | E30: Used Hub | F30: BHJ, UNIX
A31: Highlighted Refinements Enhancement | B31: BHP-7226 | D31: Web Experience | E31: PLP/Search | F31: BHJ
A32: Homepage Header: B2B | B32: BHP-7274 | D32: B2B | F32: BHJ
A33: Increase Awareness of Trade In Offers - Best Buy Inspiration/Competitive Effort | B33: BHP-6827 | D33: Used Operations | E33: PLP/Search | F33: BHJ

Sheet Obsolete
A3: Product | B3: Portfolio | C3: Theme | D3: Title | E3: Jira | F3: Status
A4: Brendan Bagley | D4: Tax & Net 30 Terms On CompanyID | E4: BHUX-33524 | F4: 06. Architecutre
A5: Brendan Bagley | B5: B2B | D5: B2B Updated Expired Tax Exemption | E5: BHUX-33186 | F5: 05. Business Review
A6: Brendan Bagley | B6: Site Support | D6: Enable Editable Email Addresses in the ShipTo | E6: BHUX-34079 | F6: 05. Business Review
A7: Brendan Bagley | B7: B2B Portals | D7: Identify Users via the PunchoutSetupRequest and Give them Limited User-Based Features | E7: BHUX-33409 | F7: 05. Business Review
A8: Brendan Bagley | B8: B2B | D8: Update Punch out Cart to match B2B/B2B cart/checkout | E8: BHUX-33526 | F8: 05. Business Review
A9: Brendan Bagley | B9: B2B | D9: Gradus equivalents in B2B Quotes | E9: BHUX-33797 | F9: Closed as later

Sheet Control (Don’t Touch)
A3: Portfolio | B3: Status | E3: Theme | F3: Description | G3: Measure Adoption | H3: Measure Impact | K3: Event Taxonomy
A4: B2B | B4: 00. Parking Lot | E4: Improve Discovery | F4: OG Find initaitives that Jerel still owns
A5: Used | B5: 01A. Research - Foundational | E5: Increase Trade In Awareness | F5: Surface trade-in as a clear, relevant option at high-intent moments, Order History, PDPs, post-purchase, so customers who own eligible gear know they can trade it in. | G5: Trade-in CTA Impressions (Order History/PDP), CTA Click through rate, % of eligible sessions exposed to CTA | H5: New to trade in quote starts, Quote start rate among CTA exposed users, Assisted trade-in revenue (CTA attributed) | K5: listing_page_clicks
A6: Find | B6: 01. Prod Discovery | E6: Improve Trade In User Flow | F6: Reduce friction in the sell/trade-in submission flow: search, quote, shipping/drop-off, to raise completion and quote-to-conversion rates. | G6: % started quotes completed, Time to quote (median), Post-acceptance ststus engagement rate | H6: Quote-to-accepted-offer rate, Drop-off rate by flow step, sell-flow CSAT (isolated), Support contact rate per quote, Payout cycle time (accepted>paid) | K6: category_page_clicks
B7: 02. UX Req | E7: Increase Trade In Reactivation | F7: Re-engage past customers with unused eligible gear via triggered emails tied to purchase timing and inventory demand signals. | G7: Reactivation email open rate, reactivation email CTR, quote starts attributed to email | H7: Reactivated quote to completion rate, revenue from reactivated sellers, days since last purchase > trade in (trend) | K7: detail_page_clicks
B8: 03. UX Discovery | E8: Increase Buy Used Awareness | F8: Grow discovery of the Used Hub and used inventory through SEO, brand listing pages, and internal linking so more shoppers know B&H sells used gear. | G8: Organic sessions to Used Hub/brand pages, Search impressions & CTR (used pages), Internal link CTR (New>used cross links), Cross-sell CTA impressions (used alt. on New PDP) | H8: New-to-used buyer sessions, Used PDP views per session, Used share to total category traffic, cross sell attributed used PDP views/purchases | K8: header_clicks
B9: 04. UX Design | E9: Improve Buy Used Customer Experience | F9: Make used PDPs and listing pages easier to evaluate, increase condition clarity, provide product photos, and filtering, so shoppers can confidently purchase used gear | G9: PLP filter usage rate, used pdp engagement rate (photo/spec expansion), order status page engagement rate | H9: Used PDP-to-cart rate, Used cart-to-purchase rate, Post-Purchase CSAT (isolated) | K9: mega_menu_clicks
B10: 04A. Research - Design Validation | E10: Increase Buy Used Reactivation | F10: Win back past buyers with relevant used-inventory alerts and win-back offers matched to their purchase history | G10: Win Back email open rate, win-back email CTR, Browse to used PDP rate from email | H10: Repeat used-purchase rate, Revenue from reactivated buyers, Time-since-last-purchase > repurchase (trend) | K10: typeahead_suggestion_clicks
B11: 05. Business Review | E11: Increase B2B Acquisition | K11: footer_clicks
B12: 06. Architecture | E12: Increase The Studio B&H Awareness | K12: home_page_clicks
B13: 07. Grooming | E13: Improve The Studio B&H Customer Experience | K13: nav_drawer_clicks
B14: 08. Ready for Dev | E14: Increase Trust & Condition Transparency | F14: Cross-cutting theme covering whether customers believe the grading/condition information is accurate and complete, ties directly to condition rating scale and PDP condition grouping work, and carries COO-level visibility | K14: cart_page_clicks
B15: 09. In Dev | E15: Improve Search & Findability | F15: Cross-cutting theme spanning sell-side item search (finding what you own to quote it) and buy-side discovery (finding used inventory to purchase). Flagged as the single highest-priority friction point across VoC research on both sides. | K15: checkout_page_clicks
B16: 10. QA | K16: checkout_impression
B17: 11. UAT | K17: login_layer_clicks
B18: 12. Release | K18: profile_menu_clicks
B19: 13. Live | K19: my_account_clicks
K20: order_history_detail_clicks
K21: modify_order_page_clicks
K22: static_pages_clicks
K23: gift_ideas_clicks
K24: leasing_page_clicks
K25: payboo_page_clicks
K26: payboo_sdk_clicks

Sheet Metrics (Don't Touch)
A2: Portfolio | B2: Theme | C2: Metric | D2: Description | E2: Calculation | F2: Why it Matters | G2: Type | H2: Source | I2: Components | K2: Available
A3: Used | B3: Increase Trade In Awareness | C3: Trade-in CTA Impressions (Order History/PDP) | D3: The number of times a trade-in call-to-action (button, banner, or module) was actually rendered and seen through out the site. | E3: Count of CTA element view events, deduped per session. | F3: Impressions are the ceiling on everything downstream. If the CTA isn't being shown, nothing else in this theme can move. | G3: Adoption | H3: GA4 | I3: Homepage Banner, PDP, PLP, My Account
A4: Used | B4: Increase Trade In Awareness | C4: CTA Click through rate | D4: Of the sessions where the CTA was shown, the share that clicked it. | E4: CTA clicks ÷ CTA impressions. | F4: Tells you whether the CTA itself (copy, placement, design) is compelling, independent of how often it's shown. | G4: Adoption | H4: GA4 | I4: Homepage Banner, PDP, PLP, My Account
A5: Used | B5: Increase Trade In Awareness | C5: % of eligible sessions exposed to CTA | D5: Of all sessions where a customer has an eligible order/product (i.e. the CTA logic should have fired), the share that actually saw it. | E5: Sessions with CTA impression ÷ sessions meeting eligibility criteria. | F5: Separates "the CTA doesn't work well" from "the CTA isn't reaching who it should," a targeting/eligibility-logic health check. | G5: Adoption | H5: GA4 | I5: Homepage Banner, PDP, PLP, My Account
A6: Used | B6: Increase Trade In Awareness | C6: New to trade in quote starts | D6: Quote submissions started by customers who have never started a trade-in quote before. | E6: Count of first-ever quote-start events, matched against customer history in the Quote system. | F6: Isolates net-new acquisition from repeat sellers, so the awareness theme is measured on bringing in new sellers, not just repeat activity. | G6: Impact | H6: Quote system | I6: Sell Used Search, My Account Trade In Module, Trade In Page
A7: Used | B7: Increase Trade In Awareness | C7: Quote start rate among CTA exposed users | D7: Of customers exposed to the trade-in CTA, the share who went on to start a quote (not necessarily via the CTA itself, any path). | E7: Quote starts among CTA-exposed users ÷ CTA-exposed users. | F7: The real end-to-end conversion signal for the awareness surface, closer to business outcome than CTR alone. | G7: Impact | H7: GA4 + Quote system
A8: Used | B8: Increase Trade In Awareness | C8: Assisted trade-in revenue (CTA attributed) | D8: Dollar value of inventory acquired through trade-ins where the CTA played a role in the customer's path, even if not the last touch before quoting. | E8: Sum of accepted-quote $ value for quotes with a CTA touchpoint anywhere in the session/journey. | F8: Awareness surfaces often assist rather than directly convert. Last-touch attribution alone would undercount their value. | G8: Impact | H8: GA4 + Finance | I8: Homepage Banner, PDP, PLP, My Account
A9: Used | B9: Increase Trade In Awareness | C9: Cross-sell CTA impressions (New PDP / brand pages) | D9: Impressions of a trade-in prompt shown while a customer is browsing new (not used) gear, e.g. "have an old one? trade it in." | E9: Count of CTA view events on New PDP / brand pages, deduped per session. | F9: This is a different acquisition channel than Order History awareness. It reaches people who haven't bought from B&H recently. | G9: Adoption | H9: GA4 | I9: New PDP Trade In Your Gear
A10: Used | B10: Increase Trade In Awareness | C10: Cross-sell-attributed quote starts | D10: Quote starts that can be traced back to the cross-sell CTA shown on New PDP/brand pages. | E10: Quote-start events with a cross-sell CTA touchpoint in the preceding session(s). | F10: Tests whether pulling people out of the New funnel into trade-in actually works as an acquisition channel, distinct from Order History awareness. | G10: Impact | H10: GA4 + Quote system | I10: New PDP Trade In Your Gear
A11: Used | B11: Improve Trade In User Flow | C11: % started quotes completed | D11: Of all quote flows a customer started (searched/selected at least one item), the share that reached a final submitted quote. | E11: Completed quote submissions ÷ quote flows started. | F11: The single clearest signal of overall flow friction, the headline number for this theme. | G11: Adoption | H11: Quote system
A12: Used | B12: Improve Trade In User Flow | C12: Time to quote (median) | D12: How long it takes a customer to go from starting the flow to receiving a quote value, at the midpoint of the distribution. | E12: Median of (quote-received timestamp − flow-start timestamp) across completed quotes. | F12: Slow quoting is a known drop-off driver; median avoids a few slow outliers skewing the picture. | G12: Adoption | H12: Quote system
A13: Used | B13: Improve Trade In User Flow | C13: Post-acceptance status engagement rate | D13: Of customers who accepted a quote, the share who opened a status update (email or status page) about shipping/payout progress. | E13: Unique opens/views of post-acceptance status content ÷ accepted quotes. | F13: Checks whether status communications meant to reduce post-acceptance uncertainty are actually being read. | G13: Adoption | H13: ESP + GA4 | I13: Email Shipping Email, Trade in Quote Notification
A14: Used | B14: Improve Trade In User Flow | C14: Quote-to-accepted-offer rate | D14: Of quotes issued to customers, the share the customer actually accepted. | E14: Accepted quotes ÷ quotes issued. | F14: Distinguishes "the flow works but the price is wrong" (low acceptance) from "the flow itself is broken" (low completion, above). | G14: Impact | H14: Quote system | I14: Email CTA
A15: Used | B15: Improve Trade In User Flow | C15: Drop-off rate by flow step | D15: The percentage of customers who exit at each individual step of the sell flow (e.g. item search, condition selection, shipping info). | E15: (Users entering step − users entering next step) ÷ users entering step, per step. | F15: Pinpoints exactly where in the flow friction is worst, so fixes can be targeted rather than guessed at. | G15: Impact | H15: GA4 | I15: Sell Used Search Box, Sell Used Type Ahead, Sell Used Listing Page, Sell Used Detail Page, Sell Used Review Page
A16: Used | B16: Improve Trade In User Flow | C16: Sell-flow CSAT (isolated) | D16: Customer satisfaction score from a survey specifically scoped to the sell/trade-in flow, kept separate from site-wide CSAT. | E16: Medallia CSAT question average/top-box %, filtered to sell-flow survey instance. | F16: Site-wide CSAT would dilute sell-flow-specific pain; isolating it makes the score actionable for this theme. | G16: Impact | H16: Medallia
A17: Used | B17: Improve Trade In User Flow | C17: Support contact rate per quote | D17: How often a customer contacts support (chat, phone, email) in connection with a given quote. | E17: Support tickets tagged to a quote ID ÷ total quotes. | F17: A proxy for hidden friction. High contact rates mean customers can't self-serve through confusion or problems in the flow. | G17: Impact | H17: Support / CRM
A18: Used | B18: Improve Trade In User Flow | C18: Payout cycle time (accepted>paid) | D18: Time elapsed from a customer accepting a quote to the payout actually being issued. | E18: Payout-issued timestamp − quote-accepted timestamp, median across accepted quotes. | F18: Payout speed is a top driver of seller trust and repeat behavior. | G18: Impact | H18: Finance + WMS
A19: Used | B19: Increase Trade In Reactivation | C19: Reactivation email open rate | D19: Share of sent trade-in reactivation emails that were opened. | E19: Unique opens ÷ emails delivered. | F19: The first checkpoint. If subject lines/targeting aren't landing, nothing downstream can work. | G19: Adoption | H19: ESP | I19: Trade in email
A20: Used | B20: Increase Trade In Reactivation | C20: Reactivation email CTR | D20: Share of sent reactivation emails that resulted in a click. | E20: Unique clicks ÷ emails delivered (or ÷ opens, for click-to-open rate). | F20: Tests whether the email content/offer itself is compelling once someone opens it. | G20: Adoption | H20: ESP | I20: Used Email, Used Email CTA
A21: Used | B21: Increase Trade In Reactivation | C21: Quote starts attributed to email | D21: Quote flows started by a customer within a defined attribution window after clicking a reactivation email. | E21: Quote-start events with a reactivation-email click in the prior N days (window TBD). | F21: Bridges "they clicked" to "they actually engaged with the trade-in flow." | G21: Adoption | H21: ESP + Quote system
A22: Used | B22: Increase Trade In Reactivation | C22: Reactivated quote to completion rate | D22: Of quotes started via reactivation email, the share that reach a completed/accepted quote. | E22: Completed quotes (email-attributed) ÷ quote starts (email-attributed). | F22: Checks whether reactivated sellers behave differently than new/organic sellers once in the flow. | G22: Impact | H22: Quote system
A23: Used | B23: Increase Trade In Reactivation | C23: Revenue from reactivated sellers | D23: Total $ value of inventory acquired from customers reactivated via this campaign. | E23: Sum of accepted-quote $ value for email-attributed reactivated sellers. | F23: The bottom-line business case for continuing to invest in reactivation campaigns. | G23: Impact | H23: Finance + Quote system
A24: Used | B24: Increase Trade In Reactivation | C24: Days since last purchase > trade in (trend) | D24: How long, on average, it takes a past purchaser to trade in gear after their last purchase, tracked as a trend over time. | E24: Trade-in date − most recent prior purchase date, averaged/median across reactivated sellers, tracked quarter over quarter. | F24: If this trend is shortening, it suggests the timing/targeting logic behind the campaign triggers is improving. | G24: Impact | H24: CRM
A25: Used | B25: Increase Buy Used Awareness | C25: Organic sessions to Used Hub/brand pages | D25: Sessions landing on Used Hub or used brand listing pages via unpaid search. | E25: GA4 sessions filtered to organic-search channel + landing page = Used Hub/brand pages. | F25: The core SEO health signal for the whole awareness theme, a direct read on whether the hybrid listing-page architecture is working. | G25: Adoption | H25: GA4 | I25: Used Hub, Used Brand Listing Page
A26: Used | B26: Increase Buy Used Awareness | C26: Search impressions & CTR (used pages) | D26: How often used pages show up in Google search results, and what share of those impressions turn into a click. | E26: Pulled directly from Google Search Console, filtered to used-page URLs. | F26: A leading indicator ahead of organic sessions, showing whether pages are being surfaced/ranked before traffic shows up. | G26: Adoption | H26: Google Search Console
A27: Used | B27: Increase Buy Used Awareness | C27: Internal link CTR (New>used cross links) | D27: Click-through rate on links that point from new-gear pages (e.g. brand pages owned by Sammy) into used inventory. | E27: Clicks on internal used-links ÷ impressions of those links. | F27: Internal linking is both an SEO signal and a direct discovery channel. This checks it's actually being used. | G27: Adoption | H27: GA4 | I27: New PDP, Used PDP
A28: Used | B28: Increase Buy Used Awareness | C28: Cross-sell CTA impressions (used alt. on New PDP) | D28: Impressions of a "used alternative available" prompt shown on a new-gear product page. | E28: Count of CTA view events on New PDPs, deduped per session. | F28: Catches price-sensitive shoppers already in a New PDP session, a distinct discovery channel from search/SEO. | G28: Adoption | H28: GA4
A29: Used | B29: Increase Buy Used Awareness | C29: New-to-used buyer sessions | D29: Sessions from customers who have never viewed or purchased a used product before. | E29: Sessions with a used PDP view, matched against customer history for first-time-used flag. | F29: Awareness should be judged on growing the used buyer base, not just increasing traffic from existing used shoppers. | G29: Impact | H29: GA4
A30: Used | B30: Increase Buy Used Awareness | C30: Used PDP views per session | D30: Average number of used product pages viewed within a single session. | E30: Total used PDP views ÷ total sessions with at least one used PDP view. | F30: A rough proxy for browsing depth/engagement once a shopper lands in the used ecosystem. | G30: Impact | H30: GA4
A31: Used | B31: Increase Buy Used Awareness | C31: Used share to total category traffic | D31: Used PDP/category traffic as a percentage of all traffic (new + used) to the same product categories. | E31: Used-category sessions ÷ (used + new-category sessions), by category. | F31: Shows whether used is growing its footprint relative to new, not just growing alongside site-wide traffic. | G31: Impact | H31: GA4 | I31: Used PDP, Used Category Landing Page, Used Category Listing Page, New PDP, New Category Landing Page, New Category Listing Page
A32: Used | B32: Increase Buy Used Awareness | C32: Cross sell attributed used PDP views/purchases | D32: Used PDP views or purchases that followed a cross-sell CTA click on a New PDP. | E32: Used PDP views/purchases with a cross-sell CTA touchpoint in the preceding session(s). | F32: Validates whether the New→Used cross-sell mechanism is actually converting, not just generating impressions. | G32: Impact | H32: GA4 | I32: Used PDP, Used Check Out?, New Product Card Used From
A33: Used | B33: Improve Buy Used Customer Experience | C33: PLP filter usage rate | D33: Share of used listing-page sessions where a customer applies at least one filter (price, brand, condition, etc.). | E33: Sessions with a filter-applied event ÷ used PLP sessions. | F33: Low usage can mean filters aren't helpful/discoverable; high usage with low downstream conversion can flag a filter/inventory mismatch. | G33: Adoption | H33: GA4 | I33: Used PLP, Used SRP, Used Filter
A34: Used | B34: Improve Buy Used Customer Experience | C34: Used PDP engagement rate (photo/spec expansion) | D34: Share of used PDP sessions where a customer interacts with photos (zoom/gallery) or expands spec/condition detail sections. | E34: Sessions with photo-interaction or spec-expansion events ÷ used PDP sessions. | F34: A proxy for how much evaluation effort shoppers are putting in, tied directly to the photography and condition-clarity investments underway. | G34: Adoption | H34: GA4
A35: Used | B35: Improve Buy Used Customer Experience | C35: Order status page engagement rate | D35: Share of used-order customers who view their order status page after purchase. | E35: Unique order-status-page views ÷ used orders placed. | F35: Post-purchase visibility affects trust and support load, mirroring the post-acceptance metric on the sell side. | G35: Adoption | H35: GA4 | I35: My Orders
A36: Used | B36: Improve Buy Used Customer Experience | C36: Used PDP-to-cart rate | D36: Share of used PDP sessions that result in an add-to-cart. | E36: Add-to-cart events on used PDPs ÷ used PDP sessions. | F36: The core "does the PDP convince the shopper" metric, most sensitive to condition clarity and photography quality. | G36: Impact | H36: GA4 | I36: Used PDP, Used PDP CTA
A37: Used | B37: Improve Buy Used Customer Experience | C37: Used cart-to-purchase rate | D37: Share of used add-to-cart events that result in a completed purchase. | E37: Used purchases ÷ used add-to-cart events. | F37: Isolates checkout-stage friction from PDP-stage persuasion, since the two have different fixes. | G37: Impact | H37: GA4 | I37: Used PDP, Used PDP CTA, Used PLP, Used PLP CTA
A38: Used | B38: Improve Buy Used Customer Experience | C38: Post-Purchase CSAT (isolated) | D38: Customer satisfaction score from a survey scoped specifically to the used buying experience after delivery. | E38: Medallia CSAT average/top-box %, filtered to used post-purchase survey instance. | F38: Captures whether the product matched expectations set on the PDP, the buy-side counterpart to sell-flow CSAT. | G38: Impact | H38: Medallia | I38: Medallia Survey
A39: Used | B39: Increase Buy Used Reactivation | C39: Win-Back email open rate | D39: Share of sent win-back emails that were opened. | E39: Unique opens ÷ emails delivered. | F39: Same logic as trade-in reactivation, the entry checkpoint for the whole campaign. | G39: Adoption | H39: ESP
A40: Used | B40: Increase Buy Used Reactivation | C40: Win-back email CTR | D40: Share of sent win-back emails that resulted in a click. | E40: Unique clicks ÷ emails delivered (or ÷ opens for click-to-open). | F40: Tests whether the specific inventory/offer surfaced in the email is relevant enough to act on. | G40: Adoption | H40: ESP | I40: Email CTA
A41: Used | B41: Increase Buy Used Reactivation | C41: Browse to used PDP rate from email | D41: Of customers who clicked into the site from a win-back email, the share who viewed a used PDP during that session. | E41: Sessions with used PDP view ÷ sessions originating from win-back email click. | F41: Confirms the email is routing people to relevant used inventory, not just generic site traffic. | G41: Adoption | H41: GA4 + ESP | I41: Email CTA, Used PDP
A42: Used | B42: Increase Buy Used Reactivation | C42: Repeat used-purchase rate | D42: Of past used buyers targeted by win-back campaigns, the share who complete another used purchase. | E42: Repeat used purchases (email-attributed) ÷ past used buyers targeted. | F42: The core outcome metric for this theme: did the campaign actually bring buyers back. | G42: Impact | H42: Order system
A43: Used | B43: Increase Buy Used Reactivation | C43: Revenue from reactivated buyers | D43: Total $ revenue from purchases made by win-back-campaign-attributed customers. | E43: Sum of order value for email-attributed repeat purchases. | F43: The bottom-line business case, mirroring "Revenue from reactivated sellers" on the sell side. | G43: Impact | H43: Finance + Order system
A44: Used | B44: Increase Buy Used Reactivation | C44: Time-since-last-purchase > repurchase (trend) | D44: How long, on average, it takes a past buyer to make another used purchase after being targeted, tracked as a trend over time. | E44: Repurchase date − most recent prior purchase date, averaged/median, tracked quarter over quarter. | F44: A shortening trend suggests campaign timing/targeting is getting more effective at catching buyers when they're ready. | G44: Impact | H44: CRM
A45: Used | B45: Search & Findability | C45: Sell-item search success rate (Solr) | D45: Share of sell-flow item searches where the customer found and selected their item (vs. abandoning or falling back to manual entry). | E45: Searches ending in item selection ÷ total sell-flow searches. | F45: Search friction is the #1 flagged issue in VoC research for the sell side specifically. This is the direct health check on it. | G45: Adoption | H45: Solr logs | I45: Sell Used Search Box, Sell Used Type Ahead, Sell Used Listing Page
A46: Used | B46: Search & Findability | C46: Used PLP/search zero-result rate | D46: Share of used-inventory searches that return no results. | E46: Zero-result searches ÷ total used-inventory searches. | F46: A hard failure signal. Every zero-result search is a shopper who couldn't find anything, regardless of whether inventory actually existed. | G46: Adoption | H46: Solr logs | I46: Site Search, Used Site Search
A47: Used | B47: Search & Findability | C47: Used search-to-click rate | D47: Share of used-inventory searches where the customer clicked a result. | E47: Searches with a result click ÷ total used-inventory searches. | F47: Distinguishes "no results" failures from "results shown but not relevant/appealing" failures. | G47: Adoption | H47: GA4 | I47: Site Search, Used Site Search, Used Product Card
A48: Used | B48: Search & Findability | C48: Search-originated quote starts (sell side) | D48: Quote starts that began with a successful sell-flow search. | E48: Quote starts preceded by a search-with-selection event. | F48: Connects search quality directly to the acquisition funnel, not just to search-specific metrics. | G48: Impact | H48: Solr logs + Quote system | I48: Sell Used Serach
A49: Used | B49: Search & Findability | C49: Search-originated used purchases (buy side) | D49: Used purchases that began with a used-inventory search (as opposed to browsing/category navigation). | E49: Purchases preceded by a used search-with-click event in the same session. | F49: Shows how much revenue depends on search working well, making the business case for search investment concrete. | G49: Impact | H49: GA4 | I49: Site Search, Used Site Search
A50: Used | B50: Search & Findability | C50: Search abandonment rate | D50: Share of search sessions (sell or buy) where the customer leaves the site shortly after searching, without further engagement. | E50: Sessions ending within N actions of a search event ÷ total search sessions. | F50: The most direct "we lost them" signal. A search that doesn't even get a follow-up click or scroll is a clear failure. | G50: Impact | H50: GA4 + Solr logs | I50: Site Search, Used Site Search, Sell Used Search
A51: Used | B51: Trust & Condition Transparency | C51: Condition-tab view rate | D51: Share of used PDP sessions where the customer opens/expands the condition detail tab or section. | E51: Sessions with condition-tab-expand event ÷ used PDP sessions. | F51: Shows how much shoppers are actively seeking out condition information, the core evaluation input for a used purchase. | G51: Adoption | H51: GA4 | I51: PDP Condition Rating Link, PDP Condition Rating Tray
A52: Used | B52: Trust & Condition Transparency | C52: Condition rating comprehension (usability test pass rate) | D52: In moderated or unmoderated usability testing, the share of participants who correctly interpret what a given condition rating (e.g. "Good," "Excellent") means for the product they're evaluating. | E52: Correct interpretations ÷ total test participants, per study. | F52: Adoption metrics from analytics can't tell you if customers actually understand the rating scale. This is the qualitative check that they do, tied directly to the new five-tier scale rollout. | G52: Adoption | H52: Research / usability testing
A53: Used | B53: Trust & Condition Transparency | C53: "Not as described" return rate | D53: Share of used-order returns where the customer's stated reason is that the item didn't match its condition description. | E53: Returns coded "not as described" ÷ total used orders. | F53: The clearest hard evidence of a trust failure. A rising rate means the condition info shown isn't matching what customers receive. | G53: Impact | H53: Returns / CRM
A54: Used | B54: Trust & Condition Transparency | C54: Medallia condition-satisfaction / trust score | D54: Survey-based score measuring how satisfied/confident customers felt about the accuracy of condition information before and after receiving their item. | E54: Medallia average/top-box % on the condition-trust survey question(s). | F54: A softer, earlier-warning companion to the return-rate metric, capturing dissatisfaction even among customers who keep the item. | G54: Impact | H54: Medallia
A55: Used | B55: Trust & Condition Transparency | C55: Grading accuracy / consistency (QA re-grade audit) | D55: How often an independent re-grade of a sampled item matches the original evaluator's condition grade. | E55: Re-grades matching original grade ÷ total items re-graded in the audit sample. | F55: Traces trust problems back to their root cause, inaccurate grading upstream, rather than just a PDP/description-clarity issue. | G55: Impact | H55: DES eval + QA audit

Sheet GA4 (Don't Touch)
B2: Product_Type | C2: Element | D2: component type | E2: eventName | F2: component_GA4 | G2: label | H2: label_value | I2: site_type | J2: page_type | K2: Trigger & Other Parameters | L2: Flag
B3: N/A | D3: Page Load | E3: page_view | F3: — | G3: — | H3: — | I3: Desktop | J3: productList | K3: Initial render and every filter/sort/paging change (pushState)content_group: productList · site_langauge: E · bi: NoValue · pwa_source: NoValue · bh_user_id · category_page_id: 9811 | L3: observed
B4: N/A | D4: Page Load | E4: view_item_list | F4: — | G4: — | H4: — | I4: Desktop | J4: productList | K4: Results grid rendered — 28 items in one senditems[]: item_id, item_code, item_list_name, index, sales_comment · position_index: 1 | L4: observed
B5: N/A | D5: Page Load | E5: view_item_list | F5: — | G5: — | H5: — | I5: absent | J5: absent | K5: Google Ads remarketing duplicate — separate send, not the GA4 propertysend_to: google_ads · ecomm_pagetype: productList · ecomm_prodid[] · tag: AW-1056059933 | L5: by design
B6: N/A | D6: Page Load | E6: view_promotion | F6: — | G6: — | H6: — | I6: Desktop | J6: productList | K6: Hero banner impression — the Nikon trade-in unitcreative_name: IO Image Banner · creative_slot: HERO · promotion_name: 3385025 - BHUX 35089 Nikon Z6III Listing Page · promotion_url: /a/trade-in/64435 | L6: observed
B7: N/A | D7: Page Load | E7: view_promotion | F7: — | G7: — | H7: — | I7: Desktop | J7: productList | K7: Sponsored carousel — one event per slotcreative_name: spotfront list item · creative_slot: TOP · promotion_position: 1, 2, 3 · promotion_id (uuid) · promotion_url | L7: observed
B8: N/A | D8: Page Load | E8: view_promotion | F8: — | G8: — | H8: — | I8: Desktop | J8: productList | K8: Email slide-out and mega-menu banner impressionscreative_name: Email Slideout Signup / IO Banner · creative_slot: SLIDER / Top Nav · promotion_id: ESS | L8: observed
B9: New | C9: Homepage Banner | D9: Banner | E9: select_promotion
B10: New | C10: Top Nav | D10: Navigation | E10: mega_menu_clicks | F10: Top Nav | G10: Computers | H10: — | I10: Desktop | J10: category
B11: New | C11: New Mega Menu | D11: Navigation - Mega Menu | E11: mega_menu_clicks | F11: Pro Audio menu | G11: Live sound | H11: —
B12: New | C12: New Site Search Box | D12: Search | E12: header_clicks | F12: Search | G12: Enter Search | I12: Desktop | J12: home
B13: New | C13: New Site Search Type Ahead | D13: Search | E13: typeahead_suggestion_clicks | F13: Typeahead Suggestions | G13: — | H13: — | I13: — | J13: —
B14: New | C14: New Item Category Listing Page | D14: PLP | I14: Desktop | J14: productList
B15: New | C15: New Item Category Listing Page Product Card Used From CTA | D15: CTA | I15: Desktop | J15: productList
B16: N/A | C16: New Item Category Listing Page | D16: Refinements | E16: listing_page_clicks | F16: Filters | G16: — | H16: — | I16: Desktop | J16: productList | K16: Left-rail facet checkboxfilter_value: Full Frame (35mm) · filter_section: Sensor Size · filter_n_value: fct_sensor-size_3087 · from: left refinements | L16: observed
B17: N/A | C17: New Item Category Listing Page | D17: Refinements | E17: listing_page_clicks | F17: Filters | G17: — | H17: — | I17: Desktop | J17: productList | K17: Left-rail Categories link (Mirrorless Cameras)filter_value: "undefined" · filter_section: Category · filter_n_value: Mirrorless Cameras · from: "undefined" | L17: F1
B18: N/A | C18: New Item Category Listing Page | D18: Refinements | E18: listing_page_clicks | F18: Filter Labels | G18: Still Image Resolution | H18: — | I18: Desktop | J18: productList | K18: Facet accordion expand/collapse — label carries the section name | L18: observed
B19: N/A | C19: New Item Category Listing Page | D19: Refinements | E19: listing_page_clicks | F19: Listing See All Info | G19: left refinements | H19: — | I19: Desktop | J19: productList | K19: "See all + 10" opens the full-facet modal — label carries placement, not which facet | L19: F3
B20: N/A | C20: New Item Category Listing Page | D20: Refinements | E20: listing_page_clicks | F20: Listing See All Modal | G20: Clear All | H20: — | I20: Desktop | J20: productList | K20: Clear All inside the modal — the only modal control that emits anything | L20: F2
B21: N/A | C21: New Item Category Listing Page | D21: Listing Controls | E21: listing_page_clicks | F21: Sort By | G21: "" (empty) | H21: — | I21: Desktop | J21: productList | K21: Opening the sort dropdown — fires with an empty label before any choice is made | L21: F4
B22: N/A | C22: New Item Category Listing Page | D22: Listing Controls | E22: listing_page_clicks | F22: Sort By | G22: PRICE_LOW_TO_HIGH | H22: — | I22: Desktop | J22: productList | K22: Sort selected — label is the enum, not the visible "Price: Low to High" | L22: observed
B23: N/A | C23: New Item Category Listing Page | D23: Listing Controls | E23: listing_page_clicks | F23: View | G23: Grid View · List View | H23: — | I23: Desktop | J23: productList | K23: Grid/list density toggle | L23: observed
B24: N/A | C24: New Item Category Listing Page | D24: Listing Controls | E24: listing_page_clicks | F24: Paging | G24: page 2 | H24: — | I24: Desktop | J24: productList | K24: Pagination control — label is the literal "page " prefix plus the number | L24: observed
B25: New | D25: Product Title | E25: select_item | F25: Item List | G25: — | H25: — | I25: Desktop | J25: productList | K25: Product title click — GA4 ecommerce event, not a listing_page_clicksitems: [{ item_id }] · section_path: Category | L25: observed
B26: New | C26: New Item Category Listing Page Product Card | D26: Product Title | E26: listing_page_clicks | F26: Other Buying Options | G26: Used | H26: 1910936-REG | I26: Desktop | J26: productList | K26: "Used for $39.95" link on a tile — the only component on this page that populates label_valuesection_path: Category · label = buying-option type · label_value = SKU | L26: observed
B27: New | C27: New Item Category Listing Page Product Card | D27: Product Title | E27: listing_page_clicks | F27: Show More | G27: — | H27: — | I27: Desktop | J27: productList | K27: Expanding a tile's Key Featuressection_path: Category — no item_id, so it cannot be tied to a product | L27: F5
B28: New | C28: New Item Category Listing Page Product Card | D28: Product Title | E28: listing_page_clicks | F28: Add to Compare | G28: — | H28: — | I28: Desktop | J28: productList | K28: Compare checkbox on a tile — no label, no item identifier | L28: F5
B29: New | D29: Promo & Navigation | E29: select_promotion | F29: — | G29: — | H29: — | I29: Desktop | J29: productList | K29: Hero banner click — mirrors the view_promotion paramscreative_name: IO Image Banner · creative_slot: HERO · promotion_url: /a/trade-in/64435 | L29: observed
B30: New | D30: Promo & Navigation | E30: breadcrumbs | F30: Breadcrumb | G30: — | H30: — | I30: Desktop | J30: productList | K30: Breadcrumb link clickbreadcrumbs: Photography — destination in its own param rather than label | L30: observed
B31: New | C31: New Item Category Landing Page | D31: Navigation into the Catalog | E31: category_page_clicks | F31: Category Groups | G31: Cameras & Lenses | H31: Digital Cameras | I31: Desktop | J31: category | K31: Category tile — label is the section, label_value the destinationcategory_page_id: 989 | L31: model
B32: New | C32: New Item Category Landing Page | D32: Navigation into the Catalog | E32: category_page_clicks | F32: Category Groups | G32: Accessories | H32: Lens Accessories | I32: Desktop | J32: category | K32: Same component, second section — the convention holds across the page | L32: model
B33: New | C33: New Item Category Landing Page | D33: Navigation into the Catalog | E33: category_page_clicks | F33: Category Groups | G33: Applications | H33: Portrait Photography | I33: Desktop | J33: category | K33: The "What would you like to shoot?" rail — reports under its internal key, Applicationsthe only section whose label doesn't match its visible heading | L33: C3
B34: New | C34: New Item Category Landing Page | D34: Content & Banners | E34: category_page_clicks | F34: Explora banner | G34: Venus Optics Delivers Two New Ultra-Macro Laowa Lenses | H34: — | I34: Desktop | J34: category | K34: Editorial rail — label carries the full article title, so content performance is readable | L34: observed
B35: New | C35: New Item Category Landing Page | D35: Content & Banners | E35: category_page_clicks | F35: Category Banner | G35: — | H35: — | I35: Desktop | J35: category | K35: The Hasselblad "Learn More" unit — no label, so which brand banner was clicked is unknowable | L35: C2
B36: New | C36: New Item Category Landing Page | D36: Content & Banners | E36: category_page_clicks | F36: chatBanner | G36: — | H36: — | I36: Desktop | J36: category | K36: "Video Chat with a Photography Expert" strip — opens the chat widget, sends nothing about which expert path | L36: C2
B37: New | C37: New Item Category Landing Page | D37: Content & Banners | E37: category_page_clicks | F37: SEO Text | G37: Show More | H37: — | I37: Desktop | J37: category | K37: Expanding the bottom copy block — same component and label as on the listing page | L37: observed
B38: New | C38: New Item Category Landing Page | D38: Promo & Exits | E38: select_promotion | F38: — | G38: — | H38: — | I38: Desktop | J38: category | K38: Trade-in banner clicked — mirrors its impression event exactly, same promotion_idcreative_slot: TOP · promotion_url: /a/trade-in/64435 | L38: observed
B39: New | C39: New Item Category Landing Page | D39: Promo & Exits | E39: select_promotion | F39: — | G39: — | H39: — | I39: Desktop | J39: category | K39: Spotfront product rail item clicked — impression and click share promotion_id and promotion_position, so slot-level CTR is directly computable | L39: observed
B40: New | C40: New Item Category Landing Page | D40: Promo & Exits | E40: footer_clicks | F40: Trade in Your Gear | G40: — | H40: — | I40: Desktop | J40: category | K40: Footer trade-in link — a different event family from the banner above it, same destination | L40: C5
B41: N/A | C41: PDP | E41: view_item | F41: — | G41: — | H41: — | I41: Desktop | J41: productDetail | K41: Product rendered — the richest payload on the page, and still condition-blindcurrency: USD · value: 2136.95 · items: [{ item_id: 803528607-USE, item_code: 3528607, price: 2136.95, stock_status: IN_STOCK, shipping_message: FREE_ONE_DAY_DELIVERY, store_pickup_message: AVAILABLE_IN_PICKUP_TIME }] | L41: U1 U5
B42: N/A | C42: PDP | E42: view_item | F42: — | G42: — | H42: — | I42: absent | J42: absent | K42: Google Ads remarketing — this one knows it's usedecomm_pcat: ["BH Photo", "Used Department", "Photography", "Point & Shoot Cameras", "Sony RX10 V"] · ecomm_prodid: 803528607-USE · ecomm_totalvalue: 2136.95 | L42: U1
B43: N/A | C43: PDP | E43: page_view | F43: — | G43: — | H43: — | I43: Desktop | J43: productDetail | K43: Page load — content_group also productDetail, so neither dimension separates used from newsite_langauge: E · bi: NoValue · pwa_source: NoValue · bh_user_id: id_NoValue | L43: U1
B44: N/A | C44: PDP | E44: view_promotion | F44: — | G44: — | H44: — | I44: Desktop | J44: productDetail | K44: Overview banner (an Explora article on this camera) and the email slide-outcreative_slot: Overview Banner / SLIDER · promotion_name · detail_page_sku | L44: observed
B45: Used | C45: Used PDP | D45: Used Specific Interaction | E45: detail_page_clicks | F45: Used Item Condition | G45: — | H45: — | I45: Desktop | J45: productDetail | K45: "Condition: 9 Minor surface marks" → opens the B&H Used Equipment Rating System drawerdetail_page_sku only — the grade the shopper just clicked on is not sent | L45: U2
B46: Used | C46: Used PDP | D46: Used Specific Interaction | E46: detail_page_clicks | F46: Other Buying Options | G46: New | H46: — | I46: Desktop | J46: productDetail | K46: "New for $2,298.00" — the used → new switchno label_value, though the same component on the listing page sends the SKU there | L46: U4
B47: Used | C47: Used PDP | D47: Used Specific Interaction | E47: detail_page_clicks | F47: Trade In - Learn More | G47: — | H47: — | I47: Desktop | J47: productDetail | K47: "Trade in your gear for cash — Get Started" — present and tagged on used PDPs exactly as on new onesdetail_page_sku | L47: observed
B48: Used | C48: Used PDP | D48: Used Specific Interaction | E48: breadcrumbs | F48: Breadcrumb | G48: — | H48: — | I48: Desktop | J48: productDetail | K48: Breadcrumb click — the one place "Used Department" reaches GA4 as a valuebreadcrumbs: "Used Department" · only fires if someone actually clicks it | L48: U6
B49: N/A | C49: PDP | D49: Generic PDP Furniture | E49: detail_page_clicks | F49: searchDropdown | G49: — | H49: — | I49: Desktop | J49: productDetail | K49: The header search scope selector, which is pre-set to "Used" on this page — but the event doesn't say which scope was chosen | L49: U2
B50: N/A | C50: PDP | D50: Generic PDP Furniture | E50: detail_page_clicks | F50: Add to Compare | G50: — | H50: — | I50: Desktop | J50: productDetail | K50: Compare checkbox — carries the SKU here, unlike its listing-page counterpart, which carries nothing | L50: observed
B51: N/A | C51: PDP | D51: Generic PDP Furniture | E51: detail_page_clicks | F51: Tab Navigation | G51: Specs · Reviews · Q&A | H51: — | I51: Desktop | J51: productDetail | K51: Content tabs — not exercised on this page; carried over from the new-PDP audit, where label carried the tab namedetail_page_sku | L51: new PDP
B52: N/A | C52: PDP | D52: Generic PDP Furniture | E52: — | F52: — | G52: — | H52: — | I52: — | J52: — | K52: No event: Share · Print · the "Used Savings $161.05" figure · the "Warranty: B&H 90 Days" line · the 90-Second Intro video badge | L52: U7
B53: New | C53: New Item PDP Trade In Your Gear CTA
B54: N/A | C54: Cart
B55: N/A | C55: Check Out
B56: N/A | C56: My Account | E56: category_page_clicks
B57: Used | C57: Used Hub | D57: Landing Page
B58: Used | C58: Used Hub Switcher
B59: Used | C59: Used Hub Category Navigation
B60: Used | C60: Used Hub See Our Rating System | D60: Link
B61: Used | C61: Used Hub Visit Our Used Dept FAQ For Further Details | D61: Link
B62: Used | C62: Used Hub 90 Days Parts And Labor Warranty See Details | D62: Link
B63: Used | C63: Used Hub Free Shipping See Details | D63: Link
B64: Used | C64: Used Hub Sell Your Gear in 3 Easy Steps Video | D64: Video
B65: Used | C65: Used Hub NYC SuperStore | D65: Link
B66: Used | C66: Used Hub Get Started Online CTA | D66: CTA
B67: Used | C67: Used Hub Customer Reviews | D67: Carousel
B68: Used | C68: Used Hub FAQ Search
B69: Used | C69: Used Hub FAQ Title
B70: Used | C70: Used Hub FAQ Description
B71: Used | C71: Used Hub FAQ See All
B72: Used | C72: Used Hub Address
B73: Used | C73: Used Hub Phone Number
B74: Used | C74: Footer Trade In Your Gear | D74: Link
B75: Used | C75: Used Top Nav
B76: Used | C76: Used Mega Menu
B77: Used | C77: Used Mega Menu Category | D77: Mega Menu Category
B78: Used | C78: Used Mega Menu Sell Your Gear | D78: Link
B79: Used | C79: Used Site Search Box | D79: Search Field
B80: Used | C80: Used Site Search Type Ahead | D80: Search Field Type Ahead
B81: Used | C81: Used Category Landing Page | D81: PLP
B82: Used | C82: Used Category Listing Page | D82: PLP
B83: Used | C83: Used Category Listing Page Filter
B84: Used
B85: Used | C85: Used Category Listing Page Product Card | D85: Product Card
B86: Used | C86: Used Category Listing Page Product Card Used From CTA | D86: CTA
B87: Used | C87: Used PDP | D87: PDP
B88: Used | C88: Used Brand Listing Page | D88: PLP
B89: Used | C89: Trade In Page
B90: Used | C90: Sell Used Landing Page
B91: Used | C91: Sell Used Search Box
B92: Used | C92: Sell Used Detail Page
B93: Used | C93: Sell Used Review Page
B94: Used | C94: Sell Used Listing Page
B95: Used | C95: Used Category Landing Page
B96: Used | C96: Used Category Listing Page
B97: N/A | C97: My Account Trade In Module

Sheet Roadmap 26-27 (Don't Touch)

Sheet Roadmap (Auto)
A1: 2026–2027 Product Roadmap — Swim Lanes by Theme
A2: Legend: | B2: Deliverables, themes and UX dates come from the Weekly tab · dev sprints from the Initiative Tracker | I2: U | J2: UX / design (Weekly) | O2: D | P2: Dev sprint (Tracker) | U2: B | V2: Both, same month | AA2: Amber column = current month
I3: 46023 | J3: 46054 | K3: 46082 | L3: 46113 | M3: 46143 | N3: 46174 | O3: 46204 | P3: 46235 | Q3: 46266 | R3: 46296 | S3: 46327 | T3: 46357 | U3: 46388 | V3: 46419 | W3: 46447 | X3: 46478 | Y3: 46508 | Z3: 46539 | AA3: 46569 | AB3: 46600 | AC3: 46631 | AD3: 46661 | AE3: 46692 | AF3: 46722
I4: 2026 | U4: 2027
I5: Q1 | L5: Q2 | O5: Q3 | R5: Q4 | U5: Q1 | X5: Q2 | AA5: Q3 | AD5: Q4
A6: Theme (swim lane) | B6: Deliverable | C6: Jira | D6: Status | E6: UX Start | F6: UX End | G6: Dev Start | H6: Dev End | I6: Jan | J6: Feb | K6: Mar | L6: Apr | M6: May | N6: Jun | O6: Jul | P6: Aug | Q6: Sep | R6: Oct | S6: Nov | T6: Dec | U6: Jan | V6: Feb | W6: Mar | X6: Apr | Y6: May | Z6: Jun | AA6: Jul | AB6: Aug | AC6: Sep | AD6: Oct | AE6: Nov | AF6: Dec | AG6: _theme | AH6: _row
A7: =IF($AH7="","",IF($AG7=$AG6,"",$AG7)) | B7: =IF($AH7="","",INDEX('Roadmap Calc (Don’t Touch)'!$B$2:$B$205,$AH7)) | C7: =IF($AH7="","",INDEX('Roadmap Calc (Don’t Touch)'!$E$2:$E$205,$AH7)) | D7: =IF($AH7="","",INDEX('Roadmap Calc (Don’t Touch)'!$F$2:$F$205,$AH7)) | E7: =IF($AH7="","",INDEX('Roadmap Calc (Don’t Touch)'!$G$2:$G$205,$AH7)) | F7: =IF($AH7="","",INDEX('Roadmap Calc (Don’t Touch)'!$H$2:$H$205,$AH7)) | G7: =IF($AH7="","",INDEX('Roadmap Calc (Don’t Touch)'!$I$2:$I$205,$AH7)) | H7: =IF($AH7="","",INDEX('Roadmap Calc (Don’t Touch)'!$J$2:$J$205,$AH7)) | I7: =IF($AH7="","",IF(AND($E7<>"",$E7<=EOMONTH(I$3,0),$F7>=I$3),IF(AND($G7<>"",$G7<=EOMONTH(I$3,0),$H7>=I$3),"B","U"),IF(AND($G7<>"",$G7<=EOMONTH(I$3,0),$H7>=I$3),"D",""))) | J7: =IF($AH7="","",IF(AND($E7<>"",$E7<=EOMONTH(J$3,0),$F7>=J$3),IF(AND($G7<>"",$G7<=EOMONTH(J$3,0),$H7>=J$3),"B","U"),IF(AND($G7<>"",$G7<=EOMONTH(J$3,0),$H7>=J$3),"D",""))) | K7: =IF($AH7="","",IF(AND($E7<>"",$E7<=EOMONTH(K$3,0),$F7>=K$3),IF(AND($G7<>"",$G7<=EOMONTH(K$3,0),$H7>=K$3),"B","U"),IF(AND($G7<>"",$G7<=EOMONTH(K$3,0),$H7>=K$3),"D",""))) | L7: =IF($AH7="","",IF(AND($E7<>"",$E7<=EOMONTH(L$3,0),$F7>=L$3),IF(AND($G7<>"",$G7<=EOMONTH(L$3,0),$H7>=L$3),"B","U"),IF(AND($G7<>"",$G7<=EOMONTH(L$3,0),$H7>=L$3),"D",""))) | M7: =IF($AH7="","",IF(AND($E7<>"",$E7<=EOMONTH(M$3,0),$F7>=M$3),IF(AND($G7<>"",$G7<=EOMONTH(M$3,0),$H7>=M$3),"B","U"),IF(AND($G7<>"",$G7<=EOMONTH(M$3,0),$H7>=M$3),"D",""))) | N7: =IF($AH7="","",IF(AND($E7<>"",$E7<=EOMONTH(N$3,0),$F7>=N$3),IF(AND($G7<>"",$G7<=EOMONTH(N$3,0),$H7>=N$3),"B","U"),IF(AND($G7<>"",$G7<=EOMONTH(N$3,0),$H7>=N$3),"D",""))) | O7: =IF($AH7="","",IF(AND($E7<>"",$E7<=EOMONTH(O$3,0),$F7>=O$3),IF(AND($G7<>"",$G7<=EOMONTH(O$3,0),$H7>=O$3),"B","U"),IF(AND($G7<>"",$G7<=EOMONTH(O$3,0),$H7>=O$3),"D",""))) | P7: =IF($AH7="","",IF(AND($E7<>"",$E7<=EOMONTH(P$3,0),$F7>=P$3),IF(AND($G7<>"",$G7<=EOMONTH(P$3,0),$H7>=P$3),"B","U"),IF(AND($G7<>"",$G7<=EOMONTH(P$3,0),$H7>=P$3),"D",""))) | ... AF7: =IF($AH7="","",IF(AND($E7<>"",$E7<=EOMONTH(AF$3,0),$F7>=AF$3),IF(AND($G7<>"",$G7<=EOMONTH(AF$3,0),$H7>=AF$3),"B","U"),IF(AND($G7<>"",$G7<=EOMONTH(AF$3,0),$H7>=AF$3),"D",""))) | AG7: =IF($AH7="","",INDEX('Roadmap Calc (Don’t Touch)'!$D$2:$D$205,$AH7)) | AH7: =IFERROR(MATCH(1,'Roadmap Calc (Don’t Touch)'!$O$2:$O$205,0),"")
A8: =IF($AH8="","",IF($AG8=$AG7,"",$AG8)) | B8: =IF($AH8="","",INDEX('Roadmap Calc (Don’t Touch)'!$B$2:$B$205,$AH8)) | C8: =IF($AH8="","",INDEX('Roadmap Calc (Don’t Touch)'!$E$2:$E$205,$AH8)) | D8: =IF($AH8="","",INDEX('Roadmap Calc (Don’t Touch)'!$F$2:$F$205,$AH8)) | E8: =IF($AH8="","",INDEX('Roadmap Calc (Don’t Touch)'!$G$2:$G$205,$AH8)) | F8: =IF($AH8="","",INDEX('Roadmap Calc (Don’t Touch)'!$H$2:$H$205,$AH8)) | G8: =IF($AH8="","",INDEX('Roadmap Calc (Don’t Touch)'!$I$2:$I$205,$AH8)) | H8: =IF($AH8="","",INDEX('Roadmap Calc (Don’t Touch)'!$J$2:$J$205,$AH8)) | I8: =IF($AH8="","",IF(AND($E8<>"",$E8<=EOMONTH(I$3,0),$F8>=I$3),IF(AND($G8<>"",$G8<=EOMONTH(I$3,0),$H8>=I$3),"B","U"),IF(AND($G8<>"",$G8<=EOMONTH(I$3,0),$H8>=I$3),"D",""))) | J8: =IF($AH8="","",IF(AND($E8<>"",$E8<=EOMONTH(J$3,0),$F8>=J$3),IF(AND($G8<>"",$G8<=EOMONTH(J$3,0),$H8>=J$3),"B","U"),IF(AND($G8<>"",$G8<=EOMONTH(J$3,0),$H8>=J$3),"D",""))) | K8: =IF($AH8="","",IF(AND($E8<>"",$E8<=EOMONTH(K$3,0),$F8>=K$3),IF(AND($G8<>"",$G8<=EOMONTH(K$3,0),$H8>=K$3),"B","U"),IF(AND($G8<>"",$G8<=EOMONTH(K$3,0),$H8>=K$3),"D",""))) | L8: =IF($AH8="","",IF(AND($E8<>"",$E8<=EOMONTH(L$3,0),$F8>=L$3),IF(AND($G8<>"",$G8<=EOMONTH(L$3,0),$H8>=L$3),"B","U"),IF(AND($G8<>"",$G8<=EOMONTH(L$3,0),$H8>=L$3),"D",""))) | M8: =IF($AH8="","",IF(AND($E8<>"",$E8<=EOMONTH(M$3,0),$F8>=M$3),IF(AND($G8<>"",$G8<=EOMONTH(M$3,0),$H8>=M$3),"B","U"),IF(AND($G8<>"",$G8<=EOMONTH(M$3,0),$H8>=M$3),"D",""))) | N8: =IF($AH8="","",IF(AND($E8<>"",$E8<=EOMONTH(N$3,0),$F8>=N$3),IF(AND($G8<>"",$G8<=EOMONTH(N$3,0),$H8>=N$3),"B","U"),IF(AND($G8<>"",$G8<=EOMONTH(N$3,0),$H8>=N$3),"D",""))) | O8: =IF($AH8="","",IF(AND($E8<>"",$E8<=EOMONTH(O$3,0),$F8>=O$3),IF(AND($G8<>"",$G8<=EOMONTH(O$3,0),$H8>=O$3),"B","U"),IF(AND($G8<>"",$G8<=EOMONTH(O$3,0),$H8>=O$3),"D",""))) | P8: =IF($AH8="","",IF(AND($E8<>"",$E8<=EOMONTH(P$3,0),$F8>=P$3),IF(AND($G8<>"",$G8<=EOMONTH(P$3,0),$H8>=P$3),"B","U"),IF(AND($G8<>"",$G8<=EOMONTH(P$3,0),$H8>=P$3),"D",""))) | ... AF8: =IF($AH8="","",IF(AND($E8<>"",$E8<=EOMONTH(AF$3,0),$F8>=AF$3),IF(AND($G8<>"",$G8<=EOMONTH(AF$3,0),$H8>=AF$3),"B","U"),IF(AND($G8<>"",$G8<=EOMONTH(AF$3,0),$H8>=AF$3),"D",""))) | AG8: =IF($AH8="","",INDEX('Roadmap Calc (Don’t Touch)'!$D$2:$D$205,$AH8)) | AH8: =IFERROR(MATCH(2,'Roadmap Calc (Don’t Touch)'!$O$2:$O$205,0),"")
A9: =IF($AH9="","",IF($AG9=$AG8,"",$AG9)) | B9: =IF($AH9="","",INDEX('Roadmap Calc (Don’t Touch)'!$B$2:$B$205,$AH9)) | C9: =IF($AH9="","",INDEX('Roadmap Calc (Don’t Touch)'!$E$2:$E$205,$AH9)) | D9: =IF($AH9="","",INDEX('Roadmap Calc (Don’t Touch)'!$F$2:$F$205,$AH9)) | E9: =IF($AH9="","",INDEX('Roadmap Calc (Don’t Touch)'!$G$2:$G$205,$AH9)) | F9: =IF($AH9="","",INDEX('Roadmap Calc (Don’t Touch)'!$H$2:$H$205,$AH9)) | G9: =IF($AH9="","",INDEX('Roadmap Calc (Don’t Touch)'!$I$2:$I$205,$AH9)) | H9: =IF($AH9="","",INDEX('Roadmap Calc (Don’t Touch)'!$J$2:$J$205,$AH9)) | I9: =IF($AH9="","",IF(AND($E9<>"",$E9<=EOMONTH(I$3,0),$F9>=I$3),IF(AND($G9<>"",$G9<=EOMONTH(I$3,0),$H9>=I$3),"B","U"),IF(AND($G9<>"",$G9<=EOMONTH(I$3,0),$H9>=I$3),"D",""))) | J9: =IF($AH9="","",IF(AND($E9<>"",$E9<=EOMONTH(J$3,0),$F9>=J$3),IF(AND($G9<>"",$G9<=EOMONTH(J$3,0),$H9>=J$3),"B","U"),IF(AND($G9<>"",$G9<=EOMONTH(J$3,0),$H9>=J$3),"D",""))) | K9: =IF($AH9="","",IF(AND($E9<>"",$E9<=EOMONTH(K$3,0),$F9>=K$3),IF(AND($G9<>"",$G9<=EOMONTH(K$3,0),$H9>=K$3),"B","U"),IF(AND($G9<>"",$G9<=EOMONTH(K$3,0),$H9>=K$3),"D",""))) | L9: =IF($AH9="","",IF(AND($E9<>"",$E9<=EOMONTH(L$3,0),$F9>=L$3),IF(AND($G9<>"",$G9<=EOMONTH(L$3,0),$H9>=L$3),"B","U"),IF(AND($G9<>"",$G9<=EOMONTH(L$3,0),$H9>=L$3),"D",""))) | M9: =IF($AH9="","",IF(AND($E9<>"",$E9<=EOMONTH(M$3,0),$F9>=M$3),IF(AND($G9<>"",$G9<=EOMONTH(M$3,0),$H9>=M$3),"B","U"),IF(AND($G9<>"",$G9<=EOMONTH(M$3,0),$H9>=M$3),"D",""))) | N9: =IF($AH9="","",IF(AND($E9<>"",$E9<=EOMONTH(N$3,0),$F9>=N$3),IF(AND($G9<>"",$G9<=EOMONTH(N$3,0),$H9>=N$3),"B","U"),IF(AND($G9<>"",$G9<=EOMONTH(N$3,0),$H9>=N$3),"D",""))) | O9: =IF($AH9="","",IF(AND($E9<>"",$E9<=EOMONTH(O$3,0),$F9>=O$3),IF(AND($G9<>"",$G9<=EOMONTH(O$3,0),$H9>=O$3),"B","U"),IF(AND($G9<>"",$G9<=EOMONTH(O$3,0),$H9>=O$3),"D",""))) | P9: =IF($AH9="","",IF(AND($E9<>"",$E9<=EOMONTH(P$3,0),$F9>=P$3),IF(AND($G9<>"",$G9<=EOMONTH(P$3,0),$H9>=P$3),"B","U"),IF(AND($G9<>"",$G9<=EOMONTH(P$3,0),$H9>=P$3),"D",""))) | ... AF9: =IF($AH9="","",IF(AND($E9<>"",$E9<=EOMONTH(AF$3,0),$F9>=AF$3),IF(AND($G9<>"",$G9<=EOMONTH(AF$3,0),$H9>=AF$3),"B","U"),IF(AND($G9<>"",$G9<=EOMONTH(AF$3,0),$H9>=AF$3),"D",""))) | AG9: =IF($AH9="","",INDEX('Roadmap Calc (Don’t Touch)'!$D$2:$D$205,$AH9)) | AH9: =IFERROR(MATCH(3,'Roadmap Calc (Don’t Touch)'!$O$2:$O$205,0),"")
A10: =IF($AH10="","",IF($AG10=$AG9,"",$AG10)) | B10: =IF($AH10="","",INDEX('Roadmap Calc (Don’t Touch)'!$B$2:$B$205,$AH10)) | C10: =IF($AH10="","",INDEX('Roadmap Calc (Don’t Touch)'!$E$2:$E$205,$AH10)) | D10: =IF($AH10="","",INDEX('Roadmap Calc (Don’t Touch)'!$F$2:$F$205,$AH10)) | E10: =IF($AH10="","",INDEX('Roadmap Calc (Don’t Touch)'!$G$2:$G$205,$AH10)) | F10: =IF($AH10="","",INDEX('Roadmap Calc (Don’t Touch)'!$H$2:$H$205,$AH10)) | G10: =IF($AH10="","",INDEX('Roadmap Calc (Don’t Touch)'!$I$2:$I$205,$AH10)) | H10: =IF($AH10="","",INDEX('Roadmap Calc (Don’t Touch)'!$J$2:$J$205,$AH10)) | I10: =IF($AH10="","",IF(AND($E10<>"",$E10<=EOMONTH(I$3,0),$F10>=I$3),IF(AND($G10<>"",$G10<=EOMONTH(I$3,0),$H10>=I$3),"B","U"),IF(AND($G10<>"",$G10<=EOMONTH(I$3,0),$H10>=I$3),"D",""))) | J10: =IF($AH10="","",IF(AND($E10<>"",$E10<=EOMONTH(J$3,0),$F10>=J$3),IF(AND($G10<>"",$G10<=EOMONTH(J$3,0),$H10>=J$3),"B","U"),IF(AND($G10<>"",$G10<=EOMONTH(J$3,0),$H10>=J$3),"D",""))) | K10: =IF($AH10="","",IF(AND($E10<>"",$E10<=EOMONTH(K$3,0),$F10>=K$3),IF(AND($G10<>"",$G10<=EOMONTH(K$3,0),$H10>=K$3),"B","U"),IF(AND($G10<>"",$G10<=EOMONTH(K$3,0),$H10>=K$3),"D",""))) | L10: =IF($AH10="","",IF(AND($E10<>"",$E10<=EOMONTH(L$3,0),$F10>=L$3),IF(AND($G10<>"",$G10<=EOMONTH(L$3,0),$H10>=L$3),"B","U"),IF(AND($G10<>"",$G10<=EOMONTH(L$3,0),$H10>=L$3),"D",""))) | M10: =IF($AH10="","",IF(AND($E10<>"",$E10<=EOMONTH(M$3,0),$F10>=M$3),IF(AND($G10<>"",$G10<=EOMONTH(M$3,0),$H10>=M$3),"B","U"),IF(AND($G10<>"",$G10<=EOMONTH(M$3,0),$H10>=M$3),"D",""))) | N10: =IF($AH10="","",IF(AND($E10<>"",$E10<=EOMONTH(N$3,0),$F10>=N$3),IF(AND($G10<>"",$G10<=EOMONTH(N$3,0),$H10>=N$3),"B","U"),IF(AND($G10<>"",$G10<=EOMONTH(N$3,0),$H10>=N$3),"D",""))) | O10: =IF($AH10="","",IF(AND($E10<>"",$E10<=EOMONTH(O$3,0),$F10>=O$3),IF(AND($G10<>"",$G10<=EOMONTH(O$3,0),$H10>=O$3),"B","U"),IF(AND($G10<>"",$G10<=EOMONTH(O$3,0),$H10>=O$3),"D",""))) | P10: =IF($AH10="","",IF(AND($E10<>"",$E10<=EOMONTH(P$3,0),$F10>=P$3),IF(AND($G10<>"",$G10<=EOMONTH(P$3,0),$H10>=P$3),"B","U"),IF(AND($G10<>"",$G10<=EOMONTH(P$3,0),$H10>=P$3),"D",""))) | ... AF10: =IF($AH10="","",IF(AND($E10<>"",$E10<=EOMONTH(AF$3,0),$F10>=AF$3),IF(AND($G10<>"",$G10<=EOMONTH(AF$3,0),$H10>=AF$3),"B","U"),IF(AND($G10<>"",$G10<=EOMONTH(AF$3,0),$H10>=AF$3),"D",""))) | AG10: =IF($AH10="","",INDEX('Roadmap Calc (Don’t Touch)'!$D$2:$D$205,$AH10)) | AH10: =IFERROR(MATCH(4,'Roadmap Calc (Don’t Touch)'!$O$2:$O$205,0),"")
A11: =IF($AH11="","",IF($AG11=$AG10,"",$AG11)) | B11: =IF($AH11="","",INDEX('Roadmap Calc (Don’t Touch)'!$B$2:$B$205,$AH11)) | C11: =IF($AH11="","",INDEX('Roadmap Calc (Don’t Touch)'!$E$2:$E$205,$AH11)) | D11: =IF($AH11="","",INDEX('Roadmap Calc (Don’t Touch)'!$F$2:$F$205,$AH11)) | E11: =IF($AH11="","",INDEX('Roadmap Calc (Don’t Touch)'!$G$2:$G$205,$AH11)) | F11: =IF($AH11="","",INDEX('Roadmap Calc (Don’t Touch)'!$H$2:$H$205,$AH11)) | G11: =IF($AH11="","",INDEX('Roadmap Calc (Don’t Touch)'!$I$2:$I$205,$AH11)) | H11: =IF($AH11="","",INDEX('Roadmap Calc (Don’t Touch)'!$J$2:$J$205,$AH11)) | I11: =IF($AH11="","",IF(AND($E11<>"",$E11<=EOMONTH(I$3,0),$F11>=I$3),IF(AND($G11<>"",$G11<=EOMONTH(I$3,0),$H11>=I$3),"B","U"),IF(AND($G11<>"",$G11<=EOMONTH(I$3,0),$H11>=I$3),"D",""))) | J11: =IF($AH11="","",IF(AND($E11<>"",$E11<=EOMONTH(J$3,0),$F11>=J$3),IF(AND($G11<>"",$G11<=EOMONTH(J$3,0),$H11>=J$3),"B","U"),IF(AND($G11<>"",$G11<=EOMONTH(J$3,0),$H11>=J$3),"D",""))) | K11: =IF($AH11="","",IF(AND($E11<>"",$E11<=EOMONTH(K$3,0),$F11>=K$3),IF(AND($G11<>"",$G11<=EOMONTH(K$3,0),$H11>=K$3),"B","U"),IF(AND($G11<>"",$G11<=EOMONTH(K$3,0),$H11>=K$3),"D",""))) | L11: =IF($AH11="","",IF(AND($E11<>"",$E11<=EOMONTH(L$3,0),$F11>=L$3),IF(AND($G11<>"",$G11<=EOMONTH(L$3,0),$H11>=L$3),"B","U"),IF(AND($G11<>"",$G11<=EOMONTH(L$3,0),$H11>=L$3),"D",""))) | M11: =IF($AH11="","",IF(AND($E11<>"",$E11<=EOMONTH(M$3,0),$F11>=M$3),IF(AND($G11<>"",$G11<=EOMONTH(M$3,0),$H11>=M$3),"B","U"),IF(AND($G11<>"",$G11<=EOMONTH(M$3,0),$H11>=M$3),"D",""))) | N11: =IF($AH11="","",IF(AND($E11<>"",$E11<=EOMONTH(N$3,0),$F11>=N$3),IF(AND($G11<>"",$G11<=EOMONTH(N$3,0),$H11>=N$3),"B","U"),IF(AND($G11<>"",$G11<=EOMONTH(N$3,0),$H11>=N$3),"D",""))) | O11: =IF($AH11="","",IF(AND($E11<>"",$E11<=EOMONTH(O$3,0),$F11>=O$3),IF(AND($G11<>"",$G11<=EOMONTH(O$3,0),$H11>=O$3),"B","U"),IF(AND($G11<>"",$G11<=EOMONTH(O$3,0),$H11>=O$3),"D",""))) | P11: =IF($AH11="","",IF(AND($E11<>"",$E11<=EOMONTH(P$3,0),$F11>=P$3),IF(AND($G11<>"",$G11<=EOMONTH(P$3,0),$H11>=P$3),"B","U"),IF(AND($G11<>"",$G11<=EOMONTH(P$3,0),$H11>=P$3),"D",""))) | ... AF11: =IF($AH11="","",IF(AND($E11<>"",$E11<=EOMONTH(AF$3,0),$F11>=AF$3),IF(AND($G11<>"",$G11<=EOMONTH(AF$3,0),$H11>=AF$3),"B","U"),IF(AND($G11<>"",$G11<=EOMONTH(AF$3,0),$H11>=AF$3),"D",""))) | AG11: =IF($AH11="","",INDEX('Roadmap Calc (Don’t Touch)'!$D$2:$D$205,$AH11)) | AH11: =IFERROR(MATCH(5,'Roadmap Calc (Don’t Touch)'!$O$2:$O$205,0),"")
A12: =IF($AH12="","",IF($AG12=$AG11,"",$AG12)) | B12: =IF($AH12="","",INDEX('Roadmap Calc (Don’t Touch)'!$B$2:$B$205,$AH12)) | C12: =IF($AH12="","",INDEX('Roadmap Calc (Don’t Touch)'!$E$2:$E$205,$AH12)) | D12: =IF($AH12="","",INDEX('Roadmap Calc (Don’t Touch)'!$F$2:$F$205,$AH12)) | E12: =IF($AH12="","",INDEX('Roadmap Calc (Don’t Touch)'!$G$2:$G$205,$AH12)) | F12: =IF($AH12="","",INDEX('Roadmap Calc (Don’t Touch)'!$H$2:$H$205,$AH12)) | G12: =IF($AH12="","",INDEX('Roadmap Calc (Don’t Touch)'!$I$2:$I$205,$AH12)) | H12: =IF($AH12="","",INDEX('Roadmap Calc (Don’t Touch)'!$J$2:$J$205,$AH12)) | I12: =IF($AH12="","",IF(AND($E12<>"",$E12<=EOMONTH(I$3,0),$F12>=I$3),IF(AND($G12<>"",$G12<=EOMONTH(I$3,0),$H12>=I$3),"B","U"),IF(AND($G12<>"",$G12<=EOMONTH(I$3,0),$H12>=I$3),"D",""))) | J12: =IF($AH12="","",IF(AND($E12<>"",$E12<=EOMONTH(J$3,0),$F12>=J$3),IF(AND($G12<>"",$G12<=EOMONTH(J$3,0),$H12>=J$3),"B","U"),IF(AND($G12<>"",$G12<=EOMONTH(J$3,0),$H12>=J$3),"D",""))) | K12: =IF($AH12="","",IF(AND($E12<>"",$E12<=EOMONTH(K$3,0),$F12>=K$3),IF(AND($G12<>"",$G12<=EOMONTH(K$3,0),$H12>=K$3),"B","U"),IF(AND($G12<>"",$G12<=EOMONTH(K$3,0),$H12>=K$3),"D",""))) | L12: =IF($AH12="","",IF(AND($E12<>"",$E12<=EOMONTH(L$3,0),$F12>=L$3),IF(AND($G12<>"",$G12<=EOMONTH(L$3,0),$H12>=L$3),"B","U"),IF(AND($G12<>"",$G12<=EOMONTH(L$3,0),$H12>=L$3),"D",""))) | M12: =IF($AH12="","",IF(AND($E12<>"",$E12<=EOMONTH(M$3,0),$F12>=M$3),IF(AND($G12<>"",$G12<=EOMONTH(M$3,0),$H12>=M$3),"B","U"),IF(AND($G12<>"",$G12<=EOMONTH(M$3,0),$H12>=M$3),"D",""))) | N12: =IF($AH12="","",IF(AND($E12<>"",$E12<=EOMONTH(N$3,0),$F12>=N$3),IF(AND($G12<>"",$G12<=EOMONTH(N$3,0),$H12>=N$3),"B","U"),IF(AND($G12<>"",$G12<=EOMONTH(N$3,0),$H12>=N$3),"D",""))) | O12: =IF($AH12="","",IF(AND($E12<>"",$E12<=EOMONTH(O$3,0),$F12>=O$3),IF(AND($G12<>"",$G12<=EOMONTH(O$3,0),$H12>=O$3),"B","U"),IF(AND($G12<>"",$G12<=EOMONTH(O$3,0),$H12>=O$3),"D",""))) | P12: =IF($AH12="","",IF(AND($E12<>"",$E12<=EOMONTH(P$3,0),$F12>=P$3),IF(AND($G12<>"",$G12<=EOMONTH(P$3,0),$H12>=P$3),"B","U"),IF(AND($G12<>"",$G12<=EOMONTH(P$3,0),$H12>=P$3),"D",""))) | ... AF12: =IF($AH12="","",IF(AND($E12<>"",$E12<=EOMONTH(AF$3,0),$F12>=AF$3),IF(AND($G12<>"",$G12<=EOMONTH(AF$3,0),$H12>=AF$3),"B","U"),IF(AND($G12<>"",$G12<=EOMONTH(AF$3,0),$H12>=AF$3),"D",""))) | AG12: =IF($AH12="","",INDEX('Roadmap Calc (Don’t Touch)'!$D$2:$D$205,$AH12)) | AH12: =IFERROR(MATCH(6,'Roadmap Calc (Don’t Touch)'!$O$2:$O$205,0),"")
A13: =IF($AH13="","",IF($AG13=$AG12,"",$AG13)) | B13: =IF($AH13="","",INDEX('Roadmap Calc (Don’t Touch)'!$B$2:$B$205,$AH13)) | C13: =IF($AH13="","",INDEX('Roadmap Calc (Don’t Touch)'!$E$2:$E$205,$AH13)) | D13: =IF($AH13="","",INDEX('Roadmap Calc (Don’t Touch)'!$F$2:$F$205,$AH13)) | E13: =IF($AH13="","",INDEX('Roadmap Calc (Don’t Touch)'!$G$2:$G$205,$AH13)) | F13: =IF($AH13="","",INDEX('Roadmap Calc (Don’t Touch)'!$H$2:$H$205,$AH13)) | G13: =IF($AH13="","",INDEX('Roadmap Calc (Don’t Touch)'!$I$2:$I$205,$AH13)) | H13: =IF($AH13="","",INDEX('Roadmap Calc (Don’t Touch)'!$J$2:$J$205,$AH13)) | I13: =IF($AH13="","",IF(AND($E13<>"",$E13<=EOMONTH(I$3,0),$F13>=I$3),IF(AND($G13<>"",$G13<=EOMONTH(I$3,0),$H13>=I$3),"B","U"),IF(AND($G13<>"",$G13<=EOMONTH(I$3,0),$H13>=I$3),"D",""))) | J13: =IF($AH13="","",IF(AND($E13<>"",$E13<=EOMONTH(J$3,0),$F13>=J$3),IF(AND($G13<>"",$G13<=EOMONTH(J$3,0),$H13>=J$3),"B","U"),IF(AND($G13<>"",$G13<=EOMONTH(J$3,0),$H13>=J$3),"D",""))) | K13: =IF($AH13="","",IF(AND($E13<>"",$E13<=EOMONTH(K$3,0),$F13>=K$3),IF(AND($G13<>"",$G13<=EOMONTH(K$3,0),$H13>=K$3),"B","U"),IF(AND($G13<>"",$G13<=EOMONTH(K$3,0),$H13>=K$3),"D",""))) | L13: =IF($AH13="","",IF(AND($E13<>"",$E13<=EOMONTH(L$3,0),$F13>=L$3),IF(AND($G13<>"",$G13<=EOMONTH(L$3,0),$H13>=L$3),"B","U"),IF(AND($G13<>"",$G13<=EOMONTH(L$3,0),$H13>=L$3),"D",""))) | M13: =IF($AH13="","",IF(AND($E13<>"",$E13<=EOMONTH(M$3,0),$F13>=M$3),IF(AND($G13<>"",$G13<=EOMONTH(M$3,0),$H13>=M$3),"B","U"),IF(AND($G13<>"",$G13<=EOMONTH(M$3,0),$H13>=M$3),"D",""))) | N13: =IF($AH13="","",IF(AND($E13<>"",$E13<=EOMONTH(N$3,0),$F13>=N$3),IF(AND($G13<>"",$G13<=EOMONTH(N$3,0),$H13>=N$3),"B","U"),IF(AND($G13<>"",$G13<=EOMONTH(N$3,0),$H13>=N$3),"D",""))) | O13: =IF($AH13="","",IF(AND($E13<>"",$E13<=EOMONTH(O$3,0),$F13>=O$3),IF(AND($G13<>"",$G13<=EOMONTH(O$3,0),$H13>=O$3),"B","U"),IF(AND($G13<>"",$G13<=EOMONTH(O$3,0),$H13>=O$3),"D",""))) | P13: =IF($AH13="","",IF(AND($E13<>"",$E13<=EOMONTH(P$3,0),$F13>=P$3),IF(AND($G13<>"",$G13<=EOMONTH(P$3,0),$H13>=P$3),"B","U"),IF(AND($G13<>"",$G13<=EOMONTH(P$3,0),$H13>=P$3),"D",""))) | ... AF13: =IF($AH13="","",IF(AND($E13<>"",$E13<=EOMONTH(AF$3,0),$F13>=AF$3),IF(AND($G13<>"",$G13<=EOMONTH(AF$3,0),$H13>=AF$3),"B","U"),IF(AND($G13<>"",$G13<=EOMONTH(AF$3,0),$H13>=AF$3),"D",""))) | AG13: =IF($AH13="","",INDEX('Roadmap Calc (Don’t Touch)'!$D$2:$D$205,$AH13)) | AH13: =IFERROR(MATCH(7,'Roadmap Calc (Don’t Touch)'!$O$2:$O$205,0),"")
A14: =IF($AH14="","",IF($AG14=$AG13,"",$AG14)) | B14: =IF($AH14="","",INDEX('Roadmap Calc (Don’t Touch)'!$B$2:$B$205,$AH14)) | C14: =IF($AH14="","",INDEX('Roadmap Calc (Don’t Touch)'!$E$2:$E$205,$AH14)) | D14: =IF($AH14="","",INDEX('Roadmap Calc (Don’t Touch)'!$F$2:$F$205,$AH14)) | E14: =IF($AH14="","",INDEX('Roadmap Calc (Don’t Touch)'!$G$2:$G$205,$AH14)) | F14: =IF($AH14="","",INDEX('Roadmap Calc (Don’t Touch)'!$H$2:$H$205,$AH14)) | G14: =IF($AH14="","",INDEX('Roadmap Calc (Don’t Touch)'!$I$2:$I$205,$AH14)) | H14: =IF($AH14="","",INDEX('Roadmap Calc (Don’t Touch)'!$J$2:$J$205,$AH14)) | I14: =IF($AH14="","",IF(AND($E14<>"",$E14<=EOMONTH(I$3,0),$F14>=I$3),IF(AND($G14<>"",$G14<=EOMONTH(I$3,0),$H14>=I$3),"B","U"),IF(AND($G14<>"",$G14<=EOMONTH(I$3,0),$H14>=I$3),"D",""))) | J14: =IF($AH14="","",IF(AND($E14<>"",$E14<=EOMONTH(J$3,0),$F14>=J$3),IF(AND($G14<>"",$G14<=EOMONTH(J$3,0),$H14>=J$3),"B","U"),IF(AND($G14<>"",$G14<=EOMONTH(J$3,0),$H14>=J$3),"D",""))) | K14: =IF($AH14="","",IF(AND($E14<>"",$E14<=EOMONTH(K$3,0),$F14>=K$3),IF(AND($G14<>"",$G14<=EOMONTH(K$3,0),$H14>=K$3),"B","U"),IF(AND($G14<>"",$G14<=EOMONTH(K$3,0),$H14>=K$3),"D",""))) | L14: =IF($AH14="","",IF(AND($E14<>"",$E14<=EOMONTH(L$3,0),$F14>=L$3),IF(AND($G14<>"",$G14<=EOMONTH(L$3,0),$H14>=L$3),"B","U"),IF(AND($G14<>"",$G14<=EOMONTH(L$3,0),$H14>=L$3),"D",""))) | M14: =IF($AH14="","",IF(AND($E14<>"",$E14<=EOMONTH(M$3,0),$F14>=M$3),IF(AND($G14<>"",$G14<=EOMONTH(M$3,0),$H14>=M$3),"B","U"),IF(AND($G14<>"",$G14<=EOMONTH(M$3,0),$H14>=M$3),"D",""))) | N14: =IF($AH14="","",IF(AND($E14<>"",$E14<=EOMONTH(N$3,0),$F14>=N$3),IF(AND($G14<>"",$G14<=EOMONTH(N$3,0),$H14>=N$3),"B","U"),IF(AND($G14<>"",$G14<=EOMONTH(N$3,0),$H14>=N$3),"D",""))) | O14: =IF($AH14="","",IF(AND($E14<>"",$E14<=EOMONTH(O$3,0),$F14>=O$3),IF(AND($G14<>"",$G14<=EOMONTH(O$3,0),$H14>=O$3),"B","U"),IF(AND($G14<>"",$G14<=EOMONTH(O$3,0),$H14>=O$3),"D",""))) | P14: =IF($AH14="","",IF(AND($E14<>"",$E14<=EOMONTH(P$3,0),$F14>=P$3),IF(AND($G14<>"",$G14<=EOMONTH(P$3,0),$H14>=P$3),"B","U"),IF(AND($G14<>"",$G14<=EOMONTH(P$3,0),$H14>=P$3),"D",""))) | ... AF14: =IF($AH14="","",IF(AND($E14<>"",$E14<=EOMONTH(AF$3,0),$F14>=AF$3),IF(AND($G14<>"",$G14<=EOMONTH(AF$3,0),$H14>=AF$3),"B","U"),IF(AND($G14<>"",$G14<=EOMONTH(AF$3,0),$H14>=AF$3),"D",""))) | AG14: =IF($AH14="","",INDEX('Roadmap Calc (Don’t Touch)'!$D$2:$D$205,$AH14)) | AH14: =IFERROR(MATCH(8,'Roadmap Calc (Don’t Touch)'!$O$2:$O$205,0),"")
A15: =IF($AH15="","",IF($AG15=$AG14,"",$AG15)) | B15: =IF($AH15="","",INDEX('Roadmap Calc (Don’t Touch)'!$B$2:$B$205,$AH15)) | C15: =IF($AH15="","",INDEX('Roadmap Calc (Don’t Touch)'!$E$2:$E$205,$AH15)) | D15: =IF($AH15="","",INDEX('Roadmap Calc (Don’t Touch)'!$F$2:$F$205,$AH15)) | E15: =IF($AH15="","",INDEX('Roadmap Calc (Don’t Touch)'!$G$2:$G$205,$AH15)) | F15: =IF($AH15="","",INDEX('Roadmap Calc (Don’t Touch)'!$H$2:$H$205,$AH15)) | G15: =IF($AH15="","",INDEX('Roadmap Calc (Don’t Touch)'!$I$2:$I$205,$AH15)) | H15: =IF($AH15="","",INDEX('Roadmap Calc (Don’t Touch)'!$J$2:$J$205,$AH15)) | I15: =IF($AH15="","",IF(AND($E15<>"",$E15<=EOMONTH(I$3,0),$F15>=I$3),IF(AND($G15<>"",$G15<=EOMONTH(I$3,0),$H15>=I$3),"B","U"),IF(AND($G15<>"",$G15<=EOMONTH(I$3,0),$H15>=I$3),"D",""))) | J15: =IF($AH15="","",IF(AND($E15<>"",$E15<=EOMONTH(J$3,0),$F15>=J$3),IF(AND($G15<>"",$G15<=EOMONTH(J$3,0),$H15>=J$3),"B","U"),IF(AND($G15<>"",$G15<=EOMONTH(J$3,0),$H15>=J$3),"D",""))) | K15: =IF($AH15="","",IF(AND($E15<>"",$E15<=EOMONTH(K$3,0),$F15>=K$3),IF(AND($G15<>"",$G15<=EOMONTH(K$3,0),$H15>=K$3),"B","U"),IF(AND($G15<>"",$G15<=EOMONTH(K$3,0),$H15>=K$3),"D",""))) | L15: =IF($AH15="","",IF(AND($E15<>"",$E15<=EOMONTH(L$3,0),$F15>=L$3),IF(AND($G15<>"",$G15<=EOMONTH(L$3,0),$H15>=L$3),"B","U"),IF(AND($G15<>"",$G15<=EOMONTH(L$3,0),$H15>=L$3),"D",""))) | M15: =IF($AH15="","",IF(AND($E15<>"",$E15<=EOMONTH(M$3,0),$F15>=M$3),IF(AND($G15<>"",$G15<=EOMONTH(M$3,0),$H15>=M$3),"B","U"),IF(AND($G15<>"",$G15<=EOMONTH(M$3,0),$H15>=M$3),"D",""))) | N15: =IF($AH15="","",IF(AND($E15<>"",$E15<=EOMONTH(N$3,0),$F15>=N$3),IF(AND($G15<>"",$G15<=EOMONTH(N$3,0),$H15>=N$3),"B","U"),IF(AND($G15<>"",$G15<=EOMONTH(N$3,0),$H15>=N$3),"D",""))) | O15: =IF($AH15="","",IF(AND($E15<>"",$E15<=EOMONTH(O$3,0),$F15>=O$3),IF(AND($G15<>"",$G15<=EOMONTH(O$3,0),$H15>=O$3),"B","U"),IF(AND($G15<>"",$G15<=EOMONTH(O$3,0),$H15>=O$3),"D",""))) | P15: =IF($AH15="","",IF(AND($E15<>"",$E15<=EOMONTH(P$3,0),$F15>=P$3),IF(AND($G15<>"",$G15<=EOMONTH(P$3,0),$H15>=P$3),"B","U"),IF(AND($G15<>"",$G15<=EOMONTH(P$3,0),$H15>=P$3),"D",""))) | ... AF15: =IF($AH15="","",IF(AND($E15<>"",$E15<=EOMONTH(AF$3,0),$F15>=AF$3),IF(AND($G15<>"",$G15<=EOMONTH(AF$3,0),$H15>=AF$3),"B","U"),IF(AND($G15<>"",$G15<=EOMONTH(AF$3,0),$H15>=AF$3),"D",""))) | AG15: =IF($AH15="","",INDEX('Roadmap Calc (Don’t Touch)'!$D$2:$D$205,$AH15)) | AH15: =IFERROR(MATCH(9,'Roadmap Calc (Don’t Touch)'!$O$2:$O$205,0),"")
A16: =IF($AH16="","",IF($AG16=$AG15,"",$AG16)) | B16: =IF($AH16="","",INDEX('Roadmap Calc (Don’t Touch)'!$B$2:$B$205,$AH16)) | C16: =IF($AH16="","",INDEX('Roadmap Calc (Don’t Touch)'!$E$2:$E$205,$AH16)) | D16: =IF($AH16="","",INDEX('Roadmap Calc (Don’t Touch)'!$F$2:$F$205,$AH16)) | E16: =IF($AH16="","",INDEX('Roadmap Calc (Don’t Touch)'!$G$2:$G$205,$AH16)) | F16: =IF($AH16="","",INDEX('Roadmap Calc (Don’t Touch)'!$H$2:$H$205,$AH16)) | G16: =IF($AH16="","",INDEX('Roadmap Calc (Don’t Touch)'!$I$2:$I$205,$AH16)) | H16: =IF($AH16="","",INDEX('Roadmap Calc (Don’t Touch)'!$J$2:$J$205,$AH16)) | I16: =IF($AH16="","",IF(AND($E16<>"",$E16<=EOMONTH(I$3,0),$F16>=I$3),IF(AND($G16<>"",$G16<=EOMONTH(I$3,0),$H16>=I$3),"B","U"),IF(AND($G16<>"",$G16<=EOMONTH(I$3,0),$H16>=I$3),"D",""))) | J16: =IF($AH16="","",IF(AND($E16<>"",$E16<=EOMONTH(J$3,0),$F16>=J$3),IF(AND($G16<>"",$G16<=EOMONTH(J$3,0),$H16>=J$3),"B","U"),IF(AND($G16<>"",$G16<=EOMONTH(J$3,0),$H16>=J$3),"D",""))) | K16: =IF($AH16="","",IF(AND($E16<>"",$E16<=EOMONTH(K$3,0),$F16>=K$3),IF(AND($G16<>"",$G16<=EOMONTH(K$3,0),$H16>=K$3),"B","U"),IF(AND($G16<>"",$G16<=EOMONTH(K$3,0),$H16>=K$3),"D",""))) | L16: =IF($AH16="","",IF(AND($E16<>"",$E16<=EOMONTH(L$3,0),$F16>=L$3),IF(AND($G16<>"",$G16<=EOMONTH(L$3,0),$H16>=L$3),"B","U"),IF(AND($G16<>"",$G16<=EOMONTH(L$3,0),$H16>=L$3),"D",""))) | M16: =IF($AH16="","",IF(AND($E16<>"",$E16<=EOMONTH(M$3,0),$F16>=M$3),IF(AND($G16<>"",$G16<=EOMONTH(M$3,0),$H16>=M$3),"B","U"),IF(AND($G16<>"",$G16<=EOMONTH(M$3,0),$H16>=M$3),"D",""))) | N16: =IF($AH16="","",IF(AND($E16<>"",$E16<=EOMONTH(N$3,0),$F16>=N$3),IF(AND($G16<>"",$G16<=EOMONTH(N$3,0),$H16>=N$3),"B","U"),IF(AND($G16<>"",$G16<=EOMONTH(N$3,0),$H16>=N$3),"D",""))) | O16: =IF($AH16="","",IF(AND($E16<>"",$E16<=EOMONTH(O$3,0),$F16>=O$3),IF(AND($G16<>"",$G16<=EOMONTH(O$3,0),$H16>=O$3),"B","U"),IF(AND($G16<>"",$G16<=EOMONTH(O$3,0),$H16>=O$3),"D",""))) | P16: =IF($AH16="","",IF(AND($E16<>"",$E16<=EOMONTH(P$3,0),$F16>=P$3),IF(AND($G16<>"",$G16<=EOMONTH(P$3,0),$H16>=P$3),"B","U"),IF(AND($G16<>"",$G16<=EOMONTH(P$3,0),$H16>=P$3),"D",""))) | ... AF16: =IF($AH16="","",IF(AND($E16<>"",$E16<=EOMONTH(AF$3,0),$F16>=AF$3),IF(AND($G16<>"",$G16<=EOMONTH(AF$3,0),$H16>=AF$3),"B","U"),IF(AND($G16<>"",$G16<=EOMONTH(AF$3,0),$H16>=AF$3),"D",""))) | AG16: =IF($AH16="","",INDEX('Roadmap Calc (Don’t Touch)'!$D$2:$D$205,$AH16)) | AH16: =IFERROR(MATCH(10,'Roadmap Calc (Don’t Touch)'!$O$2:$O$205,0),"")
A17: =IF($AH17="","",IF($AG17=$AG16,"",$AG17)) | B17: =IF($AH17="","",INDEX('Roadmap Calc (Don’t Touch)'!$B$2:$B$205,$AH17)) | C17: =IF($AH17="","",INDEX('Roadmap Calc (Don’t Touch)'!$E$2:$E$205,$AH17)) | D17: =IF($AH17="","",INDEX('Roadmap Calc (Don’t Touch)'!$F$2:$F$205,$AH17)) | E17: =IF($AH17="","",INDEX('Roadmap Calc (Don’t Touch)'!$G$2:$G$205,$AH17)) | F17: =IF($AH17="","",INDEX('Roadmap Calc (Don’t Touch)'!$H$2:$H$205,$AH17)) | G17: =IF($AH17="","",INDEX('Roadmap Calc (Don’t Touch)'!$I$2:$I$205,$AH17)) | H17: =IF($AH17="","",INDEX('Roadmap Calc (Don’t Touch)'!$J$2:$J$205,$AH17)) | I17: =IF($AH17="","",IF(AND($E17<>"",$E17<=EOMONTH(I$3,0),$F17>=I$3),IF(AND($G17<>"",$G17<=EOMONTH(I$3,0),$H17>=I$3),"B","U"),IF(AND($G17<>"",$G17<=EOMONTH(I$3,0),$H17>=I$3),"D",""))) | J17: =IF($AH17="","",IF(AND($E17<>"",$E17<=EOMONTH(J$3,0),$F17>=J$3),IF(AND($G17<>"",$G17<=EOMONTH(J$3,0),$H17>=J$3),"B","U"),IF(AND($G17<>"",$G17<=EOMONTH(J$3,0),$H17>=J$3),"D",""))) | K17: =IF($AH17="","",IF(AND($E17<>"",$E17<=EOMONTH(K$3,0),$F17>=K$3),IF(AND($G17<>"",$G17<=EOMONTH(K$3,0),$H17>=K$3),"B","U"),IF(AND($G17<>"",$G17<=EOMONTH(K$3,0),$H17>=K$3),"D",""))) | L17: =IF($AH17="","",IF(AND($E17<>"",$E17<=EOMONTH(L$3,0),$F17>=L$3),IF(AND($G17<>"",$G17<=EOMONTH(L$3,0),$H17>=L$3),"B","U"),IF(AND($G17<>"",$G17<=EOMONTH(L$3,0),$H17>=L$3),"D",""))) | M17: =IF($AH17="","",IF(AND($E17<>"",$E17<=EOMONTH(M$3,0),$F17>=M$3),IF(AND($G17<>"",$G17<=EOMONTH(M$3,0),$H17>=M$3),"B","U"),IF(AND($G17<>"",$G17<=EOMONTH(M$3,0),$H17>=M$3),"D",""))) | N17: =IF($AH17="","",IF(AND($E17<>"",$E17<=EOMONTH(N$3,0),$F17>=N$3),IF(AND($G17<>"",$G17<=EOMONTH(N$3,0),$H17>=N$3),"B","U"),IF(AND($G17<>"",$G17<=EOMONTH(N$3,0),$H17>=N$3),"D",""))) | O17: =IF($AH17="","",IF(AND($E17<>"",$E17<=EOMONTH(O$3,0),$F17>=O$3),IF(AND($G17<>"",$G17<=EOMONTH(O$3,0),$H17>=O$3),"B","U"),IF(AND($G17<>"",$G17<=EOMONTH(O$3,0),$H17>=O$3),"D",""))) | P17: =IF($AH17="","",IF(AND($E17<>"",$E17<=EOMONTH(P$3,0),$F17>=P$3),IF(AND($G17<>"",$G17<=EOMONTH(P$3,0),$H17>=P$3),"B","U"),IF(AND($G17<>"",$G17<=EOMONTH(P$3,0),$H17>=P$3),"D",""))) | ... AF17: =IF($AH17="","",IF(AND($E17<>"",$E17<=EOMONTH(AF$3,0),$F17>=AF$3),IF(AND($G17<>"",$G17<=EOMONTH(AF$3,0),$H17>=AF$3),"B","U"),IF(AND($G17<>"",$G17<=EOMONTH(AF$3,0),$H17>=AF$3),"D",""))) | AG17: =IF($AH17="","",INDEX('Roadmap Calc (Don’t Touch)'!$D$2:$D$205,$AH17)) | AH17: =IFERROR(MATCH(11,'Roadmap Calc (Don’t Touch)'!$O$2:$O$205,0),"")
A18: =IF($AH18="","",IF($AG18=$AG17,"",$AG18)) | B18: =IF($AH18="","",INDEX('Roadmap Calc (Don’t Touch)'!$B$2:$B$205,$AH18)) | C18: =IF($AH18="","",INDEX('Roadmap Calc (Don’t Touch)'!$E$2:$E$205,$AH18)) | D18: =IF($AH18="","",INDEX('Roadmap Calc (Don’t Touch)'!$F$2:$F$205,$AH18)) | E18: =IF($AH18="","",INDEX('Roadmap Calc (Don’t Touch)'!$G$2:$G$205,$AH18)) | F18: =IF($AH18="","",INDEX('Roadmap Calc (Don’t Touch)'!$H$2:$H$205,$AH18)) | G18: =IF($AH18="","",INDEX('Roadmap Calc (Don’t Touch)'!$I$2:$I$205,$AH18)) | H18: =IF($AH18="","",INDEX('Roadmap Calc (Don’t Touch)'!$J$2:$J$205,$AH18)) | I18: =IF($AH18="","",IF(AND($E18<>"",$E18<=EOMONTH(I$3,0),$F18>=I$3),IF(AND($G18<>"",$G18<=EOMONTH(I$3,0),$H18>=I$3),"B","U"),IF(AND($G18<>"",$G18<=EOMONTH(I$3,0),$H18>=I$3),"D",""))) | J18: =IF($AH18="","",IF(AND($E18<>"",$E18<=EOMONTH(J$3,0),$F18>=J$3),IF(AND($G18<>"",$G18<=EOMONTH(J$3,0),$H18>=J$3),"B","U"),IF(AND($G18<>"",$G18<=EOMONTH(J$3,0),$H18>=J$3),"D",""))) | K18: =IF($AH18="","",IF(AND($E18<>"",$E18<=EOMONTH(K$3,0),$F18>=K$3),IF(AND($G18<>"",$G18<=EOMONTH(K$3,0),$H18>=K$3),"B","U"),IF(AND($G18<>"",$G18<=EOMONTH(K$3,0),$H18>=K$3),"D",""))) | L18: =IF($AH18="","",IF(AND($E18<>"",$E18<=EOMONTH(L$3,0),$F18>=L$3),IF(AND($G18<>"",$G18<=EOMONTH(L$3,0),$H18>=L$3),"B","U"),IF(AND($G18<>"",$G18<=EOMONTH(L$3,0),$H18>=L$3),"D",""))) | M18: =IF($AH18="","",IF(AND($E18<>"",$E18<=EOMONTH(M$3,0),$F18>=M$3),IF(AND($G18<>"",$G18<=EOMONTH(M$3,0),$H18>=M$3),"B","U"),IF(AND($G18<>"",$G18<=EOMONTH(M$3,0),$H18>=M$3),"D",""))) | N18: =IF($AH18="","",IF(AND($E18<>"",$E18<=EOMONTH(N$3,0),$F18>=N$3),IF(AND($G18<>"",$G18<=EOMONTH(N$3,0),$H18>=N$3),"B","U"),IF(AND($G18<>"",$G18<=EOMONTH(N$3,0),$H18>=N$3),"D",""))) | O18: =IF($AH18="","",IF(AND($E18<>"",$E18<=EOMONTH(O$3,0),$F18>=O$3),IF(AND($G18<>"",$G18<=EOMONTH(O$3,0),$H18>=O$3),"B","U"),IF(AND($G18<>"",$G18<=EOMONTH(O$3,0),$H18>=O$3),"D",""))) | P18: =IF($AH18="","",IF(AND($E18<>"",$E18<=EOMONTH(P$3,0),$F18>=P$3),IF(AND($G18<>"",$G18<=EOMONTH(P$3,0),$H18>=P$3),"B","U"),IF(AND($G18<>"",$G18<=EOMONTH(P$3,0),$H18>=P$3),"D",""))) | ... AF18: =IF($AH18="","",IF(AND($E18<>"",$E18<=EOMONTH(AF$3,0),$F18>=AF$3),IF(AND($G18<>"",$G18<=EOMONTH(AF$3,0),$H18>=AF$3),"B","U"),IF(AND($G18<>"",$G18<=EOMONTH(AF$3,0),$H18>=AF$3),"D",""))) | AG18: =IF($AH18="","",INDEX('Roadmap Calc (Don’t Touch)'!$D$2:$D$205,$AH18)) | AH18: =IFERROR(MATCH(12,'Roadmap Calc (Don’t Touch)'!$O$2:$O$205,0),"")
A19: =IF($AH19="","",IF($AG19=$AG18,"",$AG19)) | B19: =IF($AH19="","",INDEX('Roadmap Calc (Don’t Touch)'!$B$2:$B$205,$AH19)) | C19: =IF($AH19="","",INDEX('Roadmap Calc (Don’t Touch)'!$E$2:$E$205,$AH19)) | D19: =IF($AH19="","",INDEX('Roadmap Calc (Don’t Touch)'!$F$2:$F$205,$AH19)) | E19: =IF($AH19="","",INDEX('Roadmap Calc (Don’t Touch)'!$G$2:$G$205,$AH19)) | F19: =IF($AH19="","",INDEX('Roadmap Calc (Don’t Touch)'!$H$2:$H$205,$AH19)) | G19: =IF($AH19="","",INDEX('Roadmap Calc (Don’t Touch)'!$I$2:$I$205,$AH19)) | H19: =IF($AH19="","",INDEX('Roadmap Calc (Don’t Touch)'!$J$2:$J$205,$AH19)) | I19: =IF($AH19="","",IF(AND($E19<>"",$E19<=EOMONTH(I$3,0),$F19>=I$3),IF(AND($G19<>"",$G19<=EOMONTH(I$3,0),$H19>=I$3),"B","U"),IF(AND($G19<>"",$G19<=EOMONTH(I$3,0),$H19>=I$3),"D",""))) | J19: =IF($AH19="","",IF(AND($E19<>"",$E19<=EOMONTH(J$3,0),$F19>=J$3),IF(AND($G19<>"",$G19<=EOMONTH(J$3,0),$H19>=J$3),"B","U"),IF(AND($G19<>"",$G19<=EOMONTH(J$3,0),$H19>=J$3),"D",""))) | K19: =IF($AH19="","",IF(AND($E19<>"",$E19<=EOMONTH(K$3,0),$F19>=K$3),IF(AND($G19<>"",$G19<=EOMONTH(K$3,0),$H19>=K$3),"B","U"),IF(AND($G19<>"",$G19<=EOMONTH(K$3,0),$H19>=K$3),"D",""))) | L19: =IF($AH19="","",IF(AND($E19<>"",$E19<=EOMONTH(L$3,0),$F19>=L$3),IF(AND($G19<>"",$G19<=EOMONTH(L$3,0),$H19>=L$3),"B","U"),IF(AND($G19<>"",$G19<=EOMONTH(L$3,0),$H19>=L$3),"D",""))) | M19: =IF($AH19="","",IF(AND($E19<>"",$E19<=EOMONTH(M$3,0),$F19>=M$3),IF(AND($G19<>"",$G19<=EOMONTH(M$3,0),$H19>=M$3),"B","U"),IF(AND($G19<>"",$G19<=EOMONTH(M$3,0),$H19>=M$3),"D",""))) | N19: =IF($AH19="","",IF(AND($E19<>"",$E19<=EOMONTH(N$3,0),$F19>=N$3),IF(AND($G19<>"",$G19<=EOMONTH(N$3,0),$H19>=N$3),"B","U"),IF(AND($G19<>"",$G19<=EOMONTH(N$3,0),$H19>=N$3),"D",""))) | O19: =IF($AH19="","",IF(AND($E19<>"",$E19<=EOMONTH(O$3,0),$F19>=O$3),IF(AND($G19<>"",$G19<=EOMONTH(O$3,0),$H19>=O$3),"B","U"),IF(AND($G19<>"",$G19<=EOMONTH(O$3,0),$H19>=O$3),"D",""))) | P19: =IF($AH19="","",IF(AND($E19<>"",$E19<=EOMONTH(P$3,0),$F19>=P$3),IF(AND($G19<>"",$G19<=EOMONTH(P$3,0),$H19>=P$3),"B","U"),IF(AND($G19<>"",$G19<=EOMONTH(P$3,0),$H19>=P$3),"D",""))) | ... AF19: =IF($AH19="","",IF(AND($E19<>"",$E19<=EOMONTH(AF$3,0),$F19>=AF$3),IF(AND($G19<>"",$G19<=EOMONTH(AF$3,0),$H19>=AF$3),"B","U"),IF(AND($G19<>"",$G19<=EOMONTH(AF$3,0),$H19>=AF$3),"D",""))) | AG19: =IF($AH19="","",INDEX('Roadmap Calc (Don’t Touch)'!$D$2:$D$205,$AH19)) | AH19: =IFERROR(MATCH(13,'Roadmap Calc (Don’t Touch)'!$O$2:$O$205,0),"")
A20: =IF($AH20="","",IF($AG20=$AG19,"",$AG20)) | B20: =IF($AH20="","",INDEX('Roadmap Calc (Don’t Touch)'!$B$2:$B$205,$AH20)) | C20: =IF($AH20="","",INDEX('Roadmap Calc (Don’t Touch)'!$E$2:$E$205,$AH20)) | D20: =IF($AH20="","",INDEX('Roadmap Calc (Don’t Touch)'!$F$2:$F$205,$AH20)) | E20: =IF($AH20="","",INDEX('Roadmap Calc (Don’t Touch)'!$G$2:$G$205,$AH20)) | F20: =IF($AH20="","",INDEX('Roadmap Calc (Don’t Touch)'!$H$2:$H$205,$AH20)) | G20: =IF($AH20="","",INDEX('Roadmap Calc (Don’t Touch)'!$I$2:$I$205,$AH20)) | H20: =IF($AH20="","",INDEX('Roadmap Calc (Don’t Touch)'!$J$2:$J$205,$AH20)) | I20: =IF($AH20="","",IF(AND($E20<>"",$E20<=EOMONTH(I$3,0),$F20>=I$3),IF(AND($G20<>"",$G20<=EOMONTH(I$3,0),$H20>=I$3),"B","U"),IF(AND($G20<>"",$G20<=EOMONTH(I$3,0),$H20>=I$3),"D",""))) | J20: =IF($AH20="","",IF(AND($E20<>"",$E20<=EOMONTH(J$3,0),$F20>=J$3),IF(AND($G20<>"",$G20<=EOMONTH(J$3,0),$H20>=J$3),"B","U"),IF(AND($G20<>"",$G20<=EOMONTH(J$3,0),$H20>=J$3),"D",""))) | K20: =IF($AH20="","",IF(AND($E20<>"",$E20<=EOMONTH(K$3,0),$F20>=K$3),IF(AND($G20<>"",$G20<=EOMONTH(K$3,0),$H20>=K$3),"B","U"),IF(AND($G20<>"",$G20<=EOMONTH(K$3,0),$H20>=K$3),"D",""))) | L20: =IF($AH20="","",IF(AND($E20<>"",$E20<=EOMONTH(L$3,0),$F20>=L$3),IF(AND($G20<>"",$G20<=EOMONTH(L$3,0),$H20>=L$3),"B","U"),IF(AND($G20<>"",$G20<=EOMONTH(L$3,0),$H20>=L$3),"D",""))) | M20: =IF($AH20="","",IF(AND($E20<>"",$E20<=EOMONTH(M$3,0),$F20>=M$3),IF(AND($G20<>"",$G20<=EOMONTH(M$3,0),$H20>=M$3),"B","U"),IF(AND($G20<>"",$G20<=EOMONTH(M$3,0),$H20>=M$3),"D",""))) | N20: =IF($AH20="","",IF(AND($E20<>"",$E20<=EOMONTH(N$3,0),$F20>=N$3),IF(AND($G20<>"",$G20<=EOMONTH(N$3,0),$H20>=N$3),"B","U"),IF(AND($G20<>"",$G20<=EOMONTH(N$3,0),$H20>=N$3),"D",""))) | O20: =IF($AH20="","",IF(AND($E20<>"",$E20<=EOMONTH(O$3,0),$F20>=O$3),IF(AND($G20<>"",$G20<=EOMONTH(O$3,0),$H20>=O$3),"B","U"),IF(AND($G20<>"",$G20<=EOMONTH(O$3,0),$H20>=O$3),"D",""))) | P20: =IF($AH20="","",IF(AND($E20<>"",$E20<=EOMONTH(P$3,0),$F20>=P$3),IF(AND($G20<>"",$G20<=EOMONTH(P$3,0),$H20>=P$3),"B","U"),IF(AND($G20<>"",$G20<=EOMONTH(P$3,0),$H20>=P$3),"D",""))) | ... AF20: =IF($AH20="","",IF(AND($E20<>"",$E20<=EOMONTH(AF$3,0),$F20>=AF$3),IF(AND($G20<>"",$G20<=EOMONTH(AF$3,0),$H20>=AF$3),"B","U"),IF(AND($G20<>"",$G20<=EOMONTH(AF$3,0),$H20>=AF$3),"D",""))) | AG20: =IF($AH20="","",INDEX('Roadmap Calc (Don’t Touch)'!$D$2:$D$205,$AH20)) | AH20: =IFERROR(MATCH(14,'Roadmap Calc (Don’t Touch)'!$O$2:$O$205,0),"")
A21: =IF($AH21="","",IF($AG21=$AG20,"",$AG21)) | B21: =IF($AH21="","",INDEX('Roadmap Calc (Don’t Touch)'!$B$2:$B$205,$AH21)) | C21: =IF($AH21="","",INDEX('Roadmap Calc (Don’t Touch)'!$E$2:$E$205,$AH21)) | D21: =IF($AH21="","",INDEX('Roadmap Calc (Don’t Touch)'!$F$2:$F$205,$AH21)) | E21: =IF($AH21="","",INDEX('Roadmap Calc (Don’t Touch)'!$G$2:$G$205,$AH21)) | F21: =IF($AH21="","",INDEX('Roadmap Calc (Don’t Touch)'!$H$2:$H$205,$AH21)) | G21: =IF($AH21="","",INDEX('Roadmap Calc (Don’t Touch)'!$I$2:$I$205,$AH21)) | H21: =IF($AH21="","",INDEX('Roadmap Calc (Don’t Touch)'!$J$2:$J$205,$AH21)) | I21: =IF($AH21="","",IF(AND($E21<>"",$E21<=EOMONTH(I$3,0),$F21>=I$3),IF(AND($G21<>"",$G21<=EOMONTH(I$3,0),$H21>=I$3),"B","U"),IF(AND($G21<>"",$G21<=EOMONTH(I$3,0),$H21>=I$3),"D",""))) | J21: =IF($AH21="","",IF(AND($E21<>"",$E21<=EOMONTH(J$3,0),$F21>=J$3),IF(AND($G21<>"",$G21<=EOMONTH(J$3,0),$H21>=J$3),"B","U"),IF(AND($G21<>"",$G21<=EOMONTH(J$3,0),$H21>=J$3),"D",""))) | K21: =IF($AH21="","",IF(AND($E21<>"",$E21<=EOMONTH(K$3,0),$F21>=K$3),IF(AND($G21<>"",$G21<=EOMONTH(K$3,0),$H21>=K$3),"B","U"),IF(AND($G21<>"",$G21<=EOMONTH(K$3,0),$H21>=K$3),"D",""))) | L21: =IF($AH21="","",IF(AND($E21<>"",$E21<=EOMONTH(L$3,0),$F21>=L$3),IF(AND($G21<>"",$G21<=EOMONTH(L$3,0),$H21>=L$3),"B","U"),IF(AND($G21<>"",$G21<=EOMONTH(L$3,0),$H21>=L$3),"D",""))) | M21: =IF($AH21="","",IF(AND($E21<>"",$E21<=EOMONTH(M$3,0),$F21>=M$3),IF(AND($G21<>"",$G21<=EOMONTH(M$3,0),$H21>=M$3),"B","U"),IF(AND($G21<>"",$G21<=EOMONTH(M$3,0),$H21>=M$3),"D",""))) | N21: =IF($AH21="","",IF(AND($E21<>"",$E21<=EOMONTH(N$3,0),$F21>=N$3),IF(AND($G21<>"",$G21<=EOMONTH(N$3,0),$H21>=N$3),"B","U"),IF(AND($G21<>"",$G21<=EOMONTH(N$3,0),$H21>=N$3),"D",""))) | O21: =IF($AH21="","",IF(AND($E21<>"",$E21<=EOMONTH(O$3,0),$F21>=O$3),IF(AND($G21<>"",$G21<=EOMONTH(O$3,0),$H21>=O$3),"B","U"),IF(AND($G21<>"",$G21<=EOMONTH(O$3,0),$H21>=O$3),"D",""))) | P21: =IF($AH21="","",IF(AND($E21<>"",$E21<=EOMONTH(P$3,0),$F21>=P$3),IF(AND($G21<>"",$G21<=EOMONTH(P$3,0),$H21>=P$3),"B","U"),IF(AND($G21<>"",$G21<=EOMONTH(P$3,0),$H21>=P$3),"D",""))) | ... AF21: =IF($AH21="","",IF(AND($E21<>"",$E21<=EOMONTH(AF$3,0),$F21>=AF$3),IF(AND($G21<>"",$G21<=EOMONTH(AF$3,0),$H21>=AF$3),"B","U"),IF(AND($G21<>"",$G21<=EOMONTH(AF$3,0),$H21>=AF$3),"D",""))) | AG21: =IF($AH21="","",INDEX('Roadmap Calc (Don’t Touch)'!$D$2:$D$205,$AH21)) | AH21: =IFERROR(MATCH(15,'Roadmap Calc (Don’t Touch)'!$O$2:$O$205,0),"")
A22: =IF($AH22="","",IF($AG22=$AG21,"",$AG22)) | B22: =IF($AH22="","",INDEX('Roadmap Calc (Don’t Touch)'!$B$2:$B$205,$AH22)) | C22: =IF($AH22="","",INDEX('Roadmap Calc (Don’t Touch)'!$E$2:$E$205,$AH22)) | D22: =IF($AH22="","",INDEX('Roadmap Calc (Don’t Touch)'!$F$2:$F$205,$AH22)) | E22: =IF($AH22="","",INDEX('Roadmap Calc (Don’t Touch)'!$G$2:$G$205,$AH22)) | F22: =IF($AH22="","",INDEX('Roadmap Calc (Don’t Touch)'!$H$2:$H$205,$AH22)) | G22: =IF($AH22="","",INDEX('Roadmap Calc (Don’t Touch)'!$I$2:$I$205,$AH22)) | H22: =IF($AH22="","",INDEX('Roadmap Calc (Don’t Touch)'!$J$2:$J$205,$AH22)) | I22: =IF($AH22="","",IF(AND($E22<>"",$E22<=EOMONTH(I$3,0),$F22>=I$3),IF(AND($G22<>"",$G22<=EOMONTH(I$3,0),$H22>=I$3),"B","U"),IF(AND($G22<>"",$G22<=EOMONTH(I$3,0),$H22>=I$3),"D",""))) | J22: =IF($AH22="","",IF(AND($E22<>"",$E22<=EOMONTH(J$3,0),$F22>=J$3),IF(AND($G22<>"",$G22<=EOMONTH(J$3,0),$H22>=J$3),"B","U"),IF(AND($G22<>"",$G22<=EOMONTH(J$3,0),$H22>=J$3),"D",""))) | K22: =IF($AH22="","",IF(AND($E22<>"",$E22<=EOMONTH(K$3,0),$F22>=K$3),IF(AND($G22<>"",$G22<=EOMONTH(K$3,0),$H22>=K$3),"B","U"),IF(AND($G22<>"",$G22<=EOMONTH(K$3,0),$H22>=K$3),"D",""))) | L22: =IF($AH22="","",IF(AND($E22<>"",$E22<=EOMONTH(L$3,0),$F22>=L$3),IF(AND($G22<>"",$G22<=EOMONTH(L$3,0),$H22>=L$3),"B","U"),IF(AND($G22<>"",$G22<=EOMONTH(L$3,0),$H22>=L$3),"D",""))) | M22: =IF($AH22="","",IF(AND($E22<>"",$E22<=EOMONTH(M$3,0),$F22>=M$3),IF(AND($G22<>"",$G22<=EOMONTH(M$3,0),$H22>=M$3),"B","U"),IF(AND($G22<>"",$G22<=EOMONTH(M$3,0),$H22>=M$3),"D",""))) | N22: =IF($AH22="","",IF(AND($E22<>"",$E22<=EOMONTH(N$3,0),$F22>=N$3),IF(AND($G22<>"",$G22<=EOMONTH(N$3,0),$H22>=N$3),"B","U"),IF(AND($G22<>"",$G22<=EOMONTH(N$3,0),$H22>=N$3),"D",""))) | O22: =IF($AH22="","",IF(AND($E22<>"",$E22<=EOMONTH(O$3,0),$F22>=O$3),IF(AND($G22<>"",$G22<=EOMONTH(O$3,0),$H22>=O$3),"B","U"),IF(AND($G22<>"",$G22<=EOMONTH(O$3,0),$H22>=O$3),"D",""))) | P22: =IF($AH22="","",IF(AND($E22<>"",$E22<=EOMONTH(P$3,0),$F22>=P$3),IF(AND($G22<>"",$G22<=EOMONTH(P$3,0),$H22>=P$3),"B","U"),IF(AND($G22<>"",$G22<=EOMONTH(P$3,0),$H22>=P$3),"D",""))) | ... AF22: =IF($AH22="","",IF(AND($E22<>"",$E22<=EOMONTH(AF$3,0),$F22>=AF$3),IF(AND($G22<>"",$G22<=EOMONTH(AF$3,0),$H22>=AF$3),"B","U"),IF(AND($G22<>"",$G22<=EOMONTH(AF$3,0),$H22>=AF$3),"D",""))) | AG22: =IF($AH22="","",INDEX('Roadmap Calc (Don’t Touch)'!$D$2:$D$205,$AH22)) | AH22: =IFERROR(MATCH(16,'Roadmap Calc (Don’t Touch)'!$O$2:$O$205,0),"")
A23: =IF($AH23="","",IF($AG23=$AG22,"",$AG23)) | B23: =IF($AH23="","",INDEX('Roadmap Calc (Don’t Touch)'!$B$2:$B$205,$AH23)) | C23: =IF($AH23="","",INDEX('Roadmap Calc (Don’t Touch)'!$E$2:$E$205,$AH23)) | D23: =IF($AH23="","",INDEX('Roadmap Calc (Don’t Touch)'!$F$2:$F$205,$AH23)) | E23: =IF($AH23="","",INDEX('Roadmap Calc (Don’t Touch)'!$G$2:$G$205,$AH23)) | F23: =IF($AH23="","",INDEX('Roadmap Calc (Don’t Touch)'!$H$2:$H$205,$AH23)) | G23: =IF($AH23="","",INDEX('Roadmap Calc (Don’t Touch)'!$I$2:$I$205,$AH23)) | H23: =IF($AH23="","",INDEX('Roadmap Calc (Don’t Touch)'!$J$2:$J$205,$AH23)) | I23: =IF($AH23="","",IF(AND($E23<>"",$E23<=EOMONTH(I$3,0),$F23>=I$3),IF(AND($G23<>"",$G23<=EOMONTH(I$3,0),$H23>=I$3),"B","U"),IF(AND($G23<>"",$G23<=EOMONTH(I$3,0),$H23>=I$3),"D",""))) | J23: =IF($AH23="","",IF(AND($E23<>"",$E23<=EOMONTH(J$3,0),$F23>=J$3),IF(AND($G23<>"",$G23<=EOMONTH(J$3,0),$H23>=J$3),"B","U"),IF(AND($G23<>"",$G23<=EOMONTH(J$3,0),$H23>=J$3),"D",""))) | K23: =IF($AH23="","",IF(AND($E23<>"",$E23<=EOMONTH(K$3,0),$F23>=K$3),IF(AND($G23<>"",$G23<=EOMONTH(K$3,0),$H23>=K$3),"B","U"),IF(AND($G23<>"",$G23<=EOMONTH(K$3,0),$H23>=K$3),"D",""))) | L23: =IF($AH23="","",IF(AND($E23<>"",$E23<=EOMONTH(L$3,0),$F23>=L$3),IF(AND($G23<>"",$G23<=EOMONTH(L$3,0),$H23>=L$3),"B","U"),IF(AND($G23<>"",$G23<=EOMONTH(L$3,0),$H23>=L$3),"D",""))) | M23: =IF($AH23="","",IF(AND($E23<>"",$E23<=EOMONTH(M$3,0),$F23>=M$3),IF(AND($G23<>"",$G23<=EOMONTH(M$3,0),$H23>=M$3),"B","U"),IF(AND($G23<>"",$G23<=EOMONTH(M$3,0),$H23>=M$3),"D",""))) | N23: =IF($AH23="","",IF(AND($E23<>"",$E23<=EOMONTH(N$3,0),$F23>=N$3),IF(AND($G23<>"",$G23<=EOMONTH(N$3,0),$H23>=N$3),"B","U"),IF(AND($G23<>"",$G23<=EOMONTH(N$3,0),$H23>=N$3),"D",""))) | O23: =IF($AH23="","",IF(AND($E23<>"",$E23<=EOMONTH(O$3,0),$F23>=O$3),IF(AND($G23<>"",$G23<=EOMONTH(O$3,0),$H23>=O$3),"B","U"),IF(AND($G23<>"",$G23<=EOMONTH(O$3,0),$H23>=O$3),"D",""))) | P23: =IF($AH23="","",IF(AND($E23<>"",$E23<=EOMONTH(P$3,0),$F23>=P$3),IF(AND($G23<>"",$G23<=EOMONTH(P$3,0),$H23>=P$3),"B","U"),IF(AND($G23<>"",$G23<=EOMONTH(P$3,0),$H23>=P$3),"D",""))) | ... AF23: =IF($AH23="","",IF(AND($E23<>"",$E23<=EOMONTH(AF$3,0),$F23>=AF$3),IF(AND($G23<>"",$G23<=EOMONTH(AF$3,0),$H23>=AF$3),"B","U"),IF(AND($G23<>"",$G23<=EOMONTH(AF$3,0),$H23>=AF$3),"D",""))) | AG23: =IF($AH23="","",INDEX('Roadmap Calc (Don’t Touch)'!$D$2:$D$205,$AH23)) | AH23: =IFERROR(MATCH(17,'Roadmap Calc (Don’t Touch)'!$O$2:$O$205,0),"")
A24: =IF($AH24="","",IF($AG24=$AG23,"",$AG24)) | B24: =IF($AH24="","",INDEX('Roadmap Calc (Don’t Touch)'!$B$2:$B$205,$AH24)) | C24: =IF($AH24="","",INDEX('Roadmap Calc (Don’t Touch)'!$E$2:$E$205,$AH24)) | D24: =IF($AH24="","",INDEX('Roadmap Calc (Don’t Touch)'!$F$2:$F$205,$AH24)) | E24: =IF($AH24="","",INDEX('Roadmap Calc (Don’t Touch)'!$G$2:$G$205,$AH24)) | F24: =IF($AH24="","",INDEX('Roadmap Calc (Don’t Touch)'!$H$2:$H$205,$AH24)) | G24: =IF($AH24="","",INDEX('Roadmap Calc (Don’t Touch)'!$I$2:$I$205,$AH24)) | H24: =IF($AH24="","",INDEX('Roadmap Calc (Don’t Touch)'!$J$2:$J$205,$AH24)) | I24: =IF($AH24="","",IF(AND($E24<>"",$E24<=EOMONTH(I$3,0),$F24>=I$3),IF(AND($G24<>"",$G24<=EOMONTH(I$3,0),$H24>=I$3),"B","U"),IF(AND($G24<>"",$G24<=EOMONTH(I$3,0),$H24>=I$3),"D",""))) | J24: =IF($AH24="","",IF(AND($E24<>"",$E24<=EOMONTH(J$3,0),$F24>=J$3),IF(AND($G24<>"",$G24<=EOMONTH(J$3,0),$H24>=J$3),"B","U"),IF(AND($G24<>"",$G24<=EOMONTH(J$3,0),$H24>=J$3),"D",""))) | K24: =IF($AH24="","",IF(AND($E24<>"",$E24<=EOMONTH(K$3,0),$F24>=K$3),IF(AND($G24<>"",$G24<=EOMONTH(K$3,0),$H24>=K$3),"B","U"),IF(AND($G24<>"",$G24<=EOMONTH(K$3,0),$H24>=K$3),"D",""))) | L24: =IF($AH24="","",IF(AND($E24<>"",$E24<=EOMONTH(L$3,0),$F24>=L$3),IF(AND($G24<>"",$G24<=EOMONTH(L$3,0),$H24>=L$3),"B","U"),IF(AND($G24<>"",$G24<=EOMONTH(L$3,0),$H24>=L$3),"D",""))) | M24: =IF($AH24="","",IF(AND($E24<>"",$E24<=EOMONTH(M$3,0),$F24>=M$3),IF(AND($G24<>"",$G24<=EOMONTH(M$3,0),$H24>=M$3),"B","U"),IF(AND($G24<>"",$G24<=EOMONTH(M$3,0),$H24>=M$3),"D",""))) | N24: =IF($AH24="","",IF(AND($E24<>"",$E24<=EOMONTH(N$3,0),$F24>=N$3),IF(AND($G24<>"",$G24<=EOMONTH(N$3,0),$H24>=N$3),"B","U"),IF(AND($G24<>"",$G24<=EOMONTH(N$3,0),$H24>=N$3),"D",""))) | O24: =IF($AH24="","",IF(AND($E24<>"",$E24<=EOMONTH(O$3,0),$F24>=O$3),IF(AND($G24<>"",$G24<=EOMONTH(O$3,0),$H24>=O$3),"B","U"),IF(AND($G24<>"",$G24<=EOMONTH(O$3,0),$H24>=O$3),"D",""))) | P24: =IF($AH24="","",IF(AND($E24<>"",$E24<=EOMONTH(P$3,0),$F24>=P$3),IF(AND($G24<>"",$G24<=EOMONTH(P$3,0),$H24>=P$3),"B","U"),IF(AND($G24<>"",$G24<=EOMONTH(P$3,0),$H24>=P$3),"D",""))) | ... AF24: =IF($AH24="","",IF(AND($E24<>"",$E24<=EOMONTH(AF$3,0),$F24>=AF$3),IF(AND($G24<>"",$G24<=EOMONTH(AF$3,0),$H24>=AF$3),"B","U"),IF(AND($G24<>"",$G24<=EOMONTH(AF$3,0),$H24>=AF$3),"D",""))) | AG24: =IF($AH24="","",INDEX('Roadmap Calc (Don’t Touch)'!$D$2:$D$205,$AH24)) | AH24: =IFERROR(MATCH(18,'Roadmap Calc (Don’t Touch)'!$O$2:$O$205,0),"")
A25: =IF($AH25="","",IF($AG25=$AG24,"",$AG25)) | B25: =IF($AH25="","",INDEX('Roadmap Calc (Don’t Touch)'!$B$2:$B$205,$AH25)) | C25: =IF($AH25="","",INDEX('Roadmap Calc (Don’t Touch)'!$E$2:$E$205,$AH25)) | D25: =IF($AH25="","",INDEX('Roadmap Calc (Don’t Touch)'!$F$2:$F$205,$AH25)) | E25: =IF($AH25="","",INDEX('Roadmap Calc (Don’t Touch)'!$G$2:$G$205,$AH25)) | F25: =IF($AH25="","",INDEX('Roadmap Calc (Don’t Touch)'!$H$2:$H$205,$AH25)) | G25: =IF($AH25="","",INDEX('Roadmap Calc (Don’t Touch)'!$I$2:$I$205,$AH25)) | H25: =IF($AH25="","",INDEX('Roadmap Calc (Don’t Touch)'!$J$2:$J$205,$AH25)) | I25: =IF($AH25="","",IF(AND($E25<>"",$E25<=EOMONTH(I$3,0),$F25>=I$3),IF(AND($G25<>"",$G25<=EOMONTH(I$3,0),$H25>=I$3),"B","U"),IF(AND($G25<>"",$G25<=EOMONTH(I$3,0),$H25>=I$3),"D",""))) | J25: =IF($AH25="","",IF(AND($E25<>"",$E25<=EOMONTH(J$3,0),$F25>=J$3),IF(AND($G25<>"",$G25<=EOMONTH(J$3,0),$H25>=J$3),"B","U"),IF(AND($G25<>"",$G25<=EOMONTH(J$3,0),$H25>=J$3),"D",""))) | K25: =IF($AH25="","",IF(AND($E25<>"",$E25<=EOMONTH(K$3,0),$F25>=K$3),IF(AND($G25<>"",$G25<=EOMONTH(K$3,0),$H25>=K$3),"B","U"),IF(AND($G25<>"",$G25<=EOMONTH(K$3,0),$H25>=K$3),"D",""))) | L25: =IF($AH25="","",IF(AND($E25<>"",$E25<=EOMONTH(L$3,0),$F25>=L$3),IF(AND($G25<>"",$G25<=EOMONTH(L$3,0),$H25>=L$3),"B","U"),IF(AND($G25<>"",$G25<=EOMONTH(L$3,0),$H25>=L$3),"D",""))) | M25: =IF($AH25="","",IF(AND($E25<>"",$E25<=EOMONTH(M$3,0),$F25>=M$3),IF(AND($G25<>"",$G25<=EOMONTH(M$3,0),$H25>=M$3),"B","U"),IF(AND($G25<>"",$G25<=EOMONTH(M$3,0),$H25>=M$3),"D",""))) | N25: =IF($AH25="","",IF(AND($E25<>"",$E25<=EOMONTH(N$3,0),$F25>=N$3),IF(AND($G25<>"",$G25<=EOMONTH(N$3,0),$H25>=N$3),"B","U"),IF(AND($G25<>"",$G25<=EOMONTH(N$3,0),$H25>=N$3),"D",""))) | O25: =IF($AH25="","",IF(AND($E25<>"",$E25<=EOMONTH(O$3,0),$F25>=O$3),IF(AND($G25<>"",$G25<=EOMONTH(O$3,0),$H25>=O$3),"B","U"),IF(AND($G25<>"",$G25<=EOMONTH(O$3,0),$H25>=O$3),"D",""))) | P25: =IF($AH25="","",IF(AND($E25<>"",$E25<=EOMONTH(P$3,0),$F25>=P$3),IF(AND($G25<>"",$G25<=EOMONTH(P$3,0),$H25>=P$3),"B","U"),IF(AND($G25<>"",$G25<=EOMONTH(P$3,0),$H25>=P$3),"D",""))) | ... AF25: =IF($AH25="","",IF(AND($E25<>"",$E25<=EOMONTH(AF$3,0),$F25>=AF$3),IF(AND($G25<>"",$G25<=EOMONTH(AF$3,0),$H25>=AF$3),"B","U"),IF(AND($G25<>"",$G25<=EOMONTH(AF$3,0),$H25>=AF$3),"D",""))) | AG25: =IF($AH25="","",INDEX('Roadmap Calc (Don’t Touch)'!$D$2:$D$205,$AH25)) | AH25: =IFERROR(MATCH(19,'Roadmap Calc (Don’t Touch)'!$O$2:$O$205,0),"")
A26: =IF($AH26="","",IF($AG26=$AG25,"",$AG26)) | B26: =IF($AH26="","",INDEX('Roadmap Calc (Don’t Touch)'!$B$2:$B$205,$AH26)) | C26: =IF($AH26="","",INDEX('Roadmap Calc (Don’t Touch)'!$E$2:$E$205,$AH26)) | D26: =IF($AH26="","",INDEX('Roadmap Calc (Don’t Touch)'!$F$2:$F$205,$AH26)) | E26: =IF($AH26="","",INDEX('Roadmap Calc (Don’t Touch)'!$G$2:$G$205,$AH26)) | F26: =IF($AH26="","",INDEX('Roadmap Calc (Don’t Touch)'!$H$2:$H$205,$AH26)) | G26: =IF($AH26="","",INDEX('Roadmap Calc (Don’t Touch)'!$I$2:$I$205,$AH26)) | H26: =IF($AH26="","",INDEX('Roadmap Calc (Don’t Touch)'!$J$2:$J$205,$AH26)) | I26: =IF($AH26="","",IF(AND($E26<>"",$E26<=EOMONTH(I$3,0),$F26>=I$3),IF(AND($G26<>"",$G26<=EOMONTH(I$3,0),$H26>=I$3),"B","U"),IF(AND($G26<>"",$G26<=EOMONTH(I$3,0),$H26>=I$3),"D",""))) | J26: =IF($AH26="","",IF(AND($E26<>"",$E26<=EOMONTH(J$3,0),$F26>=J$3),IF(AND($G26<>"",$G26<=EOMONTH(J$3,0),$H26>=J$3),"B","U"),IF(AND($G26<>"",$G26<=EOMONTH(J$3,0),$H26>=J$3),"D",""))) | K26: =IF($AH26="","",IF(AND($E26<>"",$E26<=EOMONTH(K$3,0),$F26>=K$3),IF(AND($G26<>"",$G26<=EOMONTH(K$3,0),$H26>=K$3),"B","U"),IF(AND($G26<>"",$G26<=EOMONTH(K$3,0),$H26>=K$3),"D",""))) | L26: =IF($AH26="","",IF(AND($E26<>"",$E26<=EOMONTH(L$3,0),$F26>=L$3),IF(AND($G26<>"",$G26<=EOMONTH(L$3,0),$H26>=L$3),"B","U"),IF(AND($G26<>"",$G26<=EOMONTH(L$3,0),$H26>=L$3),"D",""))) | M26: =IF($AH26="","",IF(AND($E26<>"",$E26<=EOMONTH(M$3,0),$F26>=M$3),IF(AND($G26<>"",$G26<=EOMONTH(M$3,0),$H26>=M$3),"B","U"),IF(AND($G26<>"",$G26<=EOMONTH(M$3,0),$H26>=M$3),"D",""))) | N26: =IF($AH26="","",IF(AND($E26<>"",$E26<=EOMONTH(N$3,0),$F26>=N$3),IF(AND($G26<>"",$G26<=EOMONTH(N$3,0),$H26>=N$3),"B","U"),IF(AND($G26<>"",$G26<=EOMONTH(N$3,0),$H26>=N$3),"D",""))) | O26: =IF($AH26="","",IF(AND($E26<>"",$E26<=EOMONTH(O$3,0),$F26>=O$3),IF(AND($G26<>"",$G26<=EOMONTH(O$3,0),$H26>=O$3),"B","U"),IF(AND($G26<>"",$G26<=EOMONTH(O$3,0),$H26>=O$3),"D",""))) | P26: =IF($AH26="","",IF(AND($E26<>"",$E26<=EOMONTH(P$3,0),$F26>=P$3),IF(AND($G26<>"",$G26<=EOMONTH(P$3,0),$H26>=P$3),"B","U"),IF(AND($G26<>"",$G26<=EOMONTH(P$3,0),$H26>=P$3),"D",""))) | ... AF26: =IF($AH26="","",IF(AND($E26<>"",$E26<=EOMONTH(AF$3,0),$F26>=AF$3),IF(AND($G26<>"",$G26<=EOMONTH(AF$3,0),$H26>=AF$3),"B","U"),IF(AND($G26<>"",$G26<=EOMONTH(AF$3,0),$H26>=AF$3),"D",""))) | AG26: =IF($AH26="","",INDEX('Roadmap Calc (Don’t Touch)'!$D$2:$D$205,$AH26)) | AH26: =IFERROR(MATCH(20,'Roadmap Calc (Don’t Touch)'!$O$2:$O$205,0),"")
A27: =IF($AH27="","",IF($AG27=$AG26,"",$AG27)) | B27: =IF($AH27="","",INDEX('Roadmap Calc (Don’t Touch)'!$B$2:$B$205,$AH27)) | C27: =IF($AH27="","",INDEX('Roadmap Calc (Don’t Touch)'!$E$2:$E$205,$AH27)) | D27: =IF($AH27="","",INDEX('Roadmap Calc (Don’t Touch)'!$F$2:$F$205,$AH27)) | E27: =IF($AH27="","",INDEX('Roadmap Calc (Don’t Touch)'!$G$2:$G$205,$AH27)) | F27: =IF($AH27="","",INDEX('Roadmap Calc (Don’t Touch)'!$H$2:$H$205,$AH27)) | G27: =IF($AH27="","",INDEX('Roadmap Calc (Don’t Touch)'!$I$2:$I$205,$AH27)) | H27: =IF($AH27="","",INDEX('Roadmap Calc (Don’t Touch)'!$J$2:$J$205,$AH27)) | I27: =IF($AH27="","",IF(AND($E27<>"",$E27<=EOMONTH(I$3,0),$F27>=I$3),IF(AND($G27<>"",$G27<=EOMONTH(I$3,0),$H27>=I$3),"B","U"),IF(AND($G27<>"",$G27<=EOMONTH(I$3,0),$H27>=I$3),"D",""))) | J27: =IF($AH27="","",IF(AND($E27<>"",$E27<=EOMONTH(J$3,0),$F27>=J$3),IF(AND($G27<>"",$G27<=EOMONTH(J$3,0),$H27>=J$3),"B","U"),IF(AND($G27<>"",$G27<=EOMONTH(J$3,0),$H27>=J$3),"D",""))) | K27: =IF($AH27="","",IF(AND($E27<>"",$E27<=EOMONTH(K$3,0),$F27>=K$3),IF(AND($G27<>"",$G27<=EOMONTH(K$3,0),$H27>=K$3),"B","U"),IF(AND($G27<>"",$G27<=EOMONTH(K$3,0),$H27>=K$3),"D",""))) | L27: =IF($AH27="","",IF(AND($E27<>"",$E27<=EOMONTH(L$3,0),$F27>=L$3),IF(AND($G27<>"",$G27<=EOMONTH(L$3,0),$H27>=L$3),"B","U"),IF(AND($G27<>"",$G27<=EOMONTH(L$3,0),$H27>=L$3),"D",""))) | M27: =IF($AH27="","",IF(AND($E27<>"",$E27<=EOMONTH(M$3,0),$F27>=M$3),IF(AND($G27<>"",$G27<=EOMONTH(M$3,0),$H27>=M$3),"B","U"),IF(AND($G27<>"",$G27<=EOMONTH(M$3,0),$H27>=M$3),"D",""))) | N27: =IF($AH27="","",IF(AND($E27<>"",$E27<=EOMONTH(N$3,0),$F27>=N$3),IF(AND($G27<>"",$G27<=EOMONTH(N$3,0),$H27>=N$3),"B","U"),IF(AND($G27<>"",$G27<=EOMONTH(N$3,0),$H27>=N$3),"D",""))) | O27: =IF($AH27="","",IF(AND($E27<>"",$E27<=EOMONTH(O$3,0),$F27>=O$3),IF(AND($G27<>"",$G27<=EOMONTH(O$3,0),$H27>=O$3),"B","U"),IF(AND($G27<>"",$G27<=EOMONTH(O$3,0),$H27>=O$3),"D",""))) | P27: =IF($AH27="","",IF(AND($E27<>"",$E27<=EOMONTH(P$3,0),$F27>=P$3),IF(AND($G27<>"",$G27<=EOMONTH(P$3,0),$H27>=P$3),"B","U"),IF(AND($G27<>"",$G27<=EOMONTH(P$3,0),$H27>=P$3),"D",""))) | ... AF27: =IF($AH27="","",IF(AND($E27<>"",$E27<=EOMONTH(AF$3,0),$F27>=AF$3),IF(AND($G27<>"",$G27<=EOMONTH(AF$3,0),$H27>=AF$3),"B","U"),IF(AND($G27<>"",$G27<=EOMONTH(AF$3,0),$H27>=AF$3),"D",""))) | AG27: =IF($AH27="","",INDEX('Roadmap Calc (Don’t Touch)'!$D$2:$D$205,$AH27)) | AH27: =IFERROR(MATCH(21,'Roadmap Calc (Don’t Touch)'!$O$2:$O$205,0),"")
A28: =IF($AH28="","",IF($AG28=$AG27,"",$AG28)) | B28: =IF($AH28="","",INDEX('Roadmap Calc (Don’t Touch)'!$B$2:$B$205,$AH28)) | C28: =IF($AH28="","",INDEX('Roadmap Calc (Don’t Touch)'!$E$2:$E$205,$AH28)) | D28: =IF($AH28="","",INDEX('Roadmap Calc (Don’t Touch)'!$F$2:$F$205,$AH28)) | E28: =IF($AH28="","",INDEX('Roadmap Calc (Don’t Touch)'!$G$2:$G$205,$AH28)) | F28: =IF($AH28="","",INDEX('Roadmap Calc (Don’t Touch)'!$H$2:$H$205,$AH28)) | G28: =IF($AH28="","",INDEX('Roadmap Calc (Don’t Touch)'!$I$2:$I$205,$AH28)) | H28: =IF($AH28="","",INDEX('Roadmap Calc (Don’t Touch)'!$J$2:$J$205,$AH28)) | I28: =IF($AH28="","",IF(AND($E28<>"",$E28<=EOMONTH(I$3,0),$F28>=I$3),IF(AND($G28<>"",$G28<=EOMONTH(I$3,0),$H28>=I$3),"B","U"),IF(AND($G28<>"",$G28<=EOMONTH(I$3,0),$H28>=I$3),"D",""))) | J28: =IF($AH28="","",IF(AND($E28<>"",$E28<=EOMONTH(J$3,0),$F28>=J$3),IF(AND($G28<>"",$G28<=EOMONTH(J$3,0),$H28>=J$3),"B","U"),IF(AND($G28<>"",$G28<=EOMONTH(J$3,0),$H28>=J$3),"D",""))) | K28: =IF($AH28="","",IF(AND($E28<>"",$E28<=EOMONTH(K$3,0),$F28>=K$3),IF(AND($G28<>"",$G28<=EOMONTH(K$3,0),$H28>=K$3),"B","U"),IF(AND($G28<>"",$G28<=EOMONTH(K$3,0),$H28>=K$3),"D",""))) | L28: =IF($AH28="","",IF(AND($E28<>"",$E28<=EOMONTH(L$3,0),$F28>=L$3),IF(AND($G28<>"",$G28<=EOMONTH(L$3,0),$H28>=L$3),"B","U"),IF(AND($G28<>"",$G28<=EOMONTH(L$3,0),$H28>=L$3),"D",""))) | M28: =IF($AH28="","",IF(AND($E28<>"",$E28<=EOMONTH(M$3,0),$F28>=M$3),IF(AND($G28<>"",$G28<=EOMONTH(M$3,0),$H28>=M$3),"B","U"),IF(AND($G28<>"",$G28<=EOMONTH(M$3,0),$H28>=M$3),"D",""))) | N28: =IF($AH28="","",IF(AND($E28<>"",$E28<=EOMONTH(N$3,0),$F28>=N$3),IF(AND($G28<>"",$G28<=EOMONTH(N$3,0),$H28>=N$3),"B","U"),IF(AND($G28<>"",$G28<=EOMONTH(N$3,0),$H28>=N$3),"D",""))) | O28: =IF($AH28="","",IF(AND($E28<>"",$E28<=EOMONTH(O$3,0),$F28>=O$3),IF(AND($G28<>"",$G28<=EOMONTH(O$3,0),$H28>=O$3),"B","U"),IF(AND($G28<>"",$G28<=EOMONTH(O$3,0),$H28>=O$3),"D",""))) | P28: =IF($AH28="","",IF(AND($E28<>"",$E28<=EOMONTH(P$3,0),$F28>=P$3),IF(AND($G28<>"",$G28<=EOMONTH(P$3,0),$H28>=P$3),"B","U"),IF(AND($G28<>"",$G28<=EOMONTH(P$3,0),$H28>=P$3),"D",""))) | ... AF28: =IF($AH28="","",IF(AND($E28<>"",$E28<=EOMONTH(AF$3,0),$F28>=AF$3),IF(AND($G28<>"",$G28<=EOMONTH(AF$3,0),$H28>=AF$3),"B","U"),IF(AND($G28<>"",$G28<=EOMONTH(AF$3,0),$H28>=AF$3),"D",""))) | AG28: =IF($AH28="","",INDEX('Roadmap Calc (Don’t Touch)'!$D$2:$D$205,$AH28)) | AH28: =IFERROR(MATCH(22,'Roadmap Calc (Don’t Touch)'!$O$2:$O$205,0),"")
A29: =IF($AH29="","",IF($AG29=$AG28,"",$AG29)) | B29: =IF($AH29="","",INDEX('Roadmap Calc (Don’t Touch)'!$B$2:$B$205,$AH29)) | C29: =IF($AH29="","",INDEX('Roadmap Calc (Don’t Touch)'!$E$2:$E$205,$AH29)) | D29: =IF($AH29="","",INDEX('Roadmap Calc (Don’t Touch)'!$F$2:$F$205,$AH29)) | E29: =IF($AH29="","",INDEX('Roadmap Calc (Don’t Touch)'!$G$2:$G$205,$AH29)) | F29: =IF($AH29="","",INDEX('Roadmap Calc (Don’t Touch)'!$H$2:$H$205,$AH29)) | G29: =IF($AH29="","",INDEX('Roadmap Calc (Don’t Touch)'!$I$2:$I$205,$AH29)) | H29: =IF($AH29="","",INDEX('Roadmap Calc (Don’t Touch)'!$J$2:$J$205,$AH29)) | I29: =IF($AH29="","",IF(AND($E29<>"",$E29<=EOMONTH(I$3,0),$F29>=I$3),IF(AND($G29<>"",$G29<=EOMONTH(I$3,0),$H29>=I$3),"B","U"),IF(AND($G29<>"",$G29<=EOMONTH(I$3,0),$H29>=I$3),"D",""))) | J29: =IF($AH29="","",IF(AND($E29<>"",$E29<=EOMONTH(J$3,0),$F29>=J$3),IF(AND($G29<>"",$G29<=EOMONTH(J$3,0),$H29>=J$3),"B","U"),IF(AND($G29<>"",$G29<=EOMONTH(J$3,0),$H29>=J$3),"D",""))) | K29: =IF($AH29="","",IF(AND($E29<>"",$E29<=EOMONTH(K$3,0),$F29>=K$3),IF(AND($G29<>"",$G29<=EOMONTH(K$3,0),$H29>=K$3),"B","U"),IF(AND($G29<>"",$G29<=EOMONTH(K$3,0),$H29>=K$3),"D",""))) | L29: =IF($AH29="","",IF(AND($E29<>"",$E29<=EOMONTH(L$3,0),$F29>=L$3),IF(AND($G29<>"",$G29<=EOMONTH(L$3,0),$H29>=L$3),"B","U"),IF(AND($G29<>"",$G29<=EOMONTH(L$3,0),$H29>=L$3),"D",""))) | M29: =IF($AH29="","",IF(AND($E29<>"",$E29<=EOMONTH(M$3,0),$F29>=M$3),IF(AND($G29<>"",$G29<=EOMONTH(M$3,0),$H29>=M$3),"B","U"),IF(AND($G29<>"",$G29<=EOMONTH(M$3,0),$H29>=M$3),"D",""))) | N29: =IF($AH29="","",IF(AND($E29<>"",$E29<=EOMONTH(N$3,0),$F29>=N$3),IF(AND($G29<>"",$G29<=EOMONTH(N$3,0),$H29>=N$3),"B","U"),IF(AND($G29<>"",$G29<=EOMONTH(N$3,0),$H29>=N$3),"D",""))) | O29: =IF($AH29="","",IF(AND($E29<>"",$E29<=EOMONTH(O$3,0),$F29>=O$3),IF(AND($G29<>"",$G29<=EOMONTH(O$3,0),$H29>=O$3),"B","U"),IF(AND($G29<>"",$G29<=EOMONTH(O$3,0),$H29>=O$3),"D",""))) | P29: =IF($AH29="","",IF(AND($E29<>"",$E29<=EOMONTH(P$3,0),$F29>=P$3),IF(AND($G29<>"",$G29<=EOMONTH(P$3,0),$H29>=P$3),"B","U"),IF(AND($G29<>"",$G29<=EOMONTH(P$3,0),$H29>=P$3),"D",""))) | ... AF29: =IF($AH29="","",IF(AND($E29<>"",$E29<=EOMONTH(AF$3,0),$F29>=AF$3),IF(AND($G29<>"",$G29<=EOMONTH(AF$3,0),$H29>=AF$3),"B","U"),IF(AND($G29<>"",$G29<=EOMONTH(AF$3,0),$H29>=AF$3),"D",""))) | AG29: =IF($AH29="","",INDEX('Roadmap Calc (Don’t Touch)'!$D$2:$D$205,$AH29)) | AH29: =IFERROR(MATCH(23,'Roadmap Calc (Don’t Touch)'!$O$2:$O$205,0),"")
A30: =IF($AH30="","",IF($AG30=$AG29,"",$AG30)) | B30: =IF($AH30="","",INDEX('Roadmap Calc (Don’t Touch)'!$B$2:$B$205,$AH30)) | C30: =IF($AH30="","",INDEX('Roadmap Calc (Don’t Touch)'!$E$2:$E$205,$AH30)) | D30: =IF($AH30="","",INDEX('Roadmap Calc (Don’t Touch)'!$F$2:$F$205,$AH30)) | E30: =IF($AH30="","",INDEX('Roadmap Calc (Don’t Touch)'!$G$2:$G$205,$AH30)) | F30: =IF($AH30="","",INDEX('Roadmap Calc (Don’t Touch)'!$H$2:$H$205,$AH30)) | G30: =IF($AH30="","",INDEX('Roadmap Calc (Don’t Touch)'!$I$2:$I$205,$AH30)) | H30: =IF($AH30="","",INDEX('Roadmap Calc (Don’t Touch)'!$J$2:$J$205,$AH30)) | I30: =IF($AH30="","",IF(AND($E30<>"",$E30<=EOMONTH(I$3,0),$F30>=I$3),IF(AND($G30<>"",$G30<=EOMONTH(I$3,0),$H30>=I$3),"B","U"),IF(AND($G30<>"",$G30<=EOMONTH(I$3,0),$H30>=I$3),"D",""))) | J30: =IF($AH30="","",IF(AND($E30<>"",$E30<=EOMONTH(J$3,0),$F30>=J$3),IF(AND($G30<>"",$G30<=EOMONTH(J$3,0),$H30>=J$3),"B","U"),IF(AND($G30<>"",$G30<=EOMONTH(J$3,0),$H30>=J$3),"D",""))) | K30: =IF($AH30="","",IF(AND($E30<>"",$E30<=EOMONTH(K$3,0),$F30>=K$3),IF(AND($G30<>"",$G30<=EOMONTH(K$3,0),$H30>=K$3),"B","U"),IF(AND($G30<>"",$G30<=EOMONTH(K$3,0),$H30>=K$3),"D",""))) | L30: =IF($AH30="","",IF(AND($E30<>"",$E30<=EOMONTH(L$3,0),$F30>=L$3),IF(AND($G30<>"",$G30<=EOMONTH(L$3,0),$H30>=L$3),"B","U"),IF(AND($G30<>"",$G30<=EOMONTH(L$3,0),$H30>=L$3),"D",""))) | M30: =IF($AH30="","",IF(AND($E30<>"",$E30<=EOMONTH(M$3,0),$F30>=M$3),IF(AND($G30<>"",$G30<=EOMONTH(M$3,0),$H30>=M$3),"B","U"),IF(AND($G30<>"",$G30<=EOMONTH(M$3,0),$H30>=M$3),"D",""))) | N30: =IF($AH30="","",IF(AND($E30<>"",$E30<=EOMONTH(N$3,0),$F30>=N$3),IF(AND($G30<>"",$G30<=EOMONTH(N$3,0),$H30>=N$3),"B","U"),IF(AND($G30<>"",$G30<=EOMONTH(N$3,0),$H30>=N$3),"D",""))) | O30: =IF($AH30="","",IF(AND($E30<>"",$E30<=EOMONTH(O$3,0),$F30>=O$3),IF(AND($G30<>"",$G30<=EOMONTH(O$3,0),$H30>=O$3),"B","U"),IF(AND($G30<>"",$G30<=EOMONTH(O$3,0),$H30>=O$3),"D",""))) | P30: =IF($AH30="","",IF(AND($E30<>"",$E30<=EOMONTH(P$3,0),$F30>=P$3),IF(AND($G30<>"",$G30<=EOMONTH(P$3,0),$H30>=P$3),"B","U"),IF(AND($G30<>"",$G30<=EOMONTH(P$3,0),$H30>=P$3),"D",""))) | ... AF30: =IF($AH30="","",IF(AND($E30<>"",$E30<=EOMONTH(AF$3,0),$F30>=AF$3),IF(AND($G30<>"",$G30<=EOMONTH(AF$3,0),$H30>=AF$3),"B","U"),IF(AND($G30<>"",$G30<=EOMONTH(AF$3,0),$H30>=AF$3),"D",""))) | AG30: =IF($AH30="","",INDEX('Roadmap Calc (Don’t Touch)'!$D$2:$D$205,$AH30)) | AH30: =IFERROR(MATCH(24,'Roadmap Calc (Don’t Touch)'!$O$2:$O$205,0),"")
A31: =IF($AH31="","",IF($AG31=$AG30,"",$AG31)) | B31: =IF($AH31="","",INDEX('Roadmap Calc (Don’t Touch)'!$B$2:$B$205,$AH31)) | C31: =IF($AH31="","",INDEX('Roadmap Calc (Don’t Touch)'!$E$2:$E$205,$AH31)) | D31: =IF($AH31="","",INDEX('Roadmap Calc (Don’t Touch)'!$F$2:$F$205,$AH31)) | E31: =IF($AH31="","",INDEX('Roadmap Calc (Don’t Touch)'!$G$2:$G$205,$AH31)) | F31: =IF($AH31="","",INDEX('Roadmap Calc (Don’t Touch)'!$H$2:$H$205,$AH31)) | G31: =IF($AH31="","",INDEX('Roadmap Calc (Don’t Touch)'!$I$2:$I$205,$AH31)) | H31: =IF($AH31="","",INDEX('Roadmap Calc (Don’t Touch)'!$J$2:$J$205,$AH31)) | I31: =IF($AH31="","",IF(AND($E31<>"",$E31<=EOMONTH(I$3,0),$F31>=I$3),IF(AND($G31<>"",$G31<=EOMONTH(I$3,0),$H31>=I$3),"B","U"),IF(AND($G31<>"",$G31<=EOMONTH(I$3,0),$H31>=I$3),"D",""))) | J31: =IF($AH31="","",IF(AND($E31<>"",$E31<=EOMONTH(J$3,0),$F31>=J$3),IF(AND($G31<>"",$G31<=EOMONTH(J$3,0),$H31>=J$3),"B","U"),IF(AND($G31<>"",$G31<=EOMONTH(J$3,0),$H31>=J$3),"D",""))) | K31: =IF($AH31="","",IF(AND($E31<>"",$E31<=EOMONTH(K$3,0),$F31>=K$3),IF(AND($G31<>"",$G31<=EOMONTH(K$3,0),$H31>=K$3),"B","U"),IF(AND($G31<>"",$G31<=EOMONTH(K$3,0),$H31>=K$3),"D",""))) | L31: =IF($AH31="","",IF(AND($E31<>"",$E31<=EOMONTH(L$3,0),$F31>=L$3),IF(AND($G31<>"",$G31<=EOMONTH(L$3,0),$H31>=L$3),"B","U"),IF(AND($G31<>"",$G31<=EOMONTH(L$3,0),$H31>=L$3),"D",""))) | M31: =IF($AH31="","",IF(AND($E31<>"",$E31<=EOMONTH(M$3,0),$F31>=M$3),IF(AND($G31<>"",$G31<=EOMONTH(M$3,0),$H31>=M$3),"B","U"),IF(AND($G31<>"",$G31<=EOMONTH(M$3,0),$H31>=M$3),"D",""))) | N31: =IF($AH31="","",IF(AND($E31<>"",$E31<=EOMONTH(N$3,0),$F31>=N$3),IF(AND($G31<>"",$G31<=EOMONTH(N$3,0),$H31>=N$3),"B","U"),IF(AND($G31<>"",$G31<=EOMONTH(N$3,0),$H31>=N$3),"D",""))) | O31: =IF($AH31="","",IF(AND($E31<>"",$E31<=EOMONTH(O$3,0),$F31>=O$3),IF(AND($G31<>"",$G31<=EOMONTH(O$3,0),$H31>=O$3),"B","U"),IF(AND($G31<>"",$G31<=EOMONTH(O$3,0),$H31>=O$3),"D",""))) | P31: =IF($AH31="","",IF(AND($E31<>"",$E31<=EOMONTH(P$3,0),$F31>=P$3),IF(AND($G31<>"",$G31<=EOMONTH(P$3,0),$H31>=P$3),"B","U"),IF(AND($G31<>"",$G31<=EOMONTH(P$3,0),$H31>=P$3),"D",""))) | ... AF31: =IF($AH31="","",IF(AND($E31<>"",$E31<=EOMONTH(AF$3,0),$F31>=AF$3),IF(AND($G31<>"",$G31<=EOMONTH(AF$3,0),$H31>=AF$3),"B","U"),IF(AND($G31<>"",$G31<=EOMONTH(AF$3,0),$H31>=AF$3),"D",""))) | AG31: =IF($AH31="","",INDEX('Roadmap Calc (Don’t Touch)'!$D$2:$D$205,$AH31)) | AH31: =IFERROR(MATCH(25,'Roadmap Calc (Don’t Touch)'!$O$2:$O$205,0),"")
A32: =IF($AH32="","",IF($AG32=$AG31,"",$AG32)) | B32: =IF($AH32="","",INDEX('Roadmap Calc (Don’t Touch)'!$B$2:$B$205,$AH32)) | C32: =IF($AH32="","",INDEX('Roadmap Calc (Don’t Touch)'!$E$2:$E$205,$AH32)) | D32: =IF($AH32="","",INDEX('Roadmap Calc (Don’t Touch)'!$F$2:$F$205,$AH32)) | E32: =IF($AH32="","",INDEX('Roadmap Calc (Don’t Touch)'!$G$2:$G$205,$AH32)) | F32: =IF($AH32="","",INDEX('Roadmap Calc (Don’t Touch)'!$H$2:$H$205,$AH32)) | G32: =IF($AH32="","",INDEX('Roadmap Calc (Don’t Touch)'!$I$2:$I$205,$AH32)) | H32: =IF($AH32="","",INDEX('Roadmap Calc (Don’t Touch)'!$J$2:$J$205,$AH32)) | I32: =IF($AH32="","",IF(AND($E32<>"",$E32<=EOMONTH(I$3,0),$F32>=I$3),IF(AND($G32<>"",$G32<=EOMONTH(I$3,0),$H32>=I$3),"B","U"),IF(AND($G32<>"",$G32<=EOMONTH(I$3,0),$H32>=I$3),"D",""))) | J32: =IF($AH32="","",IF(AND($E32<>"",$E32<=EOMONTH(J$3,0),$F32>=J$3),IF(AND($G32<>"",$G32<=EOMONTH(J$3,0),$H32>=J$3),"B","U"),IF(AND($G32<>"",$G32<=EOMONTH(J$3,0),$H32>=J$3),"D",""))) | K32: =IF($AH32="","",IF(AND($E32<>"",$E32<=EOMONTH(K$3,0),$F32>=K$3),IF(AND($G32<>"",$G32<=EOMONTH(K$3,0),$H32>=K$3),"B","U"),IF(AND($G32<>"",$G32<=EOMONTH(K$3,0),$H32>=K$3),"D",""))) | L32: =IF($AH32="","",IF(AND($E32<>"",$E32<=EOMONTH(L$3,0),$F32>=L$3),IF(AND($G32<>"",$G32<=EOMONTH(L$3,0),$H32>=L$3),"B","U"),IF(AND($G32<>"",$G32<=EOMONTH(L$3,0),$H32>=L$3),"D",""))) | M32: =IF($AH32="","",IF(AND($E32<>"",$E32<=EOMONTH(M$3,0),$F32>=M$3),IF(AND($G32<>"",$G32<=EOMONTH(M$3,0),$H32>=M$3),"B","U"),IF(AND($G32<>"",$G32<=EOMONTH(M$3,0),$H32>=M$3),"D",""))) | N32: =IF($AH32="","",IF(AND($E32<>"",$E32<=EOMONTH(N$3,0),$F32>=N$3),IF(AND($G32<>"",$G32<=EOMONTH(N$3,0),$H32>=N$3),"B","U"),IF(AND($G32<>"",$G32<=EOMONTH(N$3,0),$H32>=N$3),"D",""))) | O32: =IF($AH32="","",IF(AND($E32<>"",$E32<=EOMONTH(O$3,0),$F32>=O$3),IF(AND($G32<>"",$G32<=EOMONTH(O$3,0),$H32>=O$3),"B","U"),IF(AND($G32<>"",$G32<=EOMONTH(O$3,0),$H32>=O$3),"D",""))) | P32: =IF($AH32="","",IF(AND($E32<>"",$E32<=EOMONTH(P$3,0),$F32>=P$3),IF(AND($G32<>"",$G32<=EOMONTH(P$3,0),$H32>=P$3),"B","U"),IF(AND($G32<>"",$G32<=EOMONTH(P$3,0),$H32>=P$3),"D",""))) | ... AF32: =IF($AH32="","",IF(AND($E32<>"",$E32<=EOMONTH(AF$3,0),$F32>=AF$3),IF(AND($G32<>"",$G32<=EOMONTH(AF$3,0),$H32>=AF$3),"B","U"),IF(AND($G32<>"",$G32<=EOMONTH(AF$3,0),$H32>=AF$3),"D",""))) | AG32: =IF($AH32="","",INDEX('Roadmap Calc (Don’t Touch)'!$D$2:$D$205,$AH32)) | AH32: =IFERROR(MATCH(26,'Roadmap Calc (Don’t Touch)'!$O$2:$O$205,0),"")
A33: =IF($AH33="","",IF($AG33=$AG32,"",$AG33)) | B33: =IF($AH33="","",INDEX('Roadmap Calc (Don’t Touch)'!$B$2:$B$205,$AH33)) | C33: =IF($AH33="","",INDEX('Roadmap Calc (Don’t Touch)'!$E$2:$E$205,$AH33)) | D33: =IF($AH33="","",INDEX('Roadmap Calc (Don’t Touch)'!$F$2:$F$205,$AH33)) | E33: =IF($AH33="","",INDEX('Roadmap Calc (Don’t Touch)'!$G$2:$G$205,$AH33)) | F33: =IF($AH33="","",INDEX('Roadmap Calc (Don’t Touch)'!$H$2:$H$205,$AH33)) | G33: =IF($AH33="","",INDEX('Roadmap Calc (Don’t Touch)'!$I$2:$I$205,$AH33)) | H33: =IF($AH33="","",INDEX('Roadmap Calc (Don’t Touch)'!$J$2:$J$205,$AH33)) | I33: =IF($AH33="","",IF(AND($E33<>"",$E33<=EOMONTH(I$3,0),$F33>=I$3),IF(AND($G33<>"",$G33<=EOMONTH(I$3,0),$H33>=I$3),"B","U"),IF(AND($G33<>"",$G33<=EOMONTH(I$3,0),$H33>=I$3),"D",""))) | J33: =IF($AH33="","",IF(AND($E33<>"",$E33<=EOMONTH(J$3,0),$F33>=J$3),IF(AND($G33<>"",$G33<=EOMONTH(J$3,0),$H33>=J$3),"B","U"),IF(AND($G33<>"",$G33<=EOMONTH(J$3,0),$H33>=J$3),"D",""))) | K33: =IF($AH33="","",IF(AND($E33<>"",$E33<=EOMONTH(K$3,0),$F33>=K$3),IF(AND($G33<>"",$G33<=EOMONTH(K$3,0),$H33>=K$3),"B","U"),IF(AND($G33<>"",$G33<=EOMONTH(K$3,0),$H33>=K$3),"D",""))) | L33: =IF($AH33="","",IF(AND($E33<>"",$E33<=EOMONTH(L$3,0),$F33>=L$3),IF(AND($G33<>"",$G33<=EOMONTH(L$3,0),$H33>=L$3),"B","U"),IF(AND($G33<>"",$G33<=EOMONTH(L$3,0),$H33>=L$3),"D",""))) | M33: =IF($AH33="","",IF(AND($E33<>"",$E33<=EOMONTH(M$3,0),$F33>=M$3),IF(AND($G33<>"",$G33<=EOMONTH(M$3,0),$H33>=M$3),"B","U"),IF(AND($G33<>"",$G33<=EOMONTH(M$3,0),$H33>=M$3),"D",""))) | N33: =IF($AH33="","",IF(AND($E33<>"",$E33<=EOMONTH(N$3,0),$F33>=N$3),IF(AND($G33<>"",$G33<=EOMONTH(N$3,0),$H33>=N$3),"B","U"),IF(AND($G33<>"",$G33<=EOMONTH(N$3,0),$H33>=N$3),"D",""))) | O33: =IF($AH33="","",IF(AND($E33<>"",$E33<=EOMONTH(O$3,0),$F33>=O$3),IF(AND($G33<>"",$G33<=EOMONTH(O$3,0),$H33>=O$3),"B","U"),IF(AND($G33<>"",$G33<=EOMONTH(O$3,0),$H33>=O$3),"D",""))) | P33: =IF($AH33="","",IF(AND($E33<>"",$E33<=EOMONTH(P$3,0),$F33>=P$3),IF(AND($G33<>"",$G33<=EOMONTH(P$3,0),$H33>=P$3),"B","U"),IF(AND($G33<>"",$G33<=EOMONTH(P$3,0),$H33>=P$3),"D",""))) | ... AF33: =IF($AH33="","",IF(AND($E33<>"",$E33<=EOMONTH(AF$3,0),$F33>=AF$3),IF(AND($G33<>"",$G33<=EOMONTH(AF$3,0),$H33>=AF$3),"B","U"),IF(AND($G33<>"",$G33<=EOMONTH(AF$3,0),$H33>=AF$3),"D",""))) | AG33: =IF($AH33="","",INDEX('Roadmap Calc (Don’t Touch)'!$D$2:$D$205,$AH33)) | AH33: =IFERROR(MATCH(27,'Roadmap Calc (Don’t Touch)'!$O$2:$O$205,0),"")
A34: =IF($AH34="","",IF($AG34=$AG33,"",$AG34)) | B34: =IF($AH34="","",INDEX('Roadmap Calc (Don’t Touch)'!$B$2:$B$205,$AH34)) | C34: =IF($AH34="","",INDEX('Roadmap Calc (Don’t Touch)'!$E$2:$E$205,$AH34)) | D34: =IF($AH34="","",INDEX('Roadmap Calc (Don’t Touch)'!$F$2:$F$205,$AH34)) | E34: =IF($AH34="","",INDEX('Roadmap Calc (Don’t Touch)'!$G$2:$G$205,$AH34)) | F34: =IF($AH34="","",INDEX('Roadmap Calc (Don’t Touch)'!$H$2:$H$205,$AH34)) | G34: =IF($AH34="","",INDEX('Roadmap Calc (Don’t Touch)'!$I$2:$I$205,$AH34)) | H34: =IF($AH34="","",INDEX('Roadmap Calc (Don’t Touch)'!$J$2:$J$205,$AH34)) | I34: =IF($AH34="","",IF(AND($E34<>"",$E34<=EOMONTH(I$3,0),$F34>=I$3),IF(AND($G34<>"",$G34<=EOMONTH(I$3,0),$H34>=I$3),"B","U"),IF(AND($G34<>"",$G34<=EOMONTH(I$3,0),$H34>=I$3),"D",""))) | J34: =IF($AH34="","",IF(AND($E34<>"",$E34<=EOMONTH(J$3,0),$F34>=J$3),IF(AND($G34<>"",$G34<=EOMONTH(J$3,0),$H34>=J$3),"B","U"),IF(AND($G34<>"",$G34<=EOMONTH(J$3,0),$H34>=J$3),"D",""))) | K34: =IF($AH34="","",IF(AND($E34<>"",$E34<=EOMONTH(K$3,0),$F34>=K$3),IF(AND($G34<>"",$G34<=EOMONTH(K$3,0),$H34>=K$3),"B","U"),IF(AND($G34<>"",$G34<=EOMONTH(K$3,0),$H34>=K$3),"D",""))) | L34: =IF($AH34="","",IF(AND($E34<>"",$E34<=EOMONTH(L$3,0),$F34>=L$3),IF(AND($G34<>"",$G34<=EOMONTH(L$3,0),$H34>=L$3),"B","U"),IF(AND($G34<>"",$G34<=EOMONTH(L$3,0),$H34>=L$3),"D",""))) | M34: =IF($AH34="","",IF(AND($E34<>"",$E34<=EOMONTH(M$3,0),$F34>=M$3),IF(AND($G34<>"",$G34<=EOMONTH(M$3,0),$H34>=M$3),"B","U"),IF(AND($G34<>"",$G34<=EOMONTH(M$3,0),$H34>=M$3),"D",""))) | N34: =IF($AH34="","",IF(AND($E34<>"",$E34<=EOMONTH(N$3,0),$F34>=N$3),IF(AND($G34<>"",$G34<=EOMONTH(N$3,0),$H34>=N$3),"B","U"),IF(AND($G34<>"",$G34<=EOMONTH(N$3,0),$H34>=N$3),"D",""))) | O34: =IF($AH34="","",IF(AND($E34<>"",$E34<=EOMONTH(O$3,0),$F34>=O$3),IF(AND($G34<>"",$G34<=EOMONTH(O$3,0),$H34>=O$3),"B","U"),IF(AND($G34<>"",$G34<=EOMONTH(O$3,0),$H34>=O$3),"D",""))) | P34: =IF($AH34="","",IF(AND($E34<>"",$E34<=EOMONTH(P$3,0),$F34>=P$3),IF(AND($G34<>"",$G34<=EOMONTH(P$3,0),$H34>=P$3),"B","U"),IF(AND($G34<>"",$G34<=EOMONTH(P$3,0),$H34>=P$3),"D",""))) | ... AF34: =IF($AH34="","",IF(AND($E34<>"",$E34<=EOMONTH(AF$3,0),$F34>=AF$3),IF(AND($G34<>"",$G34<=EOMONTH(AF$3,0),$H34>=AF$3),"B","U"),IF(AND($G34<>"",$G34<=EOMONTH(AF$3,0),$H34>=AF$3),"D",""))) | AG34: =IF($AH34="","",INDEX('Roadmap Calc (Don’t Touch)'!$D$2:$D$205,$AH34)) | AH34: =IFERROR(MATCH(28,'Roadmap Calc (Don’t Touch)'!$O$2:$O$205,0),"")
A35: =IF($AH35="","",IF($AG35=$AG34,"",$AG35)) | B35: =IF($AH35="","",INDEX('Roadmap Calc (Don’t Touch)'!$B$2:$B$205,$AH35)) | C35: =IF($AH35="","",INDEX('Roadmap Calc (Don’t Touch)'!$E$2:$E$205,$AH35)) | D35: =IF($AH35="","",INDEX('Roadmap Calc (Don’t Touch)'!$F$2:$F$205,$AH35)) | E35: =IF($AH35="","",INDEX('Roadmap Calc (Don’t Touch)'!$G$2:$G$205,$AH35)) | F35: =IF($AH35="","",INDEX('Roadmap Calc (Don’t Touch)'!$H$2:$H$205,$AH35)) | G35: =IF($AH35="","",INDEX('Roadmap Calc (Don’t Touch)'!$I$2:$I$205,$AH35)) | H35: =IF($AH35="","",INDEX('Roadmap Calc (Don’t Touch)'!$J$2:$J$205,$AH35)) | I35: =IF($AH35="","",IF(AND($E35<>"",$E35<=EOMONTH(I$3,0),$F35>=I$3),IF(AND($G35<>"",$G35<=EOMONTH(I$3,0),$H35>=I$3),"B","U"),IF(AND($G35<>"",$G35<=EOMONTH(I$3,0),$H35>=I$3),"D",""))) | J35: =IF($AH35="","",IF(AND($E35<>"",$E35<=EOMONTH(J$3,0),$F35>=J$3),IF(AND($G35<>"",$G35<=EOMONTH(J$3,0),$H35>=J$3),"B","U"),IF(AND($G35<>"",$G35<=EOMONTH(J$3,0),$H35>=J$3),"D",""))) | K35: =IF($AH35="","",IF(AND($E35<>"",$E35<=EOMONTH(K$3,0),$F35>=K$3),IF(AND($G35<>"",$G35<=EOMONTH(K$3,0),$H35>=K$3),"B","U"),IF(AND($G35<>"",$G35<=EOMONTH(K$3,0),$H35>=K$3),"D",""))) | L35: =IF($AH35="","",IF(AND($E35<>"",$E35<=EOMONTH(L$3,0),$F35>=L$3),IF(AND($G35<>"",$G35<=EOMONTH(L$3,0),$H35>=L$3),"B","U"),IF(AND($G35<>"",$G35<=EOMONTH(L$3,0),$H35>=L$3),"D",""))) | M35: =IF($AH35="","",IF(AND($E35<>"",$E35<=EOMONTH(M$3,0),$F35>=M$3),IF(AND($G35<>"",$G35<=EOMONTH(M$3,0),$H35>=M$3),"B","U"),IF(AND($G35<>"",$G35<=EOMONTH(M$3,0),$H35>=M$3),"D",""))) | N35: =IF($AH35="","",IF(AND($E35<>"",$E35<=EOMONTH(N$3,0),$F35>=N$3),IF(AND($G35<>"",$G35<=EOMONTH(N$3,0),$H35>=N$3),"B","U"),IF(AND($G35<>"",$G35<=EOMONTH(N$3,0),$H35>=N$3),"D",""))) | O35: =IF($AH35="","",IF(AND($E35<>"",$E35<=EOMONTH(O$3,0),$F35>=O$3),IF(AND($G35<>"",$G35<=EOMONTH(O$3,0),$H35>=O$3),"B","U"),IF(AND($G35<>"",$G35<=EOMONTH(O$3,0),$H35>=O$3),"D",""))) | P35: =IF($AH35="","",IF(AND($E35<>"",$E35<=EOMONTH(P$3,0),$F35>=P$3),IF(AND($G35<>"",$G35<=EOMONTH(P$3,0),$H35>=P$3),"B","U"),IF(AND($G35<>"",$G35<=EOMONTH(P$3,0),$H35>=P$3),"D",""))) | ... AF35: =IF($AH35="","",IF(AND($E35<>"",$E35<=EOMONTH(AF$3,0),$F35>=AF$3),IF(AND($G35<>"",$G35<=EOMONTH(AF$3,0),$H35>=AF$3),"B","U"),IF(AND($G35<>"",$G35<=EOMONTH(AF$3,0),$H35>=AF$3),"D",""))) | AG35: =IF($AH35="","",INDEX('Roadmap Calc (Don’t Touch)'!$D$2:$D$205,$AH35)) | AH35: =IFERROR(MATCH(29,'Roadmap Calc (Don’t Touch)'!$O$2:$O$205,0),"")
A36: =IF($AH36="","",IF($AG36=$AG35,"",$AG36)) | B36: =IF($AH36="","",INDEX('Roadmap Calc (Don’t Touch)'!$B$2:$B$205,$AH36)) | C36: =IF($AH36="","",INDEX('Roadmap Calc (Don’t Touch)'!$E$2:$E$205,$AH36)) | D36: =IF($AH36="","",INDEX('Roadmap Calc (Don’t Touch)'!$F$2:$F$205,$AH36)) | E36: =IF($AH36="","",INDEX('Roadmap Calc (Don’t Touch)'!$G$2:$G$205,$AH36)) | F36: =IF($AH36="","",INDEX('Roadmap Calc (Don’t Touch)'!$H$2:$H$205,$AH36)) | G36: =IF($AH36="","",INDEX('Roadmap Calc (Don’t Touch)'!$I$2:$I$205,$AH36)) | H36: =IF($AH36="","",INDEX('Roadmap Calc (Don’t Touch)'!$J$2:$J$205,$AH36)) | I36: =IF($AH36="","",IF(AND($E36<>"",$E36<=EOMONTH(I$3,0),$F36>=I$3),IF(AND($G36<>"",$G36<=EOMONTH(I$3,0),$H36>=I$3),"B","U"),IF(AND($G36<>"",$G36<=EOMONTH(I$3,0),$H36>=I$3),"D",""))) | J36: =IF($AH36="","",IF(AND($E36<>"",$E36<=EOMONTH(J$3,0),$F36>=J$3),IF(AND($G36<>"",$G36<=EOMONTH(J$3,0),$H36>=J$3),"B","U"),IF(AND($G36<>"",$G36<=EOMONTH(J$3,0),$H36>=J$3),"D",""))) | K36: =IF($AH36="","",IF(AND($E36<>"",$E36<=EOMONTH(K$3,0),$F36>=K$3),IF(AND($G36<>"",$G36<=EOMONTH(K$3,0),$H36>=K$3),"B","U"),IF(AND($G36<>"",$G36<=EOMONTH(K$3,0),$H36>=K$3),"D",""))) | L36: =IF($AH36="","",IF(AND($E36<>"",$E36<=EOMONTH(L$3,0),$F36>=L$3),IF(AND($G36<>"",$G36<=EOMONTH(L$3,0),$H36>=L$3),"B","U"),IF(AND($G36<>"",$G36<=EOMONTH(L$3,0),$H36>=L$3),"D",""))) | M36: =IF($AH36="","",IF(AND($E36<>"",$E36<=EOMONTH(M$3,0),$F36>=M$3),IF(AND($G36<>"",$G36<=EOMONTH(M$3,0),$H36>=M$3),"B","U"),IF(AND($G36<>"",$G36<=EOMONTH(M$3,0),$H36>=M$3),"D",""))) | N36: =IF($AH36="","",IF(AND($E36<>"",$E36<=EOMONTH(N$3,0),$F36>=N$3),IF(AND($G36<>"",$G36<=EOMONTH(N$3,0),$H36>=N$3),"B","U"),IF(AND($G36<>"",$G36<=EOMONTH(N$3,0),$H36>=N$3),"D",""))) | O36: =IF($AH36="","",IF(AND($E36<>"",$E36<=EOMONTH(O$3,0),$F36>=O$3),IF(AND($G36<>"",$G36<=EOMONTH(O$3,0),$H36>=O$3),"B","U"),IF(AND($G36<>"",$G36<=EOMONTH(O$3,0),$H36>=O$3),"D",""))) | P36: =IF($AH36="","",IF(AND($E36<>"",$E36<=EOMONTH(P$3,0),$F36>=P$3),IF(AND($G36<>"",$G36<=EOMONTH(P$3,0),$H36>=P$3),"B","U"),IF(AND($G36<>"",$G36<=EOMONTH(P$3,0),$H36>=P$3),"D",""))) | ... AF36: =IF($AH36="","",IF(AND($E36<>"",$E36<=EOMONTH(AF$3,0),$F36>=AF$3),IF(AND($G36<>"",$G36<=EOMONTH(AF$3,0),$H36>=AF$3),"B","U"),IF(AND($G36<>"",$G36<=EOMONTH(AF$3,0),$H36>=AF$3),"D",""))) | AG36: =IF($AH36="","",INDEX('Roadmap Calc (Don’t Touch)'!$D$2:$D$205,$AH36)) | AH36: =IFERROR(MATCH(30,'Roadmap Calc (Don’t Touch)'!$O$2:$O$205,0),"")
A37: =IF($AH37="","",IF($AG37=$AG36,"",$AG37)) | B37: =IF($AH37="","",INDEX('Roadmap Calc (Don’t Touch)'!$B$2:$B$205,$AH37)) | C37: =IF($AH37="","",INDEX('Roadmap Calc (Don’t Touch)'!$E$2:$E$205,$AH37)) | D37: =IF($AH37="","",INDEX('Roadmap Calc (Don’t Touch)'!$F$2:$F$205,$AH37)) | E37: =IF($AH37="","",INDEX('Roadmap Calc (Don’t Touch)'!$G$2:$G$205,$AH37)) | F37: =IF($AH37="","",INDEX('Roadmap Calc (Don’t Touch)'!$H$2:$H$205,$AH37)) | G37: =IF($AH37="","",INDEX('Roadmap Calc (Don’t Touch)'!$I$2:$I$205,$AH37)) | H37: =IF($AH37="","",INDEX('Roadmap Calc (Don’t Touch)'!$J$2:$J$205,$AH37)) | I37: =IF($AH37="","",IF(AND($E37<>"",$E37<=EOMONTH(I$3,0),$F37>=I$3),IF(AND($G37<>"",$G37<=EOMONTH(I$3,0),$H37>=I$3),"B","U"),IF(AND($G37<>"",$G37<=EOMONTH(I$3,0),$H37>=I$3),"D",""))) | J37: =IF($AH37="","",IF(AND($E37<>"",$E37<=EOMONTH(J$3,0),$F37>=J$3),IF(AND($G37<>"",$G37<=EOMONTH(J$3,0),$H37>=J$3),"B","U"),IF(AND($G37<>"",$G37<=EOMONTH(J$3,0),$H37>=J$3),"D",""))) | K37: =IF($AH37="","",IF(AND($E37<>"",$E37<=EOMONTH(K$3,0),$F37>=K$3),IF(AND($G37<>"",$G37<=EOMONTH(K$3,0),$H37>=K$3),"B","U"),IF(AND($G37<>"",$G37<=EOMONTH(K$3,0),$H37>=K$3),"D",""))) | L37: =IF($AH37="","",IF(AND($E37<>"",$E37<=EOMONTH(L$3,0),$F37>=L$3),IF(AND($G37<>"",$G37<=EOMONTH(L$3,0),$H37>=L$3),"B","U"),IF(AND($G37<>"",$G37<=EOMONTH(L$3,0),$H37>=L$3),"D",""))) | M37: =IF($AH37="","",IF(AND($E37<>"",$E37<=EOMONTH(M$3,0),$F37>=M$3),IF(AND($G37<>"",$G37<=EOMONTH(M$3,0),$H37>=M$3),"B","U"),IF(AND($G37<>"",$G37<=EOMONTH(M$3,0),$H37>=M$3),"D",""))) | N37: =IF($AH37="","",IF(AND($E37<>"",$E37<=EOMONTH(N$3,0),$F37>=N$3),IF(AND($G37<>"",$G37<=EOMONTH(N$3,0),$H37>=N$3),"B","U"),IF(AND($G37<>"",$G37<=EOMONTH(N$3,0),$H37>=N$3),"D",""))) | O37: =IF($AH37="","",IF(AND($E37<>"",$E37<=EOMONTH(O$3,0),$F37>=O$3),IF(AND($G37<>"",$G37<=EOMONTH(O$3,0),$H37>=O$3),"B","U"),IF(AND($G37<>"",$G37<=EOMONTH(O$3,0),$H37>=O$3),"D",""))) | P37: =IF($AH37="","",IF(AND($E37<>"",$E37<=EOMONTH(P$3,0),$F37>=P$3),IF(AND($G37<>"",$G37<=EOMONTH(P$3,0),$H37>=P$3),"B","U"),IF(AND($G37<>"",$G37<=EOMONTH(P$3,0),$H37>=P$3),"D",""))) | ... AF37: =IF($AH37="","",IF(AND($E37<>"",$E37<=EOMONTH(AF$3,0),$F37>=AF$3),IF(AND($G37<>"",$G37<=EOMONTH(AF$3,0),$H37>=AF$3),"B","U"),IF(AND($G37<>"",$G37<=EOMONTH(AF$3,0),$H37>=AF$3),"D",""))) | AG37: =IF($AH37="","",INDEX('Roadmap Calc (Don’t Touch)'!$D$2:$D$205,$AH37)) | AH37: =IFERROR(MATCH(31,'Roadmap Calc (Don’t Touch)'!$O$2:$O$205,0),"")
A38: =IF($AH38="","",IF($AG38=$AG37,"",$AG38)) | B38: =IF($AH38="","",INDEX('Roadmap Calc (Don’t Touch)'!$B$2:$B$205,$AH38)) | C38: =IF($AH38="","",INDEX('Roadmap Calc (Don’t Touch)'!$E$2:$E$205,$AH38)) | D38: =IF($AH38="","",INDEX('Roadmap Calc (Don’t Touch)'!$F$2:$F$205,$AH38)) | E38: =IF($AH38="","",INDEX('Roadmap Calc (Don’t Touch)'!$G$2:$G$205,$AH38)) | F38: =IF($AH38="","",INDEX('Roadmap Calc (Don’t Touch)'!$H$2:$H$205,$AH38)) | G38: =IF($AH38="","",INDEX('Roadmap Calc (Don’t Touch)'!$I$2:$I$205,$AH38)) | H38: =IF($AH38="","",INDEX('Roadmap Calc (Don’t Touch)'!$J$2:$J$205,$AH38)) | I38: =IF($AH38="","",IF(AND($E38<>"",$E38<=EOMONTH(I$3,0),$F38>=I$3),IF(AND($G38<>"",$G38<=EOMONTH(I$3,0),$H38>=I$3),"B","U"),IF(AND($G38<>"",$G38<=EOMONTH(I$3,0),$H38>=I$3),"D",""))) | J38: =IF($AH38="","",IF(AND($E38<>"",$E38<=EOMONTH(J$3,0),$F38>=J$3),IF(AND($G38<>"",$G38<=EOMONTH(J$3,0),$H38>=J$3),"B","U"),IF(AND($G38<>"",$G38<=EOMONTH(J$3,0),$H38>=J$3),"D",""))) | K38: =IF($AH38="","",IF(AND($E38<>"",$E38<=EOMONTH(K$3,0),$F38>=K$3),IF(AND($G38<>"",$G38<=EOMONTH(K$3,0),$H38>=K$3),"B","U"),IF(AND($G38<>"",$G38<=EOMONTH(K$3,0),$H38>=K$3),"D",""))) | L38: =IF($AH38="","",IF(AND($E38<>"",$E38<=EOMONTH(L$3,0),$F38>=L$3),IF(AND($G38<>"",$G38<=EOMONTH(L$3,0),$H38>=L$3),"B","U"),IF(AND($G38<>"",$G38<=EOMONTH(L$3,0),$H38>=L$3),"D",""))) | M38: =IF($AH38="","",IF(AND($E38<>"",$E38<=EOMONTH(M$3,0),$F38>=M$3),IF(AND($G38<>"",$G38<=EOMONTH(M$3,0),$H38>=M$3),"B","U"),IF(AND($G38<>"",$G38<=EOMONTH(M$3,0),$H38>=M$3),"D",""))) | N38: =IF($AH38="","",IF(AND($E38<>"",$E38<=EOMONTH(N$3,0),$F38>=N$3),IF(AND($G38<>"",$G38<=EOMONTH(N$3,0),$H38>=N$3),"B","U"),IF(AND($G38<>"",$G38<=EOMONTH(N$3,0),$H38>=N$3),"D",""))) | O38: =IF($AH38="","",IF(AND($E38<>"",$E38<=EOMONTH(O$3,0),$F38>=O$3),IF(AND($G38<>"",$G38<=EOMONTH(O$3,0),$H38>=O$3),"B","U"),IF(AND($G38<>"",$G38<=EOMONTH(O$3,0),$H38>=O$3),"D",""))) | P38: =IF($AH38="","",IF(AND($E38<>"",$E38<=EOMONTH(P$3,0),$F38>=P$3),IF(AND($G38<>"",$G38<=EOMONTH(P$3,0),$H38>=P$3),"B","U"),IF(AND($G38<>"",$G38<=EOMONTH(P$3,0),$H38>=P$3),"D",""))) | ... AF38: =IF($AH38="","",IF(AND($E38<>"",$E38<=EOMONTH(AF$3,0),$F38>=AF$3),IF(AND($G38<>"",$G38<=EOMONTH(AF$3,0),$H38>=AF$3),"B","U"),IF(AND($G38<>"",$G38<=EOMONTH(AF$3,0),$H38>=AF$3),"D",""))) | AG38: =IF($AH38="","",INDEX('Roadmap Calc (Don’t Touch)'!$D$2:$D$205,$AH38)) | AH38: =IFERROR(MATCH(32,'Roadmap Calc (Don’t Touch)'!$O$2:$O$205,0),"")
A39: =IF($AH39="","",IF($AG39=$AG38,"",$AG39)) | B39: =IF($AH39="","",INDEX('Roadmap Calc (Don’t Touch)'!$B$2:$B$205,$AH39)) | C39: =IF($AH39="","",INDEX('Roadmap Calc (Don’t Touch)'!$E$2:$E$205,$AH39)) | D39: =IF($AH39="","",INDEX('Roadmap Calc (Don’t Touch)'!$F$2:$F$205,$AH39)) | E39: =IF($AH39="","",INDEX('Roadmap Calc (Don’t Touch)'!$G$2:$G$205,$AH39)) | F39: =IF($AH39="","",INDEX('Roadmap Calc (Don’t Touch)'!$H$2:$H$205,$AH39)) | G39: =IF($AH39="","",INDEX('Roadmap Calc (Don’t Touch)'!$I$2:$I$205,$AH39)) | H39: =IF($AH39="","",INDEX('Roadmap Calc (Don’t Touch)'!$J$2:$J$205,$AH39)) | I39: =IF($AH39="","",IF(AND($E39<>"",$E39<=EOMONTH(I$3,0),$F39>=I$3),IF(AND($G39<>"",$G39<=EOMONTH(I$3,0),$H39>=I$3),"B","U"),IF(AND($G39<>"",$G39<=EOMONTH(I$3,0),$H39>=I$3),"D",""))) | J39: =IF($AH39="","",IF(AND($E39<>"",$E39<=EOMONTH(J$3,0),$F39>=J$3),IF(AND($G39<>"",$G39<=EOMONTH(J$3,0),$H39>=J$3),"B","U"),IF(AND($G39<>"",$G39<=EOMONTH(J$3,0),$H39>=J$3),"D",""))) | K39: =IF($AH39="","",IF(AND($E39<>"",$E39<=EOMONTH(K$3,0),$F39>=K$3),IF(AND($G39<>"",$G39<=EOMONTH(K$3,0),$H39>=K$3),"B","U"),IF(AND($G39<>"",$G39<=EOMONTH(K$3,0),$H39>=K$3),"D",""))) | L39: =IF($AH39="","",IF(AND($E39<>"",$E39<=EOMONTH(L$3,0),$F39>=L$3),IF(AND($G39<>"",$G39<=EOMONTH(L$3,0),$H39>=L$3),"B","U"),IF(AND($G39<>"",$G39<=EOMONTH(L$3,0),$H39>=L$3),"D",""))) | M39: =IF($AH39="","",IF(AND($E39<>"",$E39<=EOMONTH(M$3,0),$F39>=M$3),IF(AND($G39<>"",$G39<=EOMONTH(M$3,0),$H39>=M$3),"B","U"),IF(AND($G39<>"",$G39<=EOMONTH(M$3,0),$H39>=M$3),"D",""))) | N39: =IF($AH39="","",IF(AND($E39<>"",$E39<=EOMONTH(N$3,0),$F39>=N$3),IF(AND($G39<>"",$G39<=EOMONTH(N$3,0),$H39>=N$3),"B","U"),IF(AND($G39<>"",$G39<=EOMONTH(N$3,0),$H39>=N$3),"D",""))) | O39: =IF($AH39="","",IF(AND($E39<>"",$E39<=EOMONTH(O$3,0),$F39>=O$3),IF(AND($G39<>"",$G39<=EOMONTH(O$3,0),$H39>=O$3),"B","U"),IF(AND($G39<>"",$G39<=EOMONTH(O$3,0),$H39>=O$3),"D",""))) | P39: =IF($AH39="","",IF(AND($E39<>"",$E39<=EOMONTH(P$3,0),$F39>=P$3),IF(AND($G39<>"",$G39<=EOMONTH(P$3,0),$H39>=P$3),"B","U"),IF(AND($G39<>"",$G39<=EOMONTH(P$3,0),$H39>=P$3),"D",""))) | ... AF39: =IF($AH39="","",IF(AND($E39<>"",$E39<=EOMONTH(AF$3,0),$F39>=AF$3),IF(AND($G39<>"",$G39<=EOMONTH(AF$3,0),$H39>=AF$3),"B","U"),IF(AND($G39<>"",$G39<=EOMONTH(AF$3,0),$H39>=AF$3),"D",""))) | AG39: =IF($AH39="","",INDEX('Roadmap Calc (Don’t Touch)'!$D$2:$D$205,$AH39)) | AH39: =IFERROR(MATCH(33,'Roadmap Calc (Don’t Touch)'!$O$2:$O$205,0),"")
A40: =IF($AH40="","",IF($AG40=$AG39,"",$AG40)) | B40: =IF($AH40="","",INDEX('Roadmap Calc (Don’t Touch)'!$B$2:$B$205,$AH40)) | C40: =IF($AH40="","",INDEX('Roadmap Calc (Don’t Touch)'!$E$2:$E$205,$AH40)) | D40: =IF($AH40="","",INDEX('Roadmap Calc (Don’t Touch)'!$F$2:$F$205,$AH40)) | E40: =IF($AH40="","",INDEX('Roadmap Calc (Don’t Touch)'!$G$2:$G$205,$AH40)) | F40: =IF($AH40="","",INDEX('Roadmap Calc (Don’t Touch)'!$H$2:$H$205,$AH40)) | G40: =IF($AH40="","",INDEX('Roadmap Calc (Don’t Touch)'!$I$2:$I$205,$AH40)) | H40: =IF($AH40="","",INDEX('Roadmap Calc (Don’t Touch)'!$J$2:$J$205,$AH40)) | I40: =IF($AH40="","",IF(AND($E40<>"",$E40<=EOMONTH(I$3,0),$F40>=I$3),IF(AND($G40<>"",$G40<=EOMONTH(I$3,0),$H40>=I$3),"B","U"),IF(AND($G40<>"",$G40<=EOMONTH(I$3,0),$H40>=I$3),"D",""))) | J40: =IF($AH40="","",IF(AND($E40<>"",$E40<=EOMONTH(J$3,0),$F40>=J$3),IF(AND($G40<>"",$G40<=EOMONTH(J$3,0),$H40>=J$3),"B","U"),IF(AND($G40<>"",$G40<=EOMONTH(J$3,0),$H40>=J$3),"D",""))) | K40: =IF($AH40="","",IF(AND($E40<>"",$E40<=EOMONTH(K$3,0),$F40>=K$3),IF(AND($G40<>"",$G40<=EOMONTH(K$3,0),$H40>=K$3),"B","U"),IF(AND($G40<>"",$G40<=EOMONTH(K$3,0),$H40>=K$3),"D",""))) | L40: =IF($AH40="","",IF(AND($E40<>"",$E40<=EOMONTH(L$3,0),$F40>=L$3),IF(AND($G40<>"",$G40<=EOMONTH(L$3,0),$H40>=L$3),"B","U"),IF(AND($G40<>"",$G40<=EOMONTH(L$3,0),$H40>=L$3),"D",""))) | M40: =IF($AH40="","",IF(AND($E40<>"",$E40<=EOMONTH(M$3,0),$F40>=M$3),IF(AND($G40<>"",$G40<=EOMONTH(M$3,0),$H40>=M$3),"B","U"),IF(AND($G40<>"",$G40<=EOMONTH(M$3,0),$H40>=M$3),"D",""))) | N40: =IF($AH40="","",IF(AND($E40<>"",$E40<=EOMONTH(N$3,0),$F40>=N$3),IF(AND($G40<>"",$G40<=EOMONTH(N$3,0),$H40>=N$3),"B","U"),IF(AND($G40<>"",$G40<=EOMONTH(N$3,0),$H40>=N$3),"D",""))) | O40: =IF($AH40="","",IF(AND($E40<>"",$E40<=EOMONTH(O$3,0),$F40>=O$3),IF(AND($G40<>"",$G40<=EOMONTH(O$3,0),$H40>=O$3),"B","U"),IF(AND($G40<>"",$G40<=EOMONTH(O$3,0),$H40>=O$3),"D",""))) | P40: =IF($AH40="","",IF(AND($E40<>"",$E40<=EOMONTH(P$3,0),$F40>=P$3),IF(AND($G40<>"",$G40<=EOMONTH(P$3,0),$H40>=P$3),"B","U"),IF(AND($G40<>"",$G40<=EOMONTH(P$3,0),$H40>=P$3),"D",""))) | ... AF40: =IF($AH40="","",IF(AND($E40<>"",$E40<=EOMONTH(AF$3,0),$F40>=AF$3),IF(AND($G40<>"",$G40<=EOMONTH(AF$3,0),$H40>=AF$3),"B","U"),IF(AND($G40<>"",$G40<=EOMONTH(AF$3,0),$H40>=AF$3),"D",""))) | AG40: =IF($AH40="","",INDEX('Roadmap Calc (Don’t Touch)'!$D$2:$D$205,$AH40)) | AH40: =IFERROR(MATCH(34,'Roadmap Calc (Don’t Touch)'!$O$2:$O$205,0),"")
A41: =IF($AH41="","",IF($AG41=$AG40,"",$AG41)) | B41: =IF($AH41="","",INDEX('Roadmap Calc (Don’t Touch)'!$B$2:$B$205,$AH41)) | C41: =IF($AH41="","",INDEX('Roadmap Calc (Don’t Touch)'!$E$2:$E$205,$AH41)) | D41: =IF($AH41="","",INDEX('Roadmap Calc (Don’t Touch)'!$F$2:$F$205,$AH41)) | E41: =IF($AH41="","",INDEX('Roadmap Calc (Don’t Touch)'!$G$2:$G$205,$AH41)) | F41: =IF($AH41="","",INDEX('Roadmap Calc (Don’t Touch)'!$H$2:$H$205,$AH41)) | G41: =IF($AH41="","",INDEX('Roadmap Calc (Don’t Touch)'!$I$2:$I$205,$AH41)) | H41: =IF($AH41="","",INDEX('Roadmap Calc (Don’t Touch)'!$J$2:$J$205,$AH41)) | I41: =IF($AH41="","",IF(AND($E41<>"",$E41<=EOMONTH(I$3,0),$F41>=I$3),IF(AND($G41<>"",$G41<=EOMONTH(I$3,0),$H41>=I$3),"B","U"),IF(AND($G41<>"",$G41<=EOMONTH(I$3,0),$H41>=I$3),"D",""))) | J41: =IF($AH41="","",IF(AND($E41<>"",$E41<=EOMONTH(J$3,0),$F41>=J$3),IF(AND($G41<>"",$G41<=EOMONTH(J$3,0),$H41>=J$3),"B","U"),IF(AND($G41<>"",$G41<=EOMONTH(J$3,0),$H41>=J$3),"D",""))) | K41: =IF($AH41="","",IF(AND($E41<>"",$E41<=EOMONTH(K$3,0),$F41>=K$3),IF(AND($G41<>"",$G41<=EOMONTH(K$3,0),$H41>=K$3),"B","U"),IF(AND($G41<>"",$G41<=EOMONTH(K$3,0),$H41>=K$3),"D",""))) | L41: =IF($AH41="","",IF(AND($E41<>"",$E41<=EOMONTH(L$3,0),$F41>=L$3),IF(AND($G41<>"",$G41<=EOMONTH(L$3,0),$H41>=L$3),"B","U"),IF(AND($G41<>"",$G41<=EOMONTH(L$3,0),$H41>=L$3),"D",""))) | M41: =IF($AH41="","",IF(AND($E41<>"",$E41<=EOMONTH(M$3,0),$F41>=M$3),IF(AND($G41<>"",$G41<=EOMONTH(M$3,0),$H41>=M$3),"B","U"),IF(AND($G41<>"",$G41<=EOMONTH(M$3,0),$H41>=M$3),"D",""))) | N41: =IF($AH41="","",IF(AND($E41<>"",$E41<=EOMONTH(N$3,0),$F41>=N$3),IF(AND($G41<>"",$G41<=EOMONTH(N$3,0),$H41>=N$3),"B","U"),IF(AND($G41<>"",$G41<=EOMONTH(N$3,0),$H41>=N$3),"D",""))) | O41: =IF($AH41="","",IF(AND($E41<>"",$E41<=EOMONTH(O$3,0),$F41>=O$3),IF(AND($G41<>"",$G41<=EOMONTH(O$3,0),$H41>=O$3),"B","U"),IF(AND($G41<>"",$G41<=EOMONTH(O$3,0),$H41>=O$3),"D",""))) | P41: =IF($AH41="","",IF(AND($E41<>"",$E41<=EOMONTH(P$3,0),$F41>=P$3),IF(AND($G41<>"",$G41<=EOMONTH(P$3,0),$H41>=P$3),"B","U"),IF(AND($G41<>"",$G41<=EOMONTH(P$3,0),$H41>=P$3),"D",""))) | ... AF41: =IF($AH41="","",IF(AND($E41<>"",$E41<=EOMONTH(AF$3,0),$F41>=AF$3),IF(AND($G41<>"",$G41<=EOMONTH(AF$3,0),$H41>=AF$3),"B","U"),IF(AND($G41<>"",$G41<=EOMONTH(AF$3,0),$H41>=AF$3),"D",""))) | AG41: =IF($AH41="","",INDEX('Roadmap Calc (Don’t Touch)'!$D$2:$D$205,$AH41)) | AH41: =IFERROR(MATCH(35,'Roadmap Calc (Don’t Touch)'!$O$2:$O$205,0),"")
A42: =IF($AH42="","",IF($AG42=$AG41,"",$AG42)) | B42: =IF($AH42="","",INDEX('Roadmap Calc (Don’t Touch)'!$B$2:$B$205,$AH42)) | C42: =IF($AH42="","",INDEX('Roadmap Calc (Don’t Touch)'!$E$2:$E$205,$AH42)) | D42: =IF($AH42="","",INDEX('Roadmap Calc (Don’t Touch)'!$F$2:$F$205,$AH42)) | E42: =IF($AH42="","",INDEX('Roadmap Calc (Don’t Touch)'!$G$2:$G$205,$AH42)) | F42: =IF($AH42="","",INDEX('Roadmap Calc (Don’t Touch)'!$H$2:$H$205,$AH42)) | G42: =IF($AH42="","",INDEX('Roadmap Calc (Don’t Touch)'!$I$2:$I$205,$AH42)) | H42: =IF($AH42="","",INDEX('Roadmap Calc (Don’t Touch)'!$J$2:$J$205,$AH42)) | I42: =IF($AH42="","",IF(AND($E42<>"",$E42<=EOMONTH(I$3,0),$F42>=I$3),IF(AND($G42<>"",$G42<=EOMONTH(I$3,0),$H42>=I$3),"B","U"),IF(AND($G42<>"",$G42<=EOMONTH(I$3,0),$H42>=I$3),"D",""))) | J42: =IF($AH42="","",IF(AND($E42<>"",$E42<=EOMONTH(J$3,0),$F42>=J$3),IF(AND($G42<>"",$G42<=EOMONTH(J$3,0),$H42>=J$3),"B","U"),IF(AND($G42<>"",$G42<=EOMONTH(J$3,0),$H42>=J$3),"D",""))) | K42: =IF($AH42="","",IF(AND($E42<>"",$E42<=EOMONTH(K$3,0),$F42>=K$3),IF(AND($G42<>"",$G42<=EOMONTH(K$3,0),$H42>=K$3),"B","U"),IF(AND($G42<>"",$G42<=EOMONTH(K$3,0),$H42>=K$3),"D",""))) | L42: =IF($AH42="","",IF(AND($E42<>"",$E42<=EOMONTH(L$3,0),$F42>=L$3),IF(AND($G42<>"",$G42<=EOMONTH(L$3,0),$H42>=L$3),"B","U"),IF(AND($G42<>"",$G42<=EOMONTH(L$3,0),$H42>=L$3),"D",""))) | M42: =IF($AH42="","",IF(AND($E42<>"",$E42<=EOMONTH(M$3,0),$F42>=M$3),IF(AND($G42<>"",$G42<=EOMONTH(M$3,0),$H42>=M$3),"B","U"),IF(AND($G42<>"",$G42<=EOMONTH(M$3,0),$H42>=M$3),"D",""))) | N42: =IF($AH42="","",IF(AND($E42<>"",$E42<=EOMONTH(N$3,0),$F42>=N$3),IF(AND($G42<>"",$G42<=EOMONTH(N$3,0),$H42>=N$3),"B","U"),IF(AND($G42<>"",$G42<=EOMONTH(N$3,0),$H42>=N$3),"D",""))) | O42: =IF($AH42="","",IF(AND($E42<>"",$E42<=EOMONTH(O$3,0),$F42>=O$3),IF(AND($G42<>"",$G42<=EOMONTH(O$3,0),$H42>=O$3),"B","U"),IF(AND($G42<>"",$G42<=EOMONTH(O$3,0),$H42>=O$3),"D",""))) | P42: =IF($AH42="","",IF(AND($E42<>"",$E42<=EOMONTH(P$3,0),$F42>=P$3),IF(AND($G42<>"",$G42<=EOMONTH(P$3,0),$H42>=P$3),"B","U"),IF(AND($G42<>"",$G42<=EOMONTH(P$3,0),$H42>=P$3),"D",""))) | ... AF42: =IF($AH42="","",IF(AND($E42<>"",$E42<=EOMONTH(AF$3,0),$F42>=AF$3),IF(AND($G42<>"",$G42<=EOMONTH(AF$3,0),$H42>=AF$3),"B","U"),IF(AND($G42<>"",$G42<=EOMONTH(AF$3,0),$H42>=AF$3),"D",""))) | AG42: =IF($AH42="","",INDEX('Roadmap Calc (Don’t Touch)'!$D$2:$D$205,$AH42)) | AH42: =IFERROR(MATCH(36,'Roadmap Calc (Don’t Touch)'!$O$2:$O$205,0),"")
A43: =IF($AH43="","",IF($AG43=$AG42,"",$AG43)) | B43: =IF($AH43="","",INDEX('Roadmap Calc (Don’t Touch)'!$B$2:$B$205,$AH43)) | C43: =IF($AH43="","",INDEX('Roadmap Calc (Don’t Touch)'!$E$2:$E$205,$AH43)) | D43: =IF($AH43="","",INDEX('Roadmap Calc (Don’t Touch)'!$F$2:$F$205,$AH43)) | E43: =IF($AH43="","",INDEX('Roadmap Calc (Don’t Touch)'!$G$2:$G$205,$AH43)) | F43: =IF($AH43="","",INDEX('Roadmap Calc (Don’t Touch)'!$H$2:$H$205,$AH43)) | G43: =IF($AH43="","",INDEX('Roadmap Calc (Don’t Touch)'!$I$2:$I$205,$AH43)) | H43: =IF($AH43="","",INDEX('Roadmap Calc (Don’t Touch)'!$J$2:$J$205,$AH43)) | I43: =IF($AH43="","",IF(AND($E43<>"",$E43<=EOMONTH(I$3,0),$F43>=I$3),IF(AND($G43<>"",$G43<=EOMONTH(I$3,0),$H43>=I$3),"B","U"),IF(AND($G43<>"",$G43<=EOMONTH(I$3,0),$H43>=I$3),"D",""))) | J43: =IF($AH43="","",IF(AND($E43<>"",$E43<=EOMONTH(J$3,0),$F43>=J$3),IF(AND($G43<>"",$G43<=EOMONTH(J$3,0),$H43>=J$3),"B","U"),IF(AND($G43<>"",$G43<=EOMONTH(J$3,0),$H43>=J$3),"D",""))) | K43: =IF($AH43="","",IF(AND($E43<>"",$E43<=EOMONTH(K$3,0),$F43>=K$3),IF(AND($G43<>"",$G43<=EOMONTH(K$3,0),$H43>=K$3),"B","U"),IF(AND($G43<>"",$G43<=EOMONTH(K$3,0),$H43>=K$3),"D",""))) | L43: =IF($AH43="","",IF(AND($E43<>"",$E43<=EOMONTH(L$3,0),$F43>=L$3),IF(AND($G43<>"",$G43<=EOMONTH(L$3,0),$H43>=L$3),"B","U"),IF(AND($G43<>"",$G43<=EOMONTH(L$3,0),$H43>=L$3),"D",""))) | M43: =IF($AH43="","",IF(AND($E43<>"",$E43<=EOMONTH(M$3,0),$F43>=M$3),IF(AND($G43<>"",$G43<=EOMONTH(M$3,0),$H43>=M$3),"B","U"),IF(AND($G43<>"",$G43<=EOMONTH(M$3,0),$H43>=M$3),"D",""))) | N43: =IF($AH43="","",IF(AND($E43<>"",$E43<=EOMONTH(N$3,0),$F43>=N$3),IF(AND($G43<>"",$G43<=EOMONTH(N$3,0),$H43>=N$3),"B","U"),IF(AND($G43<>"",$G43<=EOMONTH(N$3,0),$H43>=N$3),"D",""))) | O43: =IF($AH43="","",IF(AND($E43<>"",$E43<=EOMONTH(O$3,0),$F43>=O$3),IF(AND($G43<>"",$G43<=EOMONTH(O$3,0),$H43>=O$3),"B","U"),IF(AND($G43<>"",$G43<=EOMONTH(O$3,0),$H43>=O$3),"D",""))) | P43: =IF($AH43="","",IF(AND($E43<>"",$E43<=EOMONTH(P$3,0),$F43>=P$3),IF(AND($G43<>"",$G43<=EOMONTH(P$3,0),$H43>=P$3),"B","U"),IF(AND($G43<>"",$G43<=EOMONTH(P$3,0),$H43>=P$3),"D",""))) | ... AF43: =IF($AH43="","",IF(AND($E43<>"",$E43<=EOMONTH(AF$3,0),$F43>=AF$3),IF(AND($G43<>"",$G43<=EOMONTH(AF$3,0),$H43>=AF$3),"B","U"),IF(AND($G43<>"",$G43<=EOMONTH(AF$3,0),$H43>=AF$3),"D",""))) | AG43: =IF($AH43="","",INDEX('Roadmap Calc (Don’t Touch)'!$D$2:$D$205,$AH43)) | AH43: =IFERROR(MATCH(37,'Roadmap Calc (Don’t Touch)'!$O$2:$O$205,0),"")
A44: =IF($AH44="","",IF($AG44=$AG43,"",$AG44)) | B44: =IF($AH44="","",INDEX('Roadmap Calc (Don’t Touch)'!$B$2:$B$205,$AH44)) | C44: =IF($AH44="","",INDEX('Roadmap Calc (Don’t Touch)'!$E$2:$E$205,$AH44)) | D44: =IF($AH44="","",INDEX('Roadmap Calc (Don’t Touch)'!$F$2:$F$205,$AH44)) | E44: =IF($AH44="","",INDEX('Roadmap Calc (Don’t Touch)'!$G$2:$G$205,$AH44)) | F44: =IF($AH44="","",INDEX('Roadmap Calc (Don’t Touch)'!$H$2:$H$205,$AH44)) | G44: =IF($AH44="","",INDEX('Roadmap Calc (Don’t Touch)'!$I$2:$I$205,$AH44)) | H44: =IF($AH44="","",INDEX('Roadmap Calc (Don’t Touch)'!$J$2:$J$205,$AH44)) | I44: =IF($AH44="","",IF(AND($E44<>"",$E44<=EOMONTH(I$3,0),$F44>=I$3),IF(AND($G44<>"",$G44<=EOMONTH(I$3,0),$H44>=I$3),"B","U"),IF(AND($G44<>"",$G44<=EOMONTH(I$3,0),$H44>=I$3),"D",""))) | J44: =IF($AH44="","",IF(AND($E44<>"",$E44<=EOMONTH(J$3,0),$F44>=J$3),IF(AND($G44<>"",$G44<=EOMONTH(J$3,0),$H44>=J$3),"B","U"),IF(AND($G44<>"",$G44<=EOMONTH(J$3,0),$H44>=J$3),"D",""))) | K44: =IF($AH44="","",IF(AND($E44<>"",$E44<=EOMONTH(K$3,0),$F44>=K$3),IF(AND($G44<>"",$G44<=EOMONTH(K$3,0),$H44>=K$3),"B","U"),IF(AND($G44<>"",$G44<=EOMONTH(K$3,0),$H44>=K$3),"D",""))) | L44: =IF($AH44="","",IF(AND($E44<>"",$E44<=EOMONTH(L$3,0),$F44>=L$3),IF(AND($G44<>"",$G44<=EOMONTH(L$3,0),$H44>=L$3),"B","U"),IF(AND($G44<>"",$G44<=EOMONTH(L$3,0),$H44>=L$3),"D",""))) | M44: =IF($AH44="","",IF(AND($E44<>"",$E44<=EOMONTH(M$3,0),$F44>=M$3),IF(AND($G44<>"",$G44<=EOMONTH(M$3,0),$H44>=M$3),"B","U"),IF(AND($G44<>"",$G44<=EOMONTH(M$3,0),$H44>=M$3),"D",""))) | N44: =IF($AH44="","",IF(AND($E44<>"",$E44<=EOMONTH(N$3,0),$F44>=N$3),IF(AND($G44<>"",$G44<=EOMONTH(N$3,0),$H44>=N$3),"B","U"),IF(AND($G44<>"",$G44<=EOMONTH(N$3,0),$H44>=N$3),"D",""))) | O44: =IF($AH44="","",IF(AND($E44<>"",$E44<=EOMONTH(O$3,0),$F44>=O$3),IF(AND($G44<>"",$G44<=EOMONTH(O$3,0),$H44>=O$3),"B","U"),IF(AND($G44<>"",$G44<=EOMONTH(O$3,0),$H44>=O$3),"D",""))) | P44: =IF($AH44="","",IF(AND($E44<>"",$E44<=EOMONTH(P$3,0),$F44>=P$3),IF(AND($G44<>"",$G44<=EOMONTH(P$3,0),$H44>=P$3),"B","U"),IF(AND($G44<>"",$G44<=EOMONTH(P$3,0),$H44>=P$3),"D",""))) | ... AF44: =IF($AH44="","",IF(AND($E44<>"",$E44<=EOMONTH(AF$3,0),$F44>=AF$3),IF(AND($G44<>"",$G44<=EOMONTH(AF$3,0),$H44>=AF$3),"B","U"),IF(AND($G44<>"",$G44<=EOMONTH(AF$3,0),$H44>=AF$3),"D",""))) | AG44: =IF($AH44="","",INDEX('Roadmap Calc (Don’t Touch)'!$D$2:$D$205,$AH44)) | AH44: =IFERROR(MATCH(38,'Roadmap Calc (Don’t Touch)'!$O$2:$O$205,0),"")
A45: =IF($AH45="","",IF($AG45=$AG44,"",$AG45)) | B45: =IF($AH45="","",INDEX('Roadmap Calc (Don’t Touch)'!$B$2:$B$205,$AH45)) | C45: =IF($AH45="","",INDEX('Roadmap Calc (Don’t Touch)'!$E$2:$E$205,$AH45)) | D45: =IF($AH45="","",INDEX('Roadmap Calc (Don’t Touch)'!$F$2:$F$205,$AH45)) | E45: =IF($AH45="","",INDEX('Roadmap Calc (Don’t Touch)'!$G$2:$G$205,$AH45)) | F45: =IF($AH45="","",INDEX('Roadmap Calc (Don’t Touch)'!$H$2:$H$205,$AH45)) | G45: =IF($AH45="","",INDEX('Roadmap Calc (Don’t Touch)'!$I$2:$I$205,$AH45)) | H45: =IF($AH45="","",INDEX('Roadmap Calc (Don’t Touch)'!$J$2:$J$205,$AH45)) | I45: =IF($AH45="","",IF(AND($E45<>"",$E45<=EOMONTH(I$3,0),$F45>=I$3),IF(AND($G45<>"",$G45<=EOMONTH(I$3,0),$H45>=I$3),"B","U"),IF(AND($G45<>"",$G45<=EOMONTH(I$3,0),$H45>=I$3),"D",""))) | J45: =IF($AH45="","",IF(AND($E45<>"",$E45<=EOMONTH(J$3,0),$F45>=J$3),IF(AND($G45<>"",$G45<=EOMONTH(J$3,0),$H45>=J$3),"B","U"),IF(AND($G45<>"",$G45<=EOMONTH(J$3,0),$H45>=J$3),"D",""))) | K45: =IF($AH45="","",IF(AND($E45<>"",$E45<=EOMONTH(K$3,0),$F45>=K$3),IF(AND($G45<>"",$G45<=EOMONTH(K$3,0),$H45>=K$3),"B","U"),IF(AND($G45<>"",$G45<=EOMONTH(K$3,0),$H45>=K$3),"D",""))) | L45: =IF($AH45="","",IF(AND($E45<>"",$E45<=EOMONTH(L$3,0),$F45>=L$3),IF(AND($G45<>"",$G45<=EOMONTH(L$3,0),$H45>=L$3),"B","U"),IF(AND($G45<>"",$G45<=EOMONTH(L$3,0),$H45>=L$3),"D",""))) | M45: =IF($AH45="","",IF(AND($E45<>"",$E45<=EOMONTH(M$3,0),$F45>=M$3),IF(AND($G45<>"",$G45<=EOMONTH(M$3,0),$H45>=M$3),"B","U"),IF(AND($G45<>"",$G45<=EOMONTH(M$3,0),$H45>=M$3),"D",""))) | N45: =IF($AH45="","",IF(AND($E45<>"",$E45<=EOMONTH(N$3,0),$F45>=N$3),IF(AND($G45<>"",$G45<=EOMONTH(N$3,0),$H45>=N$3),"B","U"),IF(AND($G45<>"",$G45<=EOMONTH(N$3,0),$H45>=N$3),"D",""))) | O45: =IF($AH45="","",IF(AND($E45<>"",$E45<=EOMONTH(O$3,0),$F45>=O$3),IF(AND($G45<>"",$G45<=EOMONTH(O$3,0),$H45>=O$3),"B","U"),IF(AND($G45<>"",$G45<=EOMONTH(O$3,0),$H45>=O$3),"D",""))) | P45: =IF($AH45="","",IF(AND($E45<>"",$E45<=EOMONTH(P$3,0),$F45>=P$3),IF(AND($G45<>"",$G45<=EOMONTH(P$3,0),$H45>=P$3),"B","U"),IF(AND($G45<>"",$G45<=EOMONTH(P$3,0),$H45>=P$3),"D",""))) | ... AF45: =IF($AH45="","",IF(AND($E45<>"",$E45<=EOMONTH(AF$3,0),$F45>=AF$3),IF(AND($G45<>"",$G45<=EOMONTH(AF$3,0),$H45>=AF$3),"B","U"),IF(AND($G45<>"",$G45<=EOMONTH(AF$3,0),$H45>=AF$3),"D",""))) | AG45: =IF($AH45="","",INDEX('Roadmap Calc (Don’t Touch)'!$D$2:$D$205,$AH45)) | AH45: =IFERROR(MATCH(39,'Roadmap Calc (Don’t Touch)'!$O$2:$O$205,0),"")
A46: =IF($AH46="","",IF($AG46=$AG45,"",$AG46)) | B46: =IF($AH46="","",INDEX('Roadmap Calc (Don’t Touch)'!$B$2:$B$205,$AH46)) | C46: =IF($AH46="","",INDEX('Roadmap Calc (Don’t Touch)'!$E$2:$E$205,$AH46)) | D46: =IF($AH46="","",INDEX('Roadmap Calc (Don’t Touch)'!$F$2:$F$205,$AH46)) | E46: =IF($AH46="","",INDEX('Roadmap Calc (Don’t Touch)'!$G$2:$G$205,$AH46)) | F46: =IF($AH46="","",INDEX('Roadmap Calc (Don’t Touch)'!$H$2:$H$205,$AH46)) | G46: =IF($AH46="","",INDEX('Roadmap Calc (Don’t Touch)'!$I$2:$I$205,$AH46)) | H46: =IF($AH46="","",INDEX('Roadmap Calc (Don’t Touch)'!$J$2:$J$205,$AH46)) | I46: =IF($AH46="","",IF(AND($E46<>"",$E46<=EOMONTH(I$3,0),$F46>=I$3),IF(AND($G46<>"",$G46<=EOMONTH(I$3,0),$H46>=I$3),"B","U"),IF(AND($G46<>"",$G46<=EOMONTH(I$3,0),$H46>=I$3),"D",""))) | J46: =IF($AH46="","",IF(AND($E46<>"",$E46<=EOMONTH(J$3,0),$F46>=J$3),IF(AND($G46<>"",$G46<=EOMONTH(J$3,0),$H46>=J$3),"B","U"),IF(AND($G46<>"",$G46<=EOMONTH(J$3,0),$H46>=J$3),"D",""))) | K46: =IF($AH46="","",IF(AND($E46<>"",$E46<=EOMONTH(K$3,0),$F46>=K$3),IF(AND($G46<>"",$G46<=EOMONTH(K$3,0),$H46>=K$3),"B","U"),IF(AND($G46<>"",$G46<=EOMONTH(K$3,0),$H46>=K$3),"D",""))) | L46: =IF($AH46="","",IF(AND($E46<>"",$E46<=EOMONTH(L$3,0),$F46>=L$3),IF(AND($G46<>"",$G46<=EOMONTH(L$3,0),$H46>=L$3),"B","U"),IF(AND($G46<>"",$G46<=EOMONTH(L$3,0),$H46>=L$3),"D",""))) | M46: =IF($AH46="","",IF(AND($E46<>"",$E46<=EOMONTH(M$3,0),$F46>=M$3),IF(AND($G46<>"",$G46<=EOMONTH(M$3,0),$H46>=M$3),"B","U"),IF(AND($G46<>"",$G46<=EOMONTH(M$3,0),$H46>=M$3),"D",""))) | N46: =IF($AH46="","",IF(AND($E46<>"",$E46<=EOMONTH(N$3,0),$F46>=N$3),IF(AND($G46<>"",$G46<=EOMONTH(N$3,0),$H46>=N$3),"B","U"),IF(AND($G46<>"",$G46<=EOMONTH(N$3,0),$H46>=N$3),"D",""))) | O46: =IF($AH46="","",IF(AND($E46<>"",$E46<=EOMONTH(O$3,0),$F46>=O$3),IF(AND($G46<>"",$G46<=EOMONTH(O$3,0),$H46>=O$3),"B","U"),IF(AND($G46<>"",$G46<=EOMONTH(O$3,0),$H46>=O$3),"D",""))) | P46: =IF($AH46="","",IF(AND($E46<>"",$E46<=EOMONTH(P$3,0),$F46>=P$3),IF(AND($G46<>"",$G46<=EOMONTH(P$3,0),$H46>=P$3),"B","U"),IF(AND($G46<>"",$G46<=EOMONTH(P$3,0),$H46>=P$3),"D",""))) | ... AF46: =IF($AH46="","",IF(AND($E46<>"",$E46<=EOMONTH(AF$3,0),$F46>=AF$3),IF(AND($G46<>"",$G46<=EOMONTH(AF$3,0),$H46>=AF$3),"B","U"),IF(AND($G46<>"",$G46<=EOMONTH(AF$3,0),$H46>=AF$3),"D",""))) | AG46: =IF($AH46="","",INDEX('Roadmap Calc (Don’t Touch)'!$D$2:$D$205,$AH46)) | AH46: =IFERROR(MATCH(40,'Roadmap Calc (Don’t Touch)'!$O$2:$O$205,0),"")
A47: =IF($AH47="","",IF($AG47=$AG46,"",$AG47)) | B47: =IF($AH47="","",INDEX('Roadmap Calc (Don’t Touch)'!$B$2:$B$205,$AH47)) | C47: =IF($AH47="","",INDEX('Roadmap Calc (Don’t Touch)'!$E$2:$E$205,$AH47)) | D47: =IF($AH47="","",INDEX('Roadmap Calc (Don’t Touch)'!$F$2:$F$205,$AH47)) | E47: =IF($AH47="","",INDEX('Roadmap Calc (Don’t Touch)'!$G$2:$G$205,$AH47)) | F47: =IF($AH47="","",INDEX('Roadmap Calc (Don’t Touch)'!$H$2:$H$205,$AH47)) | G47: =IF($AH47="","",INDEX('Roadmap Calc (Don’t Touch)'!$I$2:$I$205,$AH47)) | H47: =IF($AH47="","",INDEX('Roadmap Calc (Don’t Touch)'!$J$2:$J$205,$AH47)) | I47: =IF($AH47="","",IF(AND($E47<>"",$E47<=EOMONTH(I$3,0),$F47>=I$3),IF(AND($G47<>"",$G47<=EOMONTH(I$3,0),$H47>=I$3),"B","U"),IF(AND($G47<>"",$G47<=EOMONTH(I$3,0),$H47>=I$3),"D",""))) | J47: =IF($AH47="","",IF(AND($E47<>"",$E47<=EOMONTH(J$3,0),$F47>=J$3),IF(AND($G47<>"",$G47<=EOMONTH(J$3,0),$H47>=J$3),"B","U"),IF(AND($G47<>"",$G47<=EOMONTH(J$3,0),$H47>=J$3),"D",""))) | K47: =IF($AH47="","",IF(AND($E47<>"",$E47<=EOMONTH(K$3,0),$F47>=K$3),IF(AND($G47<>"",$G47<=EOMONTH(K$3,0),$H47>=K$3),"B","U"),IF(AND($G47<>"",$G47<=EOMONTH(K$3,0),$H47>=K$3),"D",""))) | L47: =IF($AH47="","",IF(AND($E47<>"",$E47<=EOMONTH(L$3,0),$F47>=L$3),IF(AND($G47<>"",$G47<=EOMONTH(L$3,0),$H47>=L$3),"B","U"),IF(AND($G47<>"",$G47<=EOMONTH(L$3,0),$H47>=L$3),"D",""))) | M47: =IF($AH47="","",IF(AND($E47<>"",$E47<=EOMONTH(M$3,0),$F47>=M$3),IF(AND($G47<>"",$G47<=EOMONTH(M$3,0),$H47>=M$3),"B","U"),IF(AND($G47<>"",$G47<=EOMONTH(M$3,0),$H47>=M$3),"D",""))) | N47: =IF($AH47="","",IF(AND($E47<>"",$E47<=EOMONTH(N$3,0),$F47>=N$3),IF(AND($G47<>"",$G47<=EOMONTH(N$3,0),$H47>=N$3),"B","U"),IF(AND($G47<>"",$G47<=EOMONTH(N$3,0),$H47>=N$3),"D",""))) | O47: =IF($AH47="","",IF(AND($E47<>"",$E47<=EOMONTH(O$3,0),$F47>=O$3),IF(AND($G47<>"",$G47<=EOMONTH(O$3,0),$H47>=O$3),"B","U"),IF(AND($G47<>"",$G47<=EOMONTH(O$3,0),$H47>=O$3),"D",""))) | P47: =IF($AH47="","",IF(AND($E47<>"",$E47<=EOMONTH(P$3,0),$F47>=P$3),IF(AND($G47<>"",$G47<=EOMONTH(P$3,0),$H47>=P$3),"B","U"),IF(AND($G47<>"",$G47<=EOMONTH(P$3,0),$H47>=P$3),"D",""))) | ... AF47: =IF($AH47="","",IF(AND($E47<>"",$E47<=EOMONTH(AF$3,0),$F47>=AF$3),IF(AND($G47<>"",$G47<=EOMONTH(AF$3,0),$H47>=AF$3),"B","U"),IF(AND($G47<>"",$G47<=EOMONTH(AF$3,0),$H47>=AF$3),"D",""))) | AG47: =IF($AH47="","",INDEX('Roadmap Calc (Don’t Touch)'!$D$2:$D$205,$AH47)) | AH47: =IFERROR(MATCH(41,'Roadmap Calc (Don’t Touch)'!$O$2:$O$205,0),"")
A48: =IF($AH48="","",IF($AG48=$AG47,"",$AG48)) | B48: =IF($AH48="","",INDEX('Roadmap Calc (Don’t Touch)'!$B$2:$B$205,$AH48)) | C48: =IF($AH48="","",INDEX('Roadmap Calc (Don’t Touch)'!$E$2:$E$205,$AH48)) | D48: =IF($AH48="","",INDEX('Roadmap Calc (Don’t Touch)'!$F$2:$F$205,$AH48)) | E48: =IF($AH48="","",INDEX('Roadmap Calc (Don’t Touch)'!$G$2:$G$205,$AH48)) | F48: =IF($AH48="","",INDEX('Roadmap Calc (Don’t Touch)'!$H$2:$H$205,$AH48)) | G48: =IF($AH48="","",INDEX('Roadmap Calc (Don’t Touch)'!$I$2:$I$205,$AH48)) | H48: =IF($AH48="","",INDEX('Roadmap Calc (Don’t Touch)'!$J$2:$J$205,$AH48)) | I48: =IF($AH48="","",IF(AND($E48<>"",$E48<=EOMONTH(I$3,0),$F48>=I$3),IF(AND($G48<>"",$G48<=EOMONTH(I$3,0),$H48>=I$3),"B","U"),IF(AND($G48<>"",$G48<=EOMONTH(I$3,0),$H48>=I$3),"D",""))) | J48: =IF($AH48="","",IF(AND($E48<>"",$E48<=EOMONTH(J$3,0),$F48>=J$3),IF(AND($G48<>"",$G48<=EOMONTH(J$3,0),$H48>=J$3),"B","U"),IF(AND($G48<>"",$G48<=EOMONTH(J$3,0),$H48>=J$3),"D",""))) | K48: =IF($AH48="","",IF(AND($E48<>"",$E48<=EOMONTH(K$3,0),$F48>=K$3),IF(AND($G48<>"",$G48<=EOMONTH(K$3,0),$H48>=K$3),"B","U"),IF(AND($G48<>"",$G48<=EOMONTH(K$3,0),$H48>=K$3),"D",""))) | L48: =IF($AH48="","",IF(AND($E48<>"",$E48<=EOMONTH(L$3,0),$F48>=L$3),IF(AND($G48<>"",$G48<=EOMONTH(L$3,0),$H48>=L$3),"B","U"),IF(AND($G48<>"",$G48<=EOMONTH(L$3,0),$H48>=L$3),"D",""))) | M48: =IF($AH48="","",IF(AND($E48<>"",$E48<=EOMONTH(M$3,0),$F48>=M$3),IF(AND($G48<>"",$G48<=EOMONTH(M$3,0),$H48>=M$3),"B","U"),IF(AND($G48<>"",$G48<=EOMONTH(M$3,0),$H48>=M$3),"D",""))) | N48: =IF($AH48="","",IF(AND($E48<>"",$E48<=EOMONTH(N$3,0),$F48>=N$3),IF(AND($G48<>"",$G48<=EOMONTH(N$3,0),$H48>=N$3),"B","U"),IF(AND($G48<>"",$G48<=EOMONTH(N$3,0),$H48>=N$3),"D",""))) | O48: =IF($AH48="","",IF(AND($E48<>"",$E48<=EOMONTH(O$3,0),$F48>=O$3),IF(AND($G48<>"",$G48<=EOMONTH(O$3,0),$H48>=O$3),"B","U"),IF(AND($G48<>"",$G48<=EOMONTH(O$3,0),$H48>=O$3),"D",""))) | P48: =IF($AH48="","",IF(AND($E48<>"",$E48<=EOMONTH(P$3,0),$F48>=P$3),IF(AND($G48<>"",$G48<=EOMONTH(P$3,0),$H48>=P$3),"B","U"),IF(AND($G48<>"",$G48<=EOMONTH(P$3,0),$H48>=P$3),"D",""))) | ... AF48: =IF($AH48="","",IF(AND($E48<>"",$E48<=EOMONTH(AF$3,0),$F48>=AF$3),IF(AND($G48<>"",$G48<=EOMONTH(AF$3,0),$H48>=AF$3),"B","U"),IF(AND($G48<>"",$G48<=EOMONTH(AF$3,0),$H48>=AF$3),"D",""))) | AG48: =IF($AH48="","",INDEX('Roadmap Calc (Don’t Touch)'!$D$2:$D$205,$AH48)) | AH48: =IFERROR(MATCH(42,'Roadmap Calc (Don’t Touch)'!$O$2:$O$205,0),"")
A49: =IF($AH49="","",IF($AG49=$AG48,"",$AG49)) | B49: =IF($AH49="","",INDEX('Roadmap Calc (Don’t Touch)'!$B$2:$B$205,$AH49)) | C49: =IF($AH49="","",INDEX('Roadmap Calc (Don’t Touch)'!$E$2:$E$205,$AH49)) | D49: =IF($AH49="","",INDEX('Roadmap Calc (Don’t Touch)'!$F$2:$F$205,$AH49)) | E49: =IF($AH49="","",INDEX('Roadmap Calc (Don’t Touch)'!$G$2:$G$205,$AH49)) | F49: =IF($AH49="","",INDEX('Roadmap Calc (Don’t Touch)'!$H$2:$H$205,$AH49)) | G49: =IF($AH49="","",INDEX('Roadmap Calc (Don’t Touch)'!$I$2:$I$205,$AH49)) | H49: =IF($AH49="","",INDEX('Roadmap Calc (Don’t Touch)'!$J$2:$J$205,$AH49)) | I49: =IF($AH49="","",IF(AND($E49<>"",$E49<=EOMONTH(I$3,0),$F49>=I$3),IF(AND($G49<>"",$G49<=EOMONTH(I$3,0),$H49>=I$3),"B","U"),IF(AND($G49<>"",$G49<=EOMONTH(I$3,0),$H49>=I$3),"D",""))) | J49: =IF($AH49="","",IF(AND($E49<>"",$E49<=EOMONTH(J$3,0),$F49>=J$3),IF(AND($G49<>"",$G49<=EOMONTH(J$3,0),$H49>=J$3),"B","U"),IF(AND($G49<>"",$G49<=EOMONTH(J$3,0),$H49>=J$3),"D",""))) | K49: =IF($AH49="","",IF(AND($E49<>"",$E49<=EOMONTH(K$3,0),$F49>=K$3),IF(AND($G49<>"",$G49<=EOMONTH(K$3,0),$H49>=K$3),"B","U"),IF(AND($G49<>"",$G49<=EOMONTH(K$3,0),$H49>=K$3),"D",""))) | L49: =IF($AH49="","",IF(AND($E49<>"",$E49<=EOMONTH(L$3,0),$F49>=L$3),IF(AND($G49<>"",$G49<=EOMONTH(L$3,0),$H49>=L$3),"B","U"),IF(AND($G49<>"",$G49<=EOMONTH(L$3,0),$H49>=L$3),"D",""))) | M49: =IF($AH49="","",IF(AND($E49<>"",$E49<=EOMONTH(M$3,0),$F49>=M$3),IF(AND($G49<>"",$G49<=EOMONTH(M$3,0),$H49>=M$3),"B","U"),IF(AND($G49<>"",$G49<=EOMONTH(M$3,0),$H49>=M$3),"D",""))) | N49: =IF($AH49="","",IF(AND($E49<>"",$E49<=EOMONTH(N$3,0),$F49>=N$3),IF(AND($G49<>"",$G49<=EOMONTH(N$3,0),$H49>=N$3),"B","U"),IF(AND($G49<>"",$G49<=EOMONTH(N$3,0),$H49>=N$3),"D",""))) | O49: =IF($AH49="","",IF(AND($E49<>"",$E49<=EOMONTH(O$3,0),$F49>=O$3),IF(AND($G49<>"",$G49<=EOMONTH(O$3,0),$H49>=O$3),"B","U"),IF(AND($G49<>"",$G49<=EOMONTH(O$3,0),$H49>=O$3),"D",""))) | P49: =IF($AH49="","",IF(AND($E49<>"",$E49<=EOMONTH(P$3,0),$F49>=P$3),IF(AND($G49<>"",$G49<=EOMONTH(P$3,0),$H49>=P$3),"B","U"),IF(AND($G49<>"",$G49<=EOMONTH(P$3,0),$H49>=P$3),"D",""))) | ... AF49: =IF($AH49="","",IF(AND($E49<>"",$E49<=EOMONTH(AF$3,0),$F49>=AF$3),IF(AND($G49<>"",$G49<=EOMONTH(AF$3,0),$H49>=AF$3),"B","U"),IF(AND($G49<>"",$G49<=EOMONTH(AF$3,0),$H49>=AF$3),"D",""))) | AG49: =IF($AH49="","",INDEX('Roadmap Calc (Don’t Touch)'!$D$2:$D$205,$AH49)) | AH49: =IFERROR(MATCH(43,'Roadmap Calc (Don’t Touch)'!$O$2:$O$205,0),"")
A50: =IF($AH50="","",IF($AG50=$AG49,"",$AG50)) | B50: =IF($AH50="","",INDEX('Roadmap Calc (Don’t Touch)'!$B$2:$B$205,$AH50)) | C50: =IF($AH50="","",INDEX('Roadmap Calc (Don’t Touch)'!$E$2:$E$205,$AH50)) | D50: =IF($AH50="","",INDEX('Roadmap Calc (Don’t Touch)'!$F$2:$F$205,$AH50)) | E50: =IF($AH50="","",INDEX('Roadmap Calc (Don’t Touch)'!$G$2:$G$205,$AH50)) | F50: =IF($AH50="","",INDEX('Roadmap Calc (Don’t Touch)'!$H$2:$H$205,$AH50)) | G50: =IF($AH50="","",INDEX('Roadmap Calc (Don’t Touch)'!$I$2:$I$205,$AH50)) | H50: =IF($AH50="","",INDEX('Roadmap Calc (Don’t Touch)'!$J$2:$J$205,$AH50)) | I50: =IF($AH50="","",IF(AND($E50<>"",$E50<=EOMONTH(I$3,0),$F50>=I$3),IF(AND($G50<>"",$G50<=EOMONTH(I$3,0),$H50>=I$3),"B","U"),IF(AND($G50<>"",$G50<=EOMONTH(I$3,0),$H50>=I$3),"D",""))) | J50: =IF($AH50="","",IF(AND($E50<>"",$E50<=EOMONTH(J$3,0),$F50>=J$3),IF(AND($G50<>"",$G50<=EOMONTH(J$3,0),$H50>=J$3),"B","U"),IF(AND($G50<>"",$G50<=EOMONTH(J$3,0),$H50>=J$3),"D",""))) | K50: =IF($AH50="","",IF(AND($E50<>"",$E50<=EOMONTH(K$3,0),$F50>=K$3),IF(AND($G50<>"",$G50<=EOMONTH(K$3,0),$H50>=K$3),"B","U"),IF(AND($G50<>"",$G50<=EOMONTH(K$3,0),$H50>=K$3),"D",""))) | L50: =IF($AH50="","",IF(AND($E50<>"",$E50<=EOMONTH(L$3,0),$F50>=L$3),IF(AND($G50<>"",$G50<=EOMONTH(L$3,0),$H50>=L$3),"B","U"),IF(AND($G50<>"",$G50<=EOMONTH(L$3,0),$H50>=L$3),"D",""))) | M50: =IF($AH50="","",IF(AND($E50<>"",$E50<=EOMONTH(M$3,0),$F50>=M$3),IF(AND($G50<>"",$G50<=EOMONTH(M$3,0),$H50>=M$3),"B","U"),IF(AND($G50<>"",$G50<=EOMONTH(M$3,0),$H50>=M$3),"D",""))) | N50: =IF($AH50="","",IF(AND($E50<>"",$E50<=EOMONTH(N$3,0),$F50>=N$3),IF(AND($G50<>"",$G50<=EOMONTH(N$3,0),$H50>=N$3),"B","U"),IF(AND($G50<>"",$G50<=EOMONTH(N$3,0),$H50>=N$3),"D",""))) | O50: =IF($AH50="","",IF(AND($E50<>"",$E50<=EOMONTH(O$3,0),$F50>=O$3),IF(AND($G50<>"",$G50<=EOMONTH(O$3,0),$H50>=O$3),"B","U"),IF(AND($G50<>"",$G50<=EOMONTH(O$3,0),$H50>=O$3),"D",""))) | P50: =IF($AH50="","",IF(AND($E50<>"",$E50<=EOMONTH(P$3,0),$F50>=P$3),IF(AND($G50<>"",$G50<=EOMONTH(P$3,0),$H50>=P$3),"B","U"),IF(AND($G50<>"",$G50<=EOMONTH(P$3,0),$H50>=P$3),"D",""))) | ... AF50: =IF($AH50="","",IF(AND($E50<>"",$E50<=EOMONTH(AF$3,0),$F50>=AF$3),IF(AND($G50<>"",$G50<=EOMONTH(AF$3,0),$H50>=AF$3),"B","U"),IF(AND($G50<>"",$G50<=EOMONTH(AF$3,0),$H50>=AF$3),"D",""))) | AG50: =IF($AH50="","",INDEX('Roadmap Calc (Don’t Touch)'!$D$2:$D$205,$AH50)) | AH50: =IFERROR(MATCH(44,'Roadmap Calc (Don’t Touch)'!$O$2:$O$205,0),"")
A51: =IF($AH51="","",IF($AG51=$AG50,"",$AG51)) | B51: =IF($AH51="","",INDEX('Roadmap Calc (Don’t Touch)'!$B$2:$B$205,$AH51)) | C51: =IF($AH51="","",INDEX('Roadmap Calc (Don’t Touch)'!$E$2:$E$205,$AH51)) | D51: =IF($AH51="","",INDEX('Roadmap Calc (Don’t Touch)'!$F$2:$F$205,$AH51)) | E51: =IF($AH51="","",INDEX('Roadmap Calc (Don’t Touch)'!$G$2:$G$205,$AH51)) | F51: =IF($AH51="","",INDEX('Roadmap Calc (Don’t Touch)'!$H$2:$H$205,$AH51)) | G51: =IF($AH51="","",INDEX('Roadmap Calc (Don’t Touch)'!$I$2:$I$205,$AH51)) | H51: =IF($AH51="","",INDEX('Roadmap Calc (Don’t Touch)'!$J$2:$J$205,$AH51)) | I51: =IF($AH51="","",IF(AND($E51<>"",$E51<=EOMONTH(I$3,0),$F51>=I$3),IF(AND($G51<>"",$G51<=EOMONTH(I$3,0),$H51>=I$3),"B","U"),IF(AND($G51<>"",$G51<=EOMONTH(I$3,0),$H51>=I$3),"D",""))) | J51: =IF($AH51="","",IF(AND($E51<>"",$E51<=EOMONTH(J$3,0),$F51>=J$3),IF(AND($G51<>"",$G51<=EOMONTH(J$3,0),$H51>=J$3),"B","U"),IF(AND($G51<>"",$G51<=EOMONTH(J$3,0),$H51>=J$3),"D",""))) | K51: =IF($AH51="","",IF(AND($E51<>"",$E51<=EOMONTH(K$3,0),$F51>=K$3),IF(AND($G51<>"",$G51<=EOMONTH(K$3,0),$H51>=K$3),"B","U"),IF(AND($G51<>"",$G51<=EOMONTH(K$3,0),$H51>=K$3),"D",""))) | L51: =IF($AH51="","",IF(AND($E51<>"",$E51<=EOMONTH(L$3,0),$F51>=L$3),IF(AND($G51<>"",$G51<=EOMONTH(L$3,0),$H51>=L$3),"B","U"),IF(AND($G51<>"",$G51<=EOMONTH(L$3,0),$H51>=L$3),"D",""))) | M51: =IF($AH51="","",IF(AND($E51<>"",$E51<=EOMONTH(M$3,0),$F51>=M$3),IF(AND($G51<>"",$G51<=EOMONTH(M$3,0),$H51>=M$3),"B","U"),IF(AND($G51<>"",$G51<=EOMONTH(M$3,0),$H51>=M$3),"D",""))) | N51: =IF($AH51="","",IF(AND($E51<>"",$E51<=EOMONTH(N$3,0),$F51>=N$3),IF(AND($G51<>"",$G51<=EOMONTH(N$3,0),$H51>=N$3),"B","U"),IF(AND($G51<>"",$G51<=EOMONTH(N$3,0),$H51>=N$3),"D",""))) | O51: =IF($AH51="","",IF(AND($E51<>"",$E51<=EOMONTH(O$3,0),$F51>=O$3),IF(AND($G51<>"",$G51<=EOMONTH(O$3,0),$H51>=O$3),"B","U"),IF(AND($G51<>"",$G51<=EOMONTH(O$3,0),$H51>=O$3),"D",""))) | P51: =IF($AH51="","",IF(AND($E51<>"",$E51<=EOMONTH(P$3,0),$F51>=P$3),IF(AND($G51<>"",$G51<=EOMONTH(P$3,0),$H51>=P$3),"B","U"),IF(AND($G51<>"",$G51<=EOMONTH(P$3,0),$H51>=P$3),"D",""))) | ... AF51: =IF($AH51="","",IF(AND($E51<>"",$E51<=EOMONTH(AF$3,0),$F51>=AF$3),IF(AND($G51<>"",$G51<=EOMONTH(AF$3,0),$H51>=AF$3),"B","U"),IF(AND($G51<>"",$G51<=EOMONTH(AF$3,0),$H51>=AF$3),"D",""))) | AG51: =IF($AH51="","",INDEX('Roadmap Calc (Don’t Touch)'!$D$2:$D$205,$AH51)) | AH51: =IFERROR(MATCH(45,'Roadmap Calc (Don’t Touch)'!$O$2:$O$205,0),"")
A52: =IF($AH52="","",IF($AG52=$AG51,"",$AG52)) | B52: =IF($AH52="","",INDEX('Roadmap Calc (Don’t Touch)'!$B$2:$B$205,$AH52)) | C52: =IF($AH52="","",INDEX('Roadmap Calc (Don’t Touch)'!$E$2:$E$205,$AH52)) | D52: =IF($AH52="","",INDEX('Roadmap Calc (Don’t Touch)'!$F$2:$F$205,$AH52)) | E52: =IF($AH52="","",INDEX('Roadmap Calc (Don’t Touch)'!$G$2:$G$205,$AH52)) | F52: =IF($AH52="","",INDEX('Roadmap Calc (Don’t Touch)'!$H$2:$H$205,$AH52)) | G52: =IF($AH52="","",INDEX('Roadmap Calc (Don’t Touch)'!$I$2:$I$205,$AH52)) | H52: =IF($AH52="","",INDEX('Roadmap Calc (Don’t Touch)'!$J$2:$J$205,$AH52)) | I52: =IF($AH52="","",IF(AND($E52<>"",$E52<=EOMONTH(I$3,0),$F52>=I$3),IF(AND($G52<>"",$G52<=EOMONTH(I$3,0),$H52>=I$3),"B","U"),IF(AND($G52<>"",$G52<=EOMONTH(I$3,0),$H52>=I$3),"D",""))) | J52: =IF($AH52="","",IF(AND($E52<>"",$E52<=EOMONTH(J$3,0),$F52>=J$3),IF(AND($G52<>"",$G52<=EOMONTH(J$3,0),$H52>=J$3),"B","U"),IF(AND($G52<>"",$G52<=EOMONTH(J$3,0),$H52>=J$3),"D",""))) | K52: =IF($AH52="","",IF(AND($E52<>"",$E52<=EOMONTH(K$3,0),$F52>=K$3),IF(AND($G52<>"",$G52<=EOMONTH(K$3,0),$H52>=K$3),"B","U"),IF(AND($G52<>"",$G52<=EOMONTH(K$3,0),$H52>=K$3),"D",""))) | L52: =IF($AH52="","",IF(AND($E52<>"",$E52<=EOMONTH(L$3,0),$F52>=L$3),IF(AND($G52<>"",$G52<=EOMONTH(L$3,0),$H52>=L$3),"B","U"),IF(AND($G52<>"",$G52<=EOMONTH(L$3,0),$H52>=L$3),"D",""))) | M52: =IF($AH52="","",IF(AND($E52<>"",$E52<=EOMONTH(M$3,0),$F52>=M$3),IF(AND($G52<>"",$G52<=EOMONTH(M$3,0),$H52>=M$3),"B","U"),IF(AND($G52<>"",$G52<=EOMONTH(M$3,0),$H52>=M$3),"D",""))) | N52: =IF($AH52="","",IF(AND($E52<>"",$E52<=EOMONTH(N$3,0),$F52>=N$3),IF(AND($G52<>"",$G52<=EOMONTH(N$3,0),$H52>=N$3),"B","U"),IF(AND($G52<>"",$G52<=EOMONTH(N$3,0),$H52>=N$3),"D",""))) | O52: =IF($AH52="","",IF(AND($E52<>"",$E52<=EOMONTH(O$3,0),$F52>=O$3),IF(AND($G52<>"",$G52<=EOMONTH(O$3,0),$H52>=O$3),"B","U"),IF(AND($G52<>"",$G52<=EOMONTH(O$3,0),$H52>=O$3),"D",""))) | P52: =IF($AH52="","",IF(AND($E52<>"",$E52<=EOMONTH(P$3,0),$F52>=P$3),IF(AND($G52<>"",$G52<=EOMONTH(P$3,0),$H52>=P$3),"B","U"),IF(AND($G52<>"",$G52<=EOMONTH(P$3,0),$H52>=P$3),"D",""))) | ... AF52: =IF($AH52="","",IF(AND($E52<>"",$E52<=EOMONTH(AF$3,0),$F52>=AF$3),IF(AND($G52<>"",$G52<=EOMONTH(AF$3,0),$H52>=AF$3),"B","U"),IF(AND($G52<>"",$G52<=EOMONTH(AF$3,0),$H52>=AF$3),"D",""))) | AG52: =IF($AH52="","",INDEX('Roadmap Calc (Don’t Touch)'!$D$2:$D$205,$AH52)) | AH52: =IFERROR(MATCH(46,'Roadmap Calc (Don’t Touch)'!$O$2:$O$205,0),"")
A53: =IF($AH53="","",IF($AG53=$AG52,"",$AG53)) | B53: =IF($AH53="","",INDEX('Roadmap Calc (Don’t Touch)'!$B$2:$B$205,$AH53)) | C53: =IF($AH53="","",INDEX('Roadmap Calc (Don’t Touch)'!$E$2:$E$205,$AH53)) | D53: =IF($AH53="","",INDEX('Roadmap Calc (Don’t Touch)'!$F$2:$F$205,$AH53)) | E53: =IF($AH53="","",INDEX('Roadmap Calc (Don’t Touch)'!$G$2:$G$205,$AH53)) | F53: =IF($AH53="","",INDEX('Roadmap Calc (Don’t Touch)'!$H$2:$H$205,$AH53)) | G53: =IF($AH53="","",INDEX('Roadmap Calc (Don’t Touch)'!$I$2:$I$205,$AH53)) | H53: =IF($AH53="","",INDEX('Roadmap Calc (Don’t Touch)'!$J$2:$J$205,$AH53)) | I53: =IF($AH53="","",IF(AND($E53<>"",$E53<=EOMONTH(I$3,0),$F53>=I$3),IF(AND($G53<>"",$G53<=EOMONTH(I$3,0),$H53>=I$3),"B","U"),IF(AND($G53<>"",$G53<=EOMONTH(I$3,0),$H53>=I$3),"D",""))) | J53: =IF($AH53="","",IF(AND($E53<>"",$E53<=EOMONTH(J$3,0),$F53>=J$3),IF(AND($G53<>"",$G53<=EOMONTH(J$3,0),$H53>=J$3),"B","U"),IF(AND($G53<>"",$G53<=EOMONTH(J$3,0),$H53>=J$3),"D",""))) | K53: =IF($AH53="","",IF(AND($E53<>"",$E53<=EOMONTH(K$3,0),$F53>=K$3),IF(AND($G53<>"",$G53<=EOMONTH(K$3,0),$H53>=K$3),"B","U"),IF(AND($G53<>"",$G53<=EOMONTH(K$3,0),$H53>=K$3),"D",""))) | L53: =IF($AH53="","",IF(AND($E53<>"",$E53<=EOMONTH(L$3,0),$F53>=L$3),IF(AND($G53<>"",$G53<=EOMONTH(L$3,0),$H53>=L$3),"B","U"),IF(AND($G53<>"",$G53<=EOMONTH(L$3,0),$H53>=L$3),"D",""))) | M53: =IF($AH53="","",IF(AND($E53<>"",$E53<=EOMONTH(M$3,0),$F53>=M$3),IF(AND($G53<>"",$G53<=EOMONTH(M$3,0),$H53>=M$3),"B","U"),IF(AND($G53<>"",$G53<=EOMONTH(M$3,0),$H53>=M$3),"D",""))) | N53: =IF($AH53="","",IF(AND($E53<>"",$E53<=EOMONTH(N$3,0),$F53>=N$3),IF(AND($G53<>"",$G53<=EOMONTH(N$3,0),$H53>=N$3),"B","U"),IF(AND($G53<>"",$G53<=EOMONTH(N$3,0),$H53>=N$3),"D",""))) | O53: =IF($AH53="","",IF(AND($E53<>"",$E53<=EOMONTH(O$3,0),$F53>=O$3),IF(AND($G53<>"",$G53<=EOMONTH(O$3,0),$H53>=O$3),"B","U"),IF(AND($G53<>"",$G53<=EOMONTH(O$3,0),$H53>=O$3),"D",""))) | P53: =IF($AH53="","",IF(AND($E53<>"",$E53<=EOMONTH(P$3,0),$F53>=P$3),IF(AND($G53<>"",$G53<=EOMONTH(P$3,0),$H53>=P$3),"B","U"),IF(AND($G53<>"",$G53<=EOMONTH(P$3,0),$H53>=P$3),"D",""))) | ... AF53: =IF($AH53="","",IF(AND($E53<>"",$E53<=EOMONTH(AF$3,0),$F53>=AF$3),IF(AND($G53<>"",$G53<=EOMONTH(AF$3,0),$H53>=AF$3),"B","U"),IF(AND($G53<>"",$G53<=EOMONTH(AF$3,0),$H53>=AF$3),"D",""))) | AG53: =IF($AH53="","",INDEX('Roadmap Calc (Don’t Touch)'!$D$2:$D$205,$AH53)) | AH53: =IFERROR(MATCH(47,'Roadmap Calc (Don’t Touch)'!$O$2:$O$205,0),"")
A54: =IF($AH54="","",IF($AG54=$AG53,"",$AG54)) | B54: =IF($AH54="","",INDEX('Roadmap Calc (Don’t Touch)'!$B$2:$B$205,$AH54)) | C54: =IF($AH54="","",INDEX('Roadmap Calc (Don’t Touch)'!$E$2:$E$205,$AH54)) | D54: =IF($AH54="","",INDEX('Roadmap Calc (Don’t Touch)'!$F$2:$F$205,$AH54)) | E54: =IF($AH54="","",INDEX('Roadmap Calc (Don’t Touch)'!$G$2:$G$205,$AH54)) | F54: =IF($AH54="","",INDEX('Roadmap Calc (Don’t Touch)'!$H$2:$H$205,$AH54)) | G54: =IF($AH54="","",INDEX('Roadmap Calc (Don’t Touch)'!$I$2:$I$205,$AH54)) | H54: =IF($AH54="","",INDEX('Roadmap Calc (Don’t Touch)'!$J$2:$J$205,$AH54)) | I54: =IF($AH54="","",IF(AND($E54<>"",$E54<=EOMONTH(I$3,0),$F54>=I$3),IF(AND($G54<>"",$G54<=EOMONTH(I$3,0),$H54>=I$3),"B","U"),IF(AND($G54<>"",$G54<=EOMONTH(I$3,0),$H54>=I$3),"D",""))) | J54: =IF($AH54="","",IF(AND($E54<>"",$E54<=EOMONTH(J$3,0),$F54>=J$3),IF(AND($G54<>"",$G54<=EOMONTH(J$3,0),$H54>=J$3),"B","U"),IF(AND($G54<>"",$G54<=EOMONTH(J$3,0),$H54>=J$3),"D",""))) | K54: =IF($AH54="","",IF(AND($E54<>"",$E54<=EOMONTH(K$3,0),$F54>=K$3),IF(AND($G54<>"",$G54<=EOMONTH(K$3,0),$H54>=K$3),"B","U"),IF(AND($G54<>"",$G54<=EOMONTH(K$3,0),$H54>=K$3),"D",""))) | L54: =IF($AH54="","",IF(AND($E54<>"",$E54<=EOMONTH(L$3,0),$F54>=L$3),IF(AND($G54<>"",$G54<=EOMONTH(L$3,0),$H54>=L$3),"B","U"),IF(AND($G54<>"",$G54<=EOMONTH(L$3,0),$H54>=L$3),"D",""))) | M54: =IF($AH54="","",IF(AND($E54<>"",$E54<=EOMONTH(M$3,0),$F54>=M$3),IF(AND($G54<>"",$G54<=EOMONTH(M$3,0),$H54>=M$3),"B","U"),IF(AND($G54<>"",$G54<=EOMONTH(M$3,0),$H54>=M$3),"D",""))) | N54: =IF($AH54="","",IF(AND($E54<>"",$E54<=EOMONTH(N$3,0),$F54>=N$3),IF(AND($G54<>"",$G54<=EOMONTH(N$3,0),$H54>=N$3),"B","U"),IF(AND($G54<>"",$G54<=EOMONTH(N$3,0),$H54>=N$3),"D",""))) | O54: =IF($AH54="","",IF(AND($E54<>"",$E54<=EOMONTH(O$3,0),$F54>=O$3),IF(AND($G54<>"",$G54<=EOMONTH(O$3,0),$H54>=O$3),"B","U"),IF(AND($G54<>"",$G54<=EOMONTH(O$3,0),$H54>=O$3),"D",""))) | P54: =IF($AH54="","",IF(AND($E54<>"",$E54<=EOMONTH(P$3,0),$F54>=P$3),IF(AND($G54<>"",$G54<=EOMONTH(P$3,0),$H54>=P$3),"B","U"),IF(AND($G54<>"",$G54<=EOMONTH(P$3,0),$H54>=P$3),"D",""))) | ... AF54: =IF($AH54="","",IF(AND($E54<>"",$E54<=EOMONTH(AF$3,0),$F54>=AF$3),IF(AND($G54<>"",$G54<=EOMONTH(AF$3,0),$H54>=AF$3),"B","U"),IF(AND($G54<>"",$G54<=EOMONTH(AF$3,0),$H54>=AF$3),"D",""))) | AG54: =IF($AH54="","",INDEX('Roadmap Calc (Don’t Touch)'!$D$2:$D$205,$AH54)) | AH54: =IFERROR(MATCH(48,'Roadmap Calc (Don’t Touch)'!$O$2:$O$205,0),"")
A55: =IF($AH55="","",IF($AG55=$AG54,"",$AG55)) | B55: =IF($AH55="","",INDEX('Roadmap Calc (Don’t Touch)'!$B$2:$B$205,$AH55)) | C55: =IF($AH55="","",INDEX('Roadmap Calc (Don’t Touch)'!$E$2:$E$205,$AH55)) | D55: =IF($AH55="","",INDEX('Roadmap Calc (Don’t Touch)'!$F$2:$F$205,$AH55)) | E55: =IF($AH55="","",INDEX('Roadmap Calc (Don’t Touch)'!$G$2:$G$205,$AH55)) | F55: =IF($AH55="","",INDEX('Roadmap Calc (Don’t Touch)'!$H$2:$H$205,$AH55)) | G55: =IF($AH55="","",INDEX('Roadmap Calc (Don’t Touch)'!$I$2:$I$205,$AH55)) | H55: =IF($AH55="","",INDEX('Roadmap Calc (Don’t Touch)'!$J$2:$J$205,$AH55)) | I55: =IF($AH55="","",IF(AND($E55<>"",$E55<=EOMONTH(I$3,0),$F55>=I$3),IF(AND($G55<>"",$G55<=EOMONTH(I$3,0),$H55>=I$3),"B","U"),IF(AND($G55<>"",$G55<=EOMONTH(I$3,0),$H55>=I$3),"D",""))) | J55: =IF($AH55="","",IF(AND($E55<>"",$E55<=EOMONTH(J$3,0),$F55>=J$3),IF(AND($G55<>"",$G55<=EOMONTH(J$3,0),$H55>=J$3),"B","U"),IF(AND($G55<>"",$G55<=EOMONTH(J$3,0),$H55>=J$3),"D",""))) | K55: =IF($AH55="","",IF(AND($E55<>"",$E55<=EOMONTH(K$3,0),$F55>=K$3),IF(AND($G55<>"",$G55<=EOMONTH(K$3,0),$H55>=K$3),"B","U"),IF(AND($G55<>"",$G55<=EOMONTH(K$3,0),$H55>=K$3),"D",""))) | L55: =IF($AH55="","",IF(AND($E55<>"",$E55<=EOMONTH(L$3,0),$F55>=L$3),IF(AND($G55<>"",$G55<=EOMONTH(L$3,0),$H55>=L$3),"B","U"),IF(AND($G55<>"",$G55<=EOMONTH(L$3,0),$H55>=L$3),"D",""))) | M55: =IF($AH55="","",IF(AND($E55<>"",$E55<=EOMONTH(M$3,0),$F55>=M$3),IF(AND($G55<>"",$G55<=EOMONTH(M$3,0),$H55>=M$3),"B","U"),IF(AND($G55<>"",$G55<=EOMONTH(M$3,0),$H55>=M$3),"D",""))) | N55: =IF($AH55="","",IF(AND($E55<>"",$E55<=EOMONTH(N$3,0),$F55>=N$3),IF(AND($G55<>"",$G55<=EOMONTH(N$3,0),$H55>=N$3),"B","U"),IF(AND($G55<>"",$G55<=EOMONTH(N$3,0),$H55>=N$3),"D",""))) | O55: =IF($AH55="","",IF(AND($E55<>"",$E55<=EOMONTH(O$3,0),$F55>=O$3),IF(AND($G55<>"",$G55<=EOMONTH(O$3,0),$H55>=O$3),"B","U"),IF(AND($G55<>"",$G55<=EOMONTH(O$3,0),$H55>=O$3),"D",""))) | P55: =IF($AH55="","",IF(AND($E55<>"",$E55<=EOMONTH(P$3,0),$F55>=P$3),IF(AND($G55<>"",$G55<=EOMONTH(P$3,0),$H55>=P$3),"B","U"),IF(AND($G55<>"",$G55<=EOMONTH(P$3,0),$H55>=P$3),"D",""))) | ... AF55: =IF($AH55="","",IF(AND($E55<>"",$E55<=EOMONTH(AF$3,0),$F55>=AF$3),IF(AND($G55<>"",$G55<=EOMONTH(AF$3,0),$H55>=AF$3),"B","U"),IF(AND($G55<>"",$G55<=EOMONTH(AF$3,0),$H55>=AF$3),"D",""))) | AG55: =IF($AH55="","",INDEX('Roadmap Calc (Don’t Touch)'!$D$2:$D$205,$AH55)) | AH55: =IFERROR(MATCH(49,'Roadmap Calc (Don’t Touch)'!$O$2:$O$205,0),"")
A56: =IF($AH56="","",IF($AG56=$AG55,"",$AG56)) | B56: =IF($AH56="","",INDEX('Roadmap Calc (Don’t Touch)'!$B$2:$B$205,$AH56)) | C56: =IF($AH56="","",INDEX('Roadmap Calc (Don’t Touch)'!$E$2:$E$205,$AH56)) | D56: =IF($AH56="","",INDEX('Roadmap Calc (Don’t Touch)'!$F$2:$F$205,$AH56)) | E56: =IF($AH56="","",INDEX('Roadmap Calc (Don’t Touch)'!$G$2:$G$205,$AH56)) | F56: =IF($AH56="","",INDEX('Roadmap Calc (Don’t Touch)'!$H$2:$H$205,$AH56)) | G56: =IF($AH56="","",INDEX('Roadmap Calc (Don’t Touch)'!$I$2:$I$205,$AH56)) | H56: =IF($AH56="","",INDEX('Roadmap Calc (Don’t Touch)'!$J$2:$J$205,$AH56)) | I56: =IF($AH56="","",IF(AND($E56<>"",$E56<=EOMONTH(I$3,0),$F56>=I$3),IF(AND($G56<>"",$G56<=EOMONTH(I$3,0),$H56>=I$3),"B","U"),IF(AND($G56<>"",$G56<=EOMONTH(I$3,0),$H56>=I$3),"D",""))) | J56: =IF($AH56="","",IF(AND($E56<>"",$E56<=EOMONTH(J$3,0),$F56>=J$3),IF(AND($G56<>"",$G56<=EOMONTH(J$3,0),$H56>=J$3),"B","U"),IF(AND($G56<>"",$G56<=EOMONTH(J$3,0),$H56>=J$3),"D",""))) | K56: =IF($AH56="","",IF(AND($E56<>"",$E56<=EOMONTH(K$3,0),$F56>=K$3),IF(AND($G56<>"",$G56<=EOMONTH(K$3,0),$H56>=K$3),"B","U"),IF(AND($G56<>"",$G56<=EOMONTH(K$3,0),$H56>=K$3),"D",""))) | L56: =IF($AH56="","",IF(AND($E56<>"",$E56<=EOMONTH(L$3,0),$F56>=L$3),IF(AND($G56<>"",$G56<=EOMONTH(L$3,0),$H56>=L$3),"B","U"),IF(AND($G56<>"",$G56<=EOMONTH(L$3,0),$H56>=L$3),"D",""))) | M56: =IF($AH56="","",IF(AND($E56<>"",$E56<=EOMONTH(M$3,0),$F56>=M$3),IF(AND($G56<>"",$G56<=EOMONTH(M$3,0),$H56>=M$3),"B","U"),IF(AND($G56<>"",$G56<=EOMONTH(M$3,0),$H56>=M$3),"D",""))) | N56: =IF($AH56="","",IF(AND($E56<>"",$E56<=EOMONTH(N$3,0),$F56>=N$3),IF(AND($G56<>"",$G56<=EOMONTH(N$3,0),$H56>=N$3),"B","U"),IF(AND($G56<>"",$G56<=EOMONTH(N$3,0),$H56>=N$3),"D",""))) | O56: =IF($AH56="","",IF(AND($E56<>"",$E56<=EOMONTH(O$3,0),$F56>=O$3),IF(AND($G56<>"",$G56<=EOMONTH(O$3,0),$H56>=O$3),"B","U"),IF(AND($G56<>"",$G56<=EOMONTH(O$3,0),$H56>=O$3),"D",""))) | P56: =IF($AH56="","",IF(AND($E56<>"",$E56<=EOMONTH(P$3,0),$F56>=P$3),IF(AND($G56<>"",$G56<=EOMONTH(P$3,0),$H56>=P$3),"B","U"),IF(AND($G56<>"",$G56<=EOMONTH(P$3,0),$H56>=P$3),"D",""))) | ... AF56: =IF($AH56="","",IF(AND($E56<>"",$E56<=EOMONTH(AF$3,0),$F56>=AF$3),IF(AND($G56<>"",$G56<=EOMONTH(AF$3,0),$H56>=AF$3),"B","U"),IF(AND($G56<>"",$G56<=EOMONTH(AF$3,0),$H56>=AF$3),"D",""))) | AG56: =IF($AH56="","",INDEX('Roadmap Calc (Don’t Touch)'!$D$2:$D$205,$AH56)) | AH56: =IFERROR(MATCH(50,'Roadmap Calc (Don’t Touch)'!$O$2:$O$205,0),"")
A57: =IF($AH57="","",IF($AG57=$AG56,"",$AG57)) | B57: =IF($AH57="","",INDEX('Roadmap Calc (Don’t Touch)'!$B$2:$B$205,$AH57)) | C57: =IF($AH57="","",INDEX('Roadmap Calc (Don’t Touch)'!$E$2:$E$205,$AH57)) | D57: =IF($AH57="","",INDEX('Roadmap Calc (Don’t Touch)'!$F$2:$F$205,$AH57)) | E57: =IF($AH57="","",INDEX('Roadmap Calc (Don’t Touch)'!$G$2:$G$205,$AH57)) | F57: =IF($AH57="","",INDEX('Roadmap Calc (Don’t Touch)'!$H$2:$H$205,$AH57)) | G57: =IF($AH57="","",INDEX('Roadmap Calc (Don’t Touch)'!$I$2:$I$205,$AH57)) | H57: =IF($AH57="","",INDEX('Roadmap Calc (Don’t Touch)'!$J$2:$J$205,$AH57)) | I57: =IF($AH57="","",IF(AND($E57<>"",$E57<=EOMONTH(I$3,0),$F57>=I$3),IF(AND($G57<>"",$G57<=EOMONTH(I$3,0),$H57>=I$3),"B","U"),IF(AND($G57<>"",$G57<=EOMONTH(I$3,0),$H57>=I$3),"D",""))) | J57: =IF($AH57="","",IF(AND($E57<>"",$E57<=EOMONTH(J$3,0),$F57>=J$3),IF(AND($G57<>"",$G57<=EOMONTH(J$3,0),$H57>=J$3),"B","U"),IF(AND($G57<>"",$G57<=EOMONTH(J$3,0),$H57>=J$3),"D",""))) | K57: =IF($AH57="","",IF(AND($E57<>"",$E57<=EOMONTH(K$3,0),$F57>=K$3),IF(AND($G57<>"",$G57<=EOMONTH(K$3,0),$H57>=K$3),"B","U"),IF(AND($G57<>"",$G57<=EOMONTH(K$3,0),$H57>=K$3),"D",""))) | L57: =IF($AH57="","",IF(AND($E57<>"",$E57<=EOMONTH(L$3,0),$F57>=L$3),IF(AND($G57<>"",$G57<=EOMONTH(L$3,0),$H57>=L$3),"B","U"),IF(AND($G57<>"",$G57<=EOMONTH(L$3,0),$H57>=L$3),"D",""))) | M57: =IF($AH57="","",IF(AND($E57<>"",$E57<=EOMONTH(M$3,0),$F57>=M$3),IF(AND($G57<>"",$G57<=EOMONTH(M$3,0),$H57>=M$3),"B","U"),IF(AND($G57<>"",$G57<=EOMONTH(M$3,0),$H57>=M$3),"D",""))) | N57: =IF($AH57="","",IF(AND($E57<>"",$E57<=EOMONTH(N$3,0),$F57>=N$3),IF(AND($G57<>"",$G57<=EOMONTH(N$3,0),$H57>=N$3),"B","U"),IF(AND($G57<>"",$G57<=EOMONTH(N$3,0),$H57>=N$3),"D",""))) | O57: =IF($AH57="","",IF(AND($E57<>"",$E57<=EOMONTH(O$3,0),$F57>=O$3),IF(AND($G57<>"",$G57<=EOMONTH(O$3,0),$H57>=O$3),"B","U"),IF(AND($G57<>"",$G57<=EOMONTH(O$3,0),$H57>=O$3),"D",""))) | P57: =IF($AH57="","",IF(AND($E57<>"",$E57<=EOMONTH(P$3,0),$F57>=P$3),IF(AND($G57<>"",$G57<=EOMONTH(P$3,0),$H57>=P$3),"B","U"),IF(AND($G57<>"",$G57<=EOMONTH(P$3,0),$H57>=P$3),"D",""))) | ... AF57: =IF($AH57="","",IF(AND($E57<>"",$E57<=EOMONTH(AF$3,0),$F57>=AF$3),IF(AND($G57<>"",$G57<=EOMONTH(AF$3,0),$H57>=AF$3),"B","U"),IF(AND($G57<>"",$G57<=EOMONTH(AF$3,0),$H57>=AF$3),"D",""))) | AG57: =IF($AH57="","",INDEX('Roadmap Calc (Don’t Touch)'!$D$2:$D$205,$AH57)) | AH57: =IFERROR(MATCH(51,'Roadmap Calc (Don’t Touch)'!$O$2:$O$205,0),"")
A58: =IF($AH58="","",IF($AG58=$AG57,"",$AG58)) | B58: =IF($AH58="","",INDEX('Roadmap Calc (Don’t Touch)'!$B$2:$B$205,$AH58)) | C58: =IF($AH58="","",INDEX('Roadmap Calc (Don’t Touch)'!$E$2:$E$205,$AH58)) | D58: =IF($AH58="","",INDEX('Roadmap Calc (Don’t Touch)'!$F$2:$F$205,$AH58)) | E58: =IF($AH58="","",INDEX('Roadmap Calc (Don’t Touch)'!$G$2:$G$205,$AH58)) | F58: =IF($AH58="","",INDEX('Roadmap Calc (Don’t Touch)'!$H$2:$H$205,$AH58)) | G58: =IF($AH58="","",INDEX('Roadmap Calc (Don’t Touch)'!$I$2:$I$205,$AH58)) | H58: =IF($AH58="","",INDEX('Roadmap Calc (Don’t Touch)'!$J$2:$J$205,$AH58)) | I58: =IF($AH58="","",IF(AND($E58<>"",$E58<=EOMONTH(I$3,0),$F58>=I$3),IF(AND($G58<>"",$G58<=EOMONTH(I$3,0),$H58>=I$3),"B","U"),IF(AND($G58<>"",$G58<=EOMONTH(I$3,0),$H58>=I$3),"D",""))) | J58: =IF($AH58="","",IF(AND($E58<>"",$E58<=EOMONTH(J$3,0),$F58>=J$3),IF(AND($G58<>"",$G58<=EOMONTH(J$3,0),$H58>=J$3),"B","U"),IF(AND($G58<>"",$G58<=EOMONTH(J$3,0),$H58>=J$3),"D",""))) | K58: =IF($AH58="","",IF(AND($E58<>"",$E58<=EOMONTH(K$3,0),$F58>=K$3),IF(AND($G58<>"",$G58<=EOMONTH(K$3,0),$H58>=K$3),"B","U"),IF(AND($G58<>"",$G58<=EOMONTH(K$3,0),$H58>=K$3),"D",""))) | L58: =IF($AH58="","",IF(AND($E58<>"",$E58<=EOMONTH(L$3,0),$F58>=L$3),IF(AND($G58<>"",$G58<=EOMONTH(L$3,0),$H58>=L$3),"B","U"),IF(AND($G58<>"",$G58<=EOMONTH(L$3,0),$H58>=L$3),"D",""))) | M58: =IF($AH58="","",IF(AND($E58<>"",$E58<=EOMONTH(M$3,0),$F58>=M$3),IF(AND($G58<>"",$G58<=EOMONTH(M$3,0),$H58>=M$3),"B","U"),IF(AND($G58<>"",$G58<=EOMONTH(M$3,0),$H58>=M$3),"D",""))) | N58: =IF($AH58="","",IF(AND($E58<>"",$E58<=EOMONTH(N$3,0),$F58>=N$3),IF(AND($G58<>"",$G58<=EOMONTH(N$3,0),$H58>=N$3),"B","U"),IF(AND($G58<>"",$G58<=EOMONTH(N$3,0),$H58>=N$3),"D",""))) | O58: =IF($AH58="","",IF(AND($E58<>"",$E58<=EOMONTH(O$3,0),$F58>=O$3),IF(AND($G58<>"",$G58<=EOMONTH(O$3,0),$H58>=O$3),"B","U"),IF(AND($G58<>"",$G58<=EOMONTH(O$3,0),$H58>=O$3),"D",""))) | P58: =IF($AH58="","",IF(AND($E58<>"",$E58<=EOMONTH(P$3,0),$F58>=P$3),IF(AND($G58<>"",$G58<=EOMONTH(P$3,0),$H58>=P$3),"B","U"),IF(AND($G58<>"",$G58<=EOMONTH(P$3,0),$H58>=P$3),"D",""))) | ... AF58: =IF($AH58="","",IF(AND($E58<>"",$E58<=EOMONTH(AF$3,0),$F58>=AF$3),IF(AND($G58<>"",$G58<=EOMONTH(AF$3,0),$H58>=AF$3),"B","U"),IF(AND($G58<>"",$G58<=EOMONTH(AF$3,0),$H58>=AF$3),"D",""))) | AG58: =IF($AH58="","",INDEX('Roadmap Calc (Don’t Touch)'!$D$2:$D$205,$AH58)) | AH58: =IFERROR(MATCH(52,'Roadmap Calc (Don’t Touch)'!$O$2:$O$205,0),"")
A59: =IF($AH59="","",IF($AG59=$AG58,"",$AG59)) | B59: =IF($AH59="","",INDEX('Roadmap Calc (Don’t Touch)'!$B$2:$B$205,$AH59)) | C59: =IF($AH59="","",INDEX('Roadmap Calc (Don’t Touch)'!$E$2:$E$205,$AH59)) | D59: =IF($AH59="","",INDEX('Roadmap Calc (Don’t Touch)'!$F$2:$F$205,$AH59)) | E59: =IF($AH59="","",INDEX('Roadmap Calc (Don’t Touch)'!$G$2:$G$205,$AH59)) | F59: =IF($AH59="","",INDEX('Roadmap Calc (Don’t Touch)'!$H$2:$H$205,$AH59)) | G59: =IF($AH59="","",INDEX('Roadmap Calc (Don’t Touch)'!$I$2:$I$205,$AH59)) | H59: =IF($AH59="","",INDEX('Roadmap Calc (Don’t Touch)'!$J$2:$J$205,$AH59)) | I59: =IF($AH59="","",IF(AND($E59<>"",$E59<=EOMONTH(I$3,0),$F59>=I$3),IF(AND($G59<>"",$G59<=EOMONTH(I$3,0),$H59>=I$3),"B","U"),IF(AND($G59<>"",$G59<=EOMONTH(I$3,0),$H59>=I$3),"D",""))) | J59: =IF($AH59="","",IF(AND($E59<>"",$E59<=EOMONTH(J$3,0),$F59>=J$3),IF(AND($G59<>"",$G59<=EOMONTH(J$3,0),$H59>=J$3),"B","U"),IF(AND($G59<>"",$G59<=EOMONTH(J$3,0),$H59>=J$3),"D",""))) | K59: =IF($AH59="","",IF(AND($E59<>"",$E59<=EOMONTH(K$3,0),$F59>=K$3),IF(AND($G59<>"",$G59<=EOMONTH(K$3,0),$H59>=K$3),"B","U"),IF(AND($G59<>"",$G59<=EOMONTH(K$3,0),$H59>=K$3),"D",""))) | L59: =IF($AH59="","",IF(AND($E59<>"",$E59<=EOMONTH(L$3,0),$F59>=L$3),IF(AND($G59<>"",$G59<=EOMONTH(L$3,0),$H59>=L$3),"B","U"),IF(AND($G59<>"",$G59<=EOMONTH(L$3,0),$H59>=L$3),"D",""))) | M59: =IF($AH59="","",IF(AND($E59<>"",$E59<=EOMONTH(M$3,0),$F59>=M$3),IF(AND($G59<>"",$G59<=EOMONTH(M$3,0),$H59>=M$3),"B","U"),IF(AND($G59<>"",$G59<=EOMONTH(M$3,0),$H59>=M$3),"D",""))) | N59: =IF($AH59="","",IF(AND($E59<>"",$E59<=EOMONTH(N$3,0),$F59>=N$3),IF(AND($G59<>"",$G59<=EOMONTH(N$3,0),$H59>=N$3),"B","U"),IF(AND($G59<>"",$G59<=EOMONTH(N$3,0),$H59>=N$3),"D",""))) | O59: =IF($AH59="","",IF(AND($E59<>"",$E59<=EOMONTH(O$3,0),$F59>=O$3),IF(AND($G59<>"",$G59<=EOMONTH(O$3,0),$H59>=O$3),"B","U"),IF(AND($G59<>"",$G59<=EOMONTH(O$3,0),$H59>=O$3),"D",""))) | P59: =IF($AH59="","",IF(AND($E59<>"",$E59<=EOMONTH(P$3,0),$F59>=P$3),IF(AND($G59<>"",$G59<=EOMONTH(P$3,0),$H59>=P$3),"B","U"),IF(AND($G59<>"",$G59<=EOMONTH(P$3,0),$H59>=P$3),"D",""))) | ... AF59: =IF($AH59="","",IF(AND($E59<>"",$E59<=EOMONTH(AF$3,0),$F59>=AF$3),IF(AND($G59<>"",$G59<=EOMONTH(AF$3,0),$H59>=AF$3),"B","U"),IF(AND($G59<>"",$G59<=EOMONTH(AF$3,0),$H59>=AF$3),"D",""))) | AG59: =IF($AH59="","",INDEX('Roadmap Calc (Don’t Touch)'!$D$2:$D$205,$AH59)) | AH59: =IFERROR(MATCH(53,'Roadmap Calc (Don’t Touch)'!$O$2:$O$205,0),"")
A60: =IF($AH60="","",IF($AG60=$AG59,"",$AG60)) | B60: =IF($AH60="","",INDEX('Roadmap Calc (Don’t Touch)'!$B$2:$B$205,$AH60)) | C60: =IF($AH60="","",INDEX('Roadmap Calc (Don’t Touch)'!$E$2:$E$205,$AH60)) | D60: =IF($AH60="","",INDEX('Roadmap Calc (Don’t Touch)'!$F$2:$F$205,$AH60)) | E60: =IF($AH60="","",INDEX('Roadmap Calc (Don’t Touch)'!$G$2:$G$205,$AH60)) | F60: =IF($AH60="","",INDEX('Roadmap Calc (Don’t Touch)'!$H$2:$H$205,$AH60)) | G60: =IF($AH60="","",INDEX('Roadmap Calc (Don’t Touch)'!$I$2:$I$205,$AH60)) | H60: =IF($AH60="","",INDEX('Roadmap Calc (Don’t Touch)'!$J$2:$J$205,$AH60)) | I60: =IF($AH60="","",IF(AND($E60<>"",$E60<=EOMONTH(I$3,0),$F60>=I$3),IF(AND($G60<>"",$G60<=EOMONTH(I$3,0),$H60>=I$3),"B","U"),IF(AND($G60<>"",$G60<=EOMONTH(I$3,0),$H60>=I$3),"D",""))) | J60: =IF($AH60="","",IF(AND($E60<>"",$E60<=EOMONTH(J$3,0),$F60>=J$3),IF(AND($G60<>"",$G60<=EOMONTH(J$3,0),$H60>=J$3),"B","U"),IF(AND($G60<>"",$G60<=EOMONTH(J$3,0),$H60>=J$3),"D",""))) | K60: =IF($AH60="","",IF(AND($E60<>"",$E60<=EOMONTH(K$3,0),$F60>=K$3),IF(AND($G60<>"",$G60<=EOMONTH(K$3,0),$H60>=K$3),"B","U"),IF(AND($G60<>"",$G60<=EOMONTH(K$3,0),$H60>=K$3),"D",""))) | L60: =IF($AH60="","",IF(AND($E60<>"",$E60<=EOMONTH(L$3,0),$F60>=L$3),IF(AND($G60<>"",$G60<=EOMONTH(L$3,0),$H60>=L$3),"B","U"),IF(AND($G60<>"",$G60<=EOMONTH(L$3,0),$H60>=L$3),"D",""))) | M60: =IF($AH60="","",IF(AND($E60<>"",$E60<=EOMONTH(M$3,0),$F60>=M$3),IF(AND($G60<>"",$G60<=EOMONTH(M$3,0),$H60>=M$3),"B","U"),IF(AND($G60<>"",$G60<=EOMONTH(M$3,0),$H60>=M$3),"D",""))) | N60: =IF($AH60="","",IF(AND($E60<>"",$E60<=EOMONTH(N$3,0),$F60>=N$3),IF(AND($G60<>"",$G60<=EOMONTH(N$3,0),$H60>=N$3),"B","U"),IF(AND($G60<>"",$G60<=EOMONTH(N$3,0),$H60>=N$3),"D",""))) | O60: =IF($AH60="","",IF(AND($E60<>"",$E60<=EOMONTH(O$3,0),$F60>=O$3),IF(AND($G60<>"",$G60<=EOMONTH(O$3,0),$H60>=O$3),"B","U"),IF(AND($G60<>"",$G60<=EOMONTH(O$3,0),$H60>=O$3),"D",""))) | P60: =IF($AH60="","",IF(AND($E60<>"",$E60<=EOMONTH(P$3,0),$F60>=P$3),IF(AND($G60<>"",$G60<=EOMONTH(P$3,0),$H60>=P$3),"B","U"),IF(AND($G60<>"",$G60<=EOMONTH(P$3,0),$H60>=P$3),"D",""))) | ... AF60: =IF($AH60="","",IF(AND($E60<>"",$E60<=EOMONTH(AF$3,0),$F60>=AF$3),IF(AND($G60<>"",$G60<=EOMONTH(AF$3,0),$H60>=AF$3),"B","U"),IF(AND($G60<>"",$G60<=EOMONTH(AF$3,0),$H60>=AF$3),"D",""))) | AG60: =IF($AH60="","",INDEX('Roadmap Calc (Don’t Touch)'!$D$2:$D$205,$AH60)) | AH60: =IFERROR(MATCH(54,'Roadmap Calc (Don’t Touch)'!$O$2:$O$205,0),"")
A61: =IF($AH61="","",IF($AG61=$AG60,"",$AG61)) | B61: =IF($AH61="","",INDEX('Roadmap Calc (Don’t Touch)'!$B$2:$B$205,$AH61)) | C61: =IF($AH61="","",INDEX('Roadmap Calc (Don’t Touch)'!$E$2:$E$205,$AH61)) | D61: =IF($AH61="","",INDEX('Roadmap Calc (Don’t Touch)'!$F$2:$F$205,$AH61)) | E61: =IF($AH61="","",INDEX('Roadmap Calc (Don’t Touch)'!$G$2:$G$205,$AH61)) | F61: =IF($AH61="","",INDEX('Roadmap Calc (Don’t Touch)'!$H$2:$H$205,$AH61)) | G61: =IF($AH61="","",INDEX('Roadmap Calc (Don’t Touch)'!$I$2:$I$205,$AH61)) | H61: =IF($AH61="","",INDEX('Roadmap Calc (Don’t Touch)'!$J$2:$J$205,$AH61)) | I61: =IF($AH61="","",IF(AND($E61<>"",$E61<=EOMONTH(I$3,0),$F61>=I$3),IF(AND($G61<>"",$G61<=EOMONTH(I$3,0),$H61>=I$3),"B","U"),IF(AND($G61<>"",$G61<=EOMONTH(I$3,0),$H61>=I$3),"D",""))) | J61: =IF($AH61="","",IF(AND($E61<>"",$E61<=EOMONTH(J$3,0),$F61>=J$3),IF(AND($G61<>"",$G61<=EOMONTH(J$3,0),$H61>=J$3),"B","U"),IF(AND($G61<>"",$G61<=EOMONTH(J$3,0),$H61>=J$3),"D",""))) | K61: =IF($AH61="","",IF(AND($E61<>"",$E61<=EOMONTH(K$3,0),$F61>=K$3),IF(AND($G61<>"",$G61<=EOMONTH(K$3,0),$H61>=K$3),"B","U"),IF(AND($G61<>"",$G61<=EOMONTH(K$3,0),$H61>=K$3),"D",""))) | L61: =IF($AH61="","",IF(AND($E61<>"",$E61<=EOMONTH(L$3,0),$F61>=L$3),IF(AND($G61<>"",$G61<=EOMONTH(L$3,0),$H61>=L$3),"B","U"),IF(AND($G61<>"",$G61<=EOMONTH(L$3,0),$H61>=L$3),"D",""))) | M61: =IF($AH61="","",IF(AND($E61<>"",$E61<=EOMONTH(M$3,0),$F61>=M$3),IF(AND($G61<>"",$G61<=EOMONTH(M$3,0),$H61>=M$3),"B","U"),IF(AND($G61<>"",$G61<=EOMONTH(M$3,0),$H61>=M$3),"D",""))) | N61: =IF($AH61="","",IF(AND($E61<>"",$E61<=EOMONTH(N$3,0),$F61>=N$3),IF(AND($G61<>"",$G61<=EOMONTH(N$3,0),$H61>=N$3),"B","U"),IF(AND($G61<>"",$G61<=EOMONTH(N$3,0),$H61>=N$3),"D",""))) | O61: =IF($AH61="","",IF(AND($E61<>"",$E61<=EOMONTH(O$3,0),$F61>=O$3),IF(AND($G61<>"",$G61<=EOMONTH(O$3,0),$H61>=O$3),"B","U"),IF(AND($G61<>"",$G61<=EOMONTH(O$3,0),$H61>=O$3),"D",""))) | P61: =IF($AH61="","",IF(AND($E61<>"",$E61<=EOMONTH(P$3,0),$F61>=P$3),IF(AND($G61<>"",$G61<=EOMONTH(P$3,0),$H61>=P$3),"B","U"),IF(AND($G61<>"",$G61<=EOMONTH(P$3,0),$H61>=P$3),"D",""))) | ... AF61: =IF($AH61="","",IF(AND($E61<>"",$E61<=EOMONTH(AF$3,0),$F61>=AF$3),IF(AND($G61<>"",$G61<=EOMONTH(AF$3,0),$H61>=AF$3),"B","U"),IF(AND($G61<>"",$G61<=EOMONTH(AF$3,0),$H61>=AF$3),"D",""))) | AG61: =IF($AH61="","",INDEX('Roadmap Calc (Don’t Touch)'!$D$2:$D$205,$AH61)) | AH61: =IFERROR(MATCH(55,'Roadmap Calc (Don’t Touch)'!$O$2:$O$205,0),"")
